Workbook
Name A: #REF!
Name bzfz: '[1]披露表(标准)'!$D$6:$D$29
Name bzfz: '[2]披露表(标准)'!$D$6:$D$29
Name didi: #REF!
Name dxn: [3]dxnsjtempsheet!$A:$G
Name fzxm: '[4]披露表(标准)'!$D$6:$D$42
Name fzxm: #REF!
Name gzfzfl: '[5]披露表(国资)'!$D$5:$D$10
Name gzfzxm: '[1]披露表(国资)'!$D$14:$D$54
Name gzfzxm: '[6]披露表(国资)'!$D$6:$D$15
Name gzfzxm2: '[7]披露表(国资)'!$D$43:$D$50
Name hkd: 1.0611
Name NvsASD: "V2001-12-31"
Name NvsAutoDrillOk: "VN"
Name NvsElapsedTime: 0.000181828705535736
Name NvsEndTime: 37274.7274061343
Name NvsInstSpec: "%"
Name NvsLayoutType: "M3"
Name NvsPanelEffdt: "V1900-01-01"
Name NvsPanelSetid: "VFCMNY"
Name NvsReqBU: "VFCMHK"
Name NvsReqBUOnly: "VY"
Name NvsTransLed: "VN"
Name NvsTreeASD: "V2001-12-31"
Name NvsValTbl.ACCOUNT: "GL_ACCOUNT_TBL"
Name SDZL1: [8]明细表!$AP$10
Name SDZL1: #REF!
Name SDZL2: [8]明细表!$AQ$10
Name SDZL2: #REF!
Name SDZL3: [8]明细表!$AR$10
Name SDZL3: #REF!
Name SDZL4: [8]明细表!$AS$10
Name SDZL4: #REF!
Name SDZL5: [8]明细表!$AT$10
Name SDZL5: #REF!
Name SDZL6: [9]A5明细表!$AU$30
Name SDZL6: #REF!
Name ssfzxm: '[10]披露表(上市)'!$D$6:$D$15
Name ssfzxm: '[6]披露表(上市)'!$D$6:$D$15
Name u9qphn: [11]出租开发产品明细!$A$1:$I$17
Name UFPrn20051114145239: [12]福利费1!$A$1:$Q$312
Name UFPrn20060224172848: [13]新城资金明细!$A$1:$H$646
Name UFPrn20060224172935: [13]申鑫大厦租金明细!$A$1:$F$570
Name UFPrn20060224173018: [13]三林明细!$A$1:$H$227
Name UFPrn20060224173111: [13]东陆明细!$A$1:$H$274
Name usd: 8.2773
Name 啊: #REF!
Name 啊: '[14]披露表(上市)'!$F$25
Name 报表项目: [15]会计科目表!$C:$C
Name 存货存在: #REF!
Name 存货存在二: #REF!
Name 存货分类: #REF!
Name 存货分类二: #REF!
Name 存货计价和分摊: #REF!
Name 存货计价和分摊二: #REF!
Name 存货截止: #REF!
Name 存货截止二: #REF!
Name 存货列报: #REF!
Name 存货列报二: #REF!
Name 存货权利和义务: #REF!

Sheet 账账核对
A1: 科目编码 | B1: 科目名称 | C1: 科目余额表借方 | D1: 序时账借方 | E1: 借方差额 | F1: 科目余额表贷方 | G1: 序时账贷方 | H1: 贷方差额
A2: {=OFFSET(科目余额表[科目编码],0,0,COUNT(科目余额表[科目编码]),2)} -> 1001 | B2: 库存现金 | C2: =_xlfn.XLOOKUP(A2,科目余额表[科目编码],科目余额表[本期借方],0) -> 0 | D2: =SUMIF(序时账[科目编码],A2,序时账[借方金额]) -> 0 | E2: =C2-D2 -> 0 | F2: =_xlfn.XLOOKUP(A2,科目余额表[科目编码],科目余额表[本期贷方],0) -> 50 | G2: =SUMIF(序时账[科目编码],A2,序时账[贷方金额]) -> 50 | H2: =F2-G2 -> 0
A3: 1002 | B3: 银行存款 | C3: =_xlfn.XLOOKUP(A3,科目余额表[科目编码],科目余额表[本期借方],0) -> 18485749 | D3: =SUMIF(序时账[科目编码],A3,序时账[借方金额]) -> 0 | E3: =C3-D3 -> 18485749 | F3: =_xlfn.XLOOKUP(A3,科目余额表[科目编码],科目余额表[本期贷方],0) -> 5033601.7 | G3: =SUMIF(序时账[科目编码],A3,序时账[贷方金额]) -> 0 | H3: =F3-G3 -> 5033601.7
A4: 1002001 | B4: ABC银行账户 | C4: =_xlfn.XLOOKUP(A4,科目余额表[科目编码],科目余额表[本期借方],0) -> 13194920 | D4: =SUMIF(序时账[科目编码],A4,序时账[借方金额]) -> 13194920 | E4: =C4-D4 -> 0 | F4: =_xlfn.XLOOKUP(A4,科目余额表[科目编码],科目余额表[本期贷方],0) -> 1086601.7 | G4: =SUMIF(序时账[科目编码],A4,序时账[贷方金额]) -> 1086601.7 | H4: =F4-G4 -> 0
A5: 1002002 | B5: EFG银行账户 | C5: =_xlfn.XLOOKUP(A5,科目余额表[科目编码],科目余额表[本期借方],0) -> 5290829.8 | D5: =SUMIF(序时账[科目编码],A5,序时账[借方金额]) -> 5290829.8 | E5: =C5-D5 -> 0 | F5: =_xlfn.XLOOKUP(A5,科目余额表[科目编码],科目余额表[本期贷方],0) -> 3947000 | G5: =SUMIF(序时账[科目编码],A5,序时账[贷方金额]) -> 3947000 | H5: =F5-G5 -> 0
A6: 1122 | B6: 应收账款 | C6: =_xlfn.XLOOKUP(A6,科目余额表[科目编码],科目余额表[本期借方],0) -> 15006400 | D6: =SUMIF(序时账[科目编码],A6,序时账[借方金额]) -> 0 | E6: =C6-D6 -> 15006400 | F6: =_xlfn.XLOOKUP(A6,科目余额表[科目编码],科目余额表[本期贷方],0) -> 12389000 | G6: =SUMIF(序时账[科目编码],A6,序时账[贷方金额]) -> 0 | H6: =F6-G6 -> 12389000
A7: 1122001 | B7: A有限公司 | C7: =_xlfn.XLOOKUP(A7,科目余额表[科目编码],科目余额表[本期借方],0) -> 2395600 | D7: =SUMIF(序时账[科目编码],A7,序时账[借方金额]) -> 2395600 | E7: =C7-D7 -> 0 | F7: =_xlfn.XLOOKUP(A7,科目余额表[科目编码],科目余额表[本期贷方],0) -> 2030000 | G7: =SUMIF(序时账[科目编码],A7,序时账[贷方金额]) -> 2030000 | H7: =F7-G7 -> 0
A8: 1122002 | B8: B有限公司 | C8: =_xlfn.XLOOKUP(A8,科目余额表[科目编码],科目余额表[本期借方],0) -> 1152600 | D8: =SUMIF(序时账[科目编码],A8,序时账[借方金额]) -> 1152600 | E8: =C8-D8 -> 0 | F8: =_xlfn.XLOOKUP(A8,科目余额表[科目编码],科目余额表[本期贷方],0) -> 1029000 | G8: =SUMIF(序时账[科目编码],A8,序时账[贷方金额]) -> 1029000 | H8: =F8-G8 -> 0
A9: 1122003 | B9: C有限公司 | C9: =_xlfn.XLOOKUP(A9,科目余额表[科目编码],科目余额表[本期借方],0) -> 2406900 | D9: =SUMIF(序时账[科目编码],A9,序时账[借方金额]) -> 2406900 | E9: =C9-D9 -> 0 | F9: =_xlfn.XLOOKUP(A9,科目余额表[科目编码],科目余额表[本期贷方],0) -> 1993000 | G9: =SUMIF(序时账[科目编码],A9,序时账[贷方金额]) -> 1993000 | H9: =F9-G9 -> 0
A10: 1122004 | B10: D有限公司 | C10: =_xlfn.XLOOKUP(A10,科目余额表[科目编码],科目余额表[本期借方],0) -> 1175200 | D10: =SUMIF(序时账[科目编码],A10,序时账[借方金额]) -> 1175200 | E10: =C10-D10 -> 0 | F10: =_xlfn.XLOOKUP(A10,科目余额表[科目编码],科目余额表[本期贷方],0) -> 1018000 | G10: =SUMIF(序时账[科目编码],A10,序时账[贷方金额]) -> 1018000 | H10: =F10-G10 -> 0
A11: 1122005 | B11: E有限公司 | C11: =_xlfn.XLOOKUP(A11,科目余额表[科目编码],科目余额表[本期借方],0) -> 1751500 | D11: =SUMIF(序时账[科目编码],A11,序时账[借方金额]) -> 1751500 | E11: =C11-D11 -> 0 | F11: =_xlfn.XLOOKUP(A11,科目余额表[科目编码],科目余额表[本期贷方],0) -> 2009000 | G11: =SUMIF(序时账[科目编码],A11,序时账[贷方金额]) -> 2009000 | H11: =F11-G11 -> 0
A12: 1122006 | B12: F有限公司 | C12: =_xlfn.XLOOKUP(A12,科目余额表[科目编码],科目余额表[本期借方],0) -> 1197800 | D12: =SUMIF(序时账[科目编码],A12,序时账[借方金额]) -> 1197800 | E12: =C12-D12 -> 0 | F12: =_xlfn.XLOOKUP(A12,科目余额表[科目编码],科目余额表[本期贷方],0) -> 870000 | G12: =SUMIF(序时账[科目编码],A12,序时账[贷方金额]) -> 870000 | H12: =F12-G12 -> 0
A13: 1122007 | B13: G有限公司 | C13: =_xlfn.XLOOKUP(A13,科目余额表[科目编码],科目余额表[本期借方],0) -> 1209100 | D13: =SUMIF(序时账[科目编码],A13,序时账[借方金额]) -> 1209100 | E13: =C13-D13 -> 0 | F13: =_xlfn.XLOOKUP(A13,科目余额表[科目编码],科目余额表[本期贷方],0) -> 810000 | G13: =SUMIF(序时账[科目编码],A13,序时账[贷方金额]) -> 810000 | H13: =F13-G13 -> 0
A14: 1122008 | B14: H有限公司 | C14: =_xlfn.XLOOKUP(A14,科目余额表[科目编码],科目余额表[本期借方],0) -> 1220400 | D14: =SUMIF(序时账[科目编码],A14,序时账[借方金额]) -> 1220400 | E14: =C14-D14 -> 0 | F14: =_xlfn.XLOOKUP(A14,科目余额表[科目编码],科目余额表[本期贷方],0) -> 770000 | G14: =SUMIF(序时账[科目编码],A14,序时账[贷方金额]) -> 770000 | H14: =F14-G14 -> 0
... A85: 5801 | B85: 所得税费用 | C85: =_xlfn.XLOOKUP(A85,科目余额表[科目编码],科目余额表[本期借方],0) -> 579779.36 | D85: =SUMIF(序时账[科目编码],A85,序时账[借方金额]) -> 579779.36 | E85: =C85-D85 -> 0 | F85: =_xlfn.XLOOKUP(A85,科目余额表[科目编码],科目余额表[本期贷方],0) -> 579779.36 | G85: =SUMIF(序时账[科目编码],A85,序时账[贷方金额]) -> 579779.36 | H85: =F85-G85 -> 0
C86: =_xlfn.XLOOKUP(A86,科目余额表[科目编码],科目余额表[本期借方],0) -> 0 | D86: =SUMIF(序时账[科目编码],A86,序时账[借方金额]) -> 0 | E86: =C86-D86 -> 0 | F86: =_xlfn.XLOOKUP(A86,科目余额表[科目编码],科目余额表[本期贷方],0) -> 0 | G86: =SUMIF(序时账[科目编码],A86,序时账[贷方金额]) -> 0 | H86: =F86-G86 -> 0
C87: =_xlfn.XLOOKUP(A87,科目余额表[科目编码],科目余额表[本期借方],0) -> 0 | D87: =SUMIF(序时账[科目编码],A87,序时账[借方金额]) -> 0 | E87: =C87-D87 -> 0 | F87: =_xlfn.XLOOKUP(A87,科目余额表[科目编码],科目余额表[本期贷方],0) -> 0 | G87: =SUMIF(序时账[科目编码],A87,序时账[贷方金额]) -> 0 | H87: =F87-G87 -> 0
C88: =_xlfn.XLOOKUP(A88,科目余额表[科目编码],科目余额表[本期借方],0) -> 0 | D88: =SUMIF(序时账[科目编码],A88,序时账[借方金额]) -> 0 | E88: =C88-D88 -> 0 | F88: =_xlfn.XLOOKUP(A88,科目余额表[科目编码],科目余额表[本期贷方],0) -> 0 | G88: =SUMIF(序时账[科目编码],A88,序时账[贷方金额]) -> 0 | H88: =F88-G88 -> 0
C89: =_xlfn.XLOOKUP(A89,科目余额表[科目编码],科目余额表[本期借方],0) -> 0 | D89: =SUMIF(序时账[科目编码],A89,序时账[借方金额]) -> 0 | E89: =C89-D89 -> 0 | F89: =_xlfn.XLOOKUP(A89,科目余额表[科目编码],科目余额表[本期贷方],0) -> 0 | G89: =SUMIF(序时账[科目编码],A89,序时账[贷方金额]) -> 0 | H89: =F89-G89 -> 0
C90: =_xlfn.XLOOKUP(A90,科目余额表[科目编码],科目余额表[本期借方],0) -> 0 | D90: =SUMIF(序时账[科目编码],A90,序时账[借方金额]) -> 0 | E90: =C90-D90 -> 0 | F90: =_xlfn.XLOOKUP(A90,科目余额表[科目编码],科目余额表[本期贷方],0) -> 0 | G90: =SUMIF(序时账[科目编码],A90,序时账[贷方金额]) -> 0 | H90: =F90-G90 -> 0
C91: =_xlfn.XLOOKUP(A91,科目余额表[科目编码],科目余额表[本期借方],0) -> 0 | D91: =SUMIF(序时账[科目编码],A91,序时账[借方金额]) -> 0 | E91: =C91-D91 -> 0 | F91: =_xlfn.XLOOKUP(A91,科目余额表[科目编码],科目余额表[本期贷方],0) -> 0 | G91: =SUMIF(序时账[科目编码],A91,序时账[贷方金额]) -> 0 | H91: =F91-G91 -> 0
C92: =_xlfn.XLOOKUP(A92,科目余额表[科目编码],科目余额表[本期借方],0) -> 0 | D92: =SUMIF(序时账[科目编码],A92,序时账[借方金额]) -> 0 | E92: =C92-D92 -> 0 | F92: =_xlfn.XLOOKUP(A92,科目余额表[科目编码],科目余额表[本期贷方],0) -> 0 | G92: =SUMIF(序时账[科目编码],A92,序时账[贷方金额]) -> 0 | H92: =F92-G92 -> 0
C93: =_xlfn.XLOOKUP(A93,科目余额表[科目编码],科目余额表[本期借方],0) -> 0 | D93: =SUMIF(序时账[科目编码],A93,序时账[借方金额]) -> 0 | E93: =C93-D93 -> 0 | F93: =_xlfn.XLOOKUP(A93,科目余额表[科目编码],科目余额表[本期贷方],0) -> 0 | G93: =SUMIF(序时账[科目编码],A93,序时账[贷方金额]) -> 0 | H93: =F93-G93 -> 0
C94: =_xlfn.XLOOKUP(A94,科目余额表[科目编码],科目余额表[本期借方],0) -> 0 | D94: =SUMIF(序时账[科目编码],A94,序时账[借方金额]) -> 0 | E94: =C94-D94 -> 0 | F94: =_xlfn.XLOOKUP(A94,科目余额表[科目编码],科目余额表[本期贷方],0) -> 0 | G94: =SUMIF(序时账[科目编码],A94,序时账[贷方金额]) -> 0 | H94: =F94-G94 -> 0
C95: =_xlfn.XLOOKUP(A95,科目余额表[科目编码],科目余额表[本期借方],0) -> 0 | D95: =SUMIF(序时账[科目编码],A95,序时账[借方金额]) -> 0 | E95: =C95-D95 -> 0 | F95: =_xlfn.XLOOKUP(A95,科目余额表[科目编码],科目余额表[本期贷方],0) -> 0 | G95: =SUMIF(序时账[科目编码],A95,序时账[贷方金额]) -> 0 | H95: =F95-G95 -> 0
C96: =_xlfn.XLOOKUP(A96,科目余额表[科目编码],科目余额表[本期借方],0) -> 0 | D96: =SUMIF(序时账[科目编码],A96,序时账[借方金额]) -> 0 | E96: =C96-D96 -> 0 | F96: =_xlfn.XLOOKUP(A96,科目余额表[科目编码],科目余额表[本期贷方],0) -> 0 | G96: =SUMIF(序时账[科目编码],A96,序时账[贷方金额]) -> 0 | H96: =F96-G96 -> 0
C97: =_xlfn.XLOOKUP(A97,科目余额表[科目编码],科目余额表[本期借方],0) -> 0 | D97: =SUMIF(序时账[科目编码],A97,序时账[借方金额]) -> 0 | E97: =C97-D97 -> 0 | F97: =_xlfn.XLOOKUP(A97,科目余额表[科目编码],科目余额表[本期贷方],0) -> 0 | G97: =SUMIF(序时账[科目编码],A97,序时账[贷方金额]) -> 0 | H97: =F97-G97 -> 0
... C251: =_xlfn.XLOOKUP(A251,科目余额表[科目编码],科目余额表[本期借方],0) -> 0 | D251: =SUMIF(序时账[科目编码],A251,序时账[借方金额]) -> 0 | E251: =C251-D251 -> 0 | F251: =_xlfn.XLOOKUP(A251,科目余额表[科目编码],科目余额表[本期贷方],0) -> 0 | G251: =SUMIF(序时账[科目编码],A251,序时账[贷方金额]) -> 0 | H251: =F251-G251 -> 0

Sheet 校对表
A1: 资产负债表（期初）
A2: 报表项目 | B2: 报表金额 | C2: 报表项目 | D2: 报表金额
A3: 流动资产合计 | B3: =SUM(试算平衡表!C2:C14) -> 18778262 | C3: 流动负债合计 | D3: =SUM(试算平衡表!C33:C45) -> 6154772.8
A4: 非流动资产合计 | B4: =SUM(试算平衡表!C15:C32) -> 907134.11 | C4: 非流动负债合计 | D4: =SUM(试算平衡表!C46:C54) -> 0
C5: 负债合计 | D5: =SUM(D3:D4) -> 6154772.8
C6: 所有者权益（或股东权益）合计 | D6: =SUM(试算平衡表!C55:C57)-试算平衡表!C58+SUM(试算平衡表!C59:C62) -> 13530623
A7: 资产总计 | B7: =SUM(B3:B6) -> 19685396 | C7: 负债和所有者权益（或股东权益）总计 | D7: =SUM(D5:D6) -> 19685396
A8: 资产负债表（期末）
A9: 报表项目 | B9: 报表金额 | C9: 报表项目 | D9: 报表金额
A10: 流动资产合计 | B10: =SUM(试算平衡表!D2:D14) -> 31234121 | C10: 流动负债合计 | D10: =SUM(试算平衡表!D33:D45) -> 17208982
A11: 非流动资产合计 | B11: =SUM(试算平衡表!D15:D32) -> 1244774.1 | C11: 非流动负债合计 | D11: =SUM(试算平衡表!D46:D54) -> 0
C12: 负债合计 | D12: =SUM(D10:D11) -> 17208982
C13: 所有者权益（或股东权益）合计 | D13: =SUM(试算平衡表!D55:D57)-试算平衡表!D58+SUM(试算平衡表!D59:D62) -> 15269912
A14: 资产总计 | B14: =SUM(B10:B13) -> 32478895 | C14: 负债和所有者权益（或股东权益）总计 | D14: =SUM(D12:D13) -> 32478895
A15: 资产负债表平衡
A16: 期初资产负债表平衡差额 | B16: =B7-D7 -> 0
A17: 期末资产负债表平衡差额 | B17: =B14-D14 -> 0
A18: 利润表
A19: 期初未分配利润 | B19: =试算平衡表!C62 -> 3530623.1
A20: 本期净利润 | B20: =试算平衡表!D63-SUM(试算平衡表!D64:'试算平衡表'!D69)+SUM(试算平衡表!D70:'试算平衡表'!D77)-SUM(试算平衡表!D78:'试算平衡表'!D79) -> 1739289.3
A21: 减：利润分配
A22: 加：其他调整
A23: 减：其他调整
A24: 计算年末未分配利润 | B24: =B19+B20-B21+B22-B23 -> 5269912.4
A25: 报表年末未分配利润 | B25: =试算平衡表!D62 -> 5269912.5
A26: 差额 | B26: =B24-B25 -> 0
A27: 现金流
A28: 项目 | B28: 借方发生额 | C28: 贷方发生额
A29: 科目余额表现金、银行存款、其他货币资金 | B29: =SUMIF(科目余额表!I:I,"货币资金",科目余额表!E:E) -> 18485749 | C29: =SUMIF(科目余额表!I:I,"货币资金",科目余额表!F:F) -> 5033651.7
A30: 序时账现金 | B30: =SUMIF(序时账!I:I,"现金",序时账!G:G) -> 0 | C30: =SUMIF(序时账!I:I,"现金",序时账!H:H) -> 50
A31: 序时账银行存款 | B31: =SUMIF(序时账!I:I,"银行存款",序时账!G:G) -> 18485749 | C31: =SUMIF(序时账!I:I,"银行存款",序时账!H:H) -> 5033601.7
A32: 序时账其他货币资金 | B32: =SUMIF(序时账!I:I,"其他货币资金",序时账!G:G) -> 0 | C32: =SUMIF(序时账!I:I,"其他货币资金",序时账!H:H) -> 0
A33: 差额 | B33: =B29-B30-B31 -> 0 | C33: =C29-C30-C31 -> 0
A34: 往来附注查重
A35: 往来单位 | B35: 是否有重复项
A36: {=_xlfn.UNIQUE(D36:D75)} -> F有限公司 | B36: =IF(COUNTIF($D$36:$D$75,A36)>1,COUNTIF($D$36:$D$75,A36),"—") -> — | C36: 应收账款 | D36: {=OFFSET(附注自动计算!A25:A29,0,0)} -> F有限公司
A37: H有限公司 | B37: =IF(COUNTIF($D$36:$D$75,A37)>1,COUNTIF($D$36:$D$75,A37),"—") -> — | D37: H有限公司
A38: A有限公司 | B38: =IF(COUNTIF($D$36:$D$75,A38)>1,COUNTIF($D$36:$D$75,A38),"—") -> — | D38: A有限公司
A39: I有限公司 | B39: =IF(COUNTIF($D$36:$D$75,A39)>1,COUNTIF($D$36:$D$75,A39),"—") -> — | D39: I有限公司
A40: G有限公司 | B40: =IF(COUNTIF($D$36:$D$75,A40)>1,COUNTIF($D$36:$D$75,A40),"—") -> — | D40: G有限公司
A41: O有限公司 | B41: =IF(COUNTIF($D$36:$D$75,A41)>1,COUNTIF($D$36:$D$75,A41),"—") -> — | C41: 预付款项 | D41: {=OFFSET(附注自动计算!A46:A50,0,0)} -> O有限公司
A42: 0 | B42: =IF(COUNTIF($D$36:$D$75,A42)>1,COUNTIF($D$36:$D$75,A42),"—") -> 21 | D42: 0
A43: 王五 | B43: =IF(COUNTIF($D$36:$D$75,A43)>1,COUNTIF($D$36:$D$75,A43),"—") -> — | D43: 0
A44: 张三 | B44: =IF(COUNTIF($D$36:$D$75,A44)>1,COUNTIF($D$36:$D$75,A44),"—") -> — | D44: 0
A45: 李四 | B45: =IF(COUNTIF($D$36:$D$75,A45)>1,COUNTIF($D$36:$D$75,A45),"—") -> — | D45: 0
A46: M有限公司 | B46: =IF(COUNTIF($D$36:$D$75,A46)>1,COUNTIF($D$36:$D$75,A46),"—") -> — | C46: 合同资产 | D46: {=OFFSET(附注自动计算!A67:A71,0,0)} -> 0
A47: T有限公司 | B47: =IF(COUNTIF($D$36:$D$75,A47)>1,COUNTIF($D$36:$D$75,A47),"—") -> — | D47: 0
A48: X有限公司 | B48: =IF(COUNTIF($D$36:$D$75,A48)>1,COUNTIF($D$36:$D$75,A48),"—") -> — | D48: 0
A49: V有限公司 | B49: =IF(COUNTIF($D$36:$D$75,A49)>1,COUNTIF($D$36:$D$75,A49),"—") -> — | D49: 0
A50: U有限公司 | B50: =IF(COUNTIF($D$36:$D$75,A50)>1,COUNTIF($D$36:$D$75,A50),"—") -> — | D50: 0
A51: 乙 | B51: =IF(COUNTIF($D$36:$D$75,A51)>1,COUNTIF($D$36:$D$75,A51),"—") -> — | C51: 其他应收款 | D51: {=OFFSET(附注自动计算!A88:A92,0,0)} -> 王五
A52: 甲 | B52: =IF(COUNTIF($D$36:$D$75,A52)>1,COUNTIF($D$36:$D$75,A52),"—") -> — | D52: 张三
A53: 丙 | B53: =IF(COUNTIF($D$36:$D$75,A53)>1,COUNTIF($D$36:$D$75,A53),"—") -> — | D53: 李四
A54: 丁 | B54: =IF(COUNTIF($D$36:$D$75,A54)>1,COUNTIF($D$36:$D$75,A54),"—") -> — | D54: 0
A55: 亥 | B55: =IF(COUNTIF($D$36:$D$75,A55)>1,COUNTIF($D$36:$D$75,A55),"—") -> — | D55: 0
B56: =IF(COUNTIF($D$36:$D$75,A56)>1,COUNTIF($D$36:$D$75,A56),"—") -> 21 | C56: 应付账款 | D56: {=OFFSET(附注自动计算!A163:A167,0,0)} -> M有限公司
B57: =IF(COUNTIF($D$36:$D$75,A57)>1,COUNTIF($D$36:$D$75,A57),"—") -> 21 | D57: T有限公司
B58: =IF(COUNTIF($D$36:$D$75,A58)>1,COUNTIF($D$36:$D$75,A58),"—") -> 21 | D58: X有限公司
B59: =IF(COUNTIF($D$36:$D$75,A59)>1,COUNTIF($D$36:$D$75,A59),"—") -> 21 | D59: V有限公司
B60: =IF(COUNTIF($D$36:$D$75,A60)>1,COUNTIF($D$36:$D$75,A60),"—") -> 21 | D60: U有限公司
B61: =IF(COUNTIF($D$36:$D$75,A61)>1,COUNTIF($D$36:$D$75,A61),"—") -> 21 | C61: 预收款项 | D61: {=OFFSET(附注自动计算!A182:A186,0,0)} -> 0
B62: =IF(COUNTIF($D$36:$D$75,A62)>1,COUNTIF($D$36:$D$75,A62),"—") -> 21 | D62: 0
B63: =IF(COUNTIF($D$36:$D$75,A63)>1,COUNTIF($D$36:$D$75,A63),"—") -> 21 | D63: 0
B64: =IF(COUNTIF($D$36:$D$75,A64)>1,COUNTIF($D$36:$D$75,A64),"—") -> 21 | D64: 0
B65: =IF(COUNTIF($D$36:$D$75,A65)>1,COUNTIF($D$36:$D$75,A65),"—") -> 21 | D65: 0
B66: =IF(COUNTIF($D$36:$D$75,A66)>1,COUNTIF($D$36:$D$75,A66),"—") -> 21 | C66: 合同负债 | D66: {=OFFSET(附注自动计算!A201:A205,0,0)} -> 0
B67: =IF(COUNTIF($D$36:$D$75,A67)>1,COUNTIF($D$36:$D$75,A67),"—") -> 21 | D67: 0
B68: =IF(COUNTIF($D$36:$D$75,A68)>1,COUNTIF($D$36:$D$75,A68),"—") -> 21 | D68: 0
B69: =IF(COUNTIF($D$36:$D$75,A69)>1,COUNTIF($D$36:$D$75,A69),"—") -> 21 | D69: 0
B70: =IF(COUNTIF($D$36:$D$75,A70)>1,COUNTIF($D$36:$D$75,A70),"—") -> 21 | D70: 0
B71: =IF(COUNTIF($D$36:$D$75,A71)>1,COUNTIF($D$36:$D$75,A71),"—") -> 21 | C71: 其他应付款 | D71: {=OFFSET(附注自动计算!A220:A224,0,0)} -> 乙
B72: =IF(COUNTIF($D$36:$D$75,A72)>1,COUNTIF($D$36:$D$75,A72),"—") -> 21 | D72: 甲
B73: =IF(COUNTIF($D$36:$D$75,A73)>1,COUNTIF($D$36:$D$75,A73),"—") -> 21 | D73: 丙
B74: =IF(COUNTIF($D$36:$D$75,A74)>1,COUNTIF($D$36:$D$75,A74),"—") -> 21 | D74: 丁
B75: =IF(COUNTIF($D$36:$D$75,A75)>1,COUNTIF($D$36:$D$75,A75),"—") -> 21 | D75: 亥

Sheet 科目余额表
A1: 科目编码 | B1: 科目名称 | C1: 期初借方 | D1: 期初贷方 | E1: 本期借方 | F1: 本期贷方 | G1: 期末借方 | H1: 期末贷方 | I1: 未审报表项目 | J1: 已审报表项目 | K1: 调整 | L1: 抽查项目 | M1: 测算项目
A2: 1001 | B2: 库存现金 | C2: 15002.34 | D2: 0 | E2: 0 | F2: 50 | G2: 14952.34 | H2: 0 | I2: 货币资金 | J2: 货币资金 | K2: =IF(I2<>J2,"是","否") -> 否 | L2: 现金 | M2: 现金
A3: 1002 | B3: 银行存款 | C3: 995835 | D3: 0 | E3: 18485749 | F3: 5033601.7 | G3: 14447983 | H3: 0 | K3: =IF(I3<>J3,"是","否") -> 否
A4: 1002001 | B4: ABC银行账户 | C4: 955349.35 | D4: 0 | E4: 13194920 | F4: 1086601.7 | G4: 13063667 | H4: 0 | I4: 货币资金 | J4: 货币资金 | K4: =IF(I4<>J4,"是","否") -> 否 | L4: 银行存款 | M4: 银行存款
A5: 1002002 | B5: EFG银行账户 | C5: 40485.65 | D5: 0 | E5: 5290829.8 | F5: 3947000 | G5: 1384315.4 | H5: 0 | I5: 货币资金 | J5: 货币资金 | K5: =IF(I5<>J5,"是","否") -> 否 | L5: 银行存款 | M5: 银行存款
A6: 1122 | B6: 应收账款 | C6: 5547848 | D6: 0 | E6: 15006400 | F6: 12389000 | G6: 8165248 | H6: 0 | K6: =IF(I6<>J6,"是","否") -> 否
A7: 1122001 | B7: A有限公司 | C7: 552444.45 | D7: 0 | E7: 2395600 | F7: 2030000 | G7: 918044.45 | H7: 0 | I7: 应收账款 | J7: 应收账款 | K7: =IF(I7<>J7,"是","否") -> 否 | L7: 应收账款
A8: 1122002 | B8: B有限公司 | C8: 449224.39 | D8: 0 | E8: 1152600 | F8: 1029000 | G8: 572824.39 | H8: 0 | I8: 应收账款 | J8: 应收账款 | K8: =IF(I8<>J8,"是","否") -> 否 | L8: 应收账款
A9: 1122003 | B9: C有限公司 | C9: 228599.99 | D9: 0 | E9: 2406900 | F9: 1993000 | G9: 642499.99 | H9: 0 | I9: 应收账款 | J9: 应收账款 | K9: =IF(I9<>J9,"是","否") -> 否 | L9: 应收账款
A10: 1122004 | B10: D有限公司 | C10: 669788.45 | D10: 0 | E10: 1175200 | F10: 1018000 | G10: 826988.45 | H10: 0 | I10: 应收账款 | J10: 应收账款 | K10: =IF(I10<>J10,"是","否") -> 否 | L10: 应收账款
A11: 1122005 | B11: E有限公司 | C11: 550333.49 | D11: 0 | E11: 1751500 | F11: 2009000 | G11: 292833.49 | H11: 0 | I11: 应收账款 | J11: 应收账款 | K11: =IF(I11<>J11,"是","否") -> 否 | L11: 应收账款
A12: 1122006 | B12: F有限公司 | C12: 999200.88 | D12: 0 | E12: 1197800 | F12: 870000 | G12: 1327000.9 | H12: 0 | I12: 应收账款 | J12: 应收账款 | K12: =IF(I12<>J12,"是","否") -> 否 | L12: 应收账款
A13: 1122007 | B13: G有限公司 | C13: 450055.23 | D13: 0 | E13: 1209100 | F13: 810000 | G13: 849155.23 | H13: 0 | I13: 应收账款 | J13: 应收账款 | K13: =IF(I13<>J13,"是","否") -> 否 | L13: 应收账款
A14: 1122008 | B14: H有限公司 | C14: 555455.34 | D14: 0 | E14: 1220400 | F14: 770000 | G14: 1005855.3 | H14: 0 | I14: 应收账款 | J14: 应收账款 | K14: =IF(I14<>J14,"是","否") -> 否 | L14: 应收账款
A15: 1122009 | B15: I有限公司 | C15: 566229.43 | D15: 0 | E15: 1231700 | F15: 880000 | G15: 917929.43 | H15: 0 | I15: 应收账款 | J15: 应收账款 | K15: =IF(I15<>J15,"是","否") -> 否 | L15: 应收账款
A16: 1122010 | B16: J有限公司 | C16: 526516.34 | D16: 0 | E16: 1265600 | F16: 980000 | G16: 812116.34 | H16: 0 | I16: 应收账款 | J16: 应收账款 | K16: =IF(I16<>J16,"是","否") -> 否 | L16: 应收账款
A17: 1123 | B17: 预付账款 | C17: 2001987.2 | D17: 0 | E17: 540000 | F17: 4869264 | G17: -2327276.8 | H17: 0 | K17: =IF(I17<>J17,"是","否") -> 否
A18: 1123001 | B18: K有限公司 | C18: 200199.49 | D18: 0 | E18: 0 | F18: 568842 | G18: -368642.51 | H18: 0 | I18: 预付款项 | J18: 应付账款 | K18: =IF(I18<>J18,"是","否") -> 是 | L18: 预付款项
A19: 1123002 | B19: L有限公司 | C19: 188355.45 | D19: 0 | E19: 0 | F19: 698000 | G19: -509644.55 | H19: 0 | I19: 预付款项 | J19: 应付账款 | K19: =IF(I19<>J19,"是","否") -> 是 | L19: 预付款项
A20: 1123003 | B20: M有限公司 | C20: 422009.32 | D20: 0 | E20: 0 | F20: 568842 | G20: -146832.68 | H20: 0 | I20: 预付款项 | J20: 应付账款 | K20: =IF(I20<>J20,"是","否") -> 是 | L20: 预付款项
A21: 1123004 | B21: N有限公司 | C21: 334588.9 | D21: 0 | E21: 0 | F21: 0 | G21: 334588.9 | H21: 0 | I21: 预付款项 | J21: 预付款项 | K21: =IF(I21<>J21,"是","否") -> 否 | L21: 预付款项
A22: 1123005 | B22: C有限公司 | C22: 235333.35 | D22: 0 | E22: 0 | F22: 1361700 | G22: -1126366.6 | H22: 0 | I22: 预付款项 | J22: 应付账款 | K22: =IF(I22<>J22,"是","否") -> 是 | L22: 预付款项
A23: 1123006 | B23: O有限公司 | C23: 190048.34 | D23: 0 | E23: 540000 | F23: 0 | G23: 730048.34 | H23: 0 | I23: 预付款项 | J23: 预付款项 | K23: =IF(I23<>J23,"是","否") -> 否 | L23: 预付款项
A24: 1123007 | B24: P有限公司 | C24: 230444.39 | D24: 0 | E24: 0 | F24: 763880 | G24: -533435.61 | H24: 0 | I24: 预付款项 | J24: 应付账款 | K24: =IF(I24<>J24,"是","否") -> 是 | L24: 预付款项
A25: 1123008 | B25: Q有限公司 | C25: 201008 | D25: 0 | E25: 0 | F25: 908000 | G25: -706992 | H25: 0 | I25: 预付款项 | J25: 应付账款 | K25: =IF(I25<>J25,"是","否") -> 是 | L25: 预付款项
A26: 1221 | B26: 其他应收款 | C26: 229934.57 | D26: 0 | E26: 0 | F26: 10000 | G26: 219934.57 | H26: 0 | K26: =IF(I26<>J26,"是","否") -> 否
A27: 1221001 | B27: 张三 | C27: 78922.34 | D27: 0 | E27: 0 | F27: 0 | G27: 78922.34 | H27: 0 | I27: 其他应收款 | J27: 其他应收款 | K27: =IF(I27<>J27,"是","否") -> 否 | L27: 其他应收款
A28: 1221002 | B28: 李四 | C28: 68847.87 | D28: 0 | E28: 0 | F28: 10000 | G28: 58847.87 | H28: 0 | I28: 其他应收款 | J28: 其他应收款 | K28: =IF(I28<>J28,"是","否") -> 否 | L28: 其他应收款
A29: 1221003 | B29: 王五 | C29: 82164.36 | D29: 0 | E29: 0 | F29: 0 | G29: 82164.36 | H29: 0 | I29: 其他应收款 | J29: 其他应收款 | K29: =IF(I29<>J29,"是","否") -> 否 | L29: 其他应收款
A30: 1405 | B30: 库存商品 | C30: 9987654.7 | D30: 0 | E30: 8546300 | F30: 10878000 | G30: 7655954.7 | H30: 0 | K30: =IF(I30<>J30,"是","否") -> 否
A31: 1405001 | B31: R商品 | C31: 4590388.5 | D31: 0 | E31: 5826500 | F31: 5436000 | G31: 4980888.5 | H31: 0 | I31: 存货 | J31: 存货 | K31: =IF(I31<>J31,"是","否") -> 否 | L31: 存货
A32: 1405002 | B32: S商品 | C32: 5397266.2 | D32: 0 | E32: 2719800 | F32: 5442000 | G32: 2675066.2 | H32: 0 | I32: 存货 | J32: 存货 | K32: =IF(I32<>J32,"是","否") -> 否 | L32: 存货
A33: 1601 | B33: 固定资产 | C33: 2007689 | D33: 0 | E33: 350000 | F33: 0 | G33: 2357689 | H33: 0 | K33: =IF(I33<>J33,"是","否") -> 否
A34: 1601001 | B34: 轿车 | C34: 1877654.6 | D34: 0 | E34: 350000 | F34: 0 | G34: 2227654.6 | H34: 0 | I34: 固定资产 | J34: 固定资产 | K34: =IF(I34<>J34,"是","否") -> 否 | L34: 固定资产 | M34: 固-运输工具
A35: 1601002 | B35: 电脑 | C35: 130034.38 | D35: 0 | E35: 0 | F35: 0 | G35: 130034.38 | H35: 0 | I35: 固定资产 | J35: 固定资产 | K35: =IF(I35<>J35,"是","否") -> 否 | L35: 固定资产 | M35: 固-电子设备
A36: 1602 | B36: 累计折旧 | C36: 0 | D36: 1100554.9 | E36: 0 | F36: 12360 | G36: 0 | H36: 1112914.9 | K36: =IF(I36<>J36,"是","否") -> 否
A37: 1602001 | B37: 轿车 | C37: 0 | D37: 1034677.5 | E37: 0 | F37: 0 | G37: 0 | H37: 1044677.5 | I37: 固定资产 | J37: 固定资产 | K37: =IF(I37<>J37,"是","否") -> 否 | L37: 固定资产 | M37: 折-运输工具
A38: 1602002 | B38: 电脑 | C38: 0 | D38: 65877.34 | E38: 0 | F38: 12360 | G38: 0 | H38: 68237.34 | I38: 固定资产 | J38: 固定资产 | K38: =IF(I38<>J38,"是","否") -> 否 | L38: 固定资产 | M38: 折-电子设备
A39: 2202 | B39: 应付账款 | C39: 0 | D39: 5678890.3 | E39: 3400000 | F39: 10866055 | G39: 0 | H39: 13144945 | K39: =IF(I39<>J39,"是","否") -> 否
A40: 2202001 | B40: T有限公司 | C40: 0 | D40: 566399.29 | E40: 0 | F40: 1566604 | G40: 0 | H40: 2133003.3 | I40: 应付账款 | J40: 应付账款 | K40: =IF(I40<>J40,"是","否") -> 否 | L40: 应付账款
A41: 2202002 | B41: U有限公司 | C41: 0 | D41: 688466.23 | E41: 0 | F41: 553700 | G41: 0 | H41: 1242166.2 | I41: 应付账款 | J41: 应付账款 | K41: =IF(I41<>J41,"是","否") -> 否 | L41: 应付账款
A42: 2202003 | B42: M有限公司 | C42: 0 | D42: 599799.87 | E42: 0 | F42: 3618599 | G42: 0 | H42: 4218398.9 | I42: 应付账款 | J42: 应付账款 | K42: =IF(I42<>J42,"是","否") -> 否 | L42: 应付账款
A43: 2202004 | B43: V有限公司 | C43: 0 | D43: 344886.38 | E43: 0 | F43: 1352135 | G43: 0 | H43: 1697021.4 | I43: 应付账款 | J43: 应付账款 | K43: =IF(I43<>J43,"是","否") -> 否 | L43: 应付账款
A44: 2202005 | B44: W有限公司 | C44: 0 | D44: 588952.95 | E44: 640000 | F44: 1003000 | G44: 0 | H44: 951952.95 | I44: 应付账款 | J44: 应付账款 | K44: =IF(I44<>J44,"是","否") -> 否 | L44: 应付账款
A45: 2202006 | B45: X有限公司 | C45: 0 | D45: 677366.39 | E45: 0 | F45: 1205385 | G45: 0 | H45: 1882751.4 | I45: 应付账款 | J45: 应付账款 | K45: =IF(I45<>J45,"是","否") -> 否 | L45: 应付账款
A46: 2202007 | B46: N有限公司 | C46: 0 | D46: 788776.49 | E46: 720000 | F46: 420360 | G46: 0 | H46: 489136.49 | I46: 应付账款 | J46: 应付账款 | K46: =IF(I46<>J46,"是","否") -> 否 | L46: 应付账款
A47: 2202008 | B47: Y有限公司 | C47: 0 | D47: 585576.87 | E47: 820000 | F47: 524320 | G47: 0 | H47: 289896.87 | I47: 应付账款 | J47: 应付账款 | K47: =IF(I47<>J47,"是","否") -> 否 | L47: 应付账款
A48: 2202009 | B48: Z有限公司 | C48: 0 | D48: 838665.86 | E48: 1220000 | F48: 621952 | G48: 0 | H48: 240617.86 | I48: 应付账款 | J48: 应付账款 | K48: =IF(I48<>J48,"是","否") -> 否 | L48: 应付账款
A49: 2221 | B49: 应交税费 | C49: 0 | D49: 129883.78 | E49: 5299995.7 | F49: 5832825.1 | G49: 0 | H49: 662713.12 | K49: =IF(I49<>J49,"是","否") -> 否
A50: 2221001 | B50: 增值税 | C50: 0 | D50: 0 | E50: 4563819 | F50: 4563819 | G50: 0 | H50: 0 | K50: =IF(I50<>J50,"是","否") -> 否
A51: 222100101 | B51: 进项税额 | C51: 0 | D51: 0 | E51: 1111019 | F51: 1111019 | G51: 0 | H51: 0 | K51: =IF(I51<>J51,"是","否") -> 否 | L51: 应交税费
A52: 222100102 | B52: 销项税额 | C52: 0 | D52: 0 | E52: 1726400 | F52: 1726400 | G52: 0 | H52: 0 | K52: =IF(I52<>J52,"是","否") -> 否 | L52: 应交税费
A53: 222100103 | B53: 转出未交增值税 | C53: 0 | D53: 0 | E53: 1726400 | F53: 1726400 | G53: 0 | H53: 0 | K53: =IF(I53<>J53,"是","否") -> 否 | L53: 应交税费
A54: 2221002 | B54: 未交增值税 | C54: 0 | D54: 16516.49 | E54: 557849.49 | F54: 615381 | G54: 0 | H54: 74048 | I54: 应交税费 | J54: 应交税费 | K54: =IF(I54<>J54,"是","否") -> 否 | L54: 应交税费 | M54: 增值税
A55: 2221003 | B55: 城市维护建设税 | C55: 0 | D55: 1156.15 | E55: 39049.46 | F55: 43076.67 | G55: 0 | H55: 5183.36 | I55: 应交税费 | J55: 应交税费 | K55: =IF(I55<>J55,"是","否") -> 否 | L55: 应交税费 | M55: 城市维护建设税
A56: 2221004 | B56: 教育费附加 | C56: 0 | D56: 495.49 | E56: 16735.48 | F56: 18461.43 | G56: 0 | H56: 2221.44 | I56: 应交税费 | J56: 应交税费 | K56: =IF(I56<>J56,"是","否") -> 否 | L56: 应交税费 | M56: 教育费附加
A57: 2221005 | B57: 地方教育费附加 | C57: 0 | D57: 330.33 | E57: 11156.99 | F57: 12307.62 | G57: 0 | H57: 1480.96 | I57: 应交税费 | J57: 应交税费 | K57: =IF(I57<>J57,"是","否") -> 否 | L57: 应交税费 | M57: 地方教育费附加
A58: 2221006 | B58: 企业所得税 | C58: 0 | D58: 111385.32 | E58: 111385.32 | F58: 579779.36 | H58: 579779.36 | I58: 应交税费 | J58: 应交税费 | K58: =IF(I58<>J58,"是","否") -> 否 | L58: 应交税费 | M58: 企业所得税
A59: 2241 | B59: 其他应付款 | C59: 0 | D59: 345998.65 | E59: 7000 | F59: 5000 | G59: 0 | H59: 343998.65 | K59: =IF(I59<>J59,"是","否") -> 否
A60: 2241001 | B60: 甲 | C60: 0 | D60: 58834.45 | E60: 0 | F60: 0 | G60: 0 | H60: 58834.45 | I60: 其他应付款 | J60: 其他应付款 | K60: =IF(I60<>J60,"是","否") -> 否 | L60: 其他应付款
A61: 2241002 | B61: 乙 | C61: 0 | D61: 76440.34 | E61: 0 | F61: 0 | G61: 0 | H61: 76440.34 | I61: 其他应付款 | J61: 其他应付款 | K61: =IF(I61<>J61,"是","否") -> 否 | L61: 其他应付款
A62: 2241003 | B62: 丙 | C62: 0 | D62: 48876.38 | E62: 0 | F62: 5000 | G62: 0 | H62: 53876.38 | I62: 其他应付款 | J62: 其他应付款 | K62: =IF(I62<>J62,"是","否") -> 否 | L62: 其他应付款
A63: 2241004 | B63: 丁 | C63: 0 | D63: 46739.28 | E63: 0 | F63: 0 | G63: 0 | H63: 46739.28 | I63: 其他应付款 | J63: 其他应付款 | K63: =IF(I63<>J63,"是","否") -> 否 | L63: 其他应付款
A64: 2241005 | B64: 戊 | C64: 0 | D64: 33809.67 | E64: 0 | F64: 0 | G64: 0 | H64: 33809.67 | I64: 其他应付款 | J64: 其他应付款 | K64: =IF(I64<>J64,"是","否") -> 否 | L64: 其他应付款
A65: 2241006 | B65: 申 | C65: 0 | D65: 28606.34 | E65: 0 | F65: 0 | G65: 0 | H65: 28606.34 | I65: 其他应付款 | J65: 其他应付款 | K65: =IF(I65<>J65,"是","否") -> 否 | L65: 其他应付款
A66: 2241007 | B66: 亥 | C66: 0 | D66: 52692.19 | E66: 7000 | F66: 0 | G66: 0 | H66: 45692.19 | I66: 其他应付款 | J66: 其他应付款 | K66: =IF(I66<>J66,"是","否") -> 否 | L66: 其他应付款
A67: 3001 | B67: 实收资本 | C67: 0 | D67: 10000000 | E67: 0 | F67: 0 | G67: 0 | H67: 10000000 | K67: =IF(I67<>J67,"是","否") -> 否
A68: 3001001 | B68: AAA股东 | C68: 0 | D68: 5000000 | E68: 0 | F68: 0 | G68: 0 | H68: 5000000 | I68: 实收资本 | J68: 实收资本 | K68: =IF(I68<>J68,"是","否") -> 否 | L68: 实收资本
A69: 3001002 | B69: BBB股东 | C69: 0 | D69: 5000000 | E69: 0 | F69: 0 | G69: 0 | H69: 5000000 | I69: 实收资本 | J69: 实收资本 | K69: =IF(I69<>J69,"是","否") -> 否 | L69: 实收资本
A70: 3103 | B70: 本年利润 | C70: 0 | D70: 0 | E70: 13280000 | F70: 13280000 | G70: 0 | H70: 0 | K70: =IF(I70<>J70,"是","否") -> 否
A71: 3104 | B71: 利润分配 | C71: 0 | D71: 3530623.1 | E71: 0 | F71: 1739289.3 | H71: 5269912.5 | K71: =IF(I71<>J71,"是","否") -> 否
A72: 3104002 | B72: 未分配利润 | C72: 0 | D72: 3530623.1 | E72: 0 | F72: 1739289.3 | G72: 0 | H72: 5269912.5 | I72: 未分配利润 | J72: 未分配利润 | K72: =IF(I72<>J72,"是","否") -> 否 | L72: 未分配利润
A73: 5001 | B73: 主营业务收入 | C73: 0 | D73: 0 | E73: 13280000 | F73: 13280000 | G73: 0 | H73: 0 | I73: 营业收入 | J73: 营业收入 | K73: =IF(I73<>J73,"是","否") -> 否 | L73: 营业收入
A74: 5401 | B74: 主营业务成本 | C74: 0 | D74: 0 | E74: 10878000 | F74: 10878000 | G74: 0 | H74: 0 | I74: 营业成本 | K74: =IF(I74<>J74,"是","否") -> 是 | L74: 营业成本
A75: 5403 | B75: 税金及附加 | C75: 0 | D75: 0 | E75: 73845.72 | F75: 73845.72 | G75: 0 | H75: 0 | K75: =IF(I75<>J75,"是","否") -> 否
A76: 5403001 | B76: 城市维护建设税 | C76: 0 | D76: 0 | E76: 43076.67 | F76: 43076.67 | G76: 0 | H76: 0 | I76: 税金及附加 | J76: 税金及附加 | K76: =IF(I76<>J76,"是","否") -> 否 | L76: 税金及附加 | M76: 税-城建税
A77: 5403002 | B77: 教育费附加 | C77: 0 | D77: 0 | E77: 18461.43 | F77: 18461.43 | G77: 0 | H77: 0 | I77: 税金及附加 | J77: 税金及附加 | K77: =IF(I77<>J77,"是","否") -> 否 | L77: 税金及附加 | M77: 税-教育
A78: 5403003 | B78: 地方教育费附加 | C78: 0 | D78: 0 | E78: 12307.62 | F78: 12307.62 | G78: 0 | H78: 0 | I78: 税金及附加 | J78: 税金及附加 | K78: =IF(I78<>J78,"是","否") -> 否 | L78: 税金及附加 | M78: 税-地方教育
A79: 5602 | B79: 管理费用 | C79: 0 | D79: 0 | E79: 17635 | F79: 17635 | G79: 0 | H79: 0 | K79: =IF(I79<>J79,"是","否") -> 否
A80: 5602001 | B80: 折旧费 | C80: 0 | D80: 0 | E80: 12360 | F80: 12360 | G80: 0 | H80: 0 | I80: 管理费用 | J80: 管理费用 | K80: =IF(I80<>J80,"是","否") -> 否 | L80: 管理费用
A81: 5602002 | B81: 办公费 | C81: 0 | D81: 0 | E81: 5275 | F81: 5275 | G81: 0 | H81: 0 | I81: 管理费用 | K81: =IF(I81<>J81,"是","否") -> 是 | L81: 管理费用
A82: 5603 | B82: 财务费用 | C82: 0 | D82: 0 | E82: -8549.38 | F82: -8549.38 | G82: 0 | H82: 0 | K82: =IF(I82<>J82,"是","否") -> 否
A83: 5603001 | B83: 银行手续费 | C83: 0 | D83: 0 | E83: 200 | F83: 200 | G83: 0 | H83: 0 | I83: 财务费用 | J83: 财务费用 | K83: =IF(I83<>J83,"是","否") -> 否 | L83: 财务费用
A84: 5603002 | B84: 利息收入 | C84: 0 | D84: 0 | E84: -8749.38 | F84: -8749.38 | G84: 0 | H84: 0 | I84: 财务费用 | J84: 财务费用 | K84: =IF(I84<>J84,"是","否") -> 否 | L84: 财务费用
A85: 5801 | B85: 所得税费用 | C85: 0 | D85: 0 | E85: 579779.36 | F85: 579779.36 | G85: 0 | H85: 0 | I85: 所得税费用 | J85: 所得税费用 | K85: =IF(I85<>J85,"是","否") -> 否 | L85: 所得税费用 | M85: 税-企所
B86: N有限公司 | G86: -334588.9 | H86: 0 | J86: 预付款项 | K86: =IF(I86<>J86,"是","否") -> 是
B87: N有限公司 | G87: 0 | H87: -334588.9 | J87: 应付账款 | K87: =IF(I87<>J87,"是","否") -> 是
B88: 主营业务成本 | E88: 10789000 | F88: 10789000 | J88: 营业成本 | K88: =IF(I88<>J88,"是","否") -> 是
B89: 研发费用-直接投入 | E89: 89000 | F89: 89000 | J89: 研发费用 | K89: =IF(I89<>J89,"是","否") -> 是
B90: 管理费用-办公费 | E90: 5175 | F90: 5175 | J90: 管理费用 | K90: =IF(I90<>J90,"是","否") -> 是
B91: 研发费用-办公费 | E91: 100 | F91: 100 | J91: 研发费用 | K91: =IF(I91<>J91,"是","否") -> 是
K92: =IF(I92<>J92,"是","否") -> 否
K93: =IF(I93<>J93,"是","否") -> 否
K94: =IF(I94<>J94,"是","否") -> 否
K95: =IF(I95<>J95,"是","否") -> 否
K96: =IF(I96<>J96,"是","否") -> 否
K97: =IF(I97<>J97,"是","否") -> 否
K98: =IF(I98<>J98,"是","否") -> 否
K99: =IF(I99<>J99,"是","否") -> 否
K100: =IF(I100<>J100,"是","否") -> 否
...

Sheet 序时账
A1: 涉及科目 | B1: 日期 | C1: 凭证字号 | D1: 科目编码 | E1: 科目名称 | F1: 摘要 | G1: 借方金额 | H1: 贷方金额 | I1: 抽查项目 | J1: 对方科目 | K1: 现金流分类 | L1: 测算项目 | M1: 测算金额
A2: {=_xlfn.TEXTJOIN(",", TRUE, _xlfn.UNIQUE(IF((序时账[日期]=B2)*(序时账[凭证字号]=C2), 序时账[科目编码], "")))} -> 5602001,1602002 | B2: 45667 | C2: 1 | D2: 5602001 | E2: 管理费用-折旧费 | F2: 计提折旧费用 | G2: 1030 | H2: 0 | I2: =IF(F2<>"结转本期损益",_xlfn.XLOOKUP(D2,科目余额表[科目编码],科目余额表[抽查项目],"无匹配"),"期间结转") -> 管理费用 | J2: {=_xlfn.TEXTJOIN(",", TRUE, _xlfn.UNIQUE(IF((序时账[日期]=B2)*(序时账[凭证字号]=C2)*IF(G2=0,序时账[借方金额]<>0,序时账[借方金额]=0)*(序时账[科目编码]<>D2), 序时账[科目名称], "")))} -> 电脑
A3: {=_xlfn.TEXTJOIN(",", TRUE, _xlfn.UNIQUE(IF((序时账[日期]=B3)*(序时账[凭证字号]=C3), 序时账[科目编码], "")))} -> 5602001,1602002 | B3: 45667 | C3: 1 | D3: 1602002 | E3: 电脑 | F3: 计提折旧费用 | G3: 0 | H3: 1030 | I3: =IF(F3<>"结转本期损益",_xlfn.XLOOKUP(D3,科目余额表[科目编码],科目余额表[抽查项目],"无匹配"),"期间结转") -> 固定资产 | J3: {=_xlfn.TEXTJOIN(",", TRUE, _xlfn.UNIQUE(IF((序时账[日期]=B3)*(序时账[凭证字号]=C3)*IF(G3=0,序时账[借方金额]<>0,序时账[借方金额]=0)*(序时账[科目编码]<>D3), 序时账[科目名称], "")))} -> 管理费用-折旧费
A4: {=_xlfn.TEXTJOIN(",", TRUE, _xlfn.UNIQUE(IF((序时账[日期]=B4)*(序时账[凭证字号]=C4), 序时账[科目编码], "")))} -> 1122001,5001,222100102 | B4: 45672 | C4: 2 | D4: 1122001 | E4: 应收账款-A有限公司 | F4: 销售收入 | G4: 1141300 | H4: 0 | I4: =IF(F4<>"结转本期损益",_xlfn.XLOOKUP(D4,科目余额表[科目编码],科目余额表[抽查项目],"无匹配"),"期间结转") -> 应收账款 | J4: {=_xlfn.TEXTJOIN(",", TRUE, _xlfn.UNIQUE(IF((序时账[日期]=B4)*(序时账[凭证字号]=C4)*IF(G4=0,序时账[借方金额]<>0,序时账[借方金额]=0)*(序时账[科目编码]<>D4), 序时账[科目名称], "")))} -> 主营业务收入,销项税额
A5: {=_xlfn.TEXTJOIN(",", TRUE, _xlfn.UNIQUE(IF((序时账[日期]=B5)*(序时账[凭证字号]=C5), 序时账[科目编码], "")))} -> 1122001,5001,222100102 | B5: 45672 | C5: 2 | D5: 5001 | E5: 主营业务收入 | F5: 销售收入 | G5: 0 | H5: 1010000 | I5: =IF(F5<>"结转本期损益",_xlfn.XLOOKUP(D5,科目余额表[科目编码],科目余额表[抽查项目],"无匹配"),"期间结转") -> 营业收入 | J5: {=_xlfn.TEXTJOIN(",", TRUE, _xlfn.UNIQUE(IF((序时账[日期]=B5)*(序时账[凭证字号]=C5)*IF(G5=0,序时账[借方金额]<>0,序时账[借方金额]=0)*(序时账[科目编码]<>D5), 序时账[科目名称], "")))} -> 应收账款-A有限公司
A6: {=_xlfn.TEXTJOIN(",", TRUE, _xlfn.UNIQUE(IF((序时账[日期]=B6)*(序时账[凭证字号]=C6), 序时账[科目编码], "")))} -> 1122001,5001,222100102 | B6: 45672 | C6: 2 | D6: 222100102 | E6: 销项税额 | F6: 销售收入 | G6: 0 | H6: 131300 | I6: =IF(F6<>"结转本期损益",_xlfn.XLOOKUP(D6,科目余额表[科目编码],科目余额表[抽查项目],"无匹配"),"期间结转") -> 应交税费 | J6: {=_xlfn.TEXTJOIN(",", TRUE, _xlfn.UNIQUE(IF((序时账[日期]=B6)*(序时账[凭证字号]=C6)*IF(G6=0,序时账[借方金额]<>0,序时账[借方金额]=0)*(序时账[科目编码]<>D6), 序时账[科目名称], "")))} -> 应收账款-A有限公司
A7: {=_xlfn.TEXTJOIN(",", TRUE, _xlfn.UNIQUE(IF((序时账[日期]=B7)*(序时账[凭证字号]=C7), 序时账[科目编码], "")))} -> 5401,1405001 | B7: 45672 | C7: 3 | D7: 5401 | E7: 主营业务成本 | F7: 结转销售成本 | G7: 901000 | H7: 0 | I7: =IF(F7<>"结转本期损益",_xlfn.XLOOKUP(D7,科目余额表[科目编码],科目余额表[抽查项目],"无匹配"),"期间结转") -> 营业成本 | J7: {=_xlfn.TEXTJOIN(",", TRUE, _xlfn.UNIQUE(IF((序时账[日期]=B7)*(序时账[凭证字号]=C7)*IF(G7=0,序时账[借方金额]<>0,序时账[借方金额]=0)*(序时账[科目编码]<>D7), 序时账[科目名称], "")))} -> R商品
A8: {=_xlfn.TEXTJOIN(",", TRUE, _xlfn.UNIQUE(IF((序时账[日期]=B8)*(序时账[凭证字号]=C8), 序时账[科目编码], "")))} -> 5401,1405001 | B8: 45672 | C8: 3 | D8: 1405001 | E8: R商品 | F8: 结转销售成本 | G8: 0 | H8: 901000 | I8: =IF(F8<>"结转本期损益",_xlfn.XLOOKUP(D8,科目余额表[科目编码],科目余额表[抽查项目],"无匹配"),"期间结转") -> 存货 | J8: {=_xlfn.TEXTJOIN(",", TRUE, _xlfn.UNIQUE(IF((序时账[日期]=B8)*(序时账[凭证字号]=C8)*IF(G8=0,序时账[借方金额]<>0,序时账[借方金额]=0)*(序时账[科目编码]<>D8), 序时账[科目名称], "")))} -> 主营业务成本
A9: {=_xlfn.TEXTJOIN(",", TRUE, _xlfn.UNIQUE(IF((序时账[日期]=B9)*(序时账[凭证字号]=C9), 序时账[科目编码], "")))} -> 1002001,1122001 | B9: 45677 | C9: 4 | D9: 1002001 | E9: ABC银行账户 | F9: 收货款 | G9: 2030000 | H9: 0 | I9: =IF(F9<>"结转本期损益",_xlfn.XLOOKUP(D9,科目余额表[科目编码],科目余额表[抽查项目],"无匹配"),"期间结转") -> 银行存款 | J9: {=_xlfn.TEXTJOIN(",", TRUE, _xlfn.UNIQUE(IF((序时账[日期]=B9)*(序时账[凭证字号]=C9)*IF(G9=0,序时账[借方金额]<>0,序时账[借方金额]=0)*(序时账[科目编码]<>D9), 序时账[科目名称], "")))} -> 应收账款-A有限公司 | K9: 应收账款-A有限公司
A10: {=_xlfn.TEXTJOIN(",", TRUE, _xlfn.UNIQUE(IF((序时账[日期]=B10)*(序时账[凭证字号]=C10), 序时账[科目编码], "")))} -> 1002001,1122001 | B10: 45677 | C10: 4 | D10: 1122001 | E10: 应收账款-A有限公司 | F10: 收货款 | G10: 0 | H10: 2030000 | I10: =IF(F10<>"结转本期损益",_xlfn.XLOOKUP(D10,科目余额表[科目编码],科目余额表[抽查项目],"无匹配"),"期间结转") -> 应收账款 | J10: {=_xlfn.TEXTJOIN(",", TRUE, _xlfn.UNIQUE(IF((序时账[日期]=B10)*(序时账[凭证字号]=C10)*IF(G10=0,序时账[借方金额]<>0,序时账[借方金额]=0)*(序时账[科目编码]<>D10), 序时账[科目名称], "")))} -> ABC银行账户
A11: {=_xlfn.TEXTJOIN(",", TRUE, _xlfn.UNIQUE(IF((序时账[日期]=B11)*(序时账[凭证字号]=C11), 序时账[科目编码], "")))} -> 1405001,222100101,2202001 | B11: 45677 | C11: 5 | D11: 1405001 | E11: R商品 | F11: 购货 | G11: 490800 | H11: 0 | I11: =IF(F11<>"结转本期损益",_xlfn.XLOOKUP(D11,科目余额表[科目编码],科目余额表[抽查项目],"无匹配"),"期间结转") -> 存货 | J11: {=_xlfn.TEXTJOIN(",", TRUE, _xlfn.UNIQUE(IF((序时账[日期]=B11)*(序时账[凭证字号]=C11)*IF(G11=0,序时账[借方金额]<>0,序时账[借方金额]=0)*(序时账[科目编码]<>D11), 序时账[科目名称], "")))} -> 应付账款-T有限公司
A12: {=_xlfn.TEXTJOIN(",", TRUE, _xlfn.UNIQUE(IF((序时账[日期]=B12)*(序时账[凭证字号]=C12), 序时账[科目编码], "")))} -> 1405001,222100101,2202001 | B12: 45677 | C12: 5 | D12: 222100101 | E12: 进项税额 | F12: 购货 | G12: 63804 | H12: 0 | I12: =IF(F12<>"结转本期损益",_xlfn.XLOOKUP(D12,科目余额表[科目编码],科目余额表[抽查项目],"无匹配"),"期间结转") -> 应交税费 | J12: {=_xlfn.TEXTJOIN(",", TRUE, _xlfn.UNIQUE(IF((序时账[日期]=B12)*(序时账[凭证字号]=C12)*IF(G12=0,序时账[借方金额]<>0,序时账[借方金额]=0)*(序时账[科目编码]<>D12), 序时账[科目名称], "")))} -> 应付账款-T有限公司
A13: {=_xlfn.TEXTJOIN(",", TRUE, _xlfn.UNIQUE(IF((序时账[日期]=B13)*(序时账[凭证字号]=C13), 序时账[科目编码], "")))} -> 1405001,222100101,2202001 | B13: 45677 | C13: 5 | D13: 2202001 | E13: 应付账款-T有限公司 | F13: 购货 | G13: 0 | H13: 554604 | I13: =IF(F13<>"结转本期损益",_xlfn.XLOOKUP(D13,科目余额表[科目编码],科目余额表[抽查项目],"无匹配"),"期间结转") -> 应付账款 | J13: {=_xlfn.TEXTJOIN(",", TRUE, _xlfn.UNIQUE(IF((序时账[日期]=B13)*(序时账[凭证字号]=C13)*IF(G13=0,序时账[借方金额]<>0,序时账[借方金额]=0)*(序时账[科目编码]<>D13), 序时账[科目名称], "")))} -> R商品,进项税额
A14: {=_xlfn.TEXTJOIN(",", TRUE, _xlfn.UNIQUE(IF((序时账[日期]=B14)*(序时账[凭证字号]=C14), 序时账[科目编码], "")))} -> 1002001,2202001 | B14: 45677 | C14: 6 | D14: 1002001 | E14: ABC银行账户 | F14: 付货款 | G14: 1012000 | H14: 0 | I14: =IF(F14<>"结转本期损益",_xlfn.XLOOKUP(D14,科目余额表[科目编码],科目余额表[抽查项目],"无匹配"),"期间结转") -> 银行存款 | J14: {=_xlfn.TEXTJOIN(",", TRUE, _xlfn.UNIQUE(IF((序时账[日期]=B14)*(序时账[凭证字号]=C14)*IF(G14=0,序时账[借方金额]<>0,序时账[借方金额]=0)*(序时账[科目编码]<>D14), 序时账[科目名称], "")))} -> 应付账款-T有限公司 | K14: 应付账款-T有限公司
A15: {=_xlfn.TEXTJOIN(",", TRUE, _xlfn.UNIQUE(IF((序时账[日期]=B15)*(序时账[凭证字号]=C15), 序时账[科目编码], "")))} -> 1002001,2202001 | B15: 45677 | C15: 6 | D15: 2202001 | E15: 应付账款-T有限公司 | F15: 付货款 | G15: 0 | H15: 1012000 | I15: =IF(F15<>"结转本期损益",_xlfn.XLOOKUP(D15,科目余额表[科目编码],科目余额表[抽查项目],"无匹配"),"期间结转") -> 应付账款 | J15: {=_xlfn.TEXTJOIN(",", TRUE, _xlfn.UNIQUE(IF((序时账[日期]=B15)*(序时账[凭证字号]=C15)*IF(G15=0,序时账[借方金额]<>0,序时账[借方金额]=0)*(序时账[科目编码]<>D15), 序时账[科目名称], "")))} -> ABC银行账户
A16: {=_xlfn.TEXTJOIN(",", TRUE, _xlfn.UNIQUE(IF((序时账[日期]=B16)*(序时账[凭证字号]=C16), 序时账[科目编码], "")))} -> 222100102,222100103,222100101,2221002 | B16: 45682 | C16: 7 | D16: 222100102 | E16: 销项税额 | F16: 转出未交增值税 | G16: 131300 | H16: 0 | I16: =IF(F16<>"结转本期损益",_xlfn.XLOOKUP(D16,科目余额表[科目编码],科目余额表[抽查项目],"无匹配"),"期间结转") -> 应交税费 | J16: {=_xlfn.TEXTJOIN(",", TRUE, _xlfn.UNIQUE(IF((序时账[日期]=B16)*(序时账[凭证字号]=C16)*IF(G16=0,序时账[借方金额]<>0,序时账[借方金额]=0)*(序时账[科目编码]<>D16), 序时账[科目名称], "")))} -> 转出未交增值税,进项税额,未交增值税
A17: {=_xlfn.TEXTJOIN(",", TRUE, _xlfn.UNIQUE(IF((序时账[日期]=B17)*(序时账[凭证字号]=C17), 序时账[科目编码], "")))} -> 222100102,222100103,222100101,2221002 | B17: 45682 | C17: 7 | D17: 222100103 | E17: 转出未交增值税 | F17: 转出未交增值税 | G17: 0 | H17: 131300 | I17: =IF(F17<>"结转本期损益",_xlfn.XLOOKUP(D17,科目余额表[科目编码],科目余额表[抽查项目],"无匹配"),"期间结转") -> 应交税费 | J17: {=_xlfn.TEXTJOIN(",", TRUE, _xlfn.UNIQUE(IF((序时账[日期]=B17)*(序时账[凭证字号]=C17)*IF(G17=0,序时账[借方金额]<>0,序时账[借方金额]=0)*(序时账[科目编码]<>D17), 序时账[科目名称], "")))} -> 销项税额
A18: {=_xlfn.TEXTJOIN(",", TRUE, _xlfn.UNIQUE(IF((序时账[日期]=B18)*(序时账[凭证字号]=C18), 序时账[科目编码], "")))} -> 222100102,222100103,222100101,2221002 | B18: 45682 | C18: 7 | D18: 222100103 | E18: 转出未交增值税 | F18: 转出未交增值税 | G18: 63804 | H18: 0 | I18: =IF(F18<>"结转本期损益",_xlfn.XLOOKUP(D18,科目余额表[科目编码],科目余额表[抽查项目],"无匹配"),"期间结转") -> 应交税费 | J18: {=_xlfn.TEXTJOIN(",", TRUE, _xlfn.UNIQUE(IF((序时账[日期]=B18)*(序时账[凭证字号]=C18)*IF(G18=0,序时账[借方金额]<>0,序时账[借方金额]=0)*(序时账[科目编码]<>D18), 序时账[科目名称], "")))} -> 进项税额,未交增值税
A19: {=_xlfn.TEXTJOIN(",", TRUE, _xlfn.UNIQUE(IF((序时账[日期]=B19)*(序时账[凭证字号]=C19), 序时账[科目编码], "")))} -> 222100102,222100103,222100101,2221002 | B19: 45682 | C19: 7 | D19: 222100101 | E19: 进项税额 | F19: 转出未交增值税 | G19: 0 | H19: 63804 | I19: =IF(F19<>"结转本期损益",_xlfn.XLOOKUP(D19,科目余额表[科目编码],科目余额表[抽查项目],"无匹配"),"期间结转") -> 应交税费 | J19: {=_xlfn.TEXTJOIN(",", TRUE, _xlfn.UNIQUE(IF((序时账[日期]=B19)*(序时账[凭证字号]=C19)*IF(G19=0,序时账[借方金额]<>0,序时账[借方金额]=0)*(序时账[科目编码]<>D19), 序时账[科目名称], "")))} -> 销项税额,转出未交增值税
A20: {=_xlfn.TEXTJOIN(",", TRUE, _xlfn.UNIQUE(IF((序时账[日期]=B20)*(序时账[凭证字号]=C20), 序时账[科目编码], "")))} -> 222100102,222100103,222100101,2221002 | B20: 45682 | C20: 7 | D20: 222100103 | E20: 转出未交增值税 | F20: 转出未交增值税 | G20: 67496 | H20: 0 | I20: =IF(F20<>"结转本期损益",_xlfn.XLOOKUP(D20,科目余额表[科目编码],科目余额表[抽查项目],"无匹配"),"期间结转") -> 应交税费 | J20: {=_xlfn.TEXTJOIN(",", TRUE, _xlfn.UNIQUE(IF((序时账[日期]=B20)*(序时账[凭证字号]=C20)*IF(G20=0,序时账[借方金额]<>0,序时账[借方金额]=0)*(序时账[科目编码]<>D20), 序时账[科目名称], "")))} -> 进项税额,未交增值税
A21: {=_xlfn.TEXTJOIN(",", TRUE, _xlfn.UNIQUE(IF((序时账[日期]=B21)*(序时账[凭证字号]=C21), 序时账[科目编码], "")))} -> 222100102,222100103,222100101,2221002 | B21: 45682 | C21: 7 | D21: 2221002 | E21: 未交增值税 | F21: 转出未交增值税 | G21: 0 | H21: 67496 | I21: =IF(F21<>"结转本期损益",_xlfn.XLOOKUP(D21,科目余额表[科目编码],科目余额表[抽查项目],"无匹配"),"期间结转") -> 应交税费 | J21: {=_xlfn.TEXTJOIN(",", TRUE, _xlfn.UNIQUE(IF((序时账[日期]=B21)*(序时账[凭证字号]=C21)*IF(G21=0,序时账[借方金额]<>0,序时账[借方金额]=0)*(序时账[科目编码]<>D21), 序时账[科目名称], "")))} -> 销项税额,转出未交增值税
A22: {=_xlfn.TEXTJOIN(",", TRUE, _xlfn.UNIQUE(IF((序时账[日期]=B22)*(序时账[凭证字号]=C22), 序时账[科目编码], "")))} -> 5403001,5403002,5403003,2221003,2221004,2221005 | B22: 45682 | C22: 8 | D22: 5403001 | E22: 城市维护建设税 | F22: 增值税附税 | G22: 4724.72 | H22: 0 | I22: =IF(F22<>"结转本期损益",_xlfn.XLOOKUP(D22,科目余额表[科目编码],科目余额表[抽查项目],"无匹配"),"期间结转") -> 税金及附加 | J22: {=_xlfn.TEXTJOIN(",", TRUE, _xlfn.UNIQUE(IF((序时账[日期]=B22)*(序时账[凭证字号]=C22)*IF(G22=0,序时账[借方金额]<>0,序时账[借方金额]=0)*(序时账[科目编码]<>D22), 序时账[科目名称], "")))} -> 城市维护建设税,教育费附加,地方教育费附加
A23: {=_xlfn.TEXTJOIN(",", TRUE, _xlfn.UNIQUE(IF((序时账[日期]=B23)*(序时账[凭证字号]=C23), 序时账[科目编码], "")))} -> 5403001,5403002,5403003,2221003,2221004,2221005 | B23: 45682 | C23: 8 | D23: 5403002 | E23: 教育费附加 | F23: 增值税附税 | G23: 2024.88 | H23: 0 | I23: =IF(F23<>"结转本期损益",_xlfn.XLOOKUP(D23,科目余额表[科目编码],科目余额表[抽查项目],"无匹配"),"期间结转") -> 税金及附加 | J23: {=_xlfn.TEXTJOIN(",", TRUE, _xlfn.UNIQUE(IF((序时账[日期]=B23)*(序时账[凭证字号]=C23)*IF(G23=0,序时账[借方金额]<>0,序时账[借方金额]=0)*(序时账[科目编码]<>D23), 序时账[科目名称], "")))} -> 城市维护建设税,教育费附加,地方教育费附加
A24: {=_xlfn.TEXTJOIN(",", TRUE, _xlfn.UNIQUE(IF((序时账[日期]=B24)*(序时账[凭证字号]=C24), 序时账[科目编码], "")))} -> 5403001,5403002,5403003,2221003,2221004,2221005 | B24: 45682 | C24: 8 | D24: 5403003 | E24: 地方教育费附加 | F24: 增值税附税 | G24: 1349.92 | H24: 0 | I24: =IF(F24<>"结转本期损益",_xlfn.XLOOKUP(D24,科目余额表[科目编码],科目余额表[抽查项目],"无匹配"),"期间结转") -> 税金及附加 | J24: {=_xlfn.TEXTJOIN(",", TRUE, _xlfn.UNIQUE(IF((序时账[日期]=B24)*(序时账[凭证字号]=C24)*IF(G24=0,序时账[借方金额]<>0,序时账[借方金额]=0)*(序时账[科目编码]<>D24), 序时账[科目名称], "")))} -> 城市维护建设税,教育费附加,地方教育费附加
A25: {=_xlfn.TEXTJOIN(",", TRUE, _xlfn.UNIQUE(IF((序时账[日期]=B25)*(序时账[凭证字号]=C25), 序时账[科目编码], "")))} -> 5403001,5403002,5403003,2221003,2221004,2221005 | B25: 45682 | C25: 8 | D25: 2221003 | E25: 城市维护建设税 | F25: 增值税附税 | G25: 0 | H25: 4724.72 | I25: =IF(F25<>"结转本期损益",_xlfn.XLOOKUP(D25,科目余额表[科目编码],科目余额表[抽查项目],"无匹配"),"期间结转") -> 应交税费 | J25: {=_xlfn.TEXTJOIN(",", TRUE, _xlfn.UNIQUE(IF((序时账[日期]=B25)*(序时账[凭证字号]=C25)*IF(G25=0,序时账[借方金额]<>0,序时账[借方金额]=0)*(序时账[科目编码]<>D25), 序时账[科目名称], "")))} -> 城市维护建设税,教育费附加,地方教育费附加
A26: {=_xlfn.TEXTJOIN(",", TRUE, _xlfn.UNIQUE(IF((序时账[日期]=B26)*(序时账[凭证字号]=C26), 序时账[科目编码], "")))} -> 5403001,5403002,5403003,2221003,2221004,2221005 | B26: 45682 | C26: 8 | D26: 2221004 | E26: 教育费附加 | F26: 增值税附税 | G26: 0 | H26: 2024.88 | I26: =IF(F26<>"结转本期损益",_xlfn.XLOOKUP(D26,科目余额表[科目编码],科目余额表[抽查项目],"无匹配"),"期间结转") -> 应交税费 | J26: {=_xlfn.TEXTJOIN(",", TRUE, _xlfn.UNIQUE(IF((序时账[日期]=B26)*(序时账[凭证字号]=C26)*IF(G26=0,序时账[借方金额]<>0,序时账[借方金额]=0)*(序时账[科目编码]<>D26), 序时账[科目名称], "")))} -> 城市维护建设税,教育费附加,地方教育费附加
... A31: {=_xlfn.TEXTJOIN(",", TRUE, _xlfn.UNIQUE(IF((序时账[日期]=B31)*(序时账[凭证字号]=C31), 序时账[科目编码], "")))} -> 2221002,2221003,2221004,2221005,1002001 | B31: 45682 | C31: 9 | D31: 2221005 | E31: 地方教育费附加 | F31: 缴税 | G31: 330.33 | H31: 0 | I31: =IF(F31<>"结转本期损益",_xlfn.XLOOKUP(D31,科目余额表[科目编码],科目余额表[抽查项目],"无匹配"),"期间结转") -> 应交税费 | J31: {=_xlfn.TEXTJOIN(",", TRUE, _xlfn.UNIQUE(IF((序时账[日期]=B31)*(序时账[凭证字号]=C31)*IF(G31=0,序时账[借方金额]<>0,序时账[借方金额]=0)*(序时账[科目编码]<>D31), 序时账[科目名称], "")))} -> ABC银行账户
A32: {=_xlfn.TEXTJOIN(",", TRUE, _xlfn.UNIQUE(IF((序时账[日期]=B32)*(序时账[凭证字号]=C32), 序时账[科目编码], "")))} -> 2221002,2221003,2221004,2221005,1002001 | B32: 45682 | C32: 9 | D32: 1002001 | E32: ABC银行账户 | F32: 缴税 | G32: 0 | H32: 18498.46 | I32: =IF(F32<>"结转本期损益",_xlfn.XLOOKUP(D32,科目余额表[科目编码],科目余额表[抽查项目],"无匹配"),"期间结转") -> 银行存款 | J32: {=_xlfn.TEXTJOIN(",", TRUE, _xlfn.UNIQUE(IF((序时账[日期]=B32)*(序时账[凭证字号]=C32)*IF(G32=0,序时账[借方金额]<>0,序时账[借方金额]=0)*(序时账[科目编码]<>D32), 序时账[科目名称], "")))} -> 未交增值税,城市维护建设税,教育费附加,地方教育费附加 | K32: 未交增值税
A33: {=_xlfn.TEXTJOIN(",", TRUE, _xlfn.UNIQUE(IF((序时账[日期]=B33)*(序时账[凭证字号]=C33), 序时账[科目编码], "")))} -> 2221006,1002001 | B33: 45687 | C33: 10 | D33: 2221006 | E33: 企业所得税 | F33: 缴纳企业所得税 | G33: 111385.32 | H33: 0 | I33: =IF(F33<>"结转本期损益",_xlfn.XLOOKUP(D33,科目余额表[科目编码],科目余额表[抽查项目],"无匹配"),"期间结转") -> 应交税费 | J33: {=_xlfn.TEXTJOIN(",", TRUE, _xlfn.UNIQUE(IF((序时账[日期]=B33)*(序时账[凭证字号]=C33)*IF(G33=0,序时账[借方金额]<>0,序时账[借方金额]=0)*(序时账[科目编码]<>D33), 序时账[科目名称], "")))} -> ABC银行账户
A34: {=_xlfn.TEXTJOIN(",", TRUE, _xlfn.UNIQUE(IF((序时账[日期]=B34)*(序时账[凭证字号]=C34), 序时账[科目编码], "")))} -> 2221006,1002001 | B34: 45687 | C34: 10 | D34: 1002001 | E34: ABC银行账户 | F34: 缴纳企业所得税 | G34: 0 | H34: 111385.32 | I34: =IF(F34<>"结转本期损益",_xlfn.XLOOKUP(D34,科目余额表[科目编码],科目余额表[抽查项目],"无匹配"),"期间结转") -> 银行存款 | J34: {=_xlfn.TEXTJOIN(",", TRUE, _xlfn.UNIQUE(IF((序时账[日期]=B34)*(序时账[凭证字号]=C34)*IF(G34=0,序时账[借方金额]<>0,序时账[借方金额]=0)*(序时账[科目编码]<>D34), 序时账[科目名称], "")))} -> 企业所得税 | K34: 企业所得税
A35: {=_xlfn.TEXTJOIN(",", TRUE, _xlfn.UNIQUE(IF((序时账[日期]=B35)*(序时账[凭证字号]=C35), 序时账[科目编码], "")))} -> 5603001,1002001 | B35: 45687 | C35: 11 | D35: 5603001 | E35: 银行手续费 | F35: 账户管理费 | G35: 200 | H35: 0 | I35: =IF(F35<>"结转本期损益",_xlfn.XLOOKUP(D35,科目余额表[科目编码],科目余额表[抽查项目],"无匹配"),"期间结转") -> 财务费用 | J35: {=_xlfn.TEXTJOIN(",", TRUE, _xlfn.UNIQUE(IF((序时账[日期]=B35)*(序时账[凭证字号]=C35)*IF(G35=0,序时账[借方金额]<>0,序时账[借方金额]=0)*(序时账[科目编码]<>D35), 序时账[科目名称], "")))} -> ABC银行账户
A36: {=_xlfn.TEXTJOIN(",", TRUE, _xlfn.UNIQUE(IF((序时账[日期]=B36)*(序时账[凭证字号]=C36), 序时账[科目编码], "")))} -> 5603001,1002001 | B36: 45687 | C36: 11 | D36: 1002001 | E36: ABC银行账户 | F36: 账户管理费 | G36: 0 | H36: 200 | I36: =IF(F36<>"结转本期损益",_xlfn.XLOOKUP(D36,科目余额表[科目编码],科目余额表[抽查项目],"无匹配"),"期间结转") -> 银行存款 | J36: {=_xlfn.TEXTJOIN(",", TRUE, _xlfn.UNIQUE(IF((序时账[日期]=B36)*(序时账[凭证字号]=C36)*IF(G36=0,序时账[借方金额]<>0,序时账[借方金额]=0)*(序时账[科目编码]<>D36), 序时账[科目名称], "")))} -> 银行手续费 | K36: 银行手续费
A37: {=_xlfn.TEXTJOIN(",", TRUE, _xlfn.UNIQUE(IF((序时账[日期]=B37)*(序时账[凭证字号]=C37), 序时账[科目编码], "")))} -> 5001,3103 | B37: 45687 | C37: 12 | D37: 5001 | E37: 主营业务收入 | F37: 结转本期损益 | G37: 1010000 | H37: 0 | I37: =IF(F37<>"结转本期损益",_xlfn.XLOOKUP(D37,科目余额表[科目编码],科目余额表[抽查项目],"无匹配"),"期间结转") -> 期间结转 | J37: {=_xlfn.TEXTJOIN(",", TRUE, _xlfn.UNIQUE(IF((序时账[日期]=B37)*(序时账[凭证字号]=C37)*IF(G37=0,序时账[借方金额]<>0,序时账[借方金额]=0)*(序时账[科目编码]<>D37), 序时账[科目名称], "")))} -> 本年利润
A38: {=_xlfn.TEXTJOIN(",", TRUE, _xlfn.UNIQUE(IF((序时账[日期]=B38)*(序时账[凭证字号]=C38), 序时账[科目编码], "")))} -> 5001,3103 | B38: 45687 | C38: 12 | D38: 3103 | E38: 本年利润 | F38: 结转本期损益 | G38: 0 | H38: 1010000 | I38: =IF(F38<>"结转本期损益",_xlfn.XLOOKUP(D38,科目余额表[科目编码],科目余额表[抽查项目],"无匹配"),"期间结转") -> 期间结转 | J38: {=_xlfn.TEXTJOIN(",", TRUE, _xlfn.UNIQUE(IF((序时账[日期]=B38)*(序时账[凭证字号]=C38)*IF(G38=0,序时账[借方金额]<>0,序时账[借方金额]=0)*(序时账[科目编码]<>D38), 序时账[科目名称], "")))} -> 主营业务收入
A39: {=_xlfn.TEXTJOIN(",", TRUE, _xlfn.UNIQUE(IF((序时账[日期]=B39)*(序时账[凭证字号]=C39), 序时账[科目编码], "")))} -> 3103,5401,5403001,5403002,5403003,5602001,5603001 | B39: 45687 | C39: 13 | D39: 3103 | E39: 本年利润 | F39: 结转本期损益 | G39: 910329.52 | H39: 0 | I39: =IF(F39<>"结转本期损益",_xlfn.XLOOKUP(D39,科目余额表[科目编码],科目余额表[抽查项目],"无匹配"),"期间结转") -> 期间结转 | J39: {=_xlfn.TEXTJOIN(",", TRUE, _xlfn.UNIQUE(IF((序时账[日期]=B39)*(序时账[凭证字号]=C39)*IF(G39=0,序时账[借方金额]<>0,序时账[借方金额]=0)*(序时账[科目编码]<>D39), 序时账[科目名称], "")))} -> 主营业务成本,城市维护建设税,教育费附加,地方教育费附加,管理费用-折旧费,银行手续费
A40: {=_xlfn.TEXTJOIN(",", TRUE, _xlfn.UNIQUE(IF((序时账[日期]=B40)*(序时账[凭证字号]=C40), 序时账[科目编码], "")))} -> 3103,5401,5403001,5403002,5403003,5602001,5603001 | B40: 45687 | C40: 13 | D40: 5401 | E40: 主营业务成本 | F40: 结转本期损益 | G40: 0 | H40: 901000 | I40: =IF(F40<>"结转本期损益",_xlfn.XLOOKUP(D40,科目余额表[科目编码],科目余额表[抽查项目],"无匹配"),"期间结转") -> 期间结转 | J40: {=_xlfn.TEXTJOIN(",", TRUE, _xlfn.UNIQUE(IF((序时账[日期]=B40)*(序时账[凭证字号]=C40)*IF(G40=0,序时账[借方金额]<>0,序时账[借方金额]=0)*(序时账[科目编码]<>D40), 序时账[科目名称], "")))} -> 本年利润
A41: {=_xlfn.TEXTJOIN(",", TRUE, _xlfn.UNIQUE(IF((序时账[日期]=B41)*(序时账[凭证字号]=C41), 序时账[科目编码], "")))} -> 3103,5401,5403001,5403002,5403003,5602001,5603001 | B41: 45687 | C41: 13 | D41: 5403001 | E41: 城市维护建设税 | F41: 结转本期损益 | G41: 0 | H41: 4724.72 | I41: =IF(F41<>"结转本期损益",_xlfn.XLOOKUP(D41,科目余额表[科目编码],科目余额表[抽查项目],"无匹配"),"期间结转") -> 期间结转 | J41: {=_xlfn.TEXTJOIN(",", TRUE, _xlfn.UNIQUE(IF((序时账[日期]=B41)*(序时账[凭证字号]=C41)*IF(G41=0,序时账[借方金额]<>0,序时账[借方金额]=0)*(序时账[科目编码]<>D41), 序时账[科目名称], "")))} -> 本年利润
A42: {=_xlfn.TEXTJOIN(",", TRUE, _xlfn.UNIQUE(IF((序时账[日期]=B42)*(序时账[凭证字号]=C42), 序时账[科目编码], "")))} -> 3103,5401,5403001,5403002,5403003,5602001,5603001 | B42: 45687 | C42: 13 | D42: 5403002 | E42: 教育费附加 | F42: 结转本期损益 | G42: 0 | H42: 2024.88 | I42: =IF(F42<>"结转本期损益",_xlfn.XLOOKUP(D42,科目余额表[科目编码],科目余额表[抽查项目],"无匹配"),"期间结转") -> 期间结转 | J42: {=_xlfn.TEXTJOIN(",", TRUE, _xlfn.UNIQUE(IF((序时账[日期]=B42)*(序时账[凭证字号]=C42)*IF(G42=0,序时账[借方金额]<>0,序时账[借方金额]=0)*(序时账[科目编码]<>D42), 序时账[科目名称], "")))} -> 本年利润
A43: {=_xlfn.TEXTJOIN(",", TRUE, _xlfn.UNIQUE(IF((序时账[日期]=B43)*(序时账[凭证字号]=C43), 序时账[科目编码], "")))} -> 3103,5401,5403001,5403002,5403003,5602001,5603001 | B43: 45687 | C43: 13 | D43: 5403003 | E43: 地方教育费附加 | F43: 结转本期损益 | G43: 0 | H43: 1349.92 | I43: =IF(F43<>"结转本期损益",_xlfn.XLOOKUP(D43,科目余额表[科目编码],科目余额表[抽查项目],"无匹配"),"期间结转") -> 期间结转 | J43: {=_xlfn.TEXTJOIN(",", TRUE, _xlfn.UNIQUE(IF((序时账[日期]=B43)*(序时账[凭证字号]=C43)*IF(G43=0,序时账[借方金额]<>0,序时账[借方金额]=0)*(序时账[科目编码]<>D43), 序时账[科目名称], "")))} -> 本年利润
A44: {=_xlfn.TEXTJOIN(",", TRUE, _xlfn.UNIQUE(IF((序时账[日期]=B44)*(序时账[凭证字号]=C44), 序时账[科目编码], "")))} -> 3103,5401,5403001,5403002,5403003,5602001,5603001 | B44: 45687 | C44: 13 | D44: 5602001 | E44: 管理费用-折旧费 | F44: 结转本期损益 | G44: 0 | H44: 1030 | I44: =IF(F44<>"结转本期损益",_xlfn.XLOOKUP(D44,科目余额表[科目编码],科目余额表[抽查项目],"无匹配"),"期间结转") -> 期间结转 | J44: {=_xlfn.TEXTJOIN(",", TRUE, _xlfn.UNIQUE(IF((序时账[日期]=B44)*(序时账[凭证字号]=C44)*IF(G44=0,序时账[借方金额]<>0,序时账[借方金额]=0)*(序时账[科目编码]<>D44), 序时账[科目名称], "")))} -> 本年利润
A45: {=_xlfn.TEXTJOIN(",", TRUE, _xlfn.UNIQUE(IF((序时账[日期]=B45)*(序时账[凭证字号]=C45), 序时账[科目编码], "")))} -> 3103,5401,5403001,5403002,5403003,5602001,5603001 | B45: 45687 | C45: 13 | D45: 5603001 | E45: 银行手续费 | F45: 结转本期损益 | G45: 0 | H45: 200 | I45: =IF(F45<>"结转本期损益",_xlfn.XLOOKUP(D45,科目余额表[科目编码],科目余额表[抽查项目],"无匹配"),"期间结转") -> 期间结转 | J45: {=_xlfn.TEXTJOIN(",", TRUE, _xlfn.UNIQUE(IF((序时账[日期]=B45)*(序时账[凭证字号]=C45)*IF(G45=0,序时账[借方金额]<>0,序时账[借方金额]=0)*(序时账[科目编码]<>D45), 序时账[科目名称], "")))} -> 本年利润
A46: {=_xlfn.TEXTJOIN(",", TRUE, _xlfn.UNIQUE(IF((序时账[日期]=B46)*(序时账[凭证字号]=C46), 序时账[科目编码], "")))} -> 5602001,1602002 | B46: 45698 | C46: 1 | D46: 5602001 | E46: 管理费用-折旧费 | F46: 计提折旧费用 | G46: 1030 | H46: 0 | I46: =IF(F46<>"结转本期损益",_xlfn.XLOOKUP(D46,科目余额表[科目编码],科目余额表[抽查项目],"无匹配"),"期间结转") -> 管理费用 | J46: {=_xlfn.TEXTJOIN(",", TRUE, _xlfn.UNIQUE(IF((序时账[日期]=B46)*(序时账[凭证字号]=C46)*IF(G46=0,序时账[借方金额]<>0,序时账[借方金额]=0)*(序时账[科目编码]<>D46), 序时账[科目名称], "")))} -> 电脑
A47: {=_xlfn.TEXTJOIN(",", TRUE, _xlfn.UNIQUE(IF((序时账[日期]=B47)*(序时账[凭证字号]=C47), 序时账[科目编码], "")))} -> 5602001,1602002 | B47: 45698 | C47: 1 | D47: 1602002 | E47: 电脑 | F47: 计提折旧费用 | G47: 0 | H47: 1030 | I47: =IF(F47<>"结转本期损益",_xlfn.XLOOKUP(D47,科目余额表[科目编码],科目余额表[抽查项目],"无匹配"),"期间结转") -> 固定资产 | J47: {=_xlfn.TEXTJOIN(",", TRUE, _xlfn.UNIQUE(IF((序时账[日期]=B47)*(序时账[凭证字号]=C47)*IF(G47=0,序时账[借方金额]<>0,序时账[借方金额]=0)*(序时账[科目编码]<>D47), 序时账[科目名称], "")))} -> 管理费用-折旧费
A48: {=_xlfn.TEXTJOIN(",", TRUE, _xlfn.UNIQUE(IF((序时账[日期]=B48)*(序时账[凭证字号]=C48), 序时账[科目编码], "")))} -> 1122002,5001,222100102 | B48: 45703 | C48: 2 | D48: 1122002 | E48: 应收账款-B有限公司 | F48: 销售收入 | G48: 1152600 | H48: 0 | I48: =IF(F48<>"结转本期损益",_xlfn.XLOOKUP(D48,科目余额表[科目编码],科目余额表[抽查项目],"无匹配"),"期间结转") -> 应收账款 | J48: {=_xlfn.TEXTJOIN(",", TRUE, _xlfn.UNIQUE(IF((序时账[日期]=B48)*(序时账[凭证字号]=C48)*IF(G48=0,序时账[借方金额]<>0,序时账[借方金额]=0)*(序时账[科目编码]<>D48), 序时账[科目名称], "")))} -> 主营业务收入,销项税额
... A52: {=_xlfn.TEXTJOIN(",", TRUE, _xlfn.UNIQUE(IF((序时账[日期]=B52)*(序时账[凭证字号]=C52), 序时账[科目编码], "")))} -> 5401,1405002 | B52: 45703 | C52: 3 | D52: 1405002 | E52: S商品 | F52: 结转销售成本 | G52: 0 | H52: 902000 | I52: =IF(F52<>"结转本期损益",_xlfn.XLOOKUP(D52,科目余额表[科目编码],科目余额表[抽查项目],"无匹配"),"期间结转") -> 存货 | J52: {=_xlfn.TEXTJOIN(",", TRUE, _xlfn.UNIQUE(IF((序时账[日期]=B52)*(序时账[凭证字号]=C52)*IF(G52=0,序时账[借方金额]<>0,序时账[借方金额]=0)*(序时账[科目编码]<>D52), 序时账[科目名称], "")))} -> 主营业务成本
A53: {=_xlfn.TEXTJOIN(",", TRUE, _xlfn.UNIQUE(IF((序时账[日期]=B53)*(序时账[凭证字号]=C53), 序时账[科目编码], "")))} -> 1002002,1122006 | B53: 45708 | C53: 4 | D53: 1002002 | E53: EFG银行账户 | F53: 收货款 | G53: 870000 | H53: 0 | I53: =IF(F53<>"结转本期损益",_xlfn.XLOOKUP(D53,科目余额表[科目编码],科目余额表[抽查项目],"无匹配"),"期间结转") -> 银行存款 | J53: {=_xlfn.TEXTJOIN(",", TRUE, _xlfn.UNIQUE(IF((序时账[日期]=B53)*(序时账[凭证字号]=C53)*IF(G53=0,序时账[借方金额]<>0,序时账[借方金额]=0)*(序时账[科目编码]<>D53), 序时账[科目名称], "")))} -> 应收账款-F有限公司 | K53: 应收账款-F有限公司
A54: {=_xlfn.TEXTJOIN(",", TRUE, _xlfn.UNIQUE(IF((序时账[日期]=B54)*(序时账[凭证字号]=C54), 序时账[科目编码], "")))} -> 1002002,1122006 | B54: 45708 | C54: 4 | D54: 1122006 | E54: 应收账款-F有限公司 | F54: 收货款 | G54: 0 | H54: 870000 | I54: =IF(F54<>"结转本期损益",_xlfn.XLOOKUP(D54,科目余额表[科目编码],科目余额表[抽查项目],"无匹配"),"期间结转") -> 应收账款 | J54: {=_xlfn.TEXTJOIN(",", TRUE, _xlfn.UNIQUE(IF((序时账[日期]=B54)*(序时账[凭证字号]=C54)*IF(G54=0,序时账[借方金额]<>0,序时账[借方金额]=0)*(序时账[科目编码]<>D54), 序时账[科目名称], "")))} -> EFG银行账户
A55: {=_xlfn.TEXTJOIN(",", TRUE, _xlfn.UNIQUE(IF((序时账[日期]=B55)*(序时账[凭证字号]=C55), 序时账[科目编码], "")))} -> 1405002,222100101,2202002 | B55: 45708 | C55: 5 | D55: 1405002 | E55: S商品 | F55: 购货 | G55: 490000 | H55: 0 | I55: =IF(F55<>"结转本期损益",_xlfn.XLOOKUP(D55,科目余额表[科目编码],科目余额表[抽查项目],"无匹配"),"期间结转") -> 存货 | J55: {=_xlfn.TEXTJOIN(",", TRUE, _xlfn.UNIQUE(IF((序时账[日期]=B55)*(序时账[凭证字号]=C55)*IF(G55=0,序时账[借方金额]<>0,序时账[借方金额]=0)*(序时账[科目编码]<>D55), 序时账[科目名称], "")))} -> 应付账款-U有限公司
A56: {=_xlfn.TEXTJOIN(",", TRUE, _xlfn.UNIQUE(IF((序时账[日期]=B56)*(序时账[凭证字号]=C56), 序时账[科目编码], "")))} -> 1405002,222100101,2202002 | B56: 45708 | C56: 5 | D56: 222100101 | E56: 进项税额 | F56: 购货 | G56: 63700 | H56: 0 | I56: =IF(F56<>"结转本期损益",_xlfn.XLOOKUP(D56,科目余额表[科目编码],科目余额表[抽查项目],"无匹配"),"期间结转") -> 应交税费 | J56: {=_xlfn.TEXTJOIN(",", TRUE, _xlfn.UNIQUE(IF((序时账[日期]=B56)*(序时账[凭证字号]=C56)*IF(G56=0,序时账[借方金额]<>0,序时账[借方金额]=0)*(序时账[科目编码]<>D56), 序时账[科目名称], "")))} -> 应付账款-U有限公司
A57: {=_xlfn.TEXTJOIN(",", TRUE, _xlfn.UNIQUE(IF((序时账[日期]=B57)*(序时账[凭证字号]=C57), 序时账[科目编码], "")))} -> 1405002,222100101,2202002 | B57: 45708 | C57: 5 | D57: 2202002 | E57: 应付账款-U有限公司 | F57: 购货 | G57: 0 | H57: 553700 | I57: =IF(F57<>"结转本期损益",_xlfn.XLOOKUP(D57,科目余额表[科目编码],科目余额表[抽查项目],"无匹配"),"期间结转") -> 应付账款 | J57: {=_xlfn.TEXTJOIN(",", TRUE, _xlfn.UNIQUE(IF((序时账[日期]=B57)*(序时账[凭证字号]=C57)*IF(G57=0,序时账[借方金额]<>0,序时账[借方金额]=0)*(序时账[科目编码]<>D57), 序时账[科目名称], "")))} -> S商品,进项税额
A58: {=_xlfn.TEXTJOIN(",", TRUE, _xlfn.UNIQUE(IF((序时账[日期]=B58)*(序时账[凭证字号]=C58), 序时账[科目编码], "")))} -> 1123006,1002002 | B58: 45708 | C58: 6 | D58: 1123006 | E58: 预付账款-O有限公司 | F58: 付货款 | G58: 540000 | H58: 0 | I58: =IF(F58<>"结转本期损益",_xlfn.XLOOKUP(D58,科目余额表[科目编码],科目余额表[抽查项目],"无匹配"),"期间结转") -> 预付款项 | J58: {=_xlfn.TEXTJOIN(",", TRUE, _xlfn.UNIQUE(IF((序时账[日期]=B58)*(序时账[凭证字号]=C58)*IF(G58=0,序时账[借方金额]<>0,序时账[借方金额]=0)*(序时账[科目编码]<>D58), 序时账[科目名称], "")))} -> EFG银行账户
A59: {=_xlfn.TEXTJOIN(",", TRUE, _xlfn.UNIQUE(IF((序时账[日期]=B59)*(序时账[凭证字号]=C59), 序时账[科目编码], "")))} -> 1123006,1002002 | B59: 45708 | C59: 6 | D59: 1002002 | E59: EFG银行账户 | F59: 付货款 | G59: 0 | H59: 540000 | I59: =IF(F59<>"结转本期损益",_xlfn.XLOOKUP(D59,科目余额表[科目编码],科目余额表[抽查项目],"无匹配"),"期间结转") -> 银行存款 | J59: {=_xlfn.TEXTJOIN(",", TRUE, _xlfn.UNIQUE(IF((序时账[日期]=B59)*(序时账[凭证字号]=C59)*IF(G59=0,序时账[借方金额]<>0,序时账[借方金额]=0)*(序时账[科目编码]<>D59), 序时账[科目名称], "")))} -> 预付账款-O有限公司 | K59: 预付账款-O有限公司
A60: {=_xlfn.TEXTJOIN(",", TRUE, _xlfn.UNIQUE(IF((序时账[日期]=B60)*(序时账[凭证字号]=C60), 序时账[科目编码], "")))} -> 222100102,222100103,222100101,2221002 | B60: 45713 | C60: 7 | D60: 222100102 | E60: 销项税额 | F60: 转出未交增值税 | G60: 132600 | H60: 0 | I60: =IF(F60<>"结转本期损益",_xlfn.XLOOKUP(D60,科目余额表[科目编码],科目余额表[抽查项目],"无匹配"),"期间结转") -> 应交税费 | J60: {=_xlfn.TEXTJOIN(",", TRUE, _xlfn.UNIQUE(IF((序时账[日期]=B60)*(序时账[凭证字号]=C60)*IF(G60=0,序时账[借方金额]<>0,序时账[借方金额]=0)*(序时账[科目编码]<>D60), 序时账[科目名称], "")))} -> 转出未交增值税,进项税额,未交增值税
A61: {=_xlfn.TEXTJOIN(",", TRUE, _xlfn.UNIQUE(IF((序时账[日期]=B61)*(序时账[凭证字号]=C61), 序时账[科目编码], "")))} -> 222100102,222100103,222100101,2221002 | B61: 45713 | C61: 7 | D61: 222100103 | E61: 转出未交增值税 | F61: 转出未交增值税 | G61: 0 | H61: 132600 | I61: =IF(F61<>"结转本期损益",_xlfn.XLOOKUP(D61,科目余额表[科目编码],科目余额表[抽查项目],"无匹配"),"期间结转") -> 应交税费 | J61: {=_xlfn.TEXTJOIN(",", TRUE, _xlfn.UNIQUE(IF((序时账[日期]=B61)*(序时账[凭证字号]=C61)*IF(G61=0,序时账[借方金额]<>0,序时账[借方金额]=0)*(序时账[科目编码]<>D61), 序时账[科目名称], "")))} -> 销项税额
A62: {=_xlfn.TEXTJOIN(",", TRUE, _xlfn.UNIQUE(IF((序时账[日期]=B62)*(序时账[凭证字号]=C62), 序时账[科目编码], "")))} -> 222100102,222100103,222100101,2221002 | B62: 45713 | C62: 7 | D62: 222100103 | E62: 转出未交增值税 | F62: 转出未交增值税 | G62: 63700 | H62: 0 | I62: =IF(F62<>"结转本期损益",_xlfn.XLOOKUP(D62,科目余额表[科目编码],科目余额表[抽查项目],"无匹配"),"期间结转") -> 应交税费 | J62: {=_xlfn.TEXTJOIN(",", TRUE, _xlfn.UNIQUE(IF((序时账[日期]=B62)*(序时账[凭证字号]=C62)*IF(G62=0,序时账[借方金额]<>0,序时账[借方金额]=0)*(序时账[科目编码]<>D62), 序时账[科目名称], "")))} -> 进项税额,未交增值税
A63: {=_xlfn.TEXTJOIN(",", TRUE, _xlfn.UNIQUE(IF((序时账[日期]=B63)*(序时账[凭证字号]=C63), 序时账[科目编码], "")))} -> 222100102,222100103,222100101,2221002 | B63: 45713 | C63: 7 | D63: 222100101 | E63: 进项税额 | F63: 转出未交增值税 | G63: 0 | H63: 63700 | I63: =IF(F63<>"结转本期损益",_xlfn.XLOOKUP(D63,科目余额表[科目编码],科目余额表[抽查项目],"无匹配"),"期间结转") -> 应交税费 | J63: {=_xlfn.TEXTJOIN(",", TRUE, _xlfn.UNIQUE(IF((序时账[日期]=B63)*(序时账[凭证字号]=C63)*IF(G63=0,序时账[借方金额]<>0,序时账[借方金额]=0)*(序时账[科目编码]<>D63), 序时账[科目名称], "")))} -> 销项税额,转出未交增值税
A64: {=_xlfn.TEXTJOIN(",", TRUE, _xlfn.UNIQUE(IF((序时账[日期]=B64)*(序时账[凭证字号]=C64), 序时账[科目编码], "")))} -> 222100102,222100103,222100101,2221002 | B64: 45713 | C64: 7 | D64: 222100103 | E64: 转出未交增值税 | F64: 转出未交增值税 | G64: 68900 | H64: 0 | I64: =IF(F64<>"结转本期损益",_xlfn.XLOOKUP(D64,科目余额表[科目编码],科目余额表[抽查项目],"无匹配"),"期间结转") -> 应交税费 | J64: {=_xlfn.TEXTJOIN(",", TRUE, _xlfn.UNIQUE(IF((序时账[日期]=B64)*(序时账[凭证字号]=C64)*IF(G64=0,序时账[借方金额]<>0,序时账[借方金额]=0)*(序时账[科目编码]<>D64), 序时账[科目名称], "")))} -> 进项税额,未交增值税
A65: {=_xlfn.TEXTJOIN(",", TRUE, _xlfn.UNIQUE(IF((序时账[日期]=B65)*(序时账[凭证字号]=C65), 序时账[科目编码], "")))} -> 222100102,222100103,222100101,2221002 | B65: 45713 | C65: 7 | D65: 2221002 | E65: 未交增值税 | F65: 转出未交增值税 | G65: 0 | H65: 68900 | I65: =IF(F65<>"结转本期损益",_xlfn.XLOOKUP(D65,科目余额表[科目编码],科目余额表[抽查项目],"无匹配"),"期间结转") -> 应交税费 | J65: {=_xlfn.TEXTJOIN(",", TRUE, _xlfn.UNIQUE(IF((序时账[日期]=B65)*(序时账[凭证字号]=C65)*IF(G65=0,序时账[借方金额]<>0,序时账[借方金额]=0)*(序时账[科目编码]<>D65), 序时账[科目名称], "")))} -> 销项税额,转出未交增值税
A66: {=_xlfn.TEXTJOIN(",", TRUE, _xlfn.UNIQUE(IF((序时账[日期]=B66)*(序时账[凭证字号]=C66), 序时账[科目编码], "")))} -> 5403001,5403002,5403003,2221003,2221004,2221005 | B66: 45713 | C66: 8 | D66: 5403001 | E66: 城市维护建设税 | F66: 增值税附税 | G66: 4823 | H66: 0 | I66: =IF(F66<>"结转本期损益",_xlfn.XLOOKUP(D66,科目余额表[科目编码],科目余额表[抽查项目],"无匹配"),"期间结转") -> 税金及附加 | J66: {=_xlfn.TEXTJOIN(",", TRUE, _xlfn.UNIQUE(IF((序时账[日期]=B66)*(序时账[凭证字号]=C66)*IF(G66=0,序时账[借方金额]<>0,序时账[借方金额]=0)*(序时账[科目编码]<>D66), 序时账[科目名称], "")))} -> 城市维护建设税,教育费附加,地方教育费附加
A67: {=_xlfn.TEXTJOIN(",", TRUE, _xlfn.UNIQUE(IF((序时账[日期]=B67)*(序时账[凭证字号]=C67), 序时账[科目编码], "")))} -> 5403001,5403002,5403003,2221003,2221004,2221005 | B67: 45713 | C67: 8 | D67: 5403002 | E67: 教育费附加 | F67: 增值税附税 | G67: 2067 | H67: 0 | I67: =IF(F67<>"结转本期损益",_xlfn.XLOOKUP(D67,科目余额表[科目编码],科目余额表[抽查项目],"无匹配"),"期间结转") -> 税金及附加 | J67: {=_xlfn.TEXTJOIN(",", TRUE, _xlfn.UNIQUE(IF((序时账[日期]=B67)*(序时账[凭证字号]=C67)*IF(G67=0,序时账[借方金额]<>0,序时账[借方金额]=0)*(序时账[科目编码]<>D67), 序时账[科目名称], "")))} -> 城市维护建设税,教育费附加,地方教育费附加
A68: {=_xlfn.TEXTJOIN(",", TRUE, _xlfn.UNIQUE(IF((序时账[日期]=B68)*(序时账[凭证字号]=C68), 序时账[科目编码], "")))} -> 5403001,5403002,5403003,2221003,2221004,2221005 | B68: 45713 | C68: 8 | D68: 5403003 | E68: 地方教育费附加 | F68: 增值税附税 | G68: 1378 | H68: 0 | I68: =IF(F68<>"结转本期损益",_xlfn.XLOOKUP(D68,科目余额表[科目编码],科目余额表[抽查项目],"无匹配"),"期间结转") -> 税金及附加 | J68: {=_xlfn.TEXTJOIN(",", TRUE, _xlfn.UNIQUE(IF((序时账[日期]=B68)*(序时账[凭证字号]=C68)*IF(G68=0,序时账[借方金额]<>0,序时账[借方金额]=0)*(序时账[科目编码]<>D68), 序时账[科目名称], "")))} -> 城市维护建设税,教育费附加,地方教育费附加
A69: {=_xlfn.TEXTJOIN(",", TRUE, _xlfn.UNIQUE(IF((序时账[日期]=B69)*(序时账[凭证字号]=C69), 序时账[科目编码], "")))} -> 5403001,5403002,5403003,2221003,2221004,2221005 | B69: 45713 | C69: 8 | D69: 2221003 | E69: 城市维护建设税 | F69: 增值税附税 | G69: 0 | H69: 4823 | I69: =IF(F69<>"结转本期损益",_xlfn.XLOOKUP(D69,科目余额表[科目编码],科目余额表[抽查项目],"无匹配"),"期间结转") -> 应交税费 | J69: {=_xlfn.TEXTJOIN(",", TRUE, _xlfn.UNIQUE(IF((序时账[日期]=B69)*(序时账[凭证字号]=C69)*IF(G69=0,序时账[借方金额]<>0,序时账[借方金额]=0)*(序时账[科目编码]<>D69), 序时账[科目名称], "")))} -> 城市维护建设税,教育费附加,地方教育费附加
A70: {=_xlfn.TEXTJOIN(",", TRUE, _xlfn.UNIQUE(IF((序时账[日期]=B70)*(序时账[凭证字号]=C70), 序时账[科目编码], "")))} -> 5403001,5403002,5403003,2221003,2221004,2221005 | B70: 45713 | C70: 8 | D70: 2221004 | E70: 教育费附加 | F70: 增值税附税 | G70: 0 | H70: 2067 | I70: =IF(F70<>"结转本期损益",_xlfn.XLOOKUP(D70,科目余额表[科目编码],科目余额表[抽查项目],"无匹配"),"期间结转") -> 应交税费 | J70: {=_xlfn.TEXTJOIN(",", TRUE, _xlfn.UNIQUE(IF((序时账[日期]=B70)*(序时账[凭证字号]=C70)*IF(G70=0,序时账[借方金额]<>0,序时账[借方金额]=0)*(序时账[科目编码]<>D70), 序时账[科目名称], "")))} -> 城市维护建设税,教育费附加,地方教育费附加
A71: {=_xlfn.TEXTJOIN(",", TRUE, _xlfn.UNIQUE(IF((序时账[日期]=B71)*(序时账[凭证字号]=C71), 序时账[科目编码], "")))} -> 5403001,5403002,5403003,2221003,2221004,2221005 | B71: 45713 | C71: 8 | D71: 2221005 | E71: 地方教育费附加 | F71: 增值税附税 | G71: 0 | H71: 1378 | I71: =IF(F71<>"结转本期损益",_xlfn.XLOOKUP(D71,科目余额表[科目编码],科目余额表[抽查项目],"无匹配"),"期间结转") -> 应交税费 | J71: {=_xlfn.TEXTJOIN(",", TRUE, _xlfn.UNIQUE(IF((序时账[日期]=B71)*(序时账[凭证字号]=C71)*IF(G71=0,序时账[借方金额]<>0,序时账[借方金额]=0)*(序时账[科目编码]<>D71), 序时账[科目名称], "")))} -> 城市维护建设税,教育费附加,地方教育费附加
... A75: {=_xlfn.TEXTJOIN(",", TRUE, _xlfn.UNIQUE(IF((序时账[日期]=B75)*(序时账[凭证字号]=C75), 序时账[科目编码], "")))} -> 2221002,2221003,2221004,2221005,1002001 | B75: 45713 | C75: 9 | D75: 2221005 | E75: 地方教育费附加 | F75: 缴税 | G75: 1349.92 | H75: 0 | I75: =IF(F75<>"结转本期损益",_xlfn.XLOOKUP(D75,科目余额表[科目编码],科目余额表[抽查项目],"无匹配"),"期间结转") -> 应交税费 | J75: {=_xlfn.TEXTJOIN(",", TRUE, _xlfn.UNIQUE(IF((序时账[日期]=B75)*(序时账[凭证字号]=C75)*IF(G75=0,序时账[借方金额]<>0,序时账[借方金额]=0)*(序时账[科目编码]<>D75), 序时账[科目名称], "")))} -> ABC银行账户
A76: {=_xlfn.TEXTJOIN(",", TRUE, _xlfn.UNIQUE(IF((序时账[日期]=B76)*(序时账[凭证字号]=C76), 序时账[科目编码], "")))} -> 2221002,2221003,2221004,2221005,1002001 | B76: 45713 | C76: 9 | D76: 1002001 | E76: ABC银行账户 | F76: 缴税 | G76: 0 | H76: 75595.52 | I76: =IF(F76<>"结转本期损益",_xlfn.XLOOKUP(D76,科目余额表[科目编码],科目余额表[抽查项目],"无匹配"),"期间结转") -> 银行存款 | J76: {=_xlfn.TEXTJOIN(",", TRUE, _xlfn.UNIQUE(IF((序时账[日期]=B76)*(序时账[凭证字号]=C76)*IF(G76=0,序时账[借方金额]<>0,序时账[借方金额]=0)*(序时账[科目编码]<>D76), 序时账[科目名称], "")))} -> 未交增值税,城市维护建设税,教育费附加,地方教育费附加 | K76: 未交增值税
A77: {=_xlfn.TEXTJOIN(",", TRUE, _xlfn.UNIQUE(IF((序时账[日期]=B77)*(序时账[凭证字号]=C77), 序时账[科目编码], "")))} -> 5602002,1001 | B77: 45716 | C77: 10 | D77: 5602002 | E77: 管理费用-办公费 | F77: 快递费 | G77: 50 | H77: 0 | I77: =IF(F77<>"结转本期损益",_xlfn.XLOOKUP(D77,科目余额表[科目编码],科目余额表[抽查项目],"无匹配"),"期间结转") -> 管理费用 | J77: {=_xlfn.TEXTJOIN(",", TRUE, _xlfn.UNIQUE(IF((序时账[日期]=B77)*(序时账[凭证字号]=C77)*IF(G77=0,序时账[借方金额]<>0,序时账[借方金额]=0)*(序时账[科目编码]<>D77), 序时账[科目名称], "")))} -> 库存现金
A78: {=_xlfn.TEXTJOIN(",", TRUE, _xlfn.UNIQUE(IF((序时账[日期]=B78)*(序时账[凭证字号]=C78), 序时账[科目编码], "")))} -> 5602002,1001 | B78: 45716 | C78: 10 | D78: 1001 | E78: 库存现金 | F78: 快递费 | G78: 0 | H78: 50 | I78: =IF(F78<>"结转本期损益",_xlfn.XLOOKUP(D78,科目余额表[科目编码],科目余额表[抽查项目],"无匹配"),"期间结转") -> 现金 | J78: {=_xlfn.TEXTJOIN(",", TRUE, _xlfn.UNIQUE(IF((序时账[日期]=B78)*(序时账[凭证字号]=C78)*IF(G78=0,序时账[借方金额]<>0,序时账[借方金额]=0)*(序时账[科目编码]<>D78), 序时账[科目名称], "")))} -> 管理费用-办公费 | K78: 办公费
A79: {=_xlfn.TEXTJOIN(",", TRUE, _xlfn.UNIQUE(IF((序时账[日期]=B79)*(序时账[凭证字号]=C79), 序时账[科目编码], "")))} -> 5001,3103 | B79: 45716 | C79: 11 | D79: 5001 | E79: 主营业务收入 | F79: 结转本期损益 | G79: 1020000 | H79: 0 | I79: =IF(F79<>"结转本期损益",_xlfn.XLOOKUP(D79,科目余额表[科目编码],科目余额表[抽查项目],"无匹配"),"期间结转") -> 期间结转 | J79: {=_xlfn.TEXTJOIN(",", TRUE, _xlfn.UNIQUE(IF((序时账[日期]=B79)*(序时账[凭证字号]=C79)*IF(G79=0,序时账[借方金额]<>0,序时账[借方金额]=0)*(序时账[科目编码]<>D79), 序时账[科目名称], "")))} -> 本年利润
A80: {=_xlfn.TEXTJOIN(",", TRUE, _xlfn.UNIQUE(IF((序时账[日期]=B80)*(序时账[凭证字号]=C80), 序时账[科目编码], "")))} -> 5001,3103 | B80: 45716 | C80: 11 | D80: 3103 | E80: 本年利润 | F80: 结转本期损益 | G80: 0 | H80: 1020000 | I80: =IF(F80<>"结转本期损益",_xlfn.XLOOKUP(D80,科目余额表[科目编码],科目余额表[抽查项目],"无匹配"),"期间结转") -> 期间结转 | J80: {=_xlfn.TEXTJOIN(",", TRUE, _xlfn.UNIQUE(IF((序时账[日期]=B80)*(序时账[凭证字号]=C80)*IF(G80=0,序时账[借方金额]<>0,序时账[借方金额]=0)*(序时账[科目编码]<>D80), 序时账[科目名称], "")))} -> 主营业务收入
A81: {=_xlfn.TEXTJOIN(",", TRUE, _xlfn.UNIQUE(IF((序时账[日期]=B81)*(序时账[凭证字号]=C81), 序时账[科目编码], "")))} -> 3103,5401,5403001,5403002,5403003,5602001,5602002 | B81: 45716 | C81: 12 | D81: 3103 | E81: 本年利润 | F81: 结转本期损益 | G81: 911348 | H81: 0 | I81: =IF(F81<>"结转本期损益",_xlfn.XLOOKUP(D81,科目余额表[科目编码],科目余额表[抽查项目],"无匹配"),"期间结转") -> 期间结转 | J81: {=_xlfn.TEXTJOIN(",", TRUE, _xlfn.UNIQUE(IF((序时账[日期]=B81)*(序时账[凭证字号]=C81)*IF(G81=0,序时账[借方金额]<>0,序时账[借方金额]=0)*(序时账[科目编码]<>D81), 序时账[科目名称], "")))} -> 主营业务成本,城市维护建设税,教育费附加,地方教育费附加,管理费用-折旧费,管理费用-办公费
A82: {=_xlfn.TEXTJOIN(",", TRUE, _xlfn.UNIQUE(IF((序时账[日期]=B82)*(序时账[凭证字号]=C82), 序时账[科目编码], "")))} -> 3103,5401,5403001,5403002,5403003,5602001,5602002 | B82: 45716 | C82: 12 | D82: 5401 | E82: 主营业务成本 | F82: 结转本期损益 | G82: 0 | H82: 902000 | I82: =IF(F82<>"结转本期损益",_xlfn.XLOOKUP(D82,科目余额表[科目编码],科目余额表[抽查项目],"无匹配"),"期间结转") -> 期间结转 | J82: {=_xlfn.TEXTJOIN(",", TRUE, _xlfn.UNIQUE(IF((序时账[日期]=B82)*(序时账[凭证字号]=C82)*IF(G82=0,序时账[借方金额]<>0,序时账[借方金额]=0)*(序时账[科目编码]<>D82), 序时账[科目名称], "")))} -> 本年利润
A83: {=_xlfn.TEXTJOIN(",", TRUE, _xlfn.UNIQUE(IF((序时账[日期]=B83)*(序时账[凭证字号]=C83), 序时账[科目编码], "")))} -> 3103,5401,5403001,5403002,5403003,5602001,5602002 | B83: 45716 | C83: 12 | D83: 5403001 | E83: 城市维护建设税 | F83: 结转本期损益 | G83: 0 | H83: 4823 | I83: =IF(F83<>"结转本期损益",_xlfn.XLOOKUP(D83,科目余额表[科目编码],科目余额表[抽查项目],"无匹配"),"期间结转") -> 期间结转 | J83: {=_xlfn.TEXTJOIN(",", TRUE, _xlfn.UNIQUE(IF((序时账[日期]=B83)*(序时账[凭证字号]=C83)*IF(G83=0,序时账[借方金额]<>0,序时账[借方金额]=0)*(序时账[科目编码]<>D83), 序时账[科目名称], "")))} -> 本年利润
A84: {=_xlfn.TEXTJOIN(",", TRUE, _xlfn.UNIQUE(IF((序时账[日期]=B84)*(序时账[凭证字号]=C84), 序时账[科目编码], "")))} -> 3103,5401,5403001,5403002,5403003,5602001,5602002 | B84: 45716 | C84: 12 | D84: 5403002 | E84: 教育费附加 | F84: 结转本期损益 | G84: 0 | H84: 2067 | I84: =IF(F84<>"结转本期损益",_xlfn.XLOOKUP(D84,科目余额表[科目编码],科目余额表[抽查项目],"无匹配"),"期间结转") -> 期间结转 | J84: {=_xlfn.TEXTJOIN(",", TRUE, _xlfn.UNIQUE(IF((序时账[日期]=B84)*(序时账[凭证字号]=C84)*IF(G84=0,序时账[借方金额]<>0,序时账[借方金额]=0)*(序时账[科目编码]<>D84), 序时账[科目名称], "")))} -> 本年利润
A85: {=_xlfn.TEXTJOIN(",", TRUE, _xlfn.UNIQUE(IF((序时账[日期]=B85)*(序时账[凭证字号]=C85), 序时账[科目编码], "")))} -> 3103,5401,5403001,5403002,5403003,5602001,5602002 | B85: 45716 | C85: 12 | D85: 5403003 | E85: 地方教育费附加 | F85: 结转本期损益 | G85: 0 | H85: 1378 | I85: =IF(F85<>"结转本期损益",_xlfn.XLOOKUP(D85,科目余额表[科目编码],科目余额表[抽查项目],"无匹配"),"期间结转") -> 期间结转 | J85: {=_xlfn.TEXTJOIN(",", TRUE, _xlfn.UNIQUE(IF((序时账[日期]=B85)*(序时账[凭证字号]=C85)*IF(G85=0,序时账[借方金额]<>0,序时账[借方金额]=0)*(序时账[科目编码]<>D85), 序时账[科目名称], "")))} -> 本年利润
A86: {=_xlfn.TEXTJOIN(",", TRUE, _xlfn.UNIQUE(IF((序时账[日期]=B86)*(序时账[凭证字号]=C86), 序时账[科目编码], "")))} -> 3103,5401,5403001,5403002,5403003,5602001,5602002 | B86: 45716 | C86: 12 | D86: 5602001 | E86: 管理费用-折旧费 | F86: 结转本期损益 | G86: 0 | H86: 1030 | I86: =IF(F86<>"结转本期损益",_xlfn.XLOOKUP(D86,科目余额表[科目编码],科目余额表[抽查项目],"无匹配"),"期间结转") -> 期间结转 | J86: {=_xlfn.TEXTJOIN(",", TRUE, _xlfn.UNIQUE(IF((序时账[日期]=B86)*(序时账[凭证字号]=C86)*IF(G86=0,序时账[借方金额]<>0,序时账[借方金额]=0)*(序时账[科目编码]<>D86), 序时账[科目名称], "")))} -> 本年利润
A87: {=_xlfn.TEXTJOIN(",", TRUE, _xlfn.UNIQUE(IF((序时账[日期]=B87)*(序时账[凭证字号]=C87), 序时账[科目编码], "")))} -> 3103,5401,5403001,5403002,5403003,5602001,5602002 | B87: 45716 | C87: 12 | D87: 5602002 | E87: 管理费用-办公费 | F87: 结转本期损益 | G87: 0 | H87: 50 | I87: =IF(F87<>"结转本期损益",_xlfn.XLOOKUP(D87,科目余额表[科目编码],科目余额表[抽查项目],"无匹配"),"期间结转") -> 期间结转 | J87: {=_xlfn.TEXTJOIN(",", TRUE, _xlfn.UNIQUE(IF((序时账[日期]=B87)*(序时账[凭证字号]=C87)*IF(G87=0,序时账[借方金额]<>0,序时账[借方金额]=0)*(序时账[科目编码]<>D87), 序时账[科目名称], "")))} -> 本年利润
A88: {=_xlfn.TEXTJOIN(",", TRUE, _xlfn.UNIQUE(IF((序时账[日期]=B88)*(序时账[凭证字号]=C88), 序时账[科目编码], "")))} -> 5602001,1602002 | B88: 45726 | C88: 1 | D88: 5602001 | E88: 管理费用-折旧费 | F88: 计提折旧费用 | G88: 1030 | H88: 0 | I88: =IF(F88<>"结转本期损益",_xlfn.XLOOKUP(D88,科目余额表[科目编码],科目余额表[抽查项目],"无匹配"),"期间结转") -> 管理费用 | J88: {=_xlfn.TEXTJOIN(",", TRUE, _xlfn.UNIQUE(IF((序时账[日期]=B88)*(序时账[凭证字号]=C88)*IF(G88=0,序时账[借方金额]<>0,序时账[借方金额]=0)*(序时账[科目编码]<>D88), 序时账[科目名称], "")))} -> 电脑
A89: {=_xlfn.TEXTJOIN(",", TRUE, _xlfn.UNIQUE(IF((序时账[日期]=B89)*(序时账[凭证字号]=C89), 序时账[科目编码], "")))} -> 5602001,1602002 | B89: 45726 | C89: 1 | D89: 1602002 | E89: 电脑 | F89: 计提折旧费用 | G89: 0 | H89: 1030 | I89: =IF(F89<>"结转本期损益",_xlfn.XLOOKUP(D89,科目余额表[科目编码],科目余额表[抽查项目],"无匹配"),"期间结转") -> 固定资产 | J89: {=_xlfn.TEXTJOIN(",", TRUE, _xlfn.UNIQUE(IF((序时账[日期]=B89)*(序时账[凭证字号]=C89)*IF(G89=0,序时账[借方金额]<>0,序时账[借方金额]=0)*(序时账[科目编码]<>D89), 序时账[科目名称], "")))} -> 管理费用-折旧费
A90: {=_xlfn.TEXTJOIN(",", TRUE, _xlfn.UNIQUE(IF((序时账[日期]=B90)*(序时账[凭证字号]=C90), 序时账[科目编码], "")))} -> 1122003,5001,222100102 | B90: 45731 | C90: 2 | D90: 1122003 | E90: 应收账款-C有限公司 | F90: 销售收入 | G90: 1163900 | H90: 0 | I90: =IF(F90<>"结转本期损益",_xlfn.XLOOKUP(D90,科目余额表[科目编码],科目余额表[抽查项目],"无匹配"),"期间结转") -> 应收账款 | J90: {=_xlfn.TEXTJOIN(",", TRUE, _xlfn.UNIQUE(IF((序时账[日期]=B90)*(序时账[凭证字号]=C90)*IF(G90=0,序时账[借方金额]<>0,序时账[借方金额]=0)*(序时账[科目编码]<>D90), 序时账[科目名称], "")))} -> 主营业务收入,销项税额
... A94: {=_xlfn.TEXTJOIN(",", TRUE, _xlfn.UNIQUE(IF((序时账[日期]=B94)*(序时账[凭证字号]=C94), 序时账[科目编码], "")))} -> 5401,1405001 | B94: 45731 | C94: 3 | D94: 1405001 | E94: R商品 | F94: 结转销售成本 | G94: 0 | H94: 903000 | I94: =IF(F94<>"结转本期损益",_xlfn.XLOOKUP(D94,科目余额表[科目编码],科目余额表[抽查项目],"无匹配"),"期间结转") -> 存货 | J94: {=_xlfn.TEXTJOIN(",", TRUE, _xlfn.UNIQUE(IF((序时账[日期]=B94)*(序时账[凭证字号]=C94)*IF(G94=0,序时账[借方金额]<>0,序时账[借方金额]=0)*(序时账[科目编码]<>D94), 序时账[科目名称], "")))} -> 主营业务成本
A95: {=_xlfn.TEXTJOIN(",", TRUE, _xlfn.UNIQUE(IF((序时账[日期]=B95)*(序时账[凭证字号]=C95), 序时账[科目编码], "")))} -> 1002002,1122007 | B95: 45736 | C95: 4 | D95: 1002002 | E95: EFG银行账户 | F95: 收货款 | G95: 810000 | H95: 0 | I95: =IF(F95<>"结转本期损益",_xlfn.XLOOKUP(D95,科目余额表[科目编码],科目余额表[抽查项目],"无匹配"),"期间结转") -> 银行存款 | J95: {=_xlfn.TEXTJOIN(",", TRUE, _xlfn.UNIQUE(IF((序时账[日期]=B95)*(序时账[凭证字号]=C95)*IF(G95=0,序时账[借方金额]<>0,序时账[借方金额]=0)*(序时账[科目编码]<>D95), 序时账[科目名称], "")))} -> 应收账款-G有限公司 | K95: 应收账款-G有限公司
A96: {=_xlfn.TEXTJOIN(",", TRUE, _xlfn.UNIQUE(IF((序时账[日期]=B96)*(序时账[凭证字号]=C96), 序时账[科目编码], "")))} -> 1002002,1122007 | B96: 45736 | C96: 4 | D96: 1122007 | E96: 应收账款-G有限公司 | F96: 收货款 | G96: 0 | H96: 810000 | I96: =IF(F96<>"结转本期损益",_xlfn.XLOOKUP(D96,科目余额表[科目编码],科目余额表[抽查项目],"无匹配"),"期间结转") -> 应收账款 | J96: {=_xlfn.TEXTJOIN(",", TRUE, _xlfn.UNIQUE(IF((序时账[日期]=B96)*(序时账[凭证字号]=C96)*IF(G96=0,序时账[借方金额]<>0,序时账[借方金额]=0)*(序时账[科目编码]<>D96), 序时账[科目名称], "")))} -> EFG银行账户
A97: {=_xlfn.TEXTJOIN(",", TRUE, _xlfn.UNIQUE(IF((序时账[日期]=B97)*(序时账[凭证字号]=C97), 序时账[科目编码], "")))} -> 1405002,222100101,1123001 | B97: 45736 | C97: 5 | D97: 1405002 | E97: S商品 | F97: 购货 | G97: 503400 | H97: 0 | I97: =IF(F97<>"结转本期损益",_xlfn.XLOOKUP(D97,科目余额表[科目编码],科目余额表[抽查项目],"无匹配"),"期间结转") -> 存货 | J97: {=_xlfn.TEXTJOIN(",", TRUE, _xlfn.UNIQUE(IF((序时账[日期]=B97)*(序时账[凭证字号]=C97)*IF(G97=0,序时账[借方金额]<>0,序时账[借方金额]=0)*(序时账[科目编码]<>D97), 序时账[科目名称], "")))} -> 预付账款-K有限公司
A98: {=_xlfn.TEXTJOIN(",", TRUE, _xlfn.UNIQUE(IF((序时账[日期]=B98)*(序时账[凭证字号]=C98), 序时账[科目编码], "")))} -> 1405002,222100101,1123001 | B98: 45736 | C98: 5 | D98: 222100101 | E98: 进项税额 | F98: 购货 | G98: 65442 | H98: 0 | I98: =IF(F98<>"结转本期损益",_xlfn.XLOOKUP(D98,科目余额表[科目编码],科目余额表[抽查项目],"无匹配"),"期间结转") -> 应交税费 | J98: {=_xlfn.TEXTJOIN(",", TRUE, _xlfn.UNIQUE(IF((序时账[日期]=B98)*(序时账[凭证字号]=C98)*IF(G98=0,序时账[借方金额]<>0,序时账[借方金额]=0)*(序时账[科目编码]<>D98), 序时账[科目名称], "")))} -> 预付账款-K有限公司
A99: {=_xlfn.TEXTJOIN(",", TRUE, _xlfn.UNIQUE(IF((序时账[日期]=B99)*(序时账[凭证字号]=C99), 序时账[科目编码], "")))} -> 1405002,222100101,1123001 | B99: 45736 | C99: 5 | D99: 1123001 | E99: 预付账款-K有限公司 | F99: 购货 | G99: 0 | H99: 568842 | I99: =IF(F99<>"结转本期损益",_xlfn.XLOOKUP(D99,科目余额表[科目编码],科目余额表[抽查项目],"无匹配"),"期间结转") -> 预付款项 | J99: {=_xlfn.TEXTJOIN(",", TRUE, _xlfn.UNIQUE(IF((序时账[日期]=B99)*(序时账[凭证字号]=C99)*IF(G99=0,序时账[借方金额]<>0,序时账[借方金额]=0)*(序时账[科目编码]<>D99), 序时账[科目名称], "")))} -> S商品,进项税额
A100: {=_xlfn.TEXTJOIN(",", TRUE, _xlfn.UNIQUE(IF((序时账[日期]=B100)*(序时账[凭证字号]=C100), 序时账[科目编码], "")))} -> 2202005,1002002 | B100: 45736 | C100: 6 | D100: 2202005 | E100: 应付账款-W有限公司 | F100: 付货款 | G100: 640000 | H100: 0 | I100: =IF(F100<>"结转本期损益",_xlfn.XLOOKUP(D100,科目余额表[科目编码],科目余额表[抽查项目],"无匹配"),"期间结转") -> 应付账款 | J100: {=_xlfn.TEXTJOIN(",", TRUE, _xlfn.UNIQUE(IF((序时账[日期]=B100)*(序时账[凭证字号]=C100)*IF(G100=0,序时账[借方金额]<>0,序时账[借方金额]=0)*(序时账[科目编码]<>D100), 序时账[科目名称], "")))} -> EFG银行账户
A101: {=_xlfn.TEXTJOIN(",", TRUE, _xlfn.UNIQUE(IF((序时账[日期]=B101)*(序时账[凭证字号]=C101), 序时账[科目编码], "")))} -> 2202005,1002002 | B101: 45736 | C101: 6 | D101: 1002002 | E101: EFG银行账户 | F101: 付货款 | G101: 0 | H101: 640000 | I101: =IF(F101<>"结转本期损益",_xlfn.XLOOKUP(D101,科目余额表[科目编码],科目余额表[抽查项目],"无匹配"),"期间结转") -> 银行存款 | J101: {=_xlfn.TEXTJOIN(",", TRUE, _xlfn.UNIQUE(IF((序时账[日期]=B101)*(序时账[凭证字号]=C101)*IF(G101=0,序时账[借方金额]<>0,序时账[借方金额]=0)*(序时账[科目编码]<>D101), 序时账[科目名称], "")))} -> 应付账款-W有限公司 | K101: 应付账款-W有限公司
A102: {=_xlfn.TEXTJOIN(",", TRUE, _xlfn.UNIQUE(IF((序时账[日期]=B102)*(序时账[凭证字号]=C102), 序时账[科目编码], "")))} -> 222100102,222100103,222100101,2221002 | B102: 45741 | C102: 7 | D102: 222100102 | E102: 销项税额 | F102: 转出未交增值税 | G102: 133900 | H102: 0 | I102: =IF(F102<>"结转本期损益",_xlfn.XLOOKUP(D102,科目余额表[科目编码],科目余额表[抽查项目],"无匹配"),"期间结转") -> 应交税费 | J102: {=_xlfn.TEXTJOIN(",", TRUE, _xlfn.UNIQUE(IF((序时账[日期]=B102)*(序时账[凭证字号]=C102)*IF(G102=0,序时账[借方金额]<>0,序时账[借方金额]=0)*(序时账[科目编码]<>D102), 序时账[科目名称], "")))} -> 转出未交增值税,进项税额,未交增值税
A103: {=_xlfn.TEXTJOIN(",", TRUE, _xlfn.UNIQUE(IF((序时账[日期]=B103)*(序时账[凭证字号]=C103), 序时账[科目编码], "")))} -> 222100102,222100103,222100101,2221002 | B103: 45741 | C103: 7 | D103: 222100103 | E103: 转出未交增值税 | F103: 转出未交增值税 | G103: 0 | H103: 133900 | I103: =IF(F103<>"结转本期损益",_xlfn.XLOOKUP(D103,科目余额表[科目编码],科目余额表[抽查项目],"无匹配"),"期间结转") -> 应交税费 | J103: {=_xlfn.TEXTJOIN(",", TRUE, _xlfn.UNIQUE(IF((序时账[日期]=B103)*(序时账[凭证字号]=C103)*IF(G103=0,序时账[借方金额]<>0,序时账[借方金额]=0)*(序时账[科目编码]<>D103), 序时账[科目名称], "")))} -> 销项税额
A104: {=_xlfn.TEXTJOIN(",", TRUE, _xlfn.UNIQUE(IF((序时账[日期]=B104)*(序时账[凭证字号]=C104), 序时账[科目编码], "")))} -> 222100102,222100103,222100101,2221002 | B104: 45741 | C104: 7 | D104: 222100103 | E104: 转出未交增值税 | F104: 转出未交增值税 | G104: 65442 | H104: 0 | I104: =IF(F104<>"结转本期损益",_xlfn.XLOOKUP(D104,科目余额表[科目编码],科目余额表[抽查项目],"无匹配"),"期间结转") -> 应交税费 | J104: {=_xlfn.TEXTJOIN(",", TRUE, _xlfn.UNIQUE(IF((序时账[日期]=B104)*(序时账[凭证字号]=C104)*IF(G104=0,序时账[借方金额]<>0,序时账[借方金额]=0)*(序时账[科目编码]<>D104), 序时账[科目名称], "")))} -> 进项税额,未交增值税
A105: {=_xlfn.TEXTJOIN(",", TRUE, _xlfn.UNIQUE(IF((序时账[日期]=B105)*(序时账[凭证字号]=C105), 序时账[科目编码], "")))} -> 222100102,222100103,222100101,2221002 | B105: 45741 | C105: 7 | D105: 222100101 | E105: 进项税额 | F105: 转出未交增值税 | G105: 0 | H105: 65442 | I105: =IF(F105<>"结转本期损益",_xlfn.XLOOKUP(D105,科目余额表[科目编码],科目余额表[抽查项目],"无匹配"),"期间结转") -> 应交税费 | J105: {=_xlfn.TEXTJOIN(",", TRUE, _xlfn.UNIQUE(IF((序时账[日期]=B105)*(序时账[凭证字号]=C105)*IF(G105=0,序时账[借方金额]<>0,序时账[借方金额]=0)*(序时账[科目编码]<>D105), 序时账[科目名称], "")))} -> 销项税额,转出未交增值税
A106: {=_xlfn.TEXTJOIN(",", TRUE, _xlfn.UNIQUE(IF((序时账[日期]=B106)*(序时账[凭证字号]=C106), 序时账[科目编码], "")))} -> 222100102,222100103,222100101,2221002 | B106: 45741 | C106: 7 | D106: 222100103 | E106: 转出未交增值税 | F106: 转出未交增值税 | G106: 68458 | H106: 0 | I106: =IF(F106<>"结转本期损益",_xlfn.XLOOKUP(D106,科目余额表[科目编码],科目余额表[抽查项目],"无匹配"),"期间结转") -> 应交税费 | J106: {=_xlfn.TEXTJOIN(",", TRUE, _xlfn.UNIQUE(IF((序时账[日期]=B106)*(序时账[凭证字号]=C106)*IF(G106=0,序时账[借方金额]<>0,序时账[借方金额]=0)*(序时账[科目编码]<>D106), 序时账[科目名称], "")))} -> 进项税额,未交增值税
A107: {=_xlfn.TEXTJOIN(",", TRUE, _xlfn.UNIQUE(IF((序时账[日期]=B107)*(序时账[凭证字号]=C107), 序时账[科目编码], "")))} -> 222100102,222100103,222100101,2221002 | B107: 45741 | C107: 7 | D107: 2221002 | E107: 未交增值税 | F107: 转出未交增值税 | G107: 0 | H107: 68458 | I107: =IF(F107<>"结转本期损益",_xlfn.XLOOKUP(D107,科目余额表[科目编码],科目余额表[抽查项目],"无匹配"),"期间结转") -> 应交税费 | J107: {=_xlfn.TEXTJOIN(",", TRUE, _xlfn.UNIQUE(IF((序时账[日期]=B107)*(序时账[凭证字号]=C107)*IF(G107=0,序时账[借方金额]<>0,序时账[借方金额]=0)*(序时账[科目编码]<>D107), 序时账[科目名称], "")))} -> 销项税额,转出未交增值税
A108: {=_xlfn.TEXTJOIN(",", TRUE, _xlfn.UNIQUE(IF((序时账[日期]=B108)*(序时账[凭证字号]=C108), 序时账[科目编码], "")))} -> 5403001,5403002,5403003,2221003,2221004,2221005 | B108: 45741 | C108: 8 | D108: 5403001 | E108: 城市维护建设税 | F108: 增值税附税 | G108: 4792.06 | H108: 0 | I108: =IF(F108<>"结转本期损益",_xlfn.XLOOKUP(D108,科目余额表[科目编码],科目余额表[抽查项目],"无匹配"),"期间结转") -> 税金及附加 | J108: {=_xlfn.TEXTJOIN(",", TRUE, _xlfn.UNIQUE(IF((序时账[日期]=B108)*(序时账[凭证字号]=C108)*IF(G108=0,序时账[借方金额]<>0,序时账[借方金额]=0)*(序时账[科目编码]<>D108), 序时账[科目名称], "")))} -> 城市维护建设税,教育费附加,地方教育费附加
A109: {=_xlfn.TEXTJOIN(",", TRUE, _xlfn.UNIQUE(IF((序时账[日期]=B109)*(序时账[凭证字号]=C109), 序时账[科目编码], "")))} -> 5403001,5403002,5403003,2221003,2221004,2221005 | B109: 45741 | C109: 8 | D109: 5403002 | E109: 教育费附加 | F109: 增值税附税 | G109: 2053.74 | H109: 0 | I109: =IF(F109<>"结转本期损益",_xlfn.XLOOKUP(D109,科目余额表[科目编码],科目余额表[抽查项目],"无匹配"),"期间结转") -> 税金及附加 | J109: {=_xlfn.TEXTJOIN(",", TRUE, _xlfn.UNIQUE(IF((序时账[日期]=B109)*(序时账[凭证字号]=C109)*IF(G109=0,序时账[借方金额]<>0,序时账[借方金额]=0)*(序时账[科目编码]<>D109), 序时账[科目名称], "")))} -> 城市维护建设税,教育费附加,地方教育费附加
A110: {=_xlfn.TEXTJOIN(",", TRUE, _xlfn.UNIQUE(IF((序时账[日期]=B110)*(序时账[凭证字号]=C110), 序时账[科目编码], "")))} -> 5403001,5403002,5403003,2221003,2221004,2221005 | B110: 45741 | C110: 8 | D110: 5403003 | E110: 地方教育费附加 | F110: 增值税附税 | G110: 1369.16 | H110: 0 | I110: =IF(F110<>"结转本期损益",_xlfn.XLOOKUP(D110,科目余额表[科目编码],科目余额表[抽查项目],"无匹配"),"期间结转") -> 税金及附加 | J110: {=_xlfn.TEXTJOIN(",", TRUE, _xlfn.UNIQUE(IF((序时账[日期]=B110)*(序时账[凭证字号]=C110)*IF(G110=0,序时账[借方金额]<>0,序时账[借方金额]=0)*(序时账[科目编码]<>D110), 序时账[科目名称], "")))} -> 城市维护建设税,教育费附加,地方教育费附加
A111: {=_xlfn.TEXTJOIN(",", TRUE, _xlfn.UNIQUE(IF((序时账[日期]=B111)*(序时账[凭证字号]=C111), 序时账[科目编码], "")))} -> 5403001,5403002,5403003,2221003,2221004,2221005 | B111: 45741 | C111: 8 | D111: 2221003 | E111: 城市维护建设税 | F111: 增值税附税 | G111: 0 | H111: 4792.06 | I111: =IF(F111<>"结转本期损益",_xlfn.XLOOKUP(D111,科目余额表[科目编码],科目余额表[抽查项目],"无匹配"),"期间结转") -> 应交税费 | J111: {=_xlfn.TEXTJOIN(",", TRUE, _xlfn.UNIQUE(IF((序时账[日期]=B111)*(序时账[凭证字号]=C111)*IF(G111=0,序时账[借方金额]<>0,序时账[借方金额]=0)*(序时账[科目编码]<>D111), 序时账[科目名称], "")))} -> 城市维护建设税,教育费附加,地方教育费附加
A112: {=_xlfn.TEXTJOIN(",", TRUE, _xlfn.UNIQUE(IF((序时账[日期]=B112)*(序时账[凭证字号]=C112), 序时账[科目编码], "")))} -> 5403001,5403002,5403003,2221003,2221004,2221005 | B112: 45741 | C112: 8 | D112: 2221004 | E112: 教育费附加 | F112: 增值税附税 | G112: 0 | H112: 2053.74 | I112: =IF(F112<>"结转本期损益",_xlfn.XLOOKUP(D112,科目余额表[科目编码],科目余额表[抽查项目],"无匹配"),"期间结转") -> 应交税费 | J112: {=_xlfn.TEXTJOIN(",", TRUE, _xlfn.UNIQUE(IF((序时账[日期]=B112)*(序时账[凭证字号]=C112)*IF(G112=0,序时账[借方金额]<>0,序时账[借方金额]=0)*(序时账[科目编码]<>D112), 序时账[科目名称], "")))} -> 城市维护建设税,教育费附加,地方教育费附加
A113: {=_xlfn.TEXTJOIN(",", TRUE, _xlfn.UNIQUE(IF((序时账[日期]=B113)*(序时账[凭证字号]=C113), 序时账[科目编码], "")))} -> 5403001,5403002,5403003,2221003,2221004,2221005 | B113: 45741 | C113: 8 | D113: 2221005 | E113: 地方教育费附加 | F113: 增值税附税 | G113: 0 | H113: 1369.16 | I113: =IF(F113<>"结转本期损益",_xlfn.XLOOKUP(D113,科目余额表[科目编码],科目余额表[抽查项目],"无匹配"),"期间结转") -> 应交税费 | J113: {=_xlfn.TEXTJOIN(",", TRUE, _xlfn.UNIQUE(IF((序时账[日期]=B113)*(序时账[凭证字号]=C113)*IF(G113=0,序时账[借方金额]<>0,序时账[借方金额]=0)*(序时账[科目编码]<>D113), 序时账[科目名称], "")))} -> 城市维护建设税,教育费附加,地方教育费附加
...

Sheet 试算平衡表
A1: 数据类别 | B1: 报表项目 | C1: 期初金额 | D1: 审定报表金额 | E1: 调整金额 | F1: 未申报表金额 | G1: 数据比对差额
A2: 借 | B2: 货币资金 | C2: 1010837.3 | D2: =IF(A2="借",SUMIF(科目余额表[已审报表项目],B2,科目余额表[期末借方])-SUMIF(科目余额表[已审报表项目],B2,科目余额表[期末贷方]),IF(A2="贷",SUMIF(科目余额表[已审报表项目],B2,科目余额表[期末贷方])-SUMIF(科目余额表[已审报表项目],B2,科目余额表[期末借方]),SUMIF(科目余额表[已审报表项目],B2,科目余额表[本期借方]))) -> 14462935 | E2: =试算平衡表[[#This Row],[审定报表金额]]-试算平衡表[[#This Row],[未申报表金额]] -> -0.0099999998 | F2: 14462935 | G2: =F2-IF(A2="借",SUMIF(科目余额表[未审报表项目],B2,科目余额表[期末借方])-SUMIF(科目余额表[未审报表项目],B2,科目余额表[期末贷方]),IF(A2="贷",SUMIF(科目余额表[未审报表项目],B2,科目余额表[期末贷方])-SUMIF(科目余额表[未审报表项目],B2,科目余额表[期末借方]),SUMIF(科目余额表[未审报表项目],B2,科目余额表[本期借方]))) -> 0.0099999998
A3: 借 | B3: 交易性金融资产 | C3: 0 | D3: =IF(A3="借",SUMIF(科目余额表[已审报表项目],B3,科目余额表[期末借方])-SUMIF(科目余额表[已审报表项目],B3,科目余额表[期末贷方]),IF(A3="贷",SUMIF(科目余额表[已审报表项目],B3,科目余额表[期末贷方])-SUMIF(科目余额表[已审报表项目],B3,科目余额表[期末借方]),SUMIF(科目余额表[已审报表项目],B3,科目余额表[本期借方]))) -> 0 | E3: =试算平衡表[[#This Row],[审定报表金额]]-试算平衡表[[#This Row],[未申报表金额]] -> 0 | F3: 0 | G3: =F3-IF(A3="借",SUMIF(科目余额表[未审报表项目],B3,科目余额表[期末借方])-SUMIF(科目余额表[未审报表项目],B3,科目余额表[期末贷方]),IF(A3="贷",SUMIF(科目余额表[未审报表项目],B3,科目余额表[期末贷方])-SUMIF(科目余额表[未审报表项目],B3,科目余额表[期末借方]),SUMIF(科目余额表[未审报表项目],B3,科目余额表[本期借方]))) -> 0
A4: 借 | B4: 衍生金融资产 | C4: 0 | D4: =IF(A4="借",SUMIF(科目余额表[已审报表项目],B4,科目余额表[期末借方])-SUMIF(科目余额表[已审报表项目],B4,科目余额表[期末贷方]),IF(A4="贷",SUMIF(科目余额表[已审报表项目],B4,科目余额表[期末贷方])-SUMIF(科目余额表[已审报表项目],B4,科目余额表[期末借方]),SUMIF(科目余额表[已审报表项目],B4,科目余额表[本期借方]))) -> 0 | E4: =试算平衡表[[#This Row],[审定报表金额]]-试算平衡表[[#This Row],[未申报表金额]] -> 0 | F4: 0 | G4: =F4-IF(A4="借",SUMIF(科目余额表[未审报表项目],B4,科目余额表[期末借方])-SUMIF(科目余额表[未审报表项目],B4,科目余额表[期末贷方]),IF(A4="贷",SUMIF(科目余额表[未审报表项目],B4,科目余额表[期末贷方])-SUMIF(科目余额表[未审报表项目],B4,科目余额表[期末借方]),SUMIF(科目余额表[未审报表项目],B4,科目余额表[本期借方]))) -> 0
A5: 借 | B5: 应收票据 | C5: 0 | D5: =IF(A5="借",SUMIF(科目余额表[已审报表项目],B5,科目余额表[期末借方])-SUMIF(科目余额表[已审报表项目],B5,科目余额表[期末贷方]),IF(A5="贷",SUMIF(科目余额表[已审报表项目],B5,科目余额表[期末贷方])-SUMIF(科目余额表[已审报表项目],B5,科目余额表[期末借方]),SUMIF(科目余额表[已审报表项目],B5,科目余额表[本期借方]))) -> 0 | E5: =试算平衡表[[#This Row],[审定报表金额]]-试算平衡表[[#This Row],[未申报表金额]] -> 0 | F5: 0 | G5: =F5-IF(A5="借",SUMIF(科目余额表[未审报表项目],B5,科目余额表[期末借方])-SUMIF(科目余额表[未审报表项目],B5,科目余额表[期末贷方]),IF(A5="贷",SUMIF(科目余额表[未审报表项目],B5,科目余额表[期末贷方])-SUMIF(科目余额表[未审报表项目],B5,科目余额表[期末借方]),SUMIF(科目余额表[未审报表项目],B5,科目余额表[本期借方]))) -> 0
A6: 借 | B6: 应收账款 | C6: 5547848 | D6: =IF(A6="借",SUMIF(科目余额表[已审报表项目],B6,科目余额表[期末借方])-SUMIF(科目余额表[已审报表项目],B6,科目余额表[期末贷方]),IF(A6="贷",SUMIF(科目余额表[已审报表项目],B6,科目余额表[期末贷方])-SUMIF(科目余额表[已审报表项目],B6,科目余额表[期末借方]),SUMIF(科目余额表[已审报表项目],B6,科目余额表[本期借方]))) -> 8165248 | E6: =试算平衡表[[#This Row],[审定报表金额]]-试算平衡表[[#This Row],[未申报表金额]] -> 0 | F6: 8165248 | G6: =F6-IF(A6="借",SUMIF(科目余额表[未审报表项目],B6,科目余额表[期末借方])-SUMIF(科目余额表[未审报表项目],B6,科目余额表[期末贷方]),IF(A6="贷",SUMIF(科目余额表[未审报表项目],B6,科目余额表[期末贷方])-SUMIF(科目余额表[未审报表项目],B6,科目余额表[期末借方]),SUMIF(科目余额表[未审报表项目],B6,科目余额表[本期借方]))) -> 0
A7: 借 | B7: 应收款项融资 | C7: 0 | D7: =IF(A7="借",SUMIF(科目余额表[已审报表项目],B7,科目余额表[期末借方])-SUMIF(科目余额表[已审报表项目],B7,科目余额表[期末贷方]),IF(A7="贷",SUMIF(科目余额表[已审报表项目],B7,科目余额表[期末贷方])-SUMIF(科目余额表[已审报表项目],B7,科目余额表[期末借方]),SUMIF(科目余额表[已审报表项目],B7,科目余额表[本期借方]))) -> 0 | E7: =试算平衡表[[#This Row],[审定报表金额]]-试算平衡表[[#This Row],[未申报表金额]] -> 0 | F7: 0 | G7: =F7-IF(A7="借",SUMIF(科目余额表[未审报表项目],B7,科目余额表[期末借方])-SUMIF(科目余额表[未审报表项目],B7,科目余额表[期末贷方]),IF(A7="贷",SUMIF(科目余额表[未审报表项目],B7,科目余额表[期末贷方])-SUMIF(科目余额表[未审报表项目],B7,科目余额表[期末借方]),SUMIF(科目余额表[未审报表项目],B7,科目余额表[本期借方]))) -> 0
A8: 借 | B8: 预付款项 | C8: 2001987.2 | D8: =IF(A8="借",SUMIF(科目余额表[已审报表项目],B8,科目余额表[期末借方])-SUMIF(科目余额表[已审报表项目],B8,科目余额表[期末贷方]),IF(A8="贷",SUMIF(科目余额表[已审报表项目],B8,科目余额表[期末贷方])-SUMIF(科目余额表[已审报表项目],B8,科目余额表[期末借方]),SUMIF(科目余额表[已审报表项目],B8,科目余额表[本期借方]))) -> 730048.34 | E8: =试算平衡表[[#This Row],[审定报表金额]]-试算平衡表[[#This Row],[未申报表金额]] -> 3057325.1 | F8: -2327276.8 | G8: =F8-IF(A8="借",SUMIF(科目余额表[未审报表项目],B8,科目余额表[期末借方])-SUMIF(科目余额表[未审报表项目],B8,科目余额表[期末贷方]),IF(A8="贷",SUMIF(科目余额表[未审报表项目],B8,科目余额表[期末贷方])-SUMIF(科目余额表[未审报表项目],B8,科目余额表[期末借方]),SUMIF(科目余额表[未审报表项目],B8,科目余额表[本期借方]))) -> 0
A9: 借 | B9: 其他应收款 | C9: 229934.57 | D9: =IF(A9="借",SUMIF(科目余额表[已审报表项目],B9,科目余额表[期末借方])-SUMIF(科目余额表[已审报表项目],B9,科目余额表[期末贷方]),IF(A9="贷",SUMIF(科目余额表[已审报表项目],B9,科目余额表[期末贷方])-SUMIF(科目余额表[已审报表项目],B9,科目余额表[期末借方]),SUMIF(科目余额表[已审报表项目],B9,科目余额表[本期借方]))) -> 219934.57 | E9: =试算平衡表[[#This Row],[审定报表金额]]-试算平衡表[[#This Row],[未申报表金额]] -> 0 | F9: 219934.57 | G9: =F9-IF(A9="借",SUMIF(科目余额表[未审报表项目],B9,科目余额表[期末借方])-SUMIF(科目余额表[未审报表项目],B9,科目余额表[期末贷方]),IF(A9="贷",SUMIF(科目余额表[未审报表项目],B9,科目余额表[期末贷方])-SUMIF(科目余额表[未审报表项目],B9,科目余额表[期末借方]),SUMIF(科目余额表[未审报表项目],B9,科目余额表[本期借方]))) -> 0
A10: 借 | B10: 存货 | C10: 9987654.7 | D10: =IF(A10="借",SUMIF(科目余额表[已审报表项目],B10,科目余额表[期末借方])-SUMIF(科目余额表[已审报表项目],B10,科目余额表[期末贷方]),IF(A10="贷",SUMIF(科目余额表[已审报表项目],B10,科目余额表[期末贷方])-SUMIF(科目余额表[已审报表项目],B10,科目余额表[期末借方]),SUMIF(科目余额表[已审报表项目],B10,科目余额表[本期借方]))) -> 7655954.7 | E10: =试算平衡表[[#This Row],[审定报表金额]]-试算平衡表[[#This Row],[未申报表金额]] -> 0 | F10: 7655954.7 | G10: =F10-IF(A10="借",SUMIF(科目余额表[未审报表项目],B10,科目余额表[期末借方])-SUMIF(科目余额表[未审报表项目],B10,科目余额表[期末贷方]),IF(A10="贷",SUMIF(科目余额表[未审报表项目],B10,科目余额表[期末贷方])-SUMIF(科目余额表[未审报表项目],B10,科目余额表[期末借方]),SUMIF(科目余额表[未审报表项目],B10,科目余额表[本期借方]))) -> 0
A11: 借 | B11: 合同资产 | C11: 0 | D11: =IF(A11="借",SUMIF(科目余额表[已审报表项目],B11,科目余额表[期末借方])-SUMIF(科目余额表[已审报表项目],B11,科目余额表[期末贷方]),IF(A11="贷",SUMIF(科目余额表[已审报表项目],B11,科目余额表[期末贷方])-SUMIF(科目余额表[已审报表项目],B11,科目余额表[期末借方]),SUMIF(科目余额表[已审报表项目],B11,科目余额表[本期借方]))) -> 0 | E11: =试算平衡表[[#This Row],[审定报表金额]]-试算平衡表[[#This Row],[未申报表金额]] -> 0 | F11: 0 | G11: =F11-IF(A11="借",SUMIF(科目余额表[未审报表项目],B11,科目余额表[期末借方])-SUMIF(科目余额表[未审报表项目],B11,科目余额表[期末贷方]),IF(A11="贷",SUMIF(科目余额表[未审报表项目],B11,科目余额表[期末贷方])-SUMIF(科目余额表[未审报表项目],B11,科目余额表[期末借方]),SUMIF(科目余额表[未审报表项目],B11,科目余额表[本期借方]))) -> 0
A12: 借 | B12: 持有待售资产 | C12: 0 | D12: =IF(A12="借",SUMIF(科目余额表[已审报表项目],B12,科目余额表[期末借方])-SUMIF(科目余额表[已审报表项目],B12,科目余额表[期末贷方]),IF(A12="贷",SUMIF(科目余额表[已审报表项目],B12,科目余额表[期末贷方])-SUMIF(科目余额表[已审报表项目],B12,科目余额表[期末借方]),SUMIF(科目余额表[已审报表项目],B12,科目余额表[本期借方]))) -> 0 | E12: =试算平衡表[[#This Row],[审定报表金额]]-试算平衡表[[#This Row],[未申报表金额]] -> 0 | F12: 0 | G12: =F12-IF(A12="借",SUMIF(科目余额表[未审报表项目],B12,科目余额表[期末借方])-SUMIF(科目余额表[未审报表项目],B12,科目余额表[期末贷方]),IF(A12="贷",SUMIF(科目余额表[未审报表项目],B12,科目余额表[期末贷方])-SUMIF(科目余额表[未审报表项目],B12,科目余额表[期末借方]),SUMIF(科目余额表[未审报表项目],B12,科目余额表[本期借方]))) -> 0
A13: 借 | B13: 一年内到期的非流动资产 | C13: 0 | D13: =IF(A13="借",SUMIF(科目余额表[已审报表项目],B13,科目余额表[期末借方])-SUMIF(科目余额表[已审报表项目],B13,科目余额表[期末贷方]),IF(A13="贷",SUMIF(科目余额表[已审报表项目],B13,科目余额表[期末贷方])-SUMIF(科目余额表[已审报表项目],B13,科目余额表[期末借方]),SUMIF(科目余额表[已审报表项目],B13,科目余额表[本期借方]))) -> 0 | E13: =试算平衡表[[#This Row],[审定报表金额]]-试算平衡表[[#This Row],[未申报表金额]] -> 0 | F13: 0 | G13: =F13-IF(A13="借",SUMIF(科目余额表[未审报表项目],B13,科目余额表[期末借方])-SUMIF(科目余额表[未审报表项目],B13,科目余额表[期末贷方]),IF(A13="贷",SUMIF(科目余额表[未审报表项目],B13,科目余额表[期末贷方])-SUMIF(科目余额表[未审报表项目],B13,科目余额表[期末借方]),SUMIF(科目余额表[未审报表项目],B13,科目余额表[本期借方]))) -> 0
... A79: 发生 | B79: 所得税费用 | C79: 0 | D79: =IF(A79="借",SUMIF(科目余额表[已审报表项目],B79,科目余额表[期末借方])-SUMIF(科目余额表[已审报表项目],B79,科目余额表[期末贷方]),IF(A79="贷",SUMIF(科目余额表[已审报表项目],B79,科目余额表[期末贷方])-SUMIF(科目余额表[已审报表项目],B79,科目余额表[期末借方]),SUMIF(科目余额表[已审报表项目],B79,科目余额表[本期借方]))) -> 579779.36 | E79: =试算平衡表[[#This Row],[审定报表金额]]-试算平衡表[[#This Row],[未申报表金额]] -> 0 | F79: 579779.36 | G79: =F79-IF(A79="借",SUMIF(科目余额表[未审报表项目],B79,科目余额表[期末借方])-SUMIF(科目余额表[未审报表项目],B79,科目余额表[期末贷方]),IF(A79="贷",SUMIF(科目余额表[未审报表项目],B79,科目余额表[期末贷方])-SUMIF(科目余额表[未审报表项目],B79,科目余额表[期末借方]),SUMIF(科目余额表[未审报表项目],B79,科目余额表[本期借方]))) -> 0

Sheet 调整目录
A1: 科目编码 | B1: 科目名称 | C1: 期初借方 | D1: 期初贷方 | E1: 本期借方 | F1: 本期贷方 | G1: 期末借方 | H1: 期末贷方 | I1: 未审报表项目 | J1: 已审报表项目 | K1: 调整 | L1: 抽查项目 | M1: 测算项目
A2: {=_xlfn._xlws.FILTER(科目余额表!A:M,科目余额表!K:K="是")} -> 1123001 | B2: K有限公司 | C2: 200199.49 | D2: 0 | E2: 0 | F2: 568842 | G2: -368642.51 | H2: 0 | I2: 预付款项 | J2: 应付账款 | K2: 是 | L2: 预付款项 | M2: 0
A3: 1123002 | B3: L有限公司 | C3: 188355.45 | D3: 0 | E3: 0 | F3: 698000 | G3: -509644.55 | H3: 0 | I3: 预付款项 | J3: 应付账款 | K3: 是 | L3: 预付款项 | M3: 0
A4: 1123003 | B4: M有限公司 | C4: 422009.32 | D4: 0 | E4: 0 | F4: 568842 | G4: -146832.68 | H4: 0 | I4: 预付款项 | J4: 应付账款 | K4: 是 | L4: 预付款项 | M4: 0
A5: 1123005 | B5: C有限公司 | C5: 235333.35 | D5: 0 | E5: 0 | F5: 1361700 | G5: -1126366.6 | H5: 0 | I5: 预付款项 | J5: 应付账款 | K5: 是 | L5: 预付款项 | M5: 0
A6: 1123007 | B6: P有限公司 | C6: 230444.39 | D6: 0 | E6: 0 | F6: 763880 | G6: -533435.61 | H6: 0 | I6: 预付款项 | J6: 应付账款 | K6: 是 | L6: 预付款项 | M6: 0
A7: 1123008 | B7: Q有限公司 | C7: 201008 | D7: 0 | E7: 0 | F7: 908000 | G7: -706992 | H7: 0 | I7: 预付款项 | J7: 应付账款 | K7: 是 | L7: 预付款项 | M7: 0
A8: 5401 | B8: 主营业务成本 | C8: 0 | D8: 0 | E8: 10878000 | F8: 10878000 | G8: 0 | H8: 0 | I8: 营业成本 | J8: 0 | K8: 是 | L8: 营业成本 | M8: 0
A9: 5602002 | B9: 办公费 | C9: 0 | D9: 0 | E9: 5275 | F9: 5275 | G9: 0 | H9: 0 | I9: 管理费用 | J9: 0 | K9: 是 | L9: 管理费用 | M9: 0
A10: 0 | B10: N有限公司 | C10: 0 | D10: 0 | E10: 0 | F10: 0 | G10: -334588.9 | H10: 0 | I10: 0 | J10: 预付款项 | K10: 是 | L10: 0 | M10: 0
A11: 0 | B11: N有限公司 | C11: 0 | D11: 0 | E11: 0 | F11: 0 | G11: 0 | H11: -334588.9 | I11: 0 | J11: 应付账款 | K11: 是 | L11: 0 | M11: 0
A12: 0 | B12: 主营业务成本 | C12: 0 | D12: 0 | E12: 10789000 | F12: 10789000 | G12: 0 | H12: 0 | I12: 0 | J12: 营业成本 | K12: 是 | L12: 0 | M12: 0
A13: 0 | B13: 研发费用-直接投入 | C13: 0 | D13: 0 | E13: 89000 | F13: 89000 | G13: 0 | H13: 0 | I13: 0 | J13: 研发费用 | K13: 是 | L13: 0 | M13: 0
A14: 0 | B14: 管理费用-办公费 | C14: 0 | D14: 0 | E14: 5175 | F14: 5175 | G14: 0 | H14: 0 | I14: 0 | J14: 管理费用 | K14: 是 | L14: 0 | M14: 0
A15: 0 | B15: 研发费用-办公费 | C15: 0 | D15: 0 | E15: 100 | F15: 100 | G15: 0 | H15: 0 | I15: 0 | J15: 研发费用 | K15: 是 | L15: 0 | M15: 0

Sheet 附注自动计算
A1: 货币资金
A2: 项目 | B2: 年末余额 | C2: 年初余额
A3: 现金 | B3: =SUMIF(科目余额表[测算项目],A3,科目余额表[期末借方]) -> 14952.34 | C3: =SUMIF(科目余额表[测算项目],A3,科目余额表[期初借方]) -> 15002.34
A4: 银行存款 | B4: =SUMIF(科目余额表[测算项目],A4,科目余额表[期末借方]) -> 14447983 | C4: =SUMIF(科目余额表[测算项目],A4,科目余额表[期初借方]) -> 995835
A5: 其他货币资金 | B5: =SUMIF(科目余额表[测算项目],A5,科目余额表[期末借方]) -> 0 | C5: =SUMIF(科目余额表[测算项目],A5,科目余额表[期初借方]) -> 0
A6: 合计 | B6: =SUM(B3:B5) -> 14462935 | C6: =SUM(C3:C5) -> 1010837.3
A7: 报表金额 | B7: =试算平衡表!D2 -> 14462935 | C7: =试算平衡表!C2 -> 1010837.3
A8: 差额 | B8: =B6-B7 -> 0 | C8: =C6-C7 -> 0
A9: 应收账款账龄
A10: 测算账龄 | B10: 年末余额
A11: 估算：1年以内（含1年） | B11: =SUM(往来项目数据聚合!I:I) -> 8036047.1
A12: 估算：1年以上 | B12: =SUM(往来项目数据聚合!J:J) -> 129200.88
A13: 账龄 | B13: 年末余额 | C13: 年初余额
A14: 1年以内（含1年）
A15: 1-2年（含2年） | D15: =IF(B15>C14,"年末1-2年（含2年）大于年初1年以内（含1年）","-") -> -
A16: 2-3年（含3年） | D16: =IF(B16>C15,"年末2-3年（含3年）大于年初1-2年（含2年）","-") -> -
A17: 3年以上 | D17: =IF(B17>C16,"年末3年以上大于年初2-3年（含3年）","-") -> -
A18: 小计 | B18: =SUM(B14:B17) -> 0 | C18: =SUM(C14:C17) -> 0
A19: 减：还账准备
A20: 合计 | B20: =B18-B19 -> 0 | C20: =C18-C19 -> 0
A21: 报表金额 | B21: =试算平衡表!D6 -> 8165248 | C21: =试算平衡表!C6 -> 5547848
A22: 差额 | B22: =B20-B21 -> -8165248 | C22: =C20-C21 -> -5547848
A23: 应收账款前五位
A24: 项目 | B24: 年末余额 | C24: 项目是否有重复项 | D24: 金额是否有重复项 | E24: 排序
A25: =IF(B25<>0,_xlfn.XLOOKUP(B25,往来项目数据聚合!CE:CE,往来项目数据聚合!CD:CD),0) -> F有限公司 | B25: =LARGE(往来项目数据聚合!CE:CE,E25) -> 1327000.9 | C25: =IF(COUNTIF(往来项目数据聚合!CD:CD,A25)>1,"有","-") -> - | D25: =IF(COUNTIF(往来项目数据聚合!CE:CE,B25)>1,"有","-") -> - | E25: 1
A26: =IF(B26<>0,_xlfn.XLOOKUP(B26,往来项目数据聚合!CE:CE,往来项目数据聚合!CD:CD),0) -> H有限公司 | B26: =LARGE(往来项目数据聚合!CE:CE,E26) -> 1005855.3 | C26: =IF(COUNTIF(往来项目数据聚合!CD:CD,A26)>1,"有","-") -> - | D26: =IF(COUNTIF(往来项目数据聚合!CE:CE,B26)>1,"有","-") -> - | E26: 2
A27: =IF(B27<>0,_xlfn.XLOOKUP(B27,往来项目数据聚合!CE:CE,往来项目数据聚合!CD:CD),0) -> A有限公司 | B27: =LARGE(往来项目数据聚合!CE:CE,E27) -> 918044.45 | C27: =IF(COUNTIF(往来项目数据聚合!CD:CD,A27)>1,"有","-") -> - | D27: =IF(COUNTIF(往来项目数据聚合!CE:CE,B27)>1,"有","-") -> - | E27: 3
A28: =IF(B28<>0,_xlfn.XLOOKUP(B28,往来项目数据聚合!CE:CE,往来项目数据聚合!CD:CD),0) -> I有限公司 | B28: =LARGE(往来项目数据聚合!CE:CE,E28) -> 917929.43 | C28: =IF(COUNTIF(往来项目数据聚合!CD:CD,A28)>1,"有","-") -> - | D28: =IF(COUNTIF(往来项目数据聚合!CE:CE,B28)>1,"有","-") -> - | E28: 4
A29: =IF(B29<>0,_xlfn.XLOOKUP(B29,往来项目数据聚合!CE:CE,往来项目数据聚合!CD:CD),0) -> G有限公司 | B29: =LARGE(往来项目数据聚合!CE:CE,E29) -> 849155.23 | C29: =IF(COUNTIF(往来项目数据聚合!CD:CD,A29)>1,"有","-") -> - | D29: =IF(COUNTIF(往来项目数据聚合!CE:CE,B29)>1,"有","-") -> - | E29: 5
A30: 预付款项账龄
A31: 测算账龄 | B31: 年末余额
A32: 估算：1年以内（含1年） | B32: =SUM(往来项目数据聚合!S:S) -> 205411.1
A33: 估算：1年以上 | B33: =SUM(往来项目数据聚合!T:T) -> 524637.24
A34: 账龄 | B34: 年末余额 | C34: 年初余额
A35: 1年以内（含1年）
A36: 1-2年（含2年） | D36: =IF(B36>C35,"年末1-2年（含2年）大于年初1年以内（含1年）","-") -> -
A37: 2-3年（含3年） | D37: =IF(B37>C36,"年末2-3年（含3年）大于年初1-2年（含2年）","-") -> -
A38: 3年以上 | D38: =IF(B38>C37,"年末3年以上大于年初2-3年（含3年）","-") -> -
A39: 小计 | B39: =SUM(B35:B38) -> 0 | C39: =SUM(C35:C38) -> 0
A40: 减：还账准备
A41: 合计 | B41: =B39-B40 -> 0 | C41: =C39-C40 -> 0
A42: 报表金额 | B42: =试算平衡表!D8 -> 730048.34 | C42: =试算平衡表!C8 -> 2001987.2
A43: 差额 | B43: =B41-B42 -> -730048.34 | C43: =C41-C42 -> -2001987.2
A44: 预付款项前五位
A45: 项目 | B45: 年末余额 | C45: 项目是否有重复项 | D45: 金额是否有重复项 | E45: 排序
A46: =IF(B46<>0,_xlfn.XLOOKUP(B46,往来项目数据聚合!CG:CG,往来项目数据聚合!CF:CF),0) -> O有限公司 | B46: =LARGE(往来项目数据聚合!CG:CG,E46) -> 730048.34 | C46: =IF(COUNTIF(往来项目数据聚合!CF:CF,A46)>1,"有","-") -> - | D46: =IF(COUNTIF(往来项目数据聚合!CG:CG,B46)>1,"有","-") -> - | E46: 1
A47: =IF(B47<>0,_xlfn.XLOOKUP(B47,往来项目数据聚合!CG:CG,往来项目数据聚合!CF:CF),0) -> 0 | B47: =LARGE(往来项目数据聚合!CG:CG,E47) -> 0 | C47: =IF(COUNTIF(往来项目数据聚合!CF:CF,A47)>1,"有","-") -> - | D47: =IF(COUNTIF(往来项目数据聚合!CG:CG,B47)>1,"有","-") -> 有 | E47: 2
A48: =IF(B48<>0,_xlfn.XLOOKUP(B48,往来项目数据聚合!CG:CG,往来项目数据聚合!CF:CF),0) -> 0 | B48: =LARGE(往来项目数据聚合!CG:CG,E48) -> 0 | C48: =IF(COUNTIF(往来项目数据聚合!CF:CF,A48)>1,"有","-") -> - | D48: =IF(COUNTIF(往来项目数据聚合!CG:CG,B48)>1,"有","-") -> 有 | E48: 3
A49: =IF(B49<>0,_xlfn.XLOOKUP(B49,往来项目数据聚合!CG:CG,往来项目数据聚合!CF:CF),0) -> 0 | B49: =LARGE(往来项目数据聚合!CG:CG,E49) -> 0 | C49: =IF(COUNTIF(往来项目数据聚合!CF:CF,A49)>1,"有","-") -> - | D49: =IF(COUNTIF(往来项目数据聚合!CG:CG,B49)>1,"有","-") -> 有 | E49: 4
A50: =IF(B50<>0,_xlfn.XLOOKUP(B50,往来项目数据聚合!CG:CG,往来项目数据聚合!CF:CF),0) -> 0 | B50: =LARGE(往来项目数据聚合!CG:CG,E50) -> 0 | C50: =IF(COUNTIF(往来项目数据聚合!CF:CF,A50)>1,"有","-") -> - | D50: =IF(COUNTIF(往来项目数据聚合!CG:CG,B50)>1,"有","-") -> 有 | E50: 5
A51: 合同资产
A52: 测算账龄 | B52: 年末余额
A53: 估算：1年以内（含1年） | B53: =SUM(往来项目数据聚合!AC:AC) -> 0
A54: 估算：1年以上 | B54: =SUM(往来项目数据聚合!AD:AD) -> 0
A55: 账龄 | B55: 年末余额 | C55: 年初余额
A56: 1年以内（含1年）
A57: 1-2年（含2年） | D57: =IF(B57>C56,"年末1-2年（含2年）大于年初1年以内（含1年）","-") -> -
A58: 2-3年（含3年） | D58: =IF(B58>C57,"年末2-3年（含3年）大于年初1-2年（含2年）","-") -> -
A59: 3年以上 | D59: =IF(B59>C58,"年末3年以上大于年初2-3年（含3年）","-") -> -
A60: 小计 | B60: =SUM(B56:B59) -> 0 | C60: =SUM(C56:C59) -> 0
A61: 减：还账准备
A62: 合计 | B62: =B60-B61 -> 0 | C62: =C60-C61 -> 0
A63: 报表金额 | B63: =试算平衡表!D11 -> 0 | C63: =试算平衡表!C11 -> 0
A64: 差额 | B64: =B62-B63 -> 0 | C64: =C62-C63 -> 0
A65: 合同资产前五位
A66: 项目 | B66: 年末余额 | C66: 项目是否有重复项 | D66: 金额是否有重复项 | E66: 排序
A67: =IF(B67<>0,_xlfn.XLOOKUP(B67,往来项目数据聚合!CI:CI,往来项目数据聚合!CH:CH),0) -> 0 | B67: =LARGE(往来项目数据聚合!CI:CI,E67) -> 0 | C67: =IF(COUNTIF(往来项目数据聚合!CH:CH,A67)>1,"有","-") -> - | D67: =IF(COUNTIF(往来项目数据聚合!CI:CI,B67)>1,"有","-") -> 有 | E67: 1
A68: =IF(B68<>0,_xlfn.XLOOKUP(B68,往来项目数据聚合!CI:CI,往来项目数据聚合!CH:CH),0) -> 0 | B68: =LARGE(往来项目数据聚合!CI:CI,E68) -> 0 | C68: =IF(COUNTIF(往来项目数据聚合!CH:CH,A68)>1,"有","-") -> - | D68: =IF(COUNTIF(往来项目数据聚合!CI:CI,B68)>1,"有","-") -> 有 | E68: 2
A69: =IF(B69<>0,_xlfn.XLOOKUP(B69,往来项目数据聚合!CI:CI,往来项目数据聚合!CH:CH),0) -> 0 | B69: =LARGE(往来项目数据聚合!CI:CI,E69) -> 0 | C69: =IF(COUNTIF(往来项目数据聚合!CH:CH,A69)>1,"有","-") -> - | D69: =IF(COUNTIF(往来项目数据聚合!CI:CI,B69)>1,"有","-") -> 有 | E69: 3
A70: =IF(B70<>0,_xlfn.XLOOKUP(B70,往来项目数据聚合!CI:CI,往来项目数据聚合!CH:CH),0) -> 0 | B70: =LARGE(往来项目数据聚合!CI:CI,E70) -> 0 | C70: =IF(COUNTIF(往来项目数据聚合!CH:CH,A70)>1,"有","-") -> - | D70: =IF(COUNTIF(往来项目数据聚合!CI:CI,B70)>1,"有","-") -> 有 | E70: 4
A71: =IF(B71<>0,_xlfn.XLOOKUP(B71,往来项目数据聚合!CI:CI,往来项目数据聚合!CH:CH),0) -> 0 | B71: =LARGE(往来项目数据聚合!CI:CI,E71) -> 0 | C71: =IF(COUNTIF(往来项目数据聚合!CH:CH,A71)>1,"有","-") -> - | D71: =IF(COUNTIF(往来项目数据聚合!CI:CI,B71)>1,"有","-") -> 有 | E71: 5
A72: 其他应收款账龄
A73: 账龄 | B73: 年末余额
A74: 估算：1年以内（含1年） | B74: =SUM(往来项目数据聚合!AM:AM) -> 0
A75: 估算：1年以上 | B75: =SUM(往来项目数据聚合!AN:AN) -> 219934.57
A76: 账龄 | B76: 年末余额 | C76: 年初余额
A77: 1年以内（含1年）
A78: 1-2年（含2年） | D78: =IF(B78>C77,"年末1-2年（含2年）大于年初1年以内（含1年）","-") -> -
A79: 2-3年（含3年） | D79: =IF(B79>C78,"年末2-3年（含3年）大于年初1-2年（含2年）","-") -> -
A80: 3年以上 | D80: =IF(B80>C79,"年末3年以上大于年初2-3年（含3年）","-") -> -
A81: 小计 | B81: =SUM(B77:B80) -> 0 | C81: =SUM(C77:C80) -> 0
A82: 减：还账准备
A83: 合计 | B83: =B81-B82 -> 0 | C83: =C81-C82 -> 0
A84: 报表金额 | B84: =试算平衡表!D9 -> 219934.57 | C84: =试算平衡表!C9 -> 229934.57
A85: 差额 | B85: =B83-B84 -> -219934.57 | C85: =C83-C84 -> -229934.57
A86: 其他应收款前五位
A87: 项目 | B87: 年末余额 | C87: 项目是否有重复项 | D87: 金额是否有重复项 | E87: 排序
A88: =IF(B88<>0,_xlfn.XLOOKUP(B88,往来项目数据聚合!CK:CK,往来项目数据聚合!CJ:CJ),0) -> 王五 | B88: =LARGE(往来项目数据聚合!CK:CK,E88) -> 82164.36 | C88: =IF(COUNTIF(往来项目数据聚合!CJ:CJ,A88)>1,"有","-") -> - | D88: =IF(COUNTIF(往来项目数据聚合!CK:CK,B88)>1,"有","-") -> - | E88: 1
A89: =IF(B89<>0,_xlfn.XLOOKUP(B89,往来项目数据聚合!CK:CK,往来项目数据聚合!CJ:CJ),0) -> 张三 | B89: =LARGE(往来项目数据聚合!CK:CK,E89) -> 78922.34 | C89: =IF(COUNTIF(往来项目数据聚合!CJ:CJ,A89)>1,"有","-") -> - | D89: =IF(COUNTIF(往来项目数据聚合!CK:CK,B89)>1,"有","-") -> - | E89: 2
A90: =IF(B90<>0,_xlfn.XLOOKUP(B90,往来项目数据聚合!CK:CK,往来项目数据聚合!CJ:CJ),0) -> 李四 | B90: =LARGE(往来项目数据聚合!CK:CK,E90) -> 58847.87 | C90: =IF(COUNTIF(往来项目数据聚合!CJ:CJ,A90)>1,"有","-") -> - | D90: =IF(COUNTIF(往来项目数据聚合!CK:CK,B90)>1,"有","-") -> - | E90: 3
A91: =IF(B91<>0,_xlfn.XLOOKUP(B91,往来项目数据聚合!CK:CK,往来项目数据聚合!CJ:CJ),0) -> 0 | B91: =LARGE(往来项目数据聚合!CK:CK,E91) -> 0 | C91: =IF(COUNTIF(往来项目数据聚合!CJ:CJ,A91)>1,"有","-") -> - | D91: =IF(COUNTIF(往来项目数据聚合!CK:CK,B91)>1,"有","-") -> 有 | E91: 4
A92: =IF(B92<>0,_xlfn.XLOOKUP(B92,往来项目数据聚合!CK:CK,往来项目数据聚合!CJ:CJ),0) -> 0 | B92: =LARGE(往来项目数据聚合!CK:CK,E92) -> 0 | C92: =IF(COUNTIF(往来项目数据聚合!CJ:CJ,A92)>1,"有","-") -> - | D92: =IF(COUNTIF(往来项目数据聚合!CK:CK,B92)>1,"有","-") -> 有 | E92: 5
A93: 固定资产
A94: 项目 | B94: 年初余额 | C94: 本年增加额 | D94: 本年减少额 | E94: 年末余额
A95: 固定资产原值 | B95: =SUM(B96:B100) -> 2007689 | C95: =SUM(C96:C100) -> 350000 | D95: =SUM(D96:D100) -> 0 | E95: =SUM(E96:E100) -> 2357689
A96: 固-运输工具 | B96: =SUMIF(科目余额表[测算项目],A96,科目余额表[期初借方]) -> 1877654.6 | C96: =SUMIF(科目余额表[测算项目],A96,科目余额表[本期借方]) -> 350000 | D96: =SUMIF(科目余额表[测算项目],A96,科目余额表[本期贷方]) -> 0 | E96: =SUMIF(科目余额表[测算项目],A96,科目余额表[期末借方]) -> 2227654.6
A97: 固-电子设备 | B97: =SUMIF(科目余额表[测算项目],A97,科目余额表[期初借方]) -> 130034.38 | C97: =SUMIF(科目余额表[测算项目],A97,科目余额表[本期借方]) -> 0 | D97: =SUMIF(科目余额表[测算项目],A97,科目余额表[本期贷方]) -> 0 | E97: =SUMIF(科目余额表[测算项目],A97,科目余额表[期末借方]) -> 130034.38
B98: =SUMIF(科目余额表[测算项目],A98,科目余额表[期初借方]) -> 0 | C98: =SUMIF(科目余额表[测算项目],A98,科目余额表[本期借方]) -> 0 | D98: =SUMIF(科目余额表[测算项目],A98,科目余额表[本期贷方]) -> 0 | E98: =SUMIF(科目余额表[测算项目],A98,科目余额表[期末借方]) -> 0
B99: =SUMIF(科目余额表[测算项目],A99,科目余额表[期初借方]) -> 0 | C99: =SUMIF(科目余额表[测算项目],A99,科目余额表[本期借方]) -> 0 | D99: =SUMIF(科目余额表[测算项目],A99,科目余额表[本期贷方]) -> 0 | E99: =SUMIF(科目余额表[测算项目],A99,科目余额表[期末借方]) -> 0
B100: =SUMIF(科目余额表[测算项目],A100,科目余额表[期初借方]) -> 0 | C100: =SUMIF(科目余额表[测算项目],A100,科目余额表[本期借方]) -> 0 | D100: =SUMIF(科目余额表[测算项目],A100,科目余额表[本期贷方]) -> 0 | E100: =SUMIF(科目余额表[测算项目],A100,科目余额表[期末借方]) -> 0
...

Sheet 附注自动列示
A1: 报表项目 | B1: 存货 | G1: 科目编码 | H1: 项目 | I1: 期初借方 | J1: 期初贷方 | K1: 本期借方 | L1: 本期贷方 | M1: 期末借方 | N1: 期末贷方
A2: 试算平衡表金额 | B2: =_xlfn.XLOOKUP(B1,试算平衡表[报表项目],试算平衡表[审定报表金额],0) -> 7655954.7 | C2: =_xlfn.XLOOKUP(B1,试算平衡表[报表项目],试算平衡表[期初金额],0) -> 9987654.7 | D2: =_xlfn.XLOOKUP(B1,试算平衡表[报表项目],试算平衡表[审定报表金额],0) -> 7655954.7 | E2: =_xlfn.XLOOKUP(B1,试算平衡表[报表项目],试算平衡表[审定报表金额],0) -> 7655954.7 | G2: {=_xlfn._xlws.FILTER(科目余额表[[科目编码]:[期末贷方]],科目余额表[已审报表项目]=B1,0)} -> 1405001 | H2: R商品 | I2: 4590388.5 | J2: 0 | K2: 5826500 | L2: 5436000 | M2: 4980888.5 | N2: 0
A3: 列示金额合计 | B3: =SUM(B5:B254) -> 7655954.7 | C3: =SUM(C5:C254) -> 9987654.7 | D3: =SUM(D5:D254) -> 8546300 | E3: =SUM(E5:E254) -> 10878000 | G3: 1405002 | H3: S商品 | I3: 5397266.2 | J3: 0 | K3: 2719800 | L3: 5442000 | M3: 2675066.2 | N3: 0
A4: {=_xlfn.UNIQUE(H:H)} -> 项目 | B4: 年末余额 | C4: 年初余额 | D4: 借方发生额 | E4: 贷方发生额
A5: R商品 | B5: =ABS(SUMIF(H:H,A5,M:M)-SUMIF(H:H,A5,N:N)) -> 4980888.5 | C5: =ABS(SUMIF(H:H,A5,I:I)-SUMIF(H:H,A5,J:J)) -> 4590388.5 | D5: =SUMIF(H:H,A5,K:K) -> 5826500 | E5: =SUMIF(H:H,A5,L:L) -> 5436000
A6: S商品 | B6: =ABS(SUMIF(H:H,A6,M:M)-SUMIF(H:H,A6,N:N)) -> 2675066.2 | C6: =ABS(SUMIF(H:H,A6,I:I)-SUMIF(H:H,A6,J:J)) -> 5397266.2 | D6: =SUMIF(H:H,A6,K:K) -> 2719800 | E6: =SUMIF(H:H,A6,L:L) -> 5442000
A7: 0 | B7: =ABS(SUMIF(H:H,A7,M:M)-SUMIF(H:H,A7,N:N)) -> 0 | C7: =ABS(SUMIF(H:H,A7,I:I)-SUMIF(H:H,A7,J:J)) -> 0 | D7: =SUMIF(H:H,A7,K:K) -> 0 | E7: =SUMIF(H:H,A7,L:L) -> 0
B8: =ABS(SUMIF(H:H,A8,M:M)-SUMIF(H:H,A8,N:N)) -> 0 | C8: =ABS(SUMIF(H:H,A8,I:I)-SUMIF(H:H,A8,J:J)) -> 0 | D8: =SUMIF(H:H,A8,K:K) -> 0 | E8: =SUMIF(H:H,A8,L:L) -> 0
B9: =ABS(SUMIF(H:H,A9,M:M)-SUMIF(H:H,A9,N:N)) -> 0 | C9: =ABS(SUMIF(H:H,A9,I:I)-SUMIF(H:H,A9,J:J)) -> 0 | D9: =SUMIF(H:H,A9,K:K) -> 0 | E9: =SUMIF(H:H,A9,L:L) -> 0
B10: =ABS(SUMIF(H:H,A10,M:M)-SUMIF(H:H,A10,N:N)) -> 0 | C10: =ABS(SUMIF(H:H,A10,I:I)-SUMIF(H:H,A10,J:J)) -> 0 | D10: =SUMIF(H:H,A10,K:K) -> 0 | E10: =SUMIF(H:H,A10,L:L) -> 0
B11: =ABS(SUMIF(H:H,A11,M:M)-SUMIF(H:H,A11,N:N)) -> 0 | C11: =ABS(SUMIF(H:H,A11,I:I)-SUMIF(H:H,A11,J:J)) -> 0 | D11: =SUMIF(H:H,A11,K:K) -> 0 | E11: =SUMIF(H:H,A11,L:L) -> 0
B12: =ABS(SUMIF(H:H,A12,M:M)-SUMIF(H:H,A12,N:N)) -> 0 | C12: =ABS(SUMIF(H:H,A12,I:I)-SUMIF(H:H,A12,J:J)) -> 0 | D12: =SUMIF(H:H,A12,K:K) -> 0 | E12: =SUMIF(H:H,A12,L:L) -> 0
B13: =ABS(SUMIF(H:H,A13,M:M)-SUMIF(H:H,A13,N:N)) -> 0 | C13: =ABS(SUMIF(H:H,A13,I:I)-SUMIF(H:H,A13,J:J)) -> 0 | D13: =SUMIF(H:H,A13,K:K) -> 0 | E13: =SUMIF(H:H,A13,L:L) -> 0
B14: =ABS(SUMIF(H:H,A14,M:M)-SUMIF(H:H,A14,N:N)) -> 0 | C14: =ABS(SUMIF(H:H,A14,I:I)-SUMIF(H:H,A14,J:J)) -> 0 | D14: =SUMIF(H:H,A14,K:K) -> 0 | E14: =SUMIF(H:H,A14,L:L) -> 0
B15: =ABS(SUMIF(H:H,A15,M:M)-SUMIF(H:H,A15,N:N)) -> 0 | C15: =ABS(SUMIF(H:H,A15,I:I)-SUMIF(H:H,A15,J:J)) -> 0 | D15: =SUMIF(H:H,A15,K:K) -> 0 | E15: =SUMIF(H:H,A15,L:L) -> 0
B16: =ABS(SUMIF(H:H,A16,M:M)-SUMIF(H:H,A16,N:N)) -> 0 | C16: =ABS(SUMIF(H:H,A16,I:I)-SUMIF(H:H,A16,J:J)) -> 0 | D16: =SUMIF(H:H,A16,K:K) -> 0 | E16: =SUMIF(H:H,A16,L:L) -> 0
B17: =ABS(SUMIF(H:H,A17,M:M)-SUMIF(H:H,A17,N:N)) -> 0 | C17: =ABS(SUMIF(H:H,A17,I:I)-SUMIF(H:H,A17,J:J)) -> 0 | D17: =SUMIF(H:H,A17,K:K) -> 0 | E17: =SUMIF(H:H,A17,L:L) -> 0
B18: =ABS(SUMIF(H:H,A18,M:M)-SUMIF(H:H,A18,N:N)) -> 0 | C18: =ABS(SUMIF(H:H,A18,I:I)-SUMIF(H:H,A18,J:J)) -> 0 | D18: =SUMIF(H:H,A18,K:K) -> 0 | E18: =SUMIF(H:H,A18,L:L) -> 0
B19: =ABS(SUMIF(H:H,A19,M:M)-SUMIF(H:H,A19,N:N)) -> 0 | C19: =ABS(SUMIF(H:H,A19,I:I)-SUMIF(H:H,A19,J:J)) -> 0 | D19: =SUMIF(H:H,A19,K:K) -> 0 | E19: =SUMIF(H:H,A19,L:L) -> 0
... B254: =ABS(SUMIF(H:H,A254,M:M)-SUMIF(H:H,A254,N:N)) -> 0 | C254: =ABS(SUMIF(H:H,A254,I:I)-SUMIF(H:H,A254,J:J)) -> 0 | D254: =SUMIF(H:H,A254,K:K) -> 0 | E254: =SUMIF(H:H,A254,L:L) -> 0

Sheet 往来抵消检查
A1: 项目 | B1: 循环重复 | C1: 总重复 | E1: 票据是否双向 | F1: 收款是否双向 | G1: 付款是否双向 | H1: 合同是否双向 | I1: 其他是否双向 | K1: 应收票据 | L1: 应付票据 | M1: 应收账款 | N1: 预收款项 | O1: 预付款项 | P1: 应付账款 | Q1: 合同资产 | R1: 合同负债 | S1: 其他应收款 | T1: 其他应付款 | V1: {=_xlfn._xlws.FILTER(科目余额表[科目名称],科目余额表[未审报表项目]="应收票据")} -> #VALUE! | W1: {=_xlfn._xlws.FILTER(科目余额表[科目名称],科目余额表[未审报表项目]="应收账款")} -> A有限公司 | X1: {=_xlfn._xlws.FILTER(科目余额表[科目名称],科目余额表[未审报表项目]="预付款项")} -> K有限公司 | Y1: {=_xlfn._xlws.FILTER(科目余额表[科目名称],科目余额表[未审报表项目]="合同资产")} -> #VALUE! | Z1: {=_xlfn._xlws.FILTER(科目余额表[科目名称],科目余额表[未审报表项目]="其他应收款")} -> 张三 | AA1: {=_xlfn._xlws.FILTER(科目余额表[科目名称],科目余额表[未审报表项目]="应付票据")} -> #VALUE! | AB1: {=_xlfn._xlws.FILTER(科目余额表[科目名称],科目余额表[未审报表项目]="应付账款")} -> T有限公司 | AC1: {=_xlfn._xlws.FILTER(科目余额表[科目名称],科目余额表[未审报表项目]="预收款项")} -> #VALUE! | AD1: {=_xlfn._xlws.FILTER(科目余额表[科目名称],科目余额表[未审报表项目]="合同资产")} -> #VALUE! | AE1: {=_xlfn._xlws.FILTER(科目余额表[科目名称],科目余额表[未审报表项目]="其他应付款")} -> 甲
A2: {=_xlfn.UNIQUE(_xlfn.TOCOL(V:AE,3,TRUE))} -> A有限公司 | B2: =IF(COUNTIF(E2:I2,"是")>0,"是","—") -> — | C2: =IF(10-COUNTIF(K2:T2,0)>1,"是","—") -> — | E2: =IF(AND(K2<>0,L2<>0),"是","—") -> — | F2: =IF(AND(M2<>0,N2<>0),"是","—") -> — | G2: =IF(AND(O2<>0,P2<>0),"是","—") -> — | H2: =IF(AND(Q2<>0,R2<>0),"是","—") -> — | I2: =IF(AND(S2<>0,T2<>0),"是","—") -> — | K2: =SUMIFS(科目余额表[期末借方],科目余额表[已审报表项目],K$1,科目余额表[科目名称],A2)-SUMIFS(科目余额表[期末贷方],科目余额表[已审报表项目],K$1,科目余额表[科目名称],A2) -> 0 | L2: =SUMIFS(科目余额表[期末贷方],科目余额表[已审报表项目],L$1,科目余额表[科目名称],A2)-SUMIFS(科目余额表[期末借方],科目余额表[已审报表项目],L$1,科目余额表[科目名称],A2) -> 0 | M2: =SUMIFS(科目余额表[期末借方],科目余额表[已审报表项目],M$1,科目余额表[科目名称],A2)-SUMIFS(科目余额表[期末贷方],科目余额表[已审报表项目],M$1,科目余额表[科目名称],A2) -> 918044.45 | N2: =SUMIFS(科目余额表[期末贷方],科目余额表[已审报表项目],N$1,科目余额表[科目名称],A2)-SUMIFS(科目余额表[期末借方],科目余额表[已审报表项目],N$1,科目余额表[科目名称],A2) -> 0 | O2: =SUMIFS(科目余额表[期末借方],科目余额表[已审报表项目],O$1,科目余额表[科目名称],A2)-SUMIFS(科目余额表[期末贷方],科目余额表[已审报表项目],O$1,科目余额表[科目名称],A2) -> 0 | P2: =SUMIFS(科目余额表[期末贷方],科目余额表[已审报表项目],P$1,科目余额表[科目名称],A2)-SUMIFS(科目余额表[期末借方],科目余额表[已审报表项目],P$1,科目余额表[科目名称],A2) -> 0 | Q2: =SUMIFS(科目余额表[期末借方],科目余额表[已审报表项目],Q$1,科目余额表[科目名称],A2)-SUMIFS(科目余额表[期末贷方],科目余额表[已审报表项目],Q$1,科目余额表[科目名称],A2) -> 0 | R2: =SUMIFS(科目余额表[期末贷方],科目余额表[已审报表项目],R$1,科目余额表[科目名称],A2)-SUMIFS(科目余额表[期末借方],科目余额表[已审报表项目],R$1,科目余额表[科目名称],A2) -> 0 | S2: =SUMIFS(科目余额表[期末借方],科目余额表[已审报表项目],S$1,科目余额表[科目名称],A2)-SUMIFS(科目余额表[期末贷方],科目余额表[已审报表项目],S$1,科目余额表[科目名称],A2) -> 0 | T2: =SUMIFS(科目余额表[期末贷方],科目余额表[已审报表项目],T$1,科目余额表[科目名称],A2)-SUMIFS(科目余额表[期末借方],科目余额表[已审报表项目],T$1,科目余额表[科目名称],A2) -> 0 | W2: B有限公司 | X2: L有限公司 | Z2: 李四 | AB2: U有限公司 | AE2: 乙
A3: B有限公司 | B3: =IF(COUNTIF(E3:I3,"是")>0,"是","—") -> — | C3: =IF(10-COUNTIF(K3:T3,0)>1,"是","—") -> — | E3: =IF(AND(K3<>0,L3<>0),"是","—") -> — | F3: =IF(AND(M3<>0,N3<>0),"是","—") -> — | G3: =IF(AND(O3<>0,P3<>0),"是","—") -> — | H3: =IF(AND(Q3<>0,R3<>0),"是","—") -> — | I3: =IF(AND(S3<>0,T3<>0),"是","—") -> — | K3: =SUMIFS(科目余额表[期末借方],科目余额表[已审报表项目],K$1,科目余额表[科目名称],A3)-SUMIFS(科目余额表[期末贷方],科目余额表[已审报表项目],K$1,科目余额表[科目名称],A3) -> 0 | L3: =SUMIFS(科目余额表[期末贷方],科目余额表[已审报表项目],L$1,科目余额表[科目名称],A3)-SUMIFS(科目余额表[期末借方],科目余额表[已审报表项目],L$1,科目余额表[科目名称],A3) -> 0 | M3: =SUMIFS(科目余额表[期末借方],科目余额表[已审报表项目],M$1,科目余额表[科目名称],A3)-SUMIFS(科目余额表[期末贷方],科目余额表[已审报表项目],M$1,科目余额表[科目名称],A3) -> 572824.39 | N3: =SUMIFS(科目余额表[期末贷方],科目余额表[已审报表项目],N$1,科目余额表[科目名称],A3)-SUMIFS(科目余额表[期末借方],科目余额表[已审报表项目],N$1,科目余额表[科目名称],A3) -> 0 | O3: =SUMIFS(科目余额表[期末借方],科目余额表[已审报表项目],O$1,科目余额表[科目名称],A3)-SUMIFS(科目余额表[期末贷方],科目余额表[已审报表项目],O$1,科目余额表[科目名称],A3) -> 0 | P3: =SUMIFS(科目余额表[期末贷方],科目余额表[已审报表项目],P$1,科目余额表[科目名称],A3)-SUMIFS(科目余额表[期末借方],科目余额表[已审报表项目],P$1,科目余额表[科目名称],A3) -> 0 | Q3: =SUMIFS(科目余额表[期末借方],科目余额表[已审报表项目],Q$1,科目余额表[科目名称],A3)-SUMIFS(科目余额表[期末贷方],科目余额表[已审报表项目],Q$1,科目余额表[科目名称],A3) -> 0 | R3: =SUMIFS(科目余额表[期末贷方],科目余额表[已审报表项目],R$1,科目余额表[科目名称],A3)-SUMIFS(科目余额表[期末借方],科目余额表[已审报表项目],R$1,科目余额表[科目名称],A3) -> 0 | S3: =SUMIFS(科目余额表[期末借方],科目余额表[已审报表项目],S$1,科目余额表[科目名称],A3)-SUMIFS(科目余额表[期末贷方],科目余额表[已审报表项目],S$1,科目余额表[科目名称],A3) -> 0 | T3: =SUMIFS(科目余额表[期末贷方],科目余额表[已审报表项目],T$1,科目余额表[科目名称],A3)-SUMIFS(科目余额表[期末借方],科目余额表[已审报表项目],T$1,科目余额表[科目名称],A3) -> 0 | W3: C有限公司 | X3: M有限公司 | Z3: 王五 | AB3: M有限公司 | AE3: 丙
A4: C有限公司 | B4: =IF(COUNTIF(E4:I4,"是")>0,"是","—") -> — | C4: =IF(10-COUNTIF(K4:T4,0)>1,"是","—") -> 是 | E4: =IF(AND(K4<>0,L4<>0),"是","—") -> — | F4: =IF(AND(M4<>0,N4<>0),"是","—") -> — | G4: =IF(AND(O4<>0,P4<>0),"是","—") -> — | H4: =IF(AND(Q4<>0,R4<>0),"是","—") -> — | I4: =IF(AND(S4<>0,T4<>0),"是","—") -> — | K4: =SUMIFS(科目余额表[期末借方],科目余额表[已审报表项目],K$1,科目余额表[科目名称],A4)-SUMIFS(科目余额表[期末贷方],科目余额表[已审报表项目],K$1,科目余额表[科目名称],A4) -> 0 | L4: =SUMIFS(科目余额表[期末贷方],科目余额表[已审报表项目],L$1,科目余额表[科目名称],A4)-SUMIFS(科目余额表[期末借方],科目余额表[已审报表项目],L$1,科目余额表[科目名称],A4) -> 0 | M4: =SUMIFS(科目余额表[期末借方],科目余额表[已审报表项目],M$1,科目余额表[科目名称],A4)-SUMIFS(科目余额表[期末贷方],科目余额表[已审报表项目],M$1,科目余额表[科目名称],A4) -> 642499.99 | N4: =SUMIFS(科目余额表[期末贷方],科目余额表[已审报表项目],N$1,科目余额表[科目名称],A4)-SUMIFS(科目余额表[期末借方],科目余额表[已审报表项目],N$1,科目余额表[科目名称],A4) -> 0 | O4: =SUMIFS(科目余额表[期末借方],科目余额表[已审报表项目],O$1,科目余额表[科目名称],A4)-SUMIFS(科目余额表[期末贷方],科目余额表[已审报表项目],O$1,科目余额表[科目名称],A4) -> 0 | P4: =SUMIFS(科目余额表[期末贷方],科目余额表[已审报表项目],P$1,科目余额表[科目名称],A4)-SUMIFS(科目余额表[期末借方],科目余额表[已审报表项目],P$1,科目余额表[科目名称],A4) -> 1126366.6 | Q4: =SUMIFS(科目余额表[期末借方],科目余额表[已审报表项目],Q$1,科目余额表[科目名称],A4)-SUMIFS(科目余额表[期末贷方],科目余额表[已审报表项目],Q$1,科目余额表[科目名称],A4) -> 0 | R4: =SUMIFS(科目余额表[期末贷方],科目余额表[已审报表项目],R$1,科目余额表[科目名称],A4)-SUMIFS(科目余额表[期末借方],科目余额表[已审报表项目],R$1,科目余额表[科目名称],A4) -> 0 | S4: =SUMIFS(科目余额表[期末借方],科目余额表[已审报表项目],S$1,科目余额表[科目名称],A4)-SUMIFS(科目余额表[期末贷方],科目余额表[已审报表项目],S$1,科目余额表[科目名称],A4) -> 0 | T4: =SUMIFS(科目余额表[期末贷方],科目余额表[已审报表项目],T$1,科目余额表[科目名称],A4)-SUMIFS(科目余额表[期末借方],科目余额表[已审报表项目],T$1,科目余额表[科目名称],A4) -> 0 | W4: D有限公司 | X4: N有限公司 | AB4: V有限公司 | AE4: 丁
A5: D有限公司 | B5: =IF(COUNTIF(E5:I5,"是")>0,"是","—") -> — | C5: =IF(10-COUNTIF(K5:T5,0)>1,"是","—") -> — | E5: =IF(AND(K5<>0,L5<>0),"是","—") -> — | F5: =IF(AND(M5<>0,N5<>0),"是","—") -> — | G5: =IF(AND(O5<>0,P5<>0),"是","—") -> — | H5: =IF(AND(Q5<>0,R5<>0),"是","—") -> — | I5: =IF(AND(S5<>0,T5<>0),"是","—") -> — | K5: =SUMIFS(科目余额表[期末借方],科目余额表[已审报表项目],K$1,科目余额表[科目名称],A5)-SUMIFS(科目余额表[期末贷方],科目余额表[已审报表项目],K$1,科目余额表[科目名称],A5) -> 0 | L5: =SUMIFS(科目余额表[期末贷方],科目余额表[已审报表项目],L$1,科目余额表[科目名称],A5)-SUMIFS(科目余额表[期末借方],科目余额表[已审报表项目],L$1,科目余额表[科目名称],A5) -> 0 | M5: =SUMIFS(科目余额表[期末借方],科目余额表[已审报表项目],M$1,科目余额表[科目名称],A5)-SUMIFS(科目余额表[期末贷方],科目余额表[已审报表项目],M$1,科目余额表[科目名称],A5) -> 826988.45 | N5: =SUMIFS(科目余额表[期末贷方],科目余额表[已审报表项目],N$1,科目余额表[科目名称],A5)-SUMIFS(科目余额表[期末借方],科目余额表[已审报表项目],N$1,科目余额表[科目名称],A5) -> 0 | O5: =SUMIFS(科目余额表[期末借方],科目余额表[已审报表项目],O$1,科目余额表[科目名称],A5)-SUMIFS(科目余额表[期末贷方],科目余额表[已审报表项目],O$1,科目余额表[科目名称],A5) -> 0 | P5: =SUMIFS(科目余额表[期末贷方],科目余额表[已审报表项目],P$1,科目余额表[科目名称],A5)-SUMIFS(科目余额表[期末借方],科目余额表[已审报表项目],P$1,科目余额表[科目名称],A5) -> 0 | Q5: =SUMIFS(科目余额表[期末借方],科目余额表[已审报表项目],Q$1,科目余额表[科目名称],A5)-SUMIFS(科目余额表[期末贷方],科目余额表[已审报表项目],Q$1,科目余额表[科目名称],A5) -> 0 | R5: =SUMIFS(科目余额表[期末贷方],科目余额表[已审报表项目],R$1,科目余额表[科目名称],A5)-SUMIFS(科目余额表[期末借方],科目余额表[已审报表项目],R$1,科目余额表[科目名称],A5) -> 0 | S5: =SUMIFS(科目余额表[期末借方],科目余额表[已审报表项目],S$1,科目余额表[科目名称],A5)-SUMIFS(科目余额表[期末贷方],科目余额表[已审报表项目],S$1,科目余额表[科目名称],A5) -> 0 | T5: =SUMIFS(科目余额表[期末贷方],科目余额表[已审报表项目],T$1,科目余额表[科目名称],A5)-SUMIFS(科目余额表[期末借方],科目余额表[已审报表项目],T$1,科目余额表[科目名称],A5) -> 0 | W5: E有限公司 | X5: C有限公司 | AB5: W有限公司 | AE5: 戊
A6: E有限公司 | B6: =IF(COUNTIF(E6:I6,"是")>0,"是","—") -> — | C6: =IF(10-COUNTIF(K6:T6,0)>1,"是","—") -> — | E6: =IF(AND(K6<>0,L6<>0),"是","—") -> — | F6: =IF(AND(M6<>0,N6<>0),"是","—") -> — | G6: =IF(AND(O6<>0,P6<>0),"是","—") -> — | H6: =IF(AND(Q6<>0,R6<>0),"是","—") -> — | I6: =IF(AND(S6<>0,T6<>0),"是","—") -> — | K6: =SUMIFS(科目余额表[期末借方],科目余额表[已审报表项目],K$1,科目余额表[科目名称],A6)-SUMIFS(科目余额表[期末贷方],科目余额表[已审报表项目],K$1,科目余额表[科目名称],A6) -> 0 | L6: =SUMIFS(科目余额表[期末贷方],科目余额表[已审报表项目],L$1,科目余额表[科目名称],A6)-SUMIFS(科目余额表[期末借方],科目余额表[已审报表项目],L$1,科目余额表[科目名称],A6) -> 0 | M6: =SUMIFS(科目余额表[期末借方],科目余额表[已审报表项目],M$1,科目余额表[科目名称],A6)-SUMIFS(科目余额表[期末贷方],科目余额表[已审报表项目],M$1,科目余额表[科目名称],A6) -> 292833.49 | N6: =SUMIFS(科目余额表[期末贷方],科目余额表[已审报表项目],N$1,科目余额表[科目名称],A6)-SUMIFS(科目余额表[期末借方],科目余额表[已审报表项目],N$1,科目余额表[科目名称],A6) -> 0 | O6: =SUMIFS(科目余额表[期末借方],科目余额表[已审报表项目],O$1,科目余额表[科目名称],A6)-SUMIFS(科目余额表[期末贷方],科目余额表[已审报表项目],O$1,科目余额表[科目名称],A6) -> 0 | P6: =SUMIFS(科目余额表[期末贷方],科目余额表[已审报表项目],P$1,科目余额表[科目名称],A6)-SUMIFS(科目余额表[期末借方],科目余额表[已审报表项目],P$1,科目余额表[科目名称],A6) -> 0 | Q6: =SUMIFS(科目余额表[期末借方],科目余额表[已审报表项目],Q$1,科目余额表[科目名称],A6)-SUMIFS(科目余额表[期末贷方],科目余额表[已审报表项目],Q$1,科目余额表[科目名称],A6) -> 0 | R6: =SUMIFS(科目余额表[期末贷方],科目余额表[已审报表项目],R$1,科目余额表[科目名称],A6)-SUMIFS(科目余额表[期末借方],科目余额表[已审报表项目],R$1,科目余额表[科目名称],A6) -> 0 | S6: =SUMIFS(科目余额表[期末借方],科目余额表[已审报表项目],S$1,科目余额表[科目名称],A6)-SUMIFS(科目余额表[期末贷方],科目余额表[已审报表项目],S$1,科目余额表[科目名称],A6) -> 0 | T6: =SUMIFS(科目余额表[期末贷方],科目余额表[已审报表项目],T$1,科目余额表[科目名称],A6)-SUMIFS(科目余额表[期末借方],科目余额表[已审报表项目],T$1,科目余额表[科目名称],A6) -> 0 | W6: F有限公司 | X6: O有限公司 | AB6: X有限公司 | AE6: 申
A7: F有限公司 | B7: =IF(COUNTIF(E7:I7,"是")>0,"是","—") -> — | C7: =IF(10-COUNTIF(K7:T7,0)>1,"是","—") -> — | E7: =IF(AND(K7<>0,L7<>0),"是","—") -> — | F7: =IF(AND(M7<>0,N7<>0),"是","—") -> — | G7: =IF(AND(O7<>0,P7<>0),"是","—") -> — | H7: =IF(AND(Q7<>0,R7<>0),"是","—") -> — | I7: =IF(AND(S7<>0,T7<>0),"是","—") -> — | K7: =SUMIFS(科目余额表[期末借方],科目余额表[已审报表项目],K$1,科目余额表[科目名称],A7)-SUMIFS(科目余额表[期末贷方],科目余额表[已审报表项目],K$1,科目余额表[科目名称],A7) -> 0 | L7: =SUMIFS(科目余额表[期末贷方],科目余额表[已审报表项目],L$1,科目余额表[科目名称],A7)-SUMIFS(科目余额表[期末借方],科目余额表[已审报表项目],L$1,科目余额表[科目名称],A7) -> 0 | M7: =SUMIFS(科目余额表[期末借方],科目余额表[已审报表项目],M$1,科目余额表[科目名称],A7)-SUMIFS(科目余额表[期末贷方],科目余额表[已审报表项目],M$1,科目余额表[科目名称],A7) -> 1327000.9 | N7: =SUMIFS(科目余额表[期末贷方],科目余额表[已审报表项目],N$1,科目余额表[科目名称],A7)-SUMIFS(科目余额表[期末借方],科目余额表[已审报表项目],N$1,科目余额表[科目名称],A7) -> 0 | O7: =SUMIFS(科目余额表[期末借方],科目余额表[已审报表项目],O$1,科目余额表[科目名称],A7)-SUMIFS(科目余额表[期末贷方],科目余额表[已审报表项目],O$1,科目余额表[科目名称],A7) -> 0 | P7: =SUMIFS(科目余额表[期末贷方],科目余额表[已审报表项目],P$1,科目余额表[科目名称],A7)-SUMIFS(科目余额表[期末借方],科目余额表[已审报表项目],P$1,科目余额表[科目名称],A7) -> 0 | Q7: =SUMIFS(科目余额表[期末借方],科目余额表[已审报表项目],Q$1,科目余额表[科目名称],A7)-SUMIFS(科目余额表[期末贷方],科目余额表[已审报表项目],Q$1,科目余额表[科目名称],A7) -> 0 | R7: =SUMIFS(科目余额表[期末贷方],科目余额表[已审报表项目],R$1,科目余额表[科目名称],A7)-SUMIFS(科目余额表[期末借方],科目余额表[已审报表项目],R$1,科目余额表[科目名称],A7) -> 0 | S7: =SUMIFS(科目余额表[期末借方],科目余额表[已审报表项目],S$1,科目余额表[科目名称],A7)-SUMIFS(科目余额表[期末贷方],科目余额表[已审报表项目],S$1,科目余额表[科目名称],A7) -> 0 | T7: =SUMIFS(科目余额表[期末贷方],科目余额表[已审报表项目],T$1,科目余额表[科目名称],A7)-SUMIFS(科目余额表[期末借方],科目余额表[已审报表项目],T$1,科目余额表[科目名称],A7) -> 0 | W7: G有限公司 | X7: P有限公司 | AB7: N有限公司 | AE7: 亥
A8: G有限公司 | B8: =IF(COUNTIF(E8:I8,"是")>0,"是","—") -> — | C8: =IF(10-COUNTIF(K8:T8,0)>1,"是","—") -> — | E8: =IF(AND(K8<>0,L8<>0),"是","—") -> — | F8: =IF(AND(M8<>0,N8<>0),"是","—") -> — | G8: =IF(AND(O8<>0,P8<>0),"是","—") -> — | H8: =IF(AND(Q8<>0,R8<>0),"是","—") -> — | I8: =IF(AND(S8<>0,T8<>0),"是","—") -> — | K8: =SUMIFS(科目余额表[期末借方],科目余额表[已审报表项目],K$1,科目余额表[科目名称],A8)-SUMIFS(科目余额表[期末贷方],科目余额表[已审报表项目],K$1,科目余额表[科目名称],A8) -> 0 | L8: =SUMIFS(科目余额表[期末贷方],科目余额表[已审报表项目],L$1,科目余额表[科目名称],A8)-SUMIFS(科目余额表[期末借方],科目余额表[已审报表项目],L$1,科目余额表[科目名称],A8) -> 0 | M8: =SUMIFS(科目余额表[期末借方],科目余额表[已审报表项目],M$1,科目余额表[科目名称],A8)-SUMIFS(科目余额表[期末贷方],科目余额表[已审报表项目],M$1,科目余额表[科目名称],A8) -> 849155.23 | N8: =SUMIFS(科目余额表[期末贷方],科目余额表[已审报表项目],N$1,科目余额表[科目名称],A8)-SUMIFS(科目余额表[期末借方],科目余额表[已审报表项目],N$1,科目余额表[科目名称],A8) -> 0 | O8: =SUMIFS(科目余额表[期末借方],科目余额表[已审报表项目],O$1,科目余额表[科目名称],A8)-SUMIFS(科目余额表[期末贷方],科目余额表[已审报表项目],O$1,科目余额表[科目名称],A8) -> 0 | P8: =SUMIFS(科目余额表[期末贷方],科目余额表[已审报表项目],P$1,科目余额表[科目名称],A8)-SUMIFS(科目余额表[期末借方],科目余额表[已审报表项目],P$1,科目余额表[科目名称],A8) -> 0 | Q8: =SUMIFS(科目余额表[期末借方],科目余额表[已审报表项目],Q$1,科目余额表[科目名称],A8)-SUMIFS(科目余额表[期末贷方],科目余额表[已审报表项目],Q$1,科目余额表[科目名称],A8) -> 0 | R8: =SUMIFS(科目余额表[期末贷方],科目余额表[已审报表项目],R$1,科目余额表[科目名称],A8)-SUMIFS(科目余额表[期末借方],科目余额表[已审报表项目],R$1,科目余额表[科目名称],A8) -> 0 | S8: =SUMIFS(科目余额表[期末借方],科目余额表[已审报表项目],S$1,科目余额表[科目名称],A8)-SUMIFS(科目余额表[期末贷方],科目余额表[已审报表项目],S$1,科目余额表[科目名称],A8) -> 0 | T8: =SUMIFS(科目余额表[期末贷方],科目余额表[已审报表项目],T$1,科目余额表[科目名称],A8)-SUMIFS(科目余额表[期末借方],科目余额表[已审报表项目],T$1,科目余额表[科目名称],A8) -> 0 | W8: H有限公司 | X8: Q有限公司 | AB8: Y有限公司
A9: H有限公司 | B9: =IF(COUNTIF(E9:I9,"是")>0,"是","—") -> — | C9: =IF(10-COUNTIF(K9:T9,0)>1,"是","—") -> — | E9: =IF(AND(K9<>0,L9<>0),"是","—") -> — | F9: =IF(AND(M9<>0,N9<>0),"是","—") -> — | G9: =IF(AND(O9<>0,P9<>0),"是","—") -> — | H9: =IF(AND(Q9<>0,R9<>0),"是","—") -> — | I9: =IF(AND(S9<>0,T9<>0),"是","—") -> — | K9: =SUMIFS(科目余额表[期末借方],科目余额表[已审报表项目],K$1,科目余额表[科目名称],A9)-SUMIFS(科目余额表[期末贷方],科目余额表[已审报表项目],K$1,科目余额表[科目名称],A9) -> 0 | L9: =SUMIFS(科目余额表[期末贷方],科目余额表[已审报表项目],L$1,科目余额表[科目名称],A9)-SUMIFS(科目余额表[期末借方],科目余额表[已审报表项目],L$1,科目余额表[科目名称],A9) -> 0 | M9: =SUMIFS(科目余额表[期末借方],科目余额表[已审报表项目],M$1,科目余额表[科目名称],A9)-SUMIFS(科目余额表[期末贷方],科目余额表[已审报表项目],M$1,科目余额表[科目名称],A9) -> 1005855.3 | N9: =SUMIFS(科目余额表[期末贷方],科目余额表[已审报表项目],N$1,科目余额表[科目名称],A9)-SUMIFS(科目余额表[期末借方],科目余额表[已审报表项目],N$1,科目余额表[科目名称],A9) -> 0 | O9: =SUMIFS(科目余额表[期末借方],科目余额表[已审报表项目],O$1,科目余额表[科目名称],A9)-SUMIFS(科目余额表[期末贷方],科目余额表[已审报表项目],O$1,科目余额表[科目名称],A9) -> 0 | P9: =SUMIFS(科目余额表[期末贷方],科目余额表[已审报表项目],P$1,科目余额表[科目名称],A9)-SUMIFS(科目余额表[期末借方],科目余额表[已审报表项目],P$1,科目余额表[科目名称],A9) -> 0 | Q9: =SUMIFS(科目余额表[期末借方],科目余额表[已审报表项目],Q$1,科目余额表[科目名称],A9)-SUMIFS(科目余额表[期末贷方],科目余额表[已审报表项目],Q$1,科目余额表[科目名称],A9) -> 0 | R9: =SUMIFS(科目余额表[期末贷方],科目余额表[已审报表项目],R$1,科目余额表[科目名称],A9)-SUMIFS(科目余额表[期末借方],科目余额表[已审报表项目],R$1,科目余额表[科目名称],A9) -> 0 | S9: =SUMIFS(科目余额表[期末借方],科目余额表[已审报表项目],S$1,科目余额表[科目名称],A9)-SUMIFS(科目余额表[期末贷方],科目余额表[已审报表项目],S$1,科目余额表[科目名称],A9) -> 0 | T9: =SUMIFS(科目余额表[期末贷方],科目余额表[已审报表项目],T$1,科目余额表[科目名称],A9)-SUMIFS(科目余额表[期末借方],科目余额表[已审报表项目],T$1,科目余额表[科目名称],A9) -> 0 | W9: I有限公司 | AB9: Z有限公司
A10: I有限公司 | B10: =IF(COUNTIF(E10:I10,"是")>0,"是","—") -> — | C10: =IF(10-COUNTIF(K10:T10,0)>1,"是","—") -> — | E10: =IF(AND(K10<>0,L10<>0),"是","—") -> — | F10: =IF(AND(M10<>0,N10<>0),"是","—") -> — | G10: =IF(AND(O10<>0,P10<>0),"是","—") -> — | H10: =IF(AND(Q10<>0,R10<>0),"是","—") -> — | I10: =IF(AND(S10<>0,T10<>0),"是","—") -> — | K10: =SUMIFS(科目余额表[期末借方],科目余额表[已审报表项目],K$1,科目余额表[科目名称],A10)-SUMIFS(科目余额表[期末贷方],科目余额表[已审报表项目],K$1,科目余额表[科目名称],A10) -> 0 | L10: =SUMIFS(科目余额表[期末贷方],科目余额表[已审报表项目],L$1,科目余额表[科目名称],A10)-SUMIFS(科目余额表[期末借方],科目余额表[已审报表项目],L$1,科目余额表[科目名称],A10) -> 0 | M10: =SUMIFS(科目余额表[期末借方],科目余额表[已审报表项目],M$1,科目余额表[科目名称],A10)-SUMIFS(科目余额表[期末贷方],科目余额表[已审报表项目],M$1,科目余额表[科目名称],A10) -> 917929.43 | N10: =SUMIFS(科目余额表[期末贷方],科目余额表[已审报表项目],N$1,科目余额表[科目名称],A10)-SUMIFS(科目余额表[期末借方],科目余额表[已审报表项目],N$1,科目余额表[科目名称],A10) -> 0 | O10: =SUMIFS(科目余额表[期末借方],科目余额表[已审报表项目],O$1,科目余额表[科目名称],A10)-SUMIFS(科目余额表[期末贷方],科目余额表[已审报表项目],O$1,科目余额表[科目名称],A10) -> 0 | P10: =SUMIFS(科目余额表[期末贷方],科目余额表[已审报表项目],P$1,科目余额表[科目名称],A10)-SUMIFS(科目余额表[期末借方],科目余额表[已审报表项目],P$1,科目余额表[科目名称],A10) -> 0 | Q10: =SUMIFS(科目余额表[期末借方],科目余额表[已审报表项目],Q$1,科目余额表[科目名称],A10)-SUMIFS(科目余额表[期末贷方],科目余额表[已审报表项目],Q$1,科目余额表[科目名称],A10) -> 0 | R10: =SUMIFS(科目余额表[期末贷方],科目余额表[已审报表项目],R$1,科目余额表[科目名称],A10)-SUMIFS(科目余额表[期末借方],科目余额表[已审报表项目],R$1,科目余额表[科目名称],A10) -> 0 | S10: =SUMIFS(科目余额表[期末借方],科目余额表[已审报表项目],S$1,科目余额表[科目名称],A10)-SUMIFS(科目余额表[期末贷方],科目余额表[已审报表项目],S$1,科目余额表[科目名称],A10) -> 0 | T10: =SUMIFS(科目余额表[期末贷方],科目余额表[已审报表项目],T$1,科目余额表[科目名称],A10)-SUMIFS(科目余额表[期末借方],科目余额表[已审报表项目],T$1,科目余额表[科目名称],A10) -> 0 | W10: J有限公司
A11: J有限公司 | B11: =IF(COUNTIF(E11:I11,"是")>0,"是","—") -> — | C11: =IF(10-COUNTIF(K11:T11,0)>1,"是","—") -> — | E11: =IF(AND(K11<>0,L11<>0),"是","—") -> — | F11: =IF(AND(M11<>0,N11<>0),"是","—") -> — | G11: =IF(AND(O11<>0,P11<>0),"是","—") -> — | H11: =IF(AND(Q11<>0,R11<>0),"是","—") -> — | I11: =IF(AND(S11<>0,T11<>0),"是","—") -> — | K11: =SUMIFS(科目余额表[期末借方],科目余额表[已审报表项目],K$1,科目余额表[科目名称],A11)-SUMIFS(科目余额表[期末贷方],科目余额表[已审报表项目],K$1,科目余额表[科目名称],A11) -> 0 | L11: =SUMIFS(科目余额表[期末贷方],科目余额表[已审报表项目],L$1,科目余额表[科目名称],A11)-SUMIFS(科目余额表[期末借方],科目余额表[已审报表项目],L$1,科目余额表[科目名称],A11) -> 0 | M11: =SUMIFS(科目余额表[期末借方],科目余额表[已审报表项目],M$1,科目余额表[科目名称],A11)-SUMIFS(科目余额表[期末贷方],科目余额表[已审报表项目],M$1,科目余额表[科目名称],A11) -> 812116.34 | N11: =SUMIFS(科目余额表[期末贷方],科目余额表[已审报表项目],N$1,科目余额表[科目名称],A11)-SUMIFS(科目余额表[期末借方],科目余额表[已审报表项目],N$1,科目余额表[科目名称],A11) -> 0 | O11: =SUMIFS(科目余额表[期末借方],科目余额表[已审报表项目],O$1,科目余额表[科目名称],A11)-SUMIFS(科目余额表[期末贷方],科目余额表[已审报表项目],O$1,科目余额表[科目名称],A11) -> 0 | P11: =SUMIFS(科目余额表[期末贷方],科目余额表[已审报表项目],P$1,科目余额表[科目名称],A11)-SUMIFS(科目余额表[期末借方],科目余额表[已审报表项目],P$1,科目余额表[科目名称],A11) -> 0 | Q11: =SUMIFS(科目余额表[期末借方],科目余额表[已审报表项目],Q$1,科目余额表[科目名称],A11)-SUMIFS(科目余额表[期末贷方],科目余额表[已审报表项目],Q$1,科目余额表[科目名称],A11) -> 0 | R11: =SUMIFS(科目余额表[期末贷方],科目余额表[已审报表项目],R$1,科目余额表[科目名称],A11)-SUMIFS(科目余额表[期末借方],科目余额表[已审报表项目],R$1,科目余额表[科目名称],A11) -> 0 | S11: =SUMIFS(科目余额表[期末借方],科目余额表[已审报表项目],S$1,科目余额表[科目名称],A11)-SUMIFS(科目余额表[期末贷方],科目余额表[已审报表项目],S$1,科目余额表[科目名称],A11) -> 0 | T11: =SUMIFS(科目余额表[期末贷方],科目余额表[已审报表项目],T$1,科目余额表[科目名称],A11)-SUMIFS(科目余额表[期末借方],科目余额表[已审报表项目],T$1,科目余额表[科目名称],A11) -> 0
A12: K有限公司 | B12: =IF(COUNTIF(E12:I12,"是")>0,"是","—") -> — | C12: =IF(10-COUNTIF(K12:T12,0)>1,"是","—") -> — | E12: =IF(AND(K12<>0,L12<>0),"是","—") -> — | F12: =IF(AND(M12<>0,N12<>0),"是","—") -> — | G12: =IF(AND(O12<>0,P12<>0),"是","—") -> — | H12: =IF(AND(Q12<>0,R12<>0),"是","—") -> — | I12: =IF(AND(S12<>0,T12<>0),"是","—") -> — | K12: =SUMIFS(科目余额表[期末借方],科目余额表[已审报表项目],K$1,科目余额表[科目名称],A12)-SUMIFS(科目余额表[期末贷方],科目余额表[已审报表项目],K$1,科目余额表[科目名称],A12) -> 0 | L12: =SUMIFS(科目余额表[期末贷方],科目余额表[已审报表项目],L$1,科目余额表[科目名称],A12)-SUMIFS(科目余额表[期末借方],科目余额表[已审报表项目],L$1,科目余额表[科目名称],A12) -> 0 | M12: =SUMIFS(科目余额表[期末借方],科目余额表[已审报表项目],M$1,科目余额表[科目名称],A12)-SUMIFS(科目余额表[期末贷方],科目余额表[已审报表项目],M$1,科目余额表[科目名称],A12) -> 0 | N12: =SUMIFS(科目余额表[期末贷方],科目余额表[已审报表项目],N$1,科目余额表[科目名称],A12)-SUMIFS(科目余额表[期末借方],科目余额表[已审报表项目],N$1,科目余额表[科目名称],A12) -> 0 | O12: =SUMIFS(科目余额表[期末借方],科目余额表[已审报表项目],O$1,科目余额表[科目名称],A12)-SUMIFS(科目余额表[期末贷方],科目余额表[已审报表项目],O$1,科目余额表[科目名称],A12) -> 0 | P12: =SUMIFS(科目余额表[期末贷方],科目余额表[已审报表项目],P$1,科目余额表[科目名称],A12)-SUMIFS(科目余额表[期末借方],科目余额表[已审报表项目],P$1,科目余额表[科目名称],A12) -> 368642.51 | Q12: =SUMIFS(科目余额表[期末借方],科目余额表[已审报表项目],Q$1,科目余额表[科目名称],A12)-SUMIFS(科目余额表[期末贷方],科目余额表[已审报表项目],Q$1,科目余额表[科目名称],A12) -> 0 | R12: =SUMIFS(科目余额表[期末贷方],科目余额表[已审报表项目],R$1,科目余额表[科目名称],A12)-SUMIFS(科目余额表[期末借方],科目余额表[已审报表项目],R$1,科目余额表[科目名称],A12) -> 0 | S12: =SUMIFS(科目余额表[期末借方],科目余额表[已审报表项目],S$1,科目余额表[科目名称],A12)-SUMIFS(科目余额表[期末贷方],科目余额表[已审报表项目],S$1,科目余额表[科目名称],A12) -> 0 | T12: =SUMIFS(科目余额表[期末贷方],科目余额表[已审报表项目],T$1,科目余额表[科目名称],A12)-SUMIFS(科目余额表[期末借方],科目余额表[已审报表项目],T$1,科目余额表[科目名称],A12) -> 0
A13: L有限公司 | B13: =IF(COUNTIF(E13:I13,"是")>0,"是","—") -> — | C13: =IF(10-COUNTIF(K13:T13,0)>1,"是","—") -> — | E13: =IF(AND(K13<>0,L13<>0),"是","—") -> — | F13: =IF(AND(M13<>0,N13<>0),"是","—") -> — | G13: =IF(AND(O13<>0,P13<>0),"是","—") -> — | H13: =IF(AND(Q13<>0,R13<>0),"是","—") -> — | I13: =IF(AND(S13<>0,T13<>0),"是","—") -> — | K13: =SUMIFS(科目余额表[期末借方],科目余额表[已审报表项目],K$1,科目余额表[科目名称],A13)-SUMIFS(科目余额表[期末贷方],科目余额表[已审报表项目],K$1,科目余额表[科目名称],A13) -> 0 | L13: =SUMIFS(科目余额表[期末贷方],科目余额表[已审报表项目],L$1,科目余额表[科目名称],A13)-SUMIFS(科目余额表[期末借方],科目余额表[已审报表项目],L$1,科目余额表[科目名称],A13) -> 0 | M13: =SUMIFS(科目余额表[期末借方],科目余额表[已审报表项目],M$1,科目余额表[科目名称],A13)-SUMIFS(科目余额表[期末贷方],科目余额表[已审报表项目],M$1,科目余额表[科目名称],A13) -> 0 | N13: =SUMIFS(科目余额表[期末贷方],科目余额表[已审报表项目],N$1,科目余额表[科目名称],A13)-SUMIFS(科目余额表[期末借方],科目余额表[已审报表项目],N$1,科目余额表[科目名称],A13) -> 0 | O13: =SUMIFS(科目余额表[期末借方],科目余额表[已审报表项目],O$1,科目余额表[科目名称],A13)-SUMIFS(科目余额表[期末贷方],科目余额表[已审报表项目],O$1,科目余额表[科目名称],A13) -> 0 | P13: =SUMIFS(科目余额表[期末贷方],科目余额表[已审报表项目],P$1,科目余额表[科目名称],A13)-SUMIFS(科目余额表[期末借方],科目余额表[已审报表项目],P$1,科目余额表[科目名称],A13) -> 509644.55 | Q13: =SUMIFS(科目余额表[期末借方],科目余额表[已审报表项目],Q$1,科目余额表[科目名称],A13)-SUMIFS(科目余额表[期末贷方],科目余额表[已审报表项目],Q$1,科目余额表[科目名称],A13) -> 0 | R13: =SUMIFS(科目余额表[期末贷方],科目余额表[已审报表项目],R$1,科目余额表[科目名称],A13)-SUMIFS(科目余额表[期末借方],科目余额表[已审报表项目],R$1,科目余额表[科目名称],A13) -> 0 | S13: =SUMIFS(科目余额表[期末借方],科目余额表[已审报表项目],S$1,科目余额表[科目名称],A13)-SUMIFS(科目余额表[期末贷方],科目余额表[已审报表项目],S$1,科目余额表[科目名称],A13) -> 0 | T13: =SUMIFS(科目余额表[期末贷方],科目余额表[已审报表项目],T$1,科目余额表[科目名称],A13)-SUMIFS(科目余额表[期末借方],科目余额表[已审报表项目],T$1,科目余额表[科目名称],A13) -> 0
A14: M有限公司 | B14: =IF(COUNTIF(E14:I14,"是")>0,"是","—") -> — | C14: =IF(10-COUNTIF(K14:T14,0)>1,"是","—") -> — | E14: =IF(AND(K14<>0,L14<>0),"是","—") -> — | F14: =IF(AND(M14<>0,N14<>0),"是","—") -> — | G14: =IF(AND(O14<>0,P14<>0),"是","—") -> — | H14: =IF(AND(Q14<>0,R14<>0),"是","—") -> — | I14: =IF(AND(S14<>0,T14<>0),"是","—") -> — | K14: =SUMIFS(科目余额表[期末借方],科目余额表[已审报表项目],K$1,科目余额表[科目名称],A14)-SUMIFS(科目余额表[期末贷方],科目余额表[已审报表项目],K$1,科目余额表[科目名称],A14) -> 0 | L14: =SUMIFS(科目余额表[期末贷方],科目余额表[已审报表项目],L$1,科目余额表[科目名称],A14)-SUMIFS(科目余额表[期末借方],科目余额表[已审报表项目],L$1,科目余额表[科目名称],A14) -> 0 | M14: =SUMIFS(科目余额表[期末借方],科目余额表[已审报表项目],M$1,科目余额表[科目名称],A14)-SUMIFS(科目余额表[期末贷方],科目余额表[已审报表项目],M$1,科目余额表[科目名称],A14) -> 0 | N14: =SUMIFS(科目余额表[期末贷方],科目余额表[已审报表项目],N$1,科目余额表[科目名称],A14)-SUMIFS(科目余额表[期末借方],科目余额表[已审报表项目],N$1,科目余额表[科目名称],A14) -> 0 | O14: =SUMIFS(科目余额表[期末借方],科目余额表[已审报表项目],O$1,科目余额表[科目名称],A14)-SUMIFS(科目余额表[期末贷方],科目余额表[已审报表项目],O$1,科目余额表[科目名称],A14) -> 0 | P14: =SUMIFS(科目余额表[期末贷方],科目余额表[已审报表项目],P$1,科目余额表[科目名称],A14)-SUMIFS(科目余额表[期末借方],科目余额表[已审报表项目],P$1,科目余额表[科目名称],A14) -> 4365231.5 | Q14: =SUMIFS(科目余额表[期末借方],科目余额表[已审报表项目],Q$1,科目余额表[科目名称],A14)-SUMIFS(科目余额表[期末贷方],科目余额表[已审报表项目],Q$1,科目余额表[科目名称],A14) -> 0 | R14: =SUMIFS(科目余额表[期末贷方],科目余额表[已审报表项目],R$1,科目余额表[科目名称],A14)-SUMIFS(科目余额表[期末借方],科目余额表[已审报表项目],R$1,科目余额表[科目名称],A14) -> 0 | S14: =SUMIFS(科目余额表[期末借方],科目余额表[已审报表项目],S$1,科目余额表[科目名称],A14)-SUMIFS(科目余额表[期末贷方],科目余额表[已审报表项目],S$1,科目余额表[科目名称],A14) -> 0 | T14: =SUMIFS(科目余额表[期末贷方],科目余额表[已审报表项目],T$1,科目余额表[科目名称],A14)-SUMIFS(科目余额表[期末借方],科目余额表[已审报表项目],T$1,科目余额表[科目名称],A14) -> 0
A15: N有限公司 | B15: =IF(COUNTIF(E15:I15,"是")>0,"是","—") -> — | C15: =IF(10-COUNTIF(K15:T15,0)>1,"是","—") -> — | E15: =IF(AND(K15<>0,L15<>0),"是","—") -> — | F15: =IF(AND(M15<>0,N15<>0),"是","—") -> — | G15: =IF(AND(O15<>0,P15<>0),"是","—") -> — | H15: =IF(AND(Q15<>0,R15<>0),"是","—") -> — | I15: =IF(AND(S15<>0,T15<>0),"是","—") -> — | K15: =SUMIFS(科目余额表[期末借方],科目余额表[已审报表项目],K$1,科目余额表[科目名称],A15)-SUMIFS(科目余额表[期末贷方],科目余额表[已审报表项目],K$1,科目余额表[科目名称],A15) -> 0 | L15: =SUMIFS(科目余额表[期末贷方],科目余额表[已审报表项目],L$1,科目余额表[科目名称],A15)-SUMIFS(科目余额表[期末借方],科目余额表[已审报表项目],L$1,科目余额表[科目名称],A15) -> 0 | M15: =SUMIFS(科目余额表[期末借方],科目余额表[已审报表项目],M$1,科目余额表[科目名称],A15)-SUMIFS(科目余额表[期末贷方],科目余额表[已审报表项目],M$1,科目余额表[科目名称],A15) -> 0 | N15: =SUMIFS(科目余额表[期末贷方],科目余额表[已审报表项目],N$1,科目余额表[科目名称],A15)-SUMIFS(科目余额表[期末借方],科目余额表[已审报表项目],N$1,科目余额表[科目名称],A15) -> 0 | O15: =SUMIFS(科目余额表[期末借方],科目余额表[已审报表项目],O$1,科目余额表[科目名称],A15)-SUMIFS(科目余额表[期末贷方],科目余额表[已审报表项目],O$1,科目余额表[科目名称],A15) -> 0 | P15: =SUMIFS(科目余额表[期末贷方],科目余额表[已审报表项目],P$1,科目余额表[科目名称],A15)-SUMIFS(科目余额表[期末借方],科目余额表[已审报表项目],P$1,科目余额表[科目名称],A15) -> 154547.59 | Q15: =SUMIFS(科目余额表[期末借方],科目余额表[已审报表项目],Q$1,科目余额表[科目名称],A15)-SUMIFS(科目余额表[期末贷方],科目余额表[已审报表项目],Q$1,科目余额表[科目名称],A15) -> 0 | R15: =SUMIFS(科目余额表[期末贷方],科目余额表[已审报表项目],R$1,科目余额表[科目名称],A15)-SUMIFS(科目余额表[期末借方],科目余额表[已审报表项目],R$1,科目余额表[科目名称],A15) -> 0 | S15: =SUMIFS(科目余额表[期末借方],科目余额表[已审报表项目],S$1,科目余额表[科目名称],A15)-SUMIFS(科目余额表[期末贷方],科目余额表[已审报表项目],S$1,科目余额表[科目名称],A15) -> 0 | T15: =SUMIFS(科目余额表[期末贷方],科目余额表[已审报表项目],T$1,科目余额表[科目名称],A15)-SUMIFS(科目余额表[期末借方],科目余额表[已审报表项目],T$1,科目余额表[科目名称],A15) -> 0
A16: O有限公司 | B16: =IF(COUNTIF(E16:I16,"是")>0,"是","—") -> — | C16: =IF(10-COUNTIF(K16:T16,0)>1,"是","—") -> — | E16: =IF(AND(K16<>0,L16<>0),"是","—") -> — | F16: =IF(AND(M16<>0,N16<>0),"是","—") -> — | G16: =IF(AND(O16<>0,P16<>0),"是","—") -> — | H16: =IF(AND(Q16<>0,R16<>0),"是","—") -> — | I16: =IF(AND(S16<>0,T16<>0),"是","—") -> — | K16: =SUMIFS(科目余额表[期末借方],科目余额表[已审报表项目],K$1,科目余额表[科目名称],A16)-SUMIFS(科目余额表[期末贷方],科目余额表[已审报表项目],K$1,科目余额表[科目名称],A16) -> 0 | L16: =SUMIFS(科目余额表[期末贷方],科目余额表[已审报表项目],L$1,科目余额表[科目名称],A16)-SUMIFS(科目余额表[期末借方],科目余额表[已审报表项目],L$1,科目余额表[科目名称],A16) -> 0 | M16: =SUMIFS(科目余额表[期末借方],科目余额表[已审报表项目],M$1,科目余额表[科目名称],A16)-SUMIFS(科目余额表[期末贷方],科目余额表[已审报表项目],M$1,科目余额表[科目名称],A16) -> 0 | N16: =SUMIFS(科目余额表[期末贷方],科目余额表[已审报表项目],N$1,科目余额表[科目名称],A16)-SUMIFS(科目余额表[期末借方],科目余额表[已审报表项目],N$1,科目余额表[科目名称],A16) -> 0 | O16: =SUMIFS(科目余额表[期末借方],科目余额表[已审报表项目],O$1,科目余额表[科目名称],A16)-SUMIFS(科目余额表[期末贷方],科目余额表[已审报表项目],O$1,科目余额表[科目名称],A16) -> 730048.34 | P16: =SUMIFS(科目余额表[期末贷方],科目余额表[已审报表项目],P$1,科目余额表[科目名称],A16)-SUMIFS(科目余额表[期末借方],科目余额表[已审报表项目],P$1,科目余额表[科目名称],A16) -> 0 | Q16: =SUMIFS(科目余额表[期末借方],科目余额表[已审报表项目],Q$1,科目余额表[科目名称],A16)-SUMIFS(科目余额表[期末贷方],科目余额表[已审报表项目],Q$1,科目余额表[科目名称],A16) -> 0 | R16: =SUMIFS(科目余额表[期末贷方],科目余额表[已审报表项目],R$1,科目余额表[科目名称],A16)-SUMIFS(科目余额表[期末借方],科目余额表[已审报表项目],R$1,科目余额表[科目名称],A16) -> 0 | S16: =SUMIFS(科目余额表[期末借方],科目余额表[已审报表项目],S$1,科目余额表[科目名称],A16)-SUMIFS(科目余额表[期末贷方],科目余额表[已审报表项目],S$1,科目余额表[科目名称],A16) -> 0 | T16: =SUMIFS(科目余额表[期末贷方],科目余额表[已审报表项目],T$1,科目余额表[科目名称],A16)-SUMIFS(科目余额表[期末借方],科目余额表[已审报表项目],T$1,科目余额表[科目名称],A16) -> 0
A17: P有限公司 | B17: =IF(COUNTIF(E17:I17,"是")>0,"是","—") -> — | C17: =IF(10-COUNTIF(K17:T17,0)>1,"是","—") -> — | E17: =IF(AND(K17<>0,L17<>0),"是","—") -> — | F17: =IF(AND(M17<>0,N17<>0),"是","—") -> — | G17: =IF(AND(O17<>0,P17<>0),"是","—") -> — | H17: =IF(AND(Q17<>0,R17<>0),"是","—") -> — | I17: =IF(AND(S17<>0,T17<>0),"是","—") -> — | K17: =SUMIFS(科目余额表[期末借方],科目余额表[已审报表项目],K$1,科目余额表[科目名称],A17)-SUMIFS(科目余额表[期末贷方],科目余额表[已审报表项目],K$1,科目余额表[科目名称],A17) -> 0 | L17: =SUMIFS(科目余额表[期末贷方],科目余额表[已审报表项目],L$1,科目余额表[科目名称],A17)-SUMIFS(科目余额表[期末借方],科目余额表[已审报表项目],L$1,科目余额表[科目名称],A17) -> 0 | M17: =SUMIFS(科目余额表[期末借方],科目余额表[已审报表项目],M$1,科目余额表[科目名称],A17)-SUMIFS(科目余额表[期末贷方],科目余额表[已审报表项目],M$1,科目余额表[科目名称],A17) -> 0 | N17: =SUMIFS(科目余额表[期末贷方],科目余额表[已审报表项目],N$1,科目余额表[科目名称],A17)-SUMIFS(科目余额表[期末借方],科目余额表[已审报表项目],N$1,科目余额表[科目名称],A17) -> 0 | O17: =SUMIFS(科目余额表[期末借方],科目余额表[已审报表项目],O$1,科目余额表[科目名称],A17)-SUMIFS(科目余额表[期末贷方],科目余额表[已审报表项目],O$1,科目余额表[科目名称],A17) -> 0 | P17: =SUMIFS(科目余额表[期末贷方],科目余额表[已审报表项目],P$1,科目余额表[科目名称],A17)-SUMIFS(科目余额表[期末借方],科目余额表[已审报表项目],P$1,科目余额表[科目名称],A17) -> 533435.61 | Q17: =SUMIFS(科目余额表[期末借方],科目余额表[已审报表项目],Q$1,科目余额表[科目名称],A17)-SUMIFS(科目余额表[期末贷方],科目余额表[已审报表项目],Q$1,科目余额表[科目名称],A17) -> 0 | R17: =SUMIFS(科目余额表[期末贷方],科目余额表[已审报表项目],R$1,科目余额表[科目名称],A17)-SUMIFS(科目余额表[期末借方],科目余额表[已审报表项目],R$1,科目余额表[科目名称],A17) -> 0 | S17: =SUMIFS(科目余额表[期末借方],科目余额表[已审报表项目],S$1,科目余额表[科目名称],A17)-SUMIFS(科目余额表[期末贷方],科目余额表[已审报表项目],S$1,科目余额表[科目名称],A17) -> 0 | T17: =SUMIFS(科目余额表[期末贷方],科目余额表[已审报表项目],T$1,科目余额表[科目名称],A17)-SUMIFS(科目余额表[期末借方],科目余额表[已审报表项目],T$1,科目余额表[科目名称],A17) -> 0
A18: Q有限公司 | B18: =IF(COUNTIF(E18:I18,"是")>0,"是","—") -> — | C18: =IF(10-COUNTIF(K18:T18,0)>1,"是","—") -> — | E18: =IF(AND(K18<>0,L18<>0),"是","—") -> — | F18: =IF(AND(M18<>0,N18<>0),"是","—") -> — | G18: =IF(AND(O18<>0,P18<>0),"是","—") -> — | H18: =IF(AND(Q18<>0,R18<>0),"是","—") -> — | I18: =IF(AND(S18<>0,T18<>0),"是","—") -> — | K18: =SUMIFS(科目余额表[期末借方],科目余额表[已审报表项目],K$1,科目余额表[科目名称],A18)-SUMIFS(科目余额表[期末贷方],科目余额表[已审报表项目],K$1,科目余额表[科目名称],A18) -> 0 | L18: =SUMIFS(科目余额表[期末贷方],科目余额表[已审报表项目],L$1,科目余额表[科目名称],A18)-SUMIFS(科目余额表[期末借方],科目余额表[已审报表项目],L$1,科目余额表[科目名称],A18) -> 0 | M18: =SUMIFS(科目余额表[期末借方],科目余额表[已审报表项目],M$1,科目余额表[科目名称],A18)-SUMIFS(科目余额表[期末贷方],科目余额表[已审报表项目],M$1,科目余额表[科目名称],A18) -> 0 | N18: =SUMIFS(科目余额表[期末贷方],科目余额表[已审报表项目],N$1,科目余额表[科目名称],A18)-SUMIFS(科目余额表[期末借方],科目余额表[已审报表项目],N$1,科目余额表[科目名称],A18) -> 0 | O18: =SUMIFS(科目余额表[期末借方],科目余额表[已审报表项目],O$1,科目余额表[科目名称],A18)-SUMIFS(科目余额表[期末贷方],科目余额表[已审报表项目],O$1,科目余额表[科目名称],A18) -> 0 | P18: =SUMIFS(科目余额表[期末贷方],科目余额表[已审报表项目],P$1,科目余额表[科目名称],A18)-SUMIFS(科目余额表[期末借方],科目余额表[已审报表项目],P$1,科目余额表[科目名称],A18) -> 706992 | Q18: =SUMIFS(科目余额表[期末借方],科目余额表[已审报表项目],Q$1,科目余额表[科目名称],A18)-SUMIFS(科目余额表[期末贷方],科目余额表[已审报表项目],Q$1,科目余额表[科目名称],A18) -> 0 | R18: =SUMIFS(科目余额表[期末贷方],科目余额表[已审报表项目],R$1,科目余额表[科目名称],A18)-SUMIFS(科目余额表[期末借方],科目余额表[已审报表项目],R$1,科目余额表[科目名称],A18) -> 0 | S18: =SUMIFS(科目余额表[期末借方],科目余额表[已审报表项目],S$1,科目余额表[科目名称],A18)-SUMIFS(科目余额表[期末贷方],科目余额表[已审报表项目],S$1,科目余额表[科目名称],A18) -> 0 | T18: =SUMIFS(科目余额表[期末贷方],科目余额表[已审报表项目],T$1,科目余额表[科目名称],A18)-SUMIFS(科目余额表[期末借方],科目余额表[已审报表项目],T$1,科目余额表[科目名称],A18) -> 0
A19: 张三 | B19: =IF(COUNTIF(E19:I19,"是")>0,"是","—") -> — | C19: =IF(10-COUNTIF(K19:T19,0)>1,"是","—") -> — | E19: =IF(AND(K19<>0,L19<>0),"是","—") -> — | F19: =IF(AND(M19<>0,N19<>0),"是","—") -> — | G19: =IF(AND(O19<>0,P19<>0),"是","—") -> — | H19: =IF(AND(Q19<>0,R19<>0),"是","—") -> — | I19: =IF(AND(S19<>0,T19<>0),"是","—") -> — | K19: =SUMIFS(科目余额表[期末借方],科目余额表[已审报表项目],K$1,科目余额表[科目名称],A19)-SUMIFS(科目余额表[期末贷方],科目余额表[已审报表项目],K$1,科目余额表[科目名称],A19) -> 0 | L19: =SUMIFS(科目余额表[期末贷方],科目余额表[已审报表项目],L$1,科目余额表[科目名称],A19)-SUMIFS(科目余额表[期末借方],科目余额表[已审报表项目],L$1,科目余额表[科目名称],A19) -> 0 | M19: =SUMIFS(科目余额表[期末借方],科目余额表[已审报表项目],M$1,科目余额表[科目名称],A19)-SUMIFS(科目余额表[期末贷方],科目余额表[已审报表项目],M$1,科目余额表[科目名称],A19) -> 0 | N19: =SUMIFS(科目余额表[期末贷方],科目余额表[已审报表项目],N$1,科目余额表[科目名称],A19)-SUMIFS(科目余额表[期末借方],科目余额表[已审报表项目],N$1,科目余额表[科目名称],A19) -> 0 | O19: =SUMIFS(科目余额表[期末借方],科目余额表[已审报表项目],O$1,科目余额表[科目名称],A19)-SUMIFS(科目余额表[期末贷方],科目余额表[已审报表项目],O$1,科目余额表[科目名称],A19) -> 0 | P19: =SUMIFS(科目余额表[期末贷方],科目余额表[已审报表项目],P$1,科目余额表[科目名称],A19)-SUMIFS(科目余额表[期末借方],科目余额表[已审报表项目],P$1,科目余额表[科目名称],A19) -> 0 | Q19: =SUMIFS(科目余额表[期末借方],科目余额表[已审报表项目],Q$1,科目余额表[科目名称],A19)-SUMIFS(科目余额表[期末贷方],科目余额表[已审报表项目],Q$1,科目余额表[科目名称],A19) -> 0 | R19: =SUMIFS(科目余额表[期末贷方],科目余额表[已审报表项目],R$1,科目余额表[科目名称],A19)-SUMIFS(科目余额表[期末借方],科目余额表[已审报表项目],R$1,科目余额表[科目名称],A19) -> 0 | S19: =SUMIFS(科目余额表[期末借方],科目余额表[已审报表项目],S$1,科目余额表[科目名称],A19)-SUMIFS(科目余额表[期末贷方],科目余额表[已审报表项目],S$1,科目余额表[科目名称],A19) -> 78922.34 | T19: =SUMIFS(科目余额表[期末贷方],科目余额表[已审报表项目],T$1,科目余额表[科目名称],A19)-SUMIFS(科目余额表[期末借方],科目余额表[已审报表项目],T$1,科目余额表[科目名称],A19) -> 0
A20: 李四 | B20: =IF(COUNTIF(E20:I20,"是")>0,"是","—") -> — | C20: =IF(10-COUNTIF(K20:T20,0)>1,"是","—") -> — | E20: =IF(AND(K20<>0,L20<>0),"是","—") -> — | F20: =IF(AND(M20<>0,N20<>0),"是","—") -> — | G20: =IF(AND(O20<>0,P20<>0),"是","—") -> — | H20: =IF(AND(Q20<>0,R20<>0),"是","—") -> — | I20: =IF(AND(S20<>0,T20<>0),"是","—") -> — | K20: =SUMIFS(科目余额表[期末借方],科目余额表[已审报表项目],K$1,科目余额表[科目名称],A20)-SUMIFS(科目余额表[期末贷方],科目余额表[已审报表项目],K$1,科目余额表[科目名称],A20) -> 0 | L20: =SUMIFS(科目余额表[期末贷方],科目余额表[已审报表项目],L$1,科目余额表[科目名称],A20)-SUMIFS(科目余额表[期末借方],科目余额表[已审报表项目],L$1,科目余额表[科目名称],A20) -> 0 | M20: =SUMIFS(科目余额表[期末借方],科目余额表[已审报表项目],M$1,科目余额表[科目名称],A20)-SUMIFS(科目余额表[期末贷方],科目余额表[已审报表项目],M$1,科目余额表[科目名称],A20) -> 0 | N20: =SUMIFS(科目余额表[期末贷方],科目余额表[已审报表项目],N$1,科目余额表[科目名称],A20)-SUMIFS(科目余额表[期末借方],科目余额表[已审报表项目],N$1,科目余额表[科目名称],A20) -> 0 | O20: =SUMIFS(科目余额表[期末借方],科目余额表[已审报表项目],O$1,科目余额表[科目名称],A20)-SUMIFS(科目余额表[期末贷方],科目余额表[已审报表项目],O$1,科目余额表[科目名称],A20) -> 0 | P20: =SUMIFS(科目余额表[期末贷方],科目余额表[已审报表项目],P$1,科目余额表[科目名称],A20)-SUMIFS(科目余额表[期末借方],科目余额表[已审报表项目],P$1,科目余额表[科目名称],A20) -> 0 | Q20: =SUMIFS(科目余额表[期末借方],科目余额表[已审报表项目],Q$1,科目余额表[科目名称],A20)-SUMIFS(科目余额表[期末贷方],科目余额表[已审报表项目],Q$1,科目余额表[科目名称],A20) -> 0 | R20: =SUMIFS(科目余额表[期末贷方],科目余额表[已审报表项目],R$1,科目余额表[科目名称],A20)-SUMIFS(科目余额表[期末借方],科目余额表[已审报表项目],R$1,科目余额表[科目名称],A20) -> 0 | S20: =SUMIFS(科目余额表[期末借方],科目余额表[已审报表项目],S$1,科目余额表[科目名称],A20)-SUMIFS(科目余额表[期末贷方],科目余额表[已审报表项目],S$1,科目余额表[科目名称],A20) -> 58847.87 | T20: =SUMIFS(科目余额表[期末贷方],科目余额表[已审报表项目],T$1,科目余额表[科目名称],A20)-SUMIFS(科目余额表[期末借方],科目余额表[已审报表项目],T$1,科目余额表[科目名称],A20) -> 0
A21: 王五 | B21: =IF(COUNTIF(E21:I21,"是")>0,"是","—") -> — | C21: =IF(10-COUNTIF(K21:T21,0)>1,"是","—") -> — | E21: =IF(AND(K21<>0,L21<>0),"是","—") -> — | F21: =IF(AND(M21<>0,N21<>0),"是","—") -> — | G21: =IF(AND(O21<>0,P21<>0),"是","—") -> — | H21: =IF(AND(Q21<>0,R21<>0),"是","—") -> — | I21: =IF(AND(S21<>0,T21<>0),"是","—") -> — | K21: =SUMIFS(科目余额表[期末借方],科目余额表[已审报表项目],K$1,科目余额表[科目名称],A21)-SUMIFS(科目余额表[期末贷方],科目余额表[已审报表项目],K$1,科目余额表[科目名称],A21) -> 0 | L21: =SUMIFS(科目余额表[期末贷方],科目余额表[已审报表项目],L$1,科目余额表[科目名称],A21)-SUMIFS(科目余额表[期末借方],科目余额表[已审报表项目],L$1,科目余额表[科目名称],A21) -> 0 | M21: =SUMIFS(科目余额表[期末借方],科目余额表[已审报表项目],M$1,科目余额表[科目名称],A21)-SUMIFS(科目余额表[期末贷方],科目余额表[已审报表项目],M$1,科目余额表[科目名称],A21) -> 0 | N21: =SUMIFS(科目余额表[期末贷方],科目余额表[已审报表项目],N$1,科目余额表[科目名称],A21)-SUMIFS(科目余额表[期末借方],科目余额表[已审报表项目],N$1,科目余额表[科目名称],A21) -> 0 | O21: =SUMIFS(科目余额表[期末借方],科目余额表[已审报表项目],O$1,科目余额表[科目名称],A21)-SUMIFS(科目余额表[期末贷方],科目余额表[已审报表项目],O$1,科目余额表[科目名称],A21) -> 0 | P21: =SUMIFS(科目余额表[期末贷方],科目余额表[已审报表项目],P$1,科目余额表[科目名称],A21)-SUMIFS(科目余额表[期末借方],科目余额表[已审报表项目],P$1,科目余额表[科目名称],A21) -> 0 | Q21: =SUMIFS(科目余额表[期末借方],科目余额表[已审报表项目],Q$1,科目余额表[科目名称],A21)-SUMIFS(科目余额表[期末贷方],科目余额表[已审报表项目],Q$1,科目余额表[科目名称],A21) -> 0 | R21: =SUMIFS(科目余额表[期末贷方],科目余额表[已审报表项目],R$1,科目余额表[科目名称],A21)-SUMIFS(科目余额表[期末借方],科目余额表[已审报表项目],R$1,科目余额表[科目名称],A21) -> 0 | S21: =SUMIFS(科目余额表[期末借方],科目余额表[已审报表项目],S$1,科目余额表[科目名称],A21)-SUMIFS(科目余额表[期末贷方],科目余额表[已审报表项目],S$1,科目余额表[科目名称],A21) -> 82164.36 | T21: =SUMIFS(科目余额表[期末贷方],科目余额表[已审报表项目],T$1,科目余额表[科目名称],A21)-SUMIFS(科目余额表[期末借方],科目余额表[已审报表项目],T$1,科目余额表[科目名称],A21) -> 0
A22: T有限公司 | B22: =IF(COUNTIF(E22:I22,"是")>0,"是","—") -> — | C22: =IF(10-COUNTIF(K22:T22,0)>1,"是","—") -> — | E22: =IF(AND(K22<>0,L22<>0),"是","—") -> — | F22: =IF(AND(M22<>0,N22<>0),"是","—") -> — | G22: =IF(AND(O22<>0,P22<>0),"是","—") -> — | H22: =IF(AND(Q22<>0,R22<>0),"是","—") -> — | I22: =IF(AND(S22<>0,T22<>0),"是","—") -> — | K22: =SUMIFS(科目余额表[期末借方],科目余额表[已审报表项目],K$1,科目余额表[科目名称],A22)-SUMIFS(科目余额表[期末贷方],科目余额表[已审报表项目],K$1,科目余额表[科目名称],A22) -> 0 | L22: =SUMIFS(科目余额表[期末贷方],科目余额表[已审报表项目],L$1,科目余额表[科目名称],A22)-SUMIFS(科目余额表[期末借方],科目余额表[已审报表项目],L$1,科目余额表[科目名称],A22) -> 0 | M22: =SUMIFS(科目余额表[期末借方],科目余额表[已审报表项目],M$1,科目余额表[科目名称],A22)-SUMIFS(科目余额表[期末贷方],科目余额表[已审报表项目],M$1,科目余额表[科目名称],A22) -> 0 | N22: =SUMIFS(科目余额表[期末贷方],科目余额表[已审报表项目],N$1,科目余额表[科目名称],A22)-SUMIFS(科目余额表[期末借方],科目余额表[已审报表项目],N$1,科目余额表[科目名称],A22) -> 0 | O22: =SUMIFS(科目余额表[期末借方],科目余额表[已审报表项目],O$1,科目余额表[科目名称],A22)-SUMIFS(科目余额表[期末贷方],科目余额表[已审报表项目],O$1,科目余额表[科目名称],A22) -> 0 | P22: =SUMIFS(科目余额表[期末贷方],科目余额表[已审报表项目],P$1,科目余额表[科目名称],A22)-SUMIFS(科目余额表[期末借方],科目余额表[已审报表项目],P$1,科目余额表[科目名称],A22) -> 2133003.3 | Q22: =SUMIFS(科目余额表[期末借方],科目余额表[已审报表项目],Q$1,科目余额表[科目名称],A22)-SUMIFS(科目余额表[期末贷方],科目余额表[已审报表项目],Q$1,科目余额表[科目名称],A22) -> 0 | R22: =SUMIFS(科目余额表[期末贷方],科目余额表[已审报表项目],R$1,科目余额表[科目名称],A22)-SUMIFS(科目余额表[期末借方],科目余额表[已审报表项目],R$1,科目余额表[科目名称],A22) -> 0 | S22: =SUMIFS(科目余额表[期末借方],科目余额表[已审报表项目],S$1,科目余额表[科目名称],A22)-SUMIFS(科目余额表[期末贷方],科目余额表[已审报表项目],S$1,科目余额表[科目名称],A22) -> 0 | T22: =SUMIFS(科目余额表[期末贷方],科目余额表[已审报表项目],T$1,科目余额表[科目名称],A22)-SUMIFS(科目余额表[期末借方],科目余额表[已审报表项目],T$1,科目余额表[科目名称],A22) -> 0
... A35: 亥 | B35: =IF(COUNTIF(E35:I35,"是")>0,"是","—") -> — | C35: =IF(10-COUNTIF(K35:T35,0)>1,"是","—") -> — | E35: =IF(AND(K35<>0,L35<>0),"是","—") -> — | F35: =IF(AND(M35<>0,N35<>0),"是","—") -> — | G35: =IF(AND(O35<>0,P35<>0),"是","—") -> — | H35: =IF(AND(Q35<>0,R35<>0),"是","—") -> — | I35: =IF(AND(S35<>0,T35<>0),"是","—") -> — | K35: =SUMIFS(科目余额表[期末借方],科目余额表[已审报表项目],K$1,科目余额表[科目名称],A35)-SUMIFS(科目余额表[期末贷方],科目余额表[已审报表项目],K$1,科目余额表[科目名称],A35) -> 0 | L35: =SUMIFS(科目余额表[期末贷方],科目余额表[已审报表项目],L$1,科目余额表[科目名称],A35)-SUMIFS(科目余额表[期末借方],科目余额表[已审报表项目],L$1,科目余额表[科目名称],A35) -> 0 | M35: =SUMIFS(科目余额表[期末借方],科目余额表[已审报表项目],M$1,科目余额表[科目名称],A35)-SUMIFS(科目余额表[期末贷方],科目余额表[已审报表项目],M$1,科目余额表[科目名称],A35) -> 0 | N35: =SUMIFS(科目余额表[期末贷方],科目余额表[已审报表项目],N$1,科目余额表[科目名称],A35)-SUMIFS(科目余额表[期末借方],科目余额表[已审报表项目],N$1,科目余额表[科目名称],A35) -> 0 | O35: =SUMIFS(科目余额表[期末借方],科目余额表[已审报表项目],O$1,科目余额表[科目名称],A35)-SUMIFS(科目余额表[期末贷方],科目余额表[已审报表项目],O$1,科目余额表[科目名称],A35) -> 0 | P35: =SUMIFS(科目余额表[期末贷方],科目余额表[已审报表项目],P$1,科目余额表[科目名称],A35)-SUMIFS(科目余额表[期末借方],科目余额表[已审报表项目],P$1,科目余额表[科目名称],A35) -> 0 | Q35: =SUMIFS(科目余额表[期末借方],科目余额表[已审报表项目],Q$1,科目余额表[科目名称],A35)-SUMIFS(科目余额表[期末贷方],科目余额表[已审报表项目],Q$1,科目余额表[科目名称],A35) -> 0 | R35: =SUMIFS(科目余额表[期末贷方],科目余额表[已审报表项目],R$1,科目余额表[科目名称],A35)-SUMIFS(科目余额表[期末借方],科目余额表[已审报表项目],R$1,科目余额表[科目名称],A35) -> 0 | S35: =SUMIFS(科目余额表[期末借方],科目余额表[已审报表项目],S$1,科目余额表[科目名称],A35)-SUMIFS(科目余额表[期末贷方],科目余额表[已审报表项目],S$1,科目余额表[科目名称],A35) -> 0 | T35: =SUMIFS(科目余额表[期末贷方],科目余额表[已审报表项目],T$1,科目余额表[科目名称],A35)-SUMIFS(科目余额表[期末借方],科目余额表[已审报表项目],T$1,科目余额表[科目名称],A35) -> 45692.19
B36: =IF(COUNTIF(E36:I36,"是")>0,"是","—") -> — | C36: =IF(10-COUNTIF(K36:T36,0)>1,"是","—") -> — | E36: =IF(AND(K36<>0,L36<>0),"是","—") -> — | F36: =IF(AND(M36<>0,N36<>0),"是","—") -> — | G36: =IF(AND(O36<>0,P36<>0),"是","—") -> — | H36: =IF(AND(Q36<>0,R36<>0),"是","—") -> — | I36: =IF(AND(S36<>0,T36<>0),"是","—") -> — | K36: =SUMIFS(科目余额表[期末借方],科目余额表[已审报表项目],K$1,科目余额表[科目名称],A36)-SUMIFS(科目余额表[期末贷方],科目余额表[已审报表项目],K$1,科目余额表[科目名称],A36) -> 0 | L36: =SUMIFS(科目余额表[期末贷方],科目余额表[已审报表项目],L$1,科目余额表[科目名称],A36)-SUMIFS(科目余额表[期末借方],科目余额表[已审报表项目],L$1,科目余额表[科目名称],A36) -> 0 | M36: =SUMIFS(科目余额表[期末借方],科目余额表[已审报表项目],M$1,科目余额表[科目名称],A36)-SUMIFS(科目余额表[期末贷方],科目余额表[已审报表项目],M$1,科目余额表[科目名称],A36) -> 0 | N36: =SUMIFS(科目余额表[期末贷方],科目余额表[已审报表项目],N$1,科目余额表[科目名称],A36)-SUMIFS(科目余额表[期末借方],科目余额表[已审报表项目],N$1,科目余额表[科目名称],A36) -> 0 | O36: =SUMIFS(科目余额表[期末借方],科目余额表[已审报表项目],O$1,科目余额表[科目名称],A36)-SUMIFS(科目余额表[期末贷方],科目余额表[已审报表项目],O$1,科目余额表[科目名称],A36) -> 0 | P36: =SUMIFS(科目余额表[期末贷方],科目余额表[已审报表项目],P$1,科目余额表[科目名称],A36)-SUMIFS(科目余额表[期末借方],科目余额表[已审报表项目],P$1,科目余额表[科目名称],A36) -> 0 | Q36: =SUMIFS(科目余额表[期末借方],科目余额表[已审报表项目],Q$1,科目余额表[科目名称],A36)-SUMIFS(科目余额表[期末贷方],科目余额表[已审报表项目],Q$1,科目余额表[科目名称],A36) -> 0 | R36: =SUMIFS(科目余额表[期末贷方],科目余额表[已审报表项目],R$1,科目余额表[科目名称],A36)-SUMIFS(科目余额表[期末借方],科目余额表[已审报表项目],R$1,科目余额表[科目名称],A36) -> 0 | S36: =SUMIFS(科目余额表[期末借方],科目余额表[已审报表项目],S$1,科目余额表[科目名称],A36)-SUMIFS(科目余额表[期末贷方],科目余额表[已审报表项目],S$1,科目余额表[科目名称],A36) -> 0 | T36: =SUMIFS(科目余额表[期末贷方],科目余额表[已审报表项目],T$1,科目余额表[科目名称],A36)-SUMIFS(科目余额表[期末借方],科目余额表[已审报表项目],T$1,科目余额表[科目名称],A36) -> 0
B37: =IF(COUNTIF(E37:I37,"是")>0,"是","—") -> — | C37: =IF(10-COUNTIF(K37:T37,0)>1,"是","—") -> — | E37: =IF(AND(K37<>0,L37<>0),"是","—") -> — | F37: =IF(AND(M37<>0,N37<>0),"是","—") -> — | G37: =IF(AND(O37<>0,P37<>0),"是","—") -> — | H37: =IF(AND(Q37<>0,R37<>0),"是","—") -> — | I37: =IF(AND(S37<>0,T37<>0),"是","—") -> — | K37: =SUMIFS(科目余额表[期末借方],科目余额表[已审报表项目],K$1,科目余额表[科目名称],A37)-SUMIFS(科目余额表[期末贷方],科目余额表[已审报表项目],K$1,科目余额表[科目名称],A37) -> 0 | L37: =SUMIFS(科目余额表[期末贷方],科目余额表[已审报表项目],L$1,科目余额表[科目名称],A37)-SUMIFS(科目余额表[期末借方],科目余额表[已审报表项目],L$1,科目余额表[科目名称],A37) -> 0 | M37: =SUMIFS(科目余额表[期末借方],科目余额表[已审报表项目],M$1,科目余额表[科目名称],A37)-SUMIFS(科目余额表[期末贷方],科目余额表[已审报表项目],M$1,科目余额表[科目名称],A37) -> 0 | N37: =SUMIFS(科目余额表[期末贷方],科目余额表[已审报表项目],N$1,科目余额表[科目名称],A37)-SUMIFS(科目余额表[期末借方],科目余额表[已审报表项目],N$1,科目余额表[科目名称],A37) -> 0 | O37: =SUMIFS(科目余额表[期末借方],科目余额表[已审报表项目],O$1,科目余额表[科目名称],A37)-SUMIFS(科目余额表[期末贷方],科目余额表[已审报表项目],O$1,科目余额表[科目名称],A37) -> 0 | P37: =SUMIFS(科目余额表[期末贷方],科目余额表[已审报表项目],P$1,科目余额表[科目名称],A37)-SUMIFS(科目余额表[期末借方],科目余额表[已审报表项目],P$1,科目余额表[科目名称],A37) -> 0 | Q37: =SUMIFS(科目余额表[期末借方],科目余额表[已审报表项目],Q$1,科目余额表[科目名称],A37)-SUMIFS(科目余额表[期末贷方],科目余额表[已审报表项目],Q$1,科目余额表[科目名称],A37) -> 0 | R37: =SUMIFS(科目余额表[期末贷方],科目余额表[已审报表项目],R$1,科目余额表[科目名称],A37)-SUMIFS(科目余额表[期末借方],科目余额表[已审报表项目],R$1,科目余额表[科目名称],A37) -> 0 | S37: =SUMIFS(科目余额表[期末借方],科目余额表[已审报表项目],S$1,科目余额表[科目名称],A37)-SUMIFS(科目余额表[期末贷方],科目余额表[已审报表项目],S$1,科目余额表[科目名称],A37) -> 0 | T37: =SUMIFS(科目余额表[期末贷方],科目余额表[已审报表项目],T$1,科目余额表[科目名称],A37)-SUMIFS(科目余额表[期末借方],科目余额表[已审报表项目],T$1,科目余额表[科目名称],A37) -> 0
B38: =IF(COUNTIF(E38:I38,"是")>0,"是","—") -> — | C38: =IF(10-COUNTIF(K38:T38,0)>1,"是","—") -> — | E38: =IF(AND(K38<>0,L38<>0),"是","—") -> — | F38: =IF(AND(M38<>0,N38<>0),"是","—") -> — | G38: =IF(AND(O38<>0,P38<>0),"是","—") -> — | H38: =IF(AND(Q38<>0,R38<>0),"是","—") -> — | I38: =IF(AND(S38<>0,T38<>0),"是","—") -> — | K38: =SUMIFS(科目余额表[期末借方],科目余额表[已审报表项目],K$1,科目余额表[科目名称],A38)-SUMIFS(科目余额表[期末贷方],科目余额表[已审报表项目],K$1,科目余额表[科目名称],A38) -> 0 | L38: =SUMIFS(科目余额表[期末贷方],科目余额表[已审报表项目],L$1,科目余额表[科目名称],A38)-SUMIFS(科目余额表[期末借方],科目余额表[已审报表项目],L$1,科目余额表[科目名称],A38) -> 0 | M38: =SUMIFS(科目余额表[期末借方],科目余额表[已审报表项目],M$1,科目余额表[科目名称],A38)-SUMIFS(科目余额表[期末贷方],科目余额表[已审报表项目],M$1,科目余额表[科目名称],A38) -> 0 | N38: =SUMIFS(科目余额表[期末贷方],科目余额表[已审报表项目],N$1,科目余额表[科目名称],A38)-SUMIFS(科目余额表[期末借方],科目余额表[已审报表项目],N$1,科目余额表[科目名称],A38) -> 0 | O38: =SUMIFS(科目余额表[期末借方],科目余额表[已审报表项目],O$1,科目余额表[科目名称],A38)-SUMIFS(科目余额表[期末贷方],科目余额表[已审报表项目],O$1,科目余额表[科目名称],A38) -> 0 | P38: =SUMIFS(科目余额表[期末贷方],科目余额表[已审报表项目],P$1,科目余额表[科目名称],A38)-SUMIFS(科目余额表[期末借方],科目余额表[已审报表项目],P$1,科目余额表[科目名称],A38) -> 0 | Q38: =SUMIFS(科目余额表[期末借方],科目余额表[已审报表项目],Q$1,科目余额表[科目名称],A38)-SUMIFS(科目余额表[期末贷方],科目余额表[已审报表项目],Q$1,科目余额表[科目名称],A38) -> 0 | R38: =SUMIFS(科目余额表[期末贷方],科目余额表[已审报表项目],R$1,科目余额表[科目名称],A38)-SUMIFS(科目余额表[期末借方],科目余额表[已审报表项目],R$1,科目余额表[科目名称],A38) -> 0 | S38: =SUMIFS(科目余额表[期末借方],科目余额表[已审报表项目],S$1,科目余额表[科目名称],A38)-SUMIFS(科目余额表[期末贷方],科目余额表[已审报表项目],S$1,科目余额表[科目名称],A38) -> 0 | T38: =SUMIFS(科目余额表[期末贷方],科目余额表[已审报表项目],T$1,科目余额表[科目名称],A38)-SUMIFS(科目余额表[期末借方],科目余额表[已审报表项目],T$1,科目余额表[科目名称],A38) -> 0
B39: =IF(COUNTIF(E39:I39,"是")>0,"是","—") -> — | C39: =IF(10-COUNTIF(K39:T39,0)>1,"是","—") -> — | E39: =IF(AND(K39<>0,L39<>0),"是","—") -> — | F39: =IF(AND(M39<>0,N39<>0),"是","—") -> — | G39: =IF(AND(O39<>0,P39<>0),"是","—") -> — | H39: =IF(AND(Q39<>0,R39<>0),"是","—") -> — | I39: =IF(AND(S39<>0,T39<>0),"是","—") -> — | K39: =SUMIFS(科目余额表[期末借方],科目余额表[已审报表项目],K$1,科目余额表[科目名称],A39)-SUMIFS(科目余额表[期末贷方],科目余额表[已审报表项目],K$1,科目余额表[科目名称],A39) -> 0 | L39: =SUMIFS(科目余额表[期末贷方],科目余额表[已审报表项目],L$1,科目余额表[科目名称],A39)-SUMIFS(科目余额表[期末借方],科目余额表[已审报表项目],L$1,科目余额表[科目名称],A39) -> 0 | M39: =SUMIFS(科目余额表[期末借方],科目余额表[已审报表项目],M$1,科目余额表[科目名称],A39)-SUMIFS(科目余额表[期末贷方],科目余额表[已审报表项目],M$1,科目余额表[科目名称],A39) -> 0 | N39: =SUMIFS(科目余额表[期末贷方],科目余额表[已审报表项目],N$1,科目余额表[科目名称],A39)-SUMIFS(科目余额表[期末借方],科目余额表[已审报表项目],N$1,科目余额表[科目名称],A39) -> 0 | O39: =SUMIFS(科目余额表[期末借方],科目余额表[已审报表项目],O$1,科目余额表[科目名称],A39)-SUMIFS(科目余额表[期末贷方],科目余额表[已审报表项目],O$1,科目余额表[科目名称],A39) -> 0 | P39: =SUMIFS(科目余额表[期末贷方],科目余额表[已审报表项目],P$1,科目余额表[科目名称],A39)-SUMIFS(科目余额表[期末借方],科目余额表[已审报表项目],P$1,科目余额表[科目名称],A39) -> 0 | Q39: =SUMIFS(科目余额表[期末借方],科目余额表[已审报表项目],Q$1,科目余额表[科目名称],A39)-SUMIFS(科目余额表[期末贷方],科目余额表[已审报表项目],Q$1,科目余额表[科目名称],A39) -> 0 | R39: =SUMIFS(科目余额表[期末贷方],科目余额表[已审报表项目],R$1,科目余额表[科目名称],A39)-SUMIFS(科目余额表[期末借方],科目余额表[已审报表项目],R$1,科目余额表[科目名称],A39) -> 0 | S39: =SUMIFS(科目余额表[期末借方],科目余额表[已审报表项目],S$1,科目余额表[科目名称],A39)-SUMIFS(科目余额表[期末贷方],科目余额表[已审报表项目],S$1,科目余额表[科目名称],A39) -> 0 | T39: =SUMIFS(科目余额表[期末贷方],科目余额表[已审报表项目],T$1,科目余额表[科目名称],A39)-SUMIFS(科目余额表[期末借方],科目余额表[已审报表项目],T$1,科目余额表[科目名称],A39) -> 0
B40: =IF(COUNTIF(E40:I40,"是")>0,"是","—") -> — | C40: =IF(10-COUNTIF(K40:T40,0)>1,"是","—") -> — | E40: =IF(AND(K40<>0,L40<>0),"是","—") -> — | F40: =IF(AND(M40<>0,N40<>0),"是","—") -> — | G40: =IF(AND(O40<>0,P40<>0),"是","—") -> — | H40: =IF(AND(Q40<>0,R40<>0),"是","—") -> — | I40: =IF(AND(S40<>0,T40<>0),"是","—") -> — | K40: =SUMIFS(科目余额表[期末借方],科目余额表[已审报表项目],K$1,科目余额表[科目名称],A40)-SUMIFS(科目余额表[期末贷方],科目余额表[已审报表项目],K$1,科目余额表[科目名称],A40) -> 0 | L40: =SUMIFS(科目余额表[期末贷方],科目余额表[已审报表项目],L$1,科目余额表[科目名称],A40)-SUMIFS(科目余额表[期末借方],科目余额表[已审报表项目],L$1,科目余额表[科目名称],A40) -> 0 | M40: =SUMIFS(科目余额表[期末借方],科目余额表[已审报表项目],M$1,科目余额表[科目名称],A40)-SUMIFS(科目余额表[期末贷方],科目余额表[已审报表项目],M$1,科目余额表[科目名称],A40) -> 0 | N40: =SUMIFS(科目余额表[期末贷方],科目余额表[已审报表项目],N$1,科目余额表[科目名称],A40)-SUMIFS(科目余额表[期末借方],科目余额表[已审报表项目],N$1,科目余额表[科目名称],A40) -> 0 | O40: =SUMIFS(科目余额表[期末借方],科目余额表[已审报表项目],O$1,科目余额表[科目名称],A40)-SUMIFS(科目余额表[期末贷方],科目余额表[已审报表项目],O$1,科目余额表[科目名称],A40) -> 0 | P40: =SUMIFS(科目余额表[期末贷方],科目余额表[已审报表项目],P$1,科目余额表[科目名称],A40)-SUMIFS(科目余额表[期末借方],科目余额表[已审报表项目],P$1,科目余额表[科目名称],A40) -> 0 | Q40: =SUMIFS(科目余额表[期末借方],科目余额表[已审报表项目],Q$1,科目余额表[科目名称],A40)-SUMIFS(科目余额表[期末贷方],科目余额表[已审报表项目],Q$1,科目余额表[科目名称],A40) -> 0 | R40: =SUMIFS(科目余额表[期末贷方],科目余额表[已审报表项目],R$1,科目余额表[科目名称],A40)-SUMIFS(科目余额表[期末借方],科目余额表[已审报表项目],R$1,科目余额表[科目名称],A40) -> 0 | S40: =SUMIFS(科目余额表[期末借方],科目余额表[已审报表项目],S$1,科目余额表[科目名称],A40)-SUMIFS(科目余额表[期末贷方],科目余额表[已审报表项目],S$1,科目余额表[科目名称],A40) -> 0 | T40: =SUMIFS(科目余额表[期末贷方],科目余额表[已审报表项目],T$1,科目余额表[科目名称],A40)-SUMIFS(科目余额表[期末借方],科目余额表[已审报表项目],T$1,科目余额表[科目名称],A40) -> 0
B41: =IF(COUNTIF(E41:I41,"是")>0,"是","—") -> — | C41: =IF(10-COUNTIF(K41:T41,0)>1,"是","—") -> — | E41: =IF(AND(K41<>0,L41<>0),"是","—") -> — | F41: =IF(AND(M41<>0,N41<>0),"是","—") -> — | G41: =IF(AND(O41<>0,P41<>0),"是","—") -> — | H41: =IF(AND(Q41<>0,R41<>0),"是","—") -> — | I41: =IF(AND(S41<>0,T41<>0),"是","—") -> — | K41: =SUMIFS(科目余额表[期末借方],科目余额表[已审报表项目],K$1,科目余额表[科目名称],A41)-SUMIFS(科目余额表[期末贷方],科目余额表[已审报表项目],K$1,科目余额表[科目名称],A41) -> 0 | L41: =SUMIFS(科目余额表[期末贷方],科目余额表[已审报表项目],L$1,科目余额表[科目名称],A41)-SUMIFS(科目余额表[期末借方],科目余额表[已审报表项目],L$1,科目余额表[科目名称],A41) -> 0 | M41: =SUMIFS(科目余额表[期末借方],科目余额表[已审报表项目],M$1,科目余额表[科目名称],A41)-SUMIFS(科目余额表[期末贷方],科目余额表[已审报表项目],M$1,科目余额表[科目名称],A41) -> 0 | N41: =SUMIFS(科目余额表[期末贷方],科目余额表[已审报表项目],N$1,科目余额表[科目名称],A41)-SUMIFS(科目余额表[期末借方],科目余额表[已审报表项目],N$1,科目余额表[科目名称],A41) -> 0 | O41: =SUMIFS(科目余额表[期末借方],科目余额表[已审报表项目],O$1,科目余额表[科目名称],A41)-SUMIFS(科目余额表[期末贷方],科目余额表[已审报表项目],O$1,科目余额表[科目名称],A41) -> 0 | P41: =SUMIFS(科目余额表[期末贷方],科目余额表[已审报表项目],P$1,科目余额表[科目名称],A41)-SUMIFS(科目余额表[期末借方],科目余额表[已审报表项目],P$1,科目余额表[科目名称],A41) -> 0 | Q41: =SUMIFS(科目余额表[期末借方],科目余额表[已审报表项目],Q$1,科目余额表[科目名称],A41)-SUMIFS(科目余额表[期末贷方],科目余额表[已审报表项目],Q$1,科目余额表[科目名称],A41) -> 0 | R41: =SUMIFS(科目余额表[期末贷方],科目余额表[已审报表项目],R$1,科目余额表[科目名称],A41)-SUMIFS(科目余额表[期末借方],科目余额表[已审报表项目],R$1,科目余额表[科目名称],A41) -> 0 | S41: =SUMIFS(科目余额表[期末借方],科目余额表[已审报表项目],S$1,科目余额表[科目名称],A41)-SUMIFS(科目余额表[期末贷方],科目余额表[已审报表项目],S$1,科目余额表[科目名称],A41) -> 0 | T41: =SUMIFS(科目余额表[期末贷方],科目余额表[已审报表项目],T$1,科目余额表[科目名称],A41)-SUMIFS(科目余额表[期末借方],科目余额表[已审报表项目],T$1,科目余额表[科目名称],A41) -> 0
B42: =IF(COUNTIF(E42:I42,"是")>0,"是","—") -> — | C42: =IF(10-COUNTIF(K42:T42,0)>1,"是","—") -> — | E42: =IF(AND(K42<>0,L42<>0),"是","—") -> — | F42: =IF(AND(M42<>0,N42<>0),"是","—") -> — | G42: =IF(AND(O42<>0,P42<>0),"是","—") -> — | H42: =IF(AND(Q42<>0,R42<>0),"是","—") -> — | I42: =IF(AND(S42<>0,T42<>0),"是","—") -> — | K42: =SUMIFS(科目余额表[期末借方],科目余额表[已审报表项目],K$1,科目余额表[科目名称],A42)-SUMIFS(科目余额表[期末贷方],科目余额表[已审报表项目],K$1,科目余额表[科目名称],A42) -> 0 | L42: =SUMIFS(科目余额表[期末贷方],科目余额表[已审报表项目],L$1,科目余额表[科目名称],A42)-SUMIFS(科目余额表[期末借方],科目余额表[已审报表项目],L$1,科目余额表[科目名称],A42) -> 0 | M42: =SUMIFS(科目余额表[期末借方],科目余额表[已审报表项目],M$1,科目余额表[科目名称],A42)-SUMIFS(科目余额表[期末贷方],科目余额表[已审报表项目],M$1,科目余额表[科目名称],A42) -> 0 | N42: =SUMIFS(科目余额表[期末贷方],科目余额表[已审报表项目],N$1,科目余额表[科目名称],A42)-SUMIFS(科目余额表[期末借方],科目余额表[已审报表项目],N$1,科目余额表[科目名称],A42) -> 0 | O42: =SUMIFS(科目余额表[期末借方],科目余额表[已审报表项目],O$1,科目余额表[科目名称],A42)-SUMIFS(科目余额表[期末贷方],科目余额表[已审报表项目],O$1,科目余额表[科目名称],A42) -> 0 | P42: =SUMIFS(科目余额表[期末贷方],科目余额表[已审报表项目],P$1,科目余额表[科目名称],A42)-SUMIFS(科目余额表[期末借方],科目余额表[已审报表项目],P$1,科目余额表[科目名称],A42) -> 0 | Q42: =SUMIFS(科目余额表[期末借方],科目余额表[已审报表项目],Q$1,科目余额表[科目名称],A42)-SUMIFS(科目余额表[期末贷方],科目余额表[已审报表项目],Q$1,科目余额表[科目名称],A42) -> 0 | R42: =SUMIFS(科目余额表[期末贷方],科目余额表[已审报表项目],R$1,科目余额表[科目名称],A42)-SUMIFS(科目余额表[期末借方],科目余额表[已审报表项目],R$1,科目余额表[科目名称],A42) -> 0 | S42: =SUMIFS(科目余额表[期末借方],科目余额表[已审报表项目],S$1,科目余额表[科目名称],A42)-SUMIFS(科目余额表[期末贷方],科目余额表[已审报表项目],S$1,科目余额表[科目名称],A42) -> 0 | T42: =SUMIFS(科目余额表[期末贷方],科目余额表[已审报表项目],T$1,科目余额表[科目名称],A42)-SUMIFS(科目余额表[期末借方],科目余额表[已审报表项目],T$1,科目余额表[科目名称],A42) -> 0
B43: =IF(COUNTIF(E43:I43,"是")>0,"是","—") -> — | C43: =IF(10-COUNTIF(K43:T43,0)>1,"是","—") -> — | E43: =IF(AND(K43<>0,L43<>0),"是","—") -> — | F43: =IF(AND(M43<>0,N43<>0),"是","—") -> — | G43: =IF(AND(O43<>0,P43<>0),"是","—") -> — | H43: =IF(AND(Q43<>0,R43<>0),"是","—") -> — | I43: =IF(AND(S43<>0,T43<>0),"是","—") -> — | K43: =SUMIFS(科目余额表[期末借方],科目余额表[已审报表项目],K$1,科目余额表[科目名称],A43)-SUMIFS(科目余额表[期末贷方],科目余额表[已审报表项目],K$1,科目余额表[科目名称],A43) -> 0 | L43: =SUMIFS(科目余额表[期末贷方],科目余额表[已审报表项目],L$1,科目余额表[科目名称],A43)-SUMIFS(科目余额表[期末借方],科目余额表[已审报表项目],L$1,科目余额表[科目名称],A43) -> 0 | M43: =SUMIFS(科目余额表[期末借方],科目余额表[已审报表项目],M$1,科目余额表[科目名称],A43)-SUMIFS(科目余额表[期末贷方],科目余额表[已审报表项目],M$1,科目余额表[科目名称],A43) -> 0 | N43: =SUMIFS(科目余额表[期末贷方],科目余额表[已审报表项目],N$1,科目余额表[科目名称],A43)-SUMIFS(科目余额表[期末借方],科目余额表[已审报表项目],N$1,科目余额表[科目名称],A43) -> 0 | O43: =SUMIFS(科目余额表[期末借方],科目余额表[已审报表项目],O$1,科目余额表[科目名称],A43)-SUMIFS(科目余额表[期末贷方],科目余额表[已审报表项目],O$1,科目余额表[科目名称],A43) -> 0 | P43: =SUMIFS(科目余额表[期末贷方],科目余额表[已审报表项目],P$1,科目余额表[科目名称],A43)-SUMIFS(科目余额表[期末借方],科目余额表[已审报表项目],P$1,科目余额表[科目名称],A43) -> 0 | Q43: =SUMIFS(科目余额表[期末借方],科目余额表[已审报表项目],Q$1,科目余额表[科目名称],A43)-SUMIFS(科目余额表[期末贷方],科目余额表[已审报表项目],Q$1,科目余额表[科目名称],A43) -> 0 | R43: =SUMIFS(科目余额表[期末贷方],科目余额表[已审报表项目],R$1,科目余额表[科目名称],A43)-SUMIFS(科目余额表[期末借方],科目余额表[已审报表项目],R$1,科目余额表[科目名称],A43) -> 0 | S43: =SUMIFS(科目余额表[期末借方],科目余额表[已审报表项目],S$1,科目余额表[科目名称],A43)-SUMIFS(科目余额表[期末贷方],科目余额表[已审报表项目],S$1,科目余额表[科目名称],A43) -> 0 | T43: =SUMIFS(科目余额表[期末贷方],科目余额表[已审报表项目],T$1,科目余额表[科目名称],A43)-SUMIFS(科目余额表[期末借方],科目余额表[已审报表项目],T$1,科目余额表[科目名称],A43) -> 0
B44: =IF(COUNTIF(E44:I44,"是")>0,"是","—") -> — | C44: =IF(10-COUNTIF(K44:T44,0)>1,"是","—") -> — | E44: =IF(AND(K44<>0,L44<>0),"是","—") -> — | F44: =IF(AND(M44<>0,N44<>0),"是","—") -> — | G44: =IF(AND(O44<>0,P44<>0),"是","—") -> — | H44: =IF(AND(Q44<>0,R44<>0),"是","—") -> — | I44: =IF(AND(S44<>0,T44<>0),"是","—") -> — | K44: =SUMIFS(科目余额表[期末借方],科目余额表[已审报表项目],K$1,科目余额表[科目名称],A44)-SUMIFS(科目余额表[期末贷方],科目余额表[已审报表项目],K$1,科目余额表[科目名称],A44) -> 0 | L44: =SUMIFS(科目余额表[期末贷方],科目余额表[已审报表项目],L$1,科目余额表[科目名称],A44)-SUMIFS(科目余额表[期末借方],科目余额表[已审报表项目],L$1,科目余额表[科目名称],A44) -> 0 | M44: =SUMIFS(科目余额表[期末借方],科目余额表[已审报表项目],M$1,科目余额表[科目名称],A44)-SUMIFS(科目余额表[期末贷方],科目余额表[已审报表项目],M$1,科目余额表[科目名称],A44) -> 0 | N44: =SUMIFS(科目余额表[期末贷方],科目余额表[已审报表项目],N$1,科目余额表[科目名称],A44)-SUMIFS(科目余额表[期末借方],科目余额表[已审报表项目],N$1,科目余额表[科目名称],A44) -> 0 | O44: =SUMIFS(科目余额表[期末借方],科目余额表[已审报表项目],O$1,科目余额表[科目名称],A44)-SUMIFS(科目余额表[期末贷方],科目余额表[已审报表项目],O$1,科目余额表[科目名称],A44) -> 0 | P44: =SUMIFS(科目余额表[期末贷方],科目余额表[已审报表项目],P$1,科目余额表[科目名称],A44)-SUMIFS(科目余额表[期末借方],科目余额表[已审报表项目],P$1,科目余额表[科目名称],A44) -> 0 | Q44: =SUMIFS(科目余额表[期末借方],科目余额表[已审报表项目],Q$1,科目余额表[科目名称],A44)-SUMIFS(科目余额表[期末贷方],科目余额表[已审报表项目],Q$1,科目余额表[科目名称],A44) -> 0 | R44: =SUMIFS(科目余额表[期末贷方],科目余额表[已审报表项目],R$1,科目余额表[科目名称],A44)-SUMIFS(科目余额表[期末借方],科目余额表[已审报表项目],R$1,科目余额表[科目名称],A44) -> 0 | S44: =SUMIFS(科目余额表[期末借方],科目余额表[已审报表项目],S$1,科目余额表[科目名称],A44)-SUMIFS(科目余额表[期末贷方],科目余额表[已审报表项目],S$1,科目余额表[科目名称],A44) -> 0 | T44: =SUMIFS(科目余额表[期末贷方],科目余额表[已审报表项目],T$1,科目余额表[科目名称],A44)-SUMIFS(科目余额表[期末借方],科目余额表[已审报表项目],T$1,科目余额表[科目名称],A44) -> 0
B45: =IF(COUNTIF(E45:I45,"是")>0,"是","—") -> — | C45: =IF(10-COUNTIF(K45:T45,0)>1,"是","—") -> — | E45: =IF(AND(K45<>0,L45<>0),"是","—") -> — | F45: =IF(AND(M45<>0,N45<>0),"是","—") -> — | G45: =IF(AND(O45<>0,P45<>0),"是","—") -> — | H45: =IF(AND(Q45<>0,R45<>0),"是","—") -> — | I45: =IF(AND(S45<>0,T45<>0),"是","—") -> — | K45: =SUMIFS(科目余额表[期末借方],科目余额表[已审报表项目],K$1,科目余额表[科目名称],A45)-SUMIFS(科目余额表[期末贷方],科目余额表[已审报表项目],K$1,科目余额表[科目名称],A45) -> 0 | L45: =SUMIFS(科目余额表[期末贷方],科目余额表[已审报表项目],L$1,科目余额表[科目名称],A45)-SUMIFS(科目余额表[期末借方],科目余额表[已审报表项目],L$1,科目余额表[科目名称],A45) -> 0 | M45: =SUMIFS(科目余额表[期末借方],科目余额表[已审报表项目],M$1,科目余额表[科目名称],A45)-SUMIFS(科目余额表[期末贷方],科目余额表[已审报表项目],M$1,科目余额表[科目名称],A45) -> 0 | N45: =SUMIFS(科目余额表[期末贷方],科目余额表[已审报表项目],N$1,科目余额表[科目名称],A45)-SUMIFS(科目余额表[期末借方],科目余额表[已审报表项目],N$1,科目余额表[科目名称],A45) -> 0 | O45: =SUMIFS(科目余额表[期末借方],科目余额表[已审报表项目],O$1,科目余额表[科目名称],A45)-SUMIFS(科目余额表[期末贷方],科目余额表[已审报表项目],O$1,科目余额表[科目名称],A45) -> 0 | P45: =SUMIFS(科目余额表[期末贷方],科目余额表[已审报表项目],P$1,科目余额表[科目名称],A45)-SUMIFS(科目余额表[期末借方],科目余额表[已审报表项目],P$1,科目余额表[科目名称],A45) -> 0 | Q45: =SUMIFS(科目余额表[期末借方],科目余额表[已审报表项目],Q$1,科目余额表[科目名称],A45)-SUMIFS(科目余额表[期末贷方],科目余额表[已审报表项目],Q$1,科目余额表[科目名称],A45) -> 0 | R45: =SUMIFS(科目余额表[期末贷方],科目余额表[已审报表项目],R$1,科目余额表[科目名称],A45)-SUMIFS(科目余额表[期末借方],科目余额表[已审报表项目],R$1,科目余额表[科目名称],A45) -> 0 | S45: =SUMIFS(科目余额表[期末借方],科目余额表[已审报表项目],S$1,科目余额表[科目名称],A45)-SUMIFS(科目余额表[期末贷方],科目余额表[已审报表项目],S$1,科目余额表[科目名称],A45) -> 0 | T45: =SUMIFS(科目余额表[期末贷方],科目余额表[已审报表项目],T$1,科目余额表[科目名称],A45)-SUMIFS(科目余额表[期末借方],科目余额表[已审报表项目],T$1,科目余额表[科目名称],A45) -> 0
B46: =IF(COUNTIF(E46:I46,"是")>0,"是","—") -> — | C46: =IF(10-COUNTIF(K46:T46,0)>1,"是","—") -> — | E46: =IF(AND(K46<>0,L46<>0),"是","—") -> — | F46: =IF(AND(M46<>0,N46<>0),"是","—") -> — | G46: =IF(AND(O46<>0,P46<>0),"是","—") -> — | H46: =IF(AND(Q46<>0,R46<>0),"是","—") -> — | I46: =IF(AND(S46<>0,T46<>0),"是","—") -> — | K46: =SUMIFS(科目余额表[期末借方],科目余额表[已审报表项目],K$1,科目余额表[科目名称],A46)-SUMIFS(科目余额表[期末贷方],科目余额表[已审报表项目],K$1,科目余额表[科目名称],A46) -> 0 | L46: =SUMIFS(科目余额表[期末贷方],科目余额表[已审报表项目],L$1,科目余额表[科目名称],A46)-SUMIFS(科目余额表[期末借方],科目余额表[已审报表项目],L$1,科目余额表[科目名称],A46) -> 0 | M46: =SUMIFS(科目余额表[期末借方],科目余额表[已审报表项目],M$1,科目余额表[科目名称],A46)-SUMIFS(科目余额表[期末贷方],科目余额表[已审报表项目],M$1,科目余额表[科目名称],A46) -> 0 | N46: =SUMIFS(科目余额表[期末贷方],科目余额表[已审报表项目],N$1,科目余额表[科目名称],A46)-SUMIFS(科目余额表[期末借方],科目余额表[已审报表项目],N$1,科目余额表[科目名称],A46) -> 0 | O46: =SUMIFS(科目余额表[期末借方],科目余额表[已审报表项目],O$1,科目余额表[科目名称],A46)-SUMIFS(科目余额表[期末贷方],科目余额表[已审报表项目],O$1,科目余额表[科目名称],A46) -> 0 | P46: =SUMIFS(科目余额表[期末贷方],科目余额表[已审报表项目],P$1,科目余额表[科目名称],A46)-SUMIFS(科目余额表[期末借方],科目余额表[已审报表项目],P$1,科目余额表[科目名称],A46) -> 0 | Q46: =SUMIFS(科目余额表[期末借方],科目余额表[已审报表项目],Q$1,科目余额表[科目名称],A46)-SUMIFS(科目余额表[期末贷方],科目余额表[已审报表项目],Q$1,科目余额表[科目名称],A46) -> 0 | R46: =SUMIFS(科目余额表[期末贷方],科目余额表[已审报表项目],R$1,科目余额表[科目名称],A46)-SUMIFS(科目余额表[期末借方],科目余额表[已审报表项目],R$1,科目余额表[科目名称],A46) -> 0 | S46: =SUMIFS(科目余额表[期末借方],科目余额表[已审报表项目],S$1,科目余额表[科目名称],A46)-SUMIFS(科目余额表[期末贷方],科目余额表[已审报表项目],S$1,科目余额表[科目名称],A46) -> 0 | T46: =SUMIFS(科目余额表[期末贷方],科目余额表[已审报表项目],T$1,科目余额表[科目名称],A46)-SUMIFS(科目余额表[期末借方],科目余额表[已审报表项目],T$1,科目余额表[科目名称],A46) -> 0
B47: =IF(COUNTIF(E47:I47,"是")>0,"是","—") -> — | C47: =IF(10-COUNTIF(K47:T47,0)>1,"是","—") -> — | E47: =IF(AND(K47<>0,L47<>0),"是","—") -> — | F47: =IF(AND(M47<>0,N47<>0),"是","—") -> — | G47: =IF(AND(O47<>0,P47<>0),"是","—") -> — | H47: =IF(AND(Q47<>0,R47<>0),"是","—") -> — | I47: =IF(AND(S47<>0,T47<>0),"是","—") -> — | K47: =SUMIFS(科目余额表[期末借方],科目余额表[已审报表项目],K$1,科目余额表[科目名称],A47)-SUMIFS(科目余额表[期末贷方],科目余额表[已审报表项目],K$1,科目余额表[科目名称],A47) -> 0 | L47: =SUMIFS(科目余额表[期末贷方],科目余额表[已审报表项目],L$1,科目余额表[科目名称],A47)-SUMIFS(科目余额表[期末借方],科目余额表[已审报表项目],L$1,科目余额表[科目名称],A47) -> 0 | M47: =SUMIFS(科目余额表[期末借方],科目余额表[已审报表项目],M$1,科目余额表[科目名称],A47)-SUMIFS(科目余额表[期末贷方],科目余额表[已审报表项目],M$1,科目余额表[科目名称],A47) -> 0 | N47: =SUMIFS(科目余额表[期末贷方],科目余额表[已审报表项目],N$1,科目余额表[科目名称],A47)-SUMIFS(科目余额表[期末借方],科目余额表[已审报表项目],N$1,科目余额表[科目名称],A47) -> 0 | O47: =SUMIFS(科目余额表[期末借方],科目余额表[已审报表项目],O$1,科目余额表[科目名称],A47)-SUMIFS(科目余额表[期末贷方],科目余额表[已审报表项目],O$1,科目余额表[科目名称],A47) -> 0 | P47: =SUMIFS(科目余额表[期末贷方],科目余额表[已审报表项目],P$1,科目余额表[科目名称],A47)-SUMIFS(科目余额表[期末借方],科目余额表[已审报表项目],P$1,科目余额表[科目名称],A47) -> 0 | Q47: =SUMIFS(科目余额表[期末借方],科目余额表[已审报表项目],Q$1,科目余额表[科目名称],A47)-SUMIFS(科目余额表[期末贷方],科目余额表[已审报表项目],Q$1,科目余额表[科目名称],A47) -> 0 | R47: =SUMIFS(科目余额表[期末贷方],科目余额表[已审报表项目],R$1,科目余额表[科目名称],A47)-SUMIFS(科目余额表[期末借方],科目余额表[已审报表项目],R$1,科目余额表[科目名称],A47) -> 0 | S47: =SUMIFS(科目余额表[期末借方],科目余额表[已审报表项目],S$1,科目余额表[科目名称],A47)-SUMIFS(科目余额表[期末贷方],科目余额表[已审报表项目],S$1,科目余额表[科目名称],A47) -> 0 | T47: =SUMIFS(科目余额表[期末贷方],科目余额表[已审报表项目],T$1,科目余额表[科目名称],A47)-SUMIFS(科目余额表[期末借方],科目余额表[已审报表项目],T$1,科目余额表[科目名称],A47) -> 0
... B251: =IF(COUNTIF(E251:I251,"是")>0,"是","—") -> — | C251: =IF(10-COUNTIF(K251:T251,0)>1,"是","—") -> — | E251: =IF(AND(K251<>0,L251<>0),"是","—") -> — | F251: =IF(AND(M251<>0,N251<>0),"是","—") -> — | G251: =IF(AND(O251<>0,P251<>0),"是","—") -> — | H251: =IF(AND(Q251<>0,R251<>0),"是","—") -> — | I251: =IF(AND(S251<>0,T251<>0),"是","—") -> — | K251: =SUMIFS(科目余额表[期末借方],科目余额表[已审报表项目],K$1,科目余额表[科目名称],A251)-SUMIFS(科目余额表[期末贷方],科目余额表[已审报表项目],K$1,科目余额表[科目名称],A251) -> 0 | L251: =SUMIFS(科目余额表[期末贷方],科目余额表[已审报表项目],L$1,科目余额表[科目名称],A251)-SUMIFS(科目余额表[期末借方],科目余额表[已审报表项目],L$1,科目余额表[科目名称],A251) -> 0 | M251: =SUMIFS(科目余额表[期末借方],科目余额表[已审报表项目],M$1,科目余额表[科目名称],A251)-SUMIFS(科目余额表[期末贷方],科目余额表[已审报表项目],M$1,科目余额表[科目名称],A251) -> 0 | N251: =SUMIFS(科目余额表[期末贷方],科目余额表[已审报表项目],N$1,科目余额表[科目名称],A251)-SUMIFS(科目余额表[期末借方],科目余额表[已审报表项目],N$1,科目余额表[科目名称],A251) -> 0 | O251: =SUMIFS(科目余额表[期末借方],科目余额表[已审报表项目],O$1,科目余额表[科目名称],A251)-SUMIFS(科目余额表[期末贷方],科目余额表[已审报表项目],O$1,科目余额表[科目名称],A251) -> 0 | P251: =SUMIFS(科目余额表[期末贷方],科目余额表[已审报表项目],P$1,科目余额表[科目名称],A251)-SUMIFS(科目余额表[期末借方],科目余额表[已审报表项目],P$1,科目余额表[科目名称],A251) -> 0 | Q251: =SUMIFS(科目余额表[期末借方],科目余额表[已审报表项目],Q$1,科目余额表[科目名称],A251)-SUMIFS(科目余额表[期末贷方],科目余额表[已审报表项目],Q$1,科目余额表[科目名称],A251) -> 0 | R251: =SUMIFS(科目余额表[期末贷方],科目余额表[已审报表项目],R$1,科目余额表[科目名称],A251)-SUMIFS(科目余额表[期末借方],科目余额表[已审报表项目],R$1,科目余额表[科目名称],A251) -> 0 | S251: =SUMIFS(科目余额表[期末借方],科目余额表[已审报表项目],S$1,科目余额表[科目名称],A251)-SUMIFS(科目余额表[期末贷方],科目余额表[已审报表项目],S$1,科目余额表[科目名称],A251) -> 0 | T251: =SUMIFS(科目余额表[期末贷方],科目余额表[已审报表项目],T$1,科目余额表[科目名称],A251)-SUMIFS(科目余额表[期末借方],科目余额表[已审报表项目],T$1,科目余额表[科目名称],A251) -> 0

Sheet 税费测算
A1: 税费明细 | G1: 流转税附加税费测算
A2: 税种 | B2: 应交税费贷方 | C2: 费用类科目借方 | D2: 差额 | E2: 备注 | G2: 测算项目 | H2: 测算税率 | I2: 备注
A3: 增值税 | B3: =SUMIF(科目余额表[测算项目],A3,科目余额表[本期贷方]) -> 615381 | G3: 城建税税率 | H3: =IFERROR(B6/(B3+B5),0) -> 0.07 | I3: 应交税费贷方
A4: 待抵扣进项税 | B4: =SUMIF(科目余额表[测算项目],A4,科目余额表[本期贷方]) -> 0 | G4: 教育费税率 | H4: =IFERROR(B7/(B3+B5),0) -> 0.03 | I4: 应交税费贷方
A5: 消费税 | B5: =SUMIF(科目余额表[测算项目],A5,科目余额表[本期贷方]) -> 0 | C5: =SUMIF(科目余额表[测算项目],"税-消费税",科目余额表[本期借方]) -> 0 | D5: =B5-C5 -> 0 | G5: 地方教育费税率 | H5: =IFERROR(B8/(B3+B5),0) -> 0.02 | I5: 应交税费贷方
A6: 城市维护建设税 | B6: =SUMIF(科目余额表[测算项目],A6,科目余额表[本期贷方]) -> 43076.67 | C6: =SUMIF(科目余额表[测算项目],"税-城建税",科目余额表[本期借方]) -> 43076.67 | D6: =B6-C6 -> 0
A7: 教育费附加 | B7: =SUMIF(科目余额表[测算项目],A7,科目余额表[本期贷方]) -> 18461.43 | C7: =SUMIF(科目余额表[测算项目],"税-教育",科目余额表[本期借方]) -> 18461.43 | D7: =B7-C7 -> 0 | G7: 企业所得税测算
A8: 地方教育费附加 | B8: =SUMIF(科目余额表[测算项目],A8,科目余额表[本期贷方]) -> 12307.62 | C8: =SUMIF(科目余额表[测算项目],"税-地方教育",科目余额表[本期借方]) -> 12307.62 | D8: =B8-C8 -> 0 | G8: 测算项目 | H8: 测算税率 | I8: 备注
A9: 关税 | B9: =SUMIF(科目余额表[测算项目],A9,科目余额表[本期贷方]) -> 0 | C9: =SUMIF(科目余额表[测算项目],"税-关税",科目余额表[本期借方]) -> 0 | D9: =B9-C9 -> 0 | G9: 所得税费用 | H9: =IFERROR(C10/(试算平衡表!D63-SUM(试算平衡表!D64:'试算平衡表'!D69)+SUM(试算平衡表!D70:'试算平衡表'!D77)-SUM(试算平衡表!D78:'试算平衡表'!D78)),0) -> 0.25000526 | I9: 所得税费用发生额
A10: 企业所得税 | B10: =SUMIF(科目余额表[测算项目],A10,科目余额表[本期贷方]) -> 579779.36 | C10: =SUMIF(科目余额表[测算项目],"税-企所",科目余额表[本期借方]) -> 579779.36 | D10: =B10-C10 -> 0
A11: 个人所得税 | B11: =SUMIF(科目余额表[测算项目],A11,科目余额表[本期贷方]) -> 0 | G11: 企业所得税扣除项目简易测算
A12: 土地增值税 | B12: =SUMIF(科目余额表[测算项目],A12,科目余额表[本期贷方]) -> 0 | C12: =SUMIF(科目余额表[测算项目],"税-土增税",科目余额表[本期借方]) -> 0 | D12: =B12-C12 -> 0 | G12: 测算项目 | H12: 账载金额 | I12: 扣除上限 | J12: 调减金额 | K12: 备注
A13: 房产税 | B13: =SUMIF(科目余额表[测算项目],A13,科目余额表[本期贷方]) -> 0 | C13: =SUMIF(科目余额表[测算项目],"税-房产税",科目余额表[本期借方]) -> 0 | D13: =B13-C13 -> 0 | G13: 工资薪金支出 | H13: =SUMIF(科目余额表[测算项目],G13,科目余额表[本期借方]) -> 0 | K13: 无标准比例限制，计算基数
A14: 车船税 | B14: =SUMIF(科目余额表[测算项目],A14,科目余额表[本期贷方]) -> 0 | C14: =SUMIF(科目余额表[测算项目],"税-车船",科目余额表[本期借方]) -> 0 | D14: =B14-C14 -> 0 | G14: 职工福利费支出 | H14: =SUMIF(科目余额表[测算项目],G14,科目余额表[本期借方]) -> 0 | I14: =H13*0.14 -> 0 | J14: =IF(H14>I14,H14-I14,0) -> 0 | K14: 不超过工资薪金总额的14%
A15: 印花税 | B15: =SUMIF(科目余额表[测算项目],A15,科目余额表[本期贷方]) -> 0 | C15: =SUMIF(科目余额表[测算项目],"税-印花税",科目余额表[本期借方]) -> 0 | D15: =B15-C15 -> 0 | G15: 职工教育经费支出 | H15: =SUMIF(科目余额表[测算项目],G15,科目余额表[本期借方]) -> 0 | I15: =H13*0.08 -> 0 | J15: =IF(H15>I15,H15-I15,0) -> 0 | K15: 不超过工资薪金总额的8%，超过部分准予在以后纳税年度结转扣除，有特殊行业例外
A16: 契税 | B16: =SUMIF(科目余额表[测算项目],A16,科目余额表[本期贷方]) -> 0 | C16: =SUMIF(科目余额表[测算项目],"税-契税",科目余额表[本期借方]) -> 0 | D16: =B16-C16 -> 0 | G16: 工会经费支出 | H16: =SUMIF(科目余额表[测算项目],G16,科目余额表[本期借方]) -> 0 | I16: =H13*0.02 -> 0 | J16: =IF(H16>I16,H16-I16,0) -> 0 | K16: 不超过工资薪金总额的2%
A17: 资源税 | B17: =SUMIF(科目余额表[测算项目],A17,科目余额表[本期贷方]) -> 0 | C17: =SUMIF(科目余额表[测算项目],"税-资源税",科目余额表[本期借方]) -> 0 | D17: =B17-C17 -> 0 | G17: 补充养老保险 | H17: =SUMIF(科目余额表[测算项目],G17,科目余额表[本期借方]) -> 0 | I17: =H13*0.05 -> 0 | J17: =IF(H17>I17,H17-I17,0) -> 0 | K17: 不超过工资薪金总额的5%
A18: 环境保护税 | B18: =SUMIF(科目余额表[测算项目],A18,科目余额表[本期贷方]) -> 0 | C18: =SUMIF(科目余额表[测算项目],"税-环保",科目余额表[本期借方]) -> 0 | D18: =B18-C18 -> 0 | G18: 补充医疗保险 | H18: =SUMIF(科目余额表[测算项目],G18,科目余额表[本期借方]) -> 0 | I18: =H13*0.05 -> 0 | J18: =IF(H18>I18,H18-I18,0) -> 0 | K18: 不超过工资薪金总额的5%
A19: 城镇土地使用税 | B19: =SUMIF(科目余额表[测算项目],A19,科目余额表[本期贷方]) -> 0 | C19: =SUMIF(科目余额表[测算项目],"税-土地使用税",科目余额表[本期借方]) -> 0 | D19: =B19-C19 -> 0 | G19: 党组织工作经费 | H19: =SUMIF(科目余额表[测算项目],G19,科目余额表[本期借方]) -> 0 | I19: =H13*0.01 -> 0 | J19: =IF(H19>I19,H19-I19,0) -> 0 | K19: 不超过工资薪金总额的1%
A20: 车船购置税 | B20: =SUMIF(科目余额表[测算项目],A20,科目余额表[本期贷方]) -> 0 | C20: =SUMIF(科目余额表[测算项目],"税-车船购置税",科目余额表[本期借方]) -> 0 | D20: =B20-C20 -> 0 | G20: 营业收入 | H20: =SUMIF(科目余额表[测算项目],G20,科目余额表[本期贷方]) -> 0 | K20: 计算基数
A21: 耕地占用税 | B21: =SUMIF(科目余额表[测算项目],A21,科目余额表[本期贷方]) -> 0 | C21: =SUMIF(科目余额表[测算项目],"税-耕地占用税",科目余额表[本期借方]) -> 0 | D21: =B21-C21 -> 0 | G21: 业务招待费支出 | H21: =SUMIF(科目余额表[测算项目],G21,科目余额表[本期借方]) -> 0 | I21: =MIN(H21*0.6,H20*0.005) -> 0 | J21: =IF(H21>I21,H21-I21,0) -> 0 | K21: 实际发生额×60%与当年销售（营业）收入×5‰中的较小值
A22: 船舶吨税 | B22: =SUMIF(科目余额表[测算项目],A22,科目余额表[本期贷方]) -> 0 | C22: =SUMIF(科目余额表[测算项目],"税-船舶吨税",科目余额表[本期借方]) -> 0 | D22: =B22-C22 -> 0 | G22: 广告费和业务宣传费支出 | H22: =SUMIF(科目余额表[测算项目],G22,科目余额表[本期借方]) -> 0 | I22: =H20*0.15 -> 0 | J22: =IF(H22>I22,H22-I22,0) -> 0 | K22: 当年销售（营业）收入×15%，超过部分准予在以后纳税年度结转扣除，有特殊行业
A23: 烟叶税 | B23: =SUMIF(科目余额表[测算项目],A23,科目余额表[本期贷方]) -> 0 | C23: =SUMIF(科目余额表[测算项目],"税-烟叶税",科目余额表[本期借方]) -> 0 | D23: =B23-C23 -> 0 | G23: 利润总额 | H23: =试算平衡表!D63-SUM(试算平衡表!D64:'试算平衡表'!D69)+SUM(试算平衡表!D70:'试算平衡表'!D77)-SUM(试算平衡表!D78:'试算平衡表'!D78) -> 2319068.7 | K23: 计算基数
A24: 合计 | B24: =SUM(B3:B23) -> 1269006.1 | C24: =SUM(C3:C23) -> 653625.08 | G24: 捐赠支出 | H24: =SUMIF(科目余额表[测算项目],G24,科目余额表[本期借方]) -> 0 | I24: =H23*0.12 -> 278288.24 | J24: =IF(H24>I24,H24-I24,0) -> 0 | K24: 当年超过年度利润总额12%的部分，往后顺延不超过3年

Sheet 现金流测算
A1: 报表项目 | B1: 企业未审报表金额 | C1: 间接法计算过程 | D1: 间接法金额 | E1: 直接法计算过程 | F1: 直接法对应金额
A2: 一、经营活动产生的现金流量：
A3: 销售商品、提供劳务收到的现金 | C3: 销售商品、提供劳务收到的现金 | D3: =SUM(D4:D10,-D11,-D12,-D13,D5:D14) -> 8045200 | E3: 销售商品、提供劳务收到的现金 | F3: =SUM(F4:F14) -> 12389000
C4: ＝ 营业收入 | D4: =试算平衡表!D63 -> 13280000 | E4: 对方科目是营业收入 | F4: =SUMIF(现金流数据聚合!D:D,E4,现金流数据聚合!B:B)-SUMIF(现金流数据聚合!D:D,E4,现金流数据聚合!C:C) -> 0
C5: ＋ 当期收到的销项税（营业收入*适用税率） | E5: 对方科目是销项税额 | F5: =SUMIF(现金流数据聚合!D:D,E5,现金流数据聚合!B:B)-SUMIF(现金流数据聚合!D:D,E5,现金流数据聚合!C:C) -> 0
C6: ＋ 应收票据期初余额-应收票据期末余额 | D6: =试算平衡表!C5-试算平衡表!D5 -> 0 | E6: 对方科目是应收票据 | F6: =SUMIF(现金流数据聚合!D:D,E6,现金流数据聚合!B:B)-SUMIF(现金流数据聚合!D:D,E6,现金流数据聚合!C:C) -> 0
C7: ＋ 应收账款期初余额-应收账款期末余额 | D7: =试算平衡表!C6-试算平衡表!D6 -> -2617400 | E7: 对方科目是应收账款 | F7: =SUMIF(现金流数据聚合!D:D,E7,现金流数据聚合!B:B)-SUMIF(现金流数据聚合!D:D,E7,现金流数据聚合!C:C) -> 12389000
C8: ＋ 合同资产期初余额-合同资产期末余额 | D8: =试算平衡表!C11-试算平衡表!D11 -> 0 | E8: 对方科目是合同资产 | F8: =SUMIF(现金流数据聚合!D:D,E8,现金流数据聚合!B:B)-SUMIF(现金流数据聚合!D:D,E8,现金流数据聚合!C:C) -> 0
C9: ＋ 预收账款期末余额-预收账款期初余额 | D9: =试算平衡表!D38-试算平衡表!C38 -> 0 | E9: 对方科目是预收账款 | F9: =SUMIF(现金流数据聚合!D:D,E9,现金流数据聚合!B:B)-SUMIF(现金流数据聚合!D:D,E9,现金流数据聚合!C:C) -> 0
C10: ＋ 当期收回前期核销的坏账
C11: — 以非现金资产抵偿债务而减少的应收账款和应收票据
C12: — 当期核销的坏账
C13: — 票据贴现的利息
C14: ＋ 其他
A15: 收到的税费返还 | C15: 收到的税费返还 | D15: =SUM(D16:D19) -> 0 | E15: 收到的税费返还 | F15: =SUM(F16:F19) -> 0
C16: ＝ 实际收到的增值税出口退税
C17: ＋ 先征后返增值税
C18: ＋ 企业所得税当期退税金额
C19: ＋ 先征后返的消费税
A20: 收到其他与经营活动有关的现金 | C20: 收到其他与经营活动有关的现金 | D20: =SUM(D21:D25) -> 15000 | E20: 收到其他与经营活动有关的现金 | F20: =SUM(F21:F25) -> 18749.38
C21: ＝ 补贴收入、应收补贴款(与其对应的部分) | E21: 对方科目是其他应收款 | F21: =SUMIF(现金流数据聚合!D:D,E21,现金流数据聚合!B:B) -> 10000
C22: ＋ 其他应收款本期贷方发生额 | D22: =SUMIF(科目余额表[科目名称],"其他应收款",科目余额表[本期贷方]) -> 10000 | E22: 对方科目是其他应付款 | F22: =SUMIF(现金流数据聚合!D:D,E22,现金流数据聚合!B:B) -> 0
C23: ＋ 其他应付款本期贷方发生额 | D23: =SUMIF(科目余额表[科目名称],"其他应付款",科目余额表[本期贷方]) -> 5000 | E23: 对方科目是利息收入 | F23: =SUMIF(现金流数据聚合!D:D,E23,现金流数据聚合!B:B)-SUMIF(现金流数据聚合!D:D,E23,现金流数据聚合!C:C) -> 8749.38
E24: 对方科目是营业外收入 | F24: =SUMIF(现金流数据聚合!D:D,E24,现金流数据聚合!B:B)-SUMIF(现金流数据聚合!D:D,E24,现金流数据聚合!C:C) -> 0
E25: 收到其他与经营-其他 | F25: =SUMIF(现金流数据聚合!D:D,E25,现金流数据聚合!B:B) -> 0
A26: 经营活动现金流入小计 | B26: =SUM(B3,B15,B20) -> 0 | C26: 经营活动现金流入小计 | D26: =D3+D15+D20 -> 8060200 | E26: 经营活动现金流入小计 | F26: =F3+F15+F20 -> 12407749
A27: 购买商品、接受劳务支付的现金 | C27: 购买商品、接受劳务支付的现金 | D27: =SUM(D28:D34,-D35,-D36,D37) -> -3338019 | E27: 购买商品、接受劳务支付的现金 | F27: =SUM(F28:F37) -> -2138000
C28: ＝ 营业成本 | D28: =试算平衡表!D64 -> 10789000 | E28: 对方科目是营业成本 | F28: =SUMIF(现金流数据聚合!D:D,E28,现金流数据聚合!C:C)-SUMIF(现金流数据聚合!D:D,E28,现金流数据聚合!B:B) -> 0
C29: ＋ 当期支付的进项税（营业成本*适用税率） | E29: 对方科目是进项税额 | F29: =SUMIF(现金流数据聚合!D:D,E29,现金流数据聚合!C:C)-SUMIF(现金流数据聚合!D:D,E29,现金流数据聚合!B:B) -> 0
C30: ＋ 存货期末余额-存货期初余额 | D30: =试算平衡表!D10-试算平衡表!C10 -> -2331700 | E30: 对方科目是存货类科目 | F30: =SUMIF(现金流数据聚合!D:D,E30,现金流数据聚合!C:C)-SUMIF(现金流数据聚合!D:D,E30,现金流数据聚合!B:B) -> 0
C31: ＋ 应付票据期初余额-应付票据期末余额 | D31: =试算平衡表!C36-试算平衡表!D36 -> 0 | E31: 对方科目是应付票据 | F31: =SUMIF(现金流数据聚合!D:D,E31,现金流数据聚合!C:C)-SUMIF(现金流数据聚合!D:D,E31,现金流数据聚合!B:B) -> 0
C32: ＋ 应付账款期初余额-应付账款期末余额 | D32: =试算平衡表!C37-试算平衡表!D37 -> -10523380 | E32: 对方科目是应付账款 | F32: =SUMIF(现金流数据聚合!D:D,E32,现金流数据聚合!C:C)-SUMIF(现金流数据聚合!D:D,E32,现金流数据聚合!B:B) -> -264000
C33: ＋ 合同负债期初余额-合同负债期末余额 | D33: =试算平衡表!C39-试算平衡表!D39 -> 0 | E33: 对方科目是合同负债 | F33: =SUMIF(现金流数据聚合!D:D,E33,现金流数据聚合!C:C)-SUMIF(现金流数据聚合!D:D,E33,现金流数据聚合!B:B) -> 0
C34: ＋ 预付账款期末余额-预付账款期初余额 | D34: =试算平衡表!D8-试算平衡表!C8 -> -1271938.9 | E34: 对方科目是预付账款 | F34: =SUMIF(现金流数据聚合!D:D,E34,现金流数据聚合!C:C)-SUMIF(现金流数据聚合!D:D,E34,现金流数据聚合!B:B) -> -1874000
C35: — 当期以非现金资产清偿债务减少的应付账款和应付票据
C36: — 当期实际发生的生产成本和制造费用中工资、福利、折旧和其他摊销费用(不包括消耗的物料)
C37: ＋ 当期支付的在管理费用、销售费用中列支的购买商品和接受劳务费用
A38: 支付给职工以及为职工支付的现金 | C38: 支付给职工以及为职工支付的现金 | D38: =SUM(D39:D45) -> 0 | E38: 支付给职工以及为职工支付的现金 | F38: =SUM(F39:F45) -> 0
C39: ＝ 应付工资借方发生额 | D39: =SUMIF(科目余额表[科目名称],"职工工资",科目余额表[本期借方]) -> 0 | E39: 对方科目是应付职工薪酬类 | F39: =SUMIF(现金流数据聚合!D:D,E39,现金流数据聚合!C:C)-SUMIF(现金流数据聚合!D:D,E39,现金流数据聚合!B:B) -> 0
C40: ＋ 生产成本、制造费用、销售费用、管理费用(工资、奖金、津贴、补贴、福利费、住房公积金、医疗、劳动保险金) | E40: 对方科目是生产成本中的职工薪酬 | F40: =SUMIF(现金流数据聚合!D:D,E40,现金流数据聚合!C:C)-SUMIF(现金流数据聚合!D:D,E40,现金流数据聚合!B:B) -> 0
C41: ＋ 其他 | E41: 对方科目是制造费用中的职工薪酬 | F41: =SUMIF(现金流数据聚合!D:D,E41,现金流数据聚合!C:C)-SUMIF(现金流数据聚合!D:D,E41,现金流数据聚合!B:B) -> 0
E42: 对方科目是销售费用中的职工薪酬 | F42: =SUMIF(现金流数据聚合!D:D,E42,现金流数据聚合!C:C)-SUMIF(现金流数据聚合!D:D,E42,现金流数据聚合!B:B) -> 0
E43: 对方科目是管理费用中的职工薪酬 | F43: =SUMIF(现金流数据聚合!D:D,E43,现金流数据聚合!C:C)-SUMIF(现金流数据聚合!D:D,E43,现金流数据聚合!B:B) -> 0
E44: 对方科目是应交个人所得税 | F44: =SUMIF(现金流数据聚合!D:D,E44,现金流数据聚合!C:C)-SUMIF(现金流数据聚合!D:D,E44,现金流数据聚合!B:B) -> 0
E45: 支付给职工-其他 | F45: =SUMIF(现金流数据聚合!D:D,E45,现金流数据聚合!C:C) -> 0
A46: 支付的各项税费 | C46: 支付的各项税费 | D46: =SUM(D47:D54) -> 727896.33 | E46: 支付的各项税费 | F46: =SUM(F47:F54) -> 736176.74
C47: ＝ 应交增值税 | D47: =SUMIF(科目余额表[科目名称],"未交增值税",科目余额表[本期借方]) -> 557849.49 | E47: 对方科目是个所税以外的应交税费类 | F47: =SUMIF(现金流数据聚合!D:D,E47,现金流数据聚合!C:C)-SUMIF(现金流数据聚合!D:D,E47,现金流数据聚合!B:B) -> 736176.74
C48: ＋ 企业所得税 | D48: =SUMIF(科目余额表[科目名称],"企业所得税",科目余额表[本期借方]) -> 111385.32 | E48: 对方科目是税金及附加类 | F48: =SUMIF(现金流数据聚合!D:D,E48,现金流数据聚合!C:C)-SUMIF(现金流数据聚合!D:D,E48,现金流数据聚合!B:B) -> 0
C49: ＋ 消费税 | D49: =SUMIF(科目余额表[科目名称],"消费税",科目余额表[本期借方]) -> 0
C50: ＋ 城市维护建设税 | D50: =SUMIF(科目余额表[科目名称],"城市维护税",科目余额表[本期借方]) -> 0
C51: ＋ 教育费附加 | D51: =SUMIF(科目余额表[科目名称],"教育费附加",科目余额表[本期借方]) -> 35196.91
C52: ＋ 地方教育费附加 | D52: =SUMIF(科目余额表[科目名称],"地方教育费附加",科目余额表[本期借方]) -> 23464.61
C53: ＋ 印花税 | D53: =SUMIF(科目余额表[科目名称],"印花税",科目余额表[本期借方]) -> 0
C54: ＋ 其他
A55: 支付其他与经营活动有关的现金 | C55: 支付其他与经营活动有关的现金 | D55: =SUM(D56,-D57,D58:D63) -> 105085.62 | E55: 支付其他与经营活动有关的现金 | F55: =SUM(F56:F63) -> 7475
C56: ＝ 销售、管理、研发、财务费用 | D56: =SUM(试算平衡表!D66:D69) -> 98085.62 | E56: 对方科目是销售费用 | F56: =SUMIF(现金流数据聚合!D:D,E56,现金流数据聚合!C:C)-SUMIF(现金流数据聚合!D:D,E56,现金流数据聚合!B:B) -> 0
C57: — 固定资产折旧、无形资产摊销、坏账准备 | E57: 对方科目是管理费用 | F57: =SUMIF(现金流数据聚合!D:D,E57,现金流数据聚合!C:C)-SUMIF(现金流数据聚合!D:D,E57,现金流数据聚合!B:B) -> 275
C58: ＋ 其他应收款本期借方发生额 | D58: =SUMIF(科目余额表[科目名称],"其他应收款",科目余额表[本期借方]) -> 0 | E58: 对方科目是研发费用 | F58: =SUMIF(现金流数据聚合!D:D,E58,现金流数据聚合!C:C)-SUMIF(现金流数据聚合!D:D,E58,现金流数据聚合!B:B) -> 0
C59: ＋ 其他应付款本期借方发生额 | D59: =SUMIF(科目余额表[科目名称],"其他应付款",科目余额表[本期借方]) -> 7000 | E59: 对方科目是银行手续费 | F59: =SUMIF(现金流数据聚合!D:D,E59,现金流数据聚合!C:C)-SUMIF(现金流数据聚合!D:D,E59,现金流数据聚合!B:B) -> 200
C60: ＋ 营业外支出 | D60: =试算平衡表!D78 -> 0 | E60: 对方科目是营业外支出 | F60: =SUMIF(现金流数据聚合!D:D,E60,现金流数据聚合!C:C)-SUMIF(现金流数据聚合!D:D,E60,现金流数据聚合!B:B) -> 0
C61: ＋ 其他 | E61: 对方科目是其他应收款 | F61: =SUMIF(现金流数据聚合!D:D,E61,现金流数据聚合!C:C) -> 0
E62: 对方科目是其他应付款 | F62: =SUMIF(现金流数据聚合!D:D,E62,现金流数据聚合!C:C) -> 7000
E63: 支付其他与经营-其他 | F63: =SUMIF(现金流数据聚合!D:D,E63,现金流数据聚合!C:C) -> 0
A64: 经营活动现金流出小计 | B64: =SUM(B27,B38,B46,B55) -> 0 | C64: 经营活动现金流出小计 | D64: =D27+D38+D46+D55 -> -2505037 | E64: 经营活动现金流出小计 | F64: =F27+F38+F46+F55 -> -1394348.3
A65: 经营活动产生的现金流量净额 | B65: =B26-B64 -> 0 | C65: 经营活动产生的现金流量净额 | D65: =D26-D64 -> 10565237 | E65: 经营活动产生的现金流量净额 | F65: =F26-F64 -> 13802098
A66: 二、投资活动产生的现金流量：
A67: 收回投资收到的现金 | C67: 收回投资收到的现金 | D67: =SUM(D68:D71) -> 0 | E67: 收回投资收到的现金 | F67: =SUM(F68:F71) -> 0
C68: ＝ 交易性金融资产(贷方发生额) | D68: =SUMIF(科目余额表[科目名称],"交易性金融资产",科目余额表[本期贷方]) -> 0 | E68: 对方科目是交易性金融资产 | F68: =SUMIF(现金流数据聚合!D:D,E68,现金流数据聚合!B:B) -> 0
C69: ＋ 长期股权投资(贷方发生额) | D69: =SUMIF(科目余额表[科目名称],"长期股权投资",科目余额表[本期贷方]) -> 0 | E69: 对方科目是长期股权投资 | F69: =SUMIF(现金流数据聚合!D:D,E69,现金流数据聚合!B:B) -> 0
C70: ＋ 长期债权投资(债券投资面值贷方发生额) | D70: =SUMIF(科目余额表[科目名称],"长期债权投资",科目余额表[本期贷方]) -> 0 | E70: 对方科目是长期债权投资 | F70: =SUMIF(现金流数据聚合!D:D,E70,现金流数据聚合!B:B) -> 0
C71: ＋ 长期债权投资(其他债权投金贷方发生额)
A72: 取得投资收益收到的现金 | C72: 取得投资收益收到的现金 | D72: =SUM(D73:D76) -> 0 | E72: 取得投资收益收到的现金 | F72: =SUM(F73:F76) -> 0
C73: ＝ 投资收益(股利或利润) | D73: =试算平衡表!D71 -> 0 | E73: 对方科目是股利收益相关 | F73: =SUMIF(现金流数据聚合!D:D,E73,现金流数据聚合!B:B)-SUMIF(现金流数据聚合!D:D,E73,现金流数据聚合!C:C) -> 0
C74: ＋ 应收股利 | E74: 对方科目是利息收益相关 | F74: =SUMIF(现金流数据聚合!D:D,E74,现金流数据聚合!B:B)-SUMIF(现金流数据聚合!D:D,E74,现金流数据聚合!C:C) -> 0
C75: ＋ 长期股权投资按权益法分享的利润
C76: ＋ 投资收益(债券利息收入)
A77: 处置固定资产、无形资产和其他长期资产收回的现金净额 | C77: 处置固定资产、无形资产和其他长期资产收回的现金净额 | D77: =SUM(D78:D80) -> 0 | E77: 处置固定资产、无形资产和其他长期资产收回的现金净额 | F77: =SUM(F78:F80) -> 0
C78: ＝ 处置固定资产收回的现金净额 | D78: =SUMIF(科目余额表[科目名称],"固定资产",科目余额表[本期贷方]) -> 0 | E78: 对方科目是固定资产 | F78: =SUMIF(现金流数据聚合!D:D,E78,现金流数据聚合!B:B) -> 0
C79: ＋ 处置无形资产收回的现金净额 | D79: =SUMIF(科目余额表[科目名称],"无形资产",科目余额表[本期贷方]) -> 0 | E79: 对方科目是无形资产 | F79: =SUMIF(现金流数据聚合!D:D,E79,现金流数据聚合!B:B) -> 0
C80: ＋ 处置其他长期资产收回的现金净额 | E80: 对方科目是其他长期资产
A81: 处置子公司及其他营业单位收到的现金净额 | C81: 处置子公司及其他营业单位收到的现金净额 | E81: 处置子公司及其他营业单位收到的现金净额
A82: 收到其他与投资活动有关的现金 | C82: 收到其他与投资活动有关的现金 | E82: 收到其他与投资活动有关的现金
A83: 投资活动现金流入小计 | B83: =SUM(B67,B72,B77,B81:B82) -> 0 | C83: 投资活动现金流入小计 | D83: =D67+D72+D77+D81+D82 -> 0 | E83: 投资活动现金流入小计 | F83: =F67+F72+F77+F81+F82 -> 0
A84: 购建固定资产、无形资产和其他长期资产支付的现金 | C84: 购建固定资产、无形资产和其他长期资产支付的现金 | D84: =SUM(D85:D88) -> 350000 | E84: 购建固定资产、无形资产和其他长期资产支付的现金 | F84: =SUM(F85:F88) -> 350000
C85: ＝ 固定资产 | D85: =SUMIF(科目余额表[科目名称],"固定资产",科目余额表[本期借方]) -> 350000 | E85: 对方科目是固定资产 | F85: =SUMIF(现金流数据聚合!D:D,E85,现金流数据聚合!C:C) -> 350000
C86: ＋ 在建工程 | D86: =SUMIF(科目余额表[科目名称],"在建工程",科目余额表[本期借方]) -> 0 | E86: 对方科目是无形资产 | F86: =SUMIF(现金流数据聚合!D:D,E86,现金流数据聚合!C:C) -> 0
C87: ＋ 无形资产 | D87: =SUMIF(科目余额表[科目名称],"无形资产",科目余额表[本期借方]) -> 0 | E87: 对方科目是其他长期资产 | F87: =SUMIF(现金流数据聚合!D:D,E87,现金流数据聚合!C:C) -> 0
C88: ＋ 其他长期资产
A89: 投资支付的现金 | C89: 投资支付的现金 | D89: =SUM(D90:D93) -> 0 | E89: 投资支付的现金 | F89: =SUM(F90:F93) -> 0
C90: ＝ 根据长期投资等账户分析确定 | E90: 对方科目是交易性金融资产 | F90: =SUMIF(现金流数据聚合!D:D,E90,现金流数据聚合!C:C) -> 0
E91: 对方科目是长期股权投资 | F91: =SUMIF(现金流数据聚合!D:D,E91,现金流数据聚合!C:C) -> 0
E92: 对方科目是长期债权投资 | F92: =SUMIF(现金流数据聚合!D:D,E92,现金流数据聚合!C:C) -> 0
A94: 取得子公司及其他营业单位支付的现金净额 | C94: 取得子公司及其他营业单位支付的现金净额 | E94: 取得子公司及其他营业单位支付的现金净额
A95: 支付其他与投资活动有关的现金 | C95: 支付其他与投资活动有关的现金 | E95: 支付其他与投资活动有关的现金
A96: 投资活动现金流出小计 | B96: =SUM(B84,B89,B94:B95) -> 0 | C96: 投资活动现金流出小计 | D96: =D84+D89+D94+D95 -> 350000 | E96: 投资活动现金流出小计 | F96: =F84+F89+F94+F95 -> 350000
A97: 投资活动产生的现金流量净额 | B97: =B83-B96 -> 0 | C97: 投资活动产生的现金流量净额 | D97: =D83-D96 -> -350000 | E97: 投资活动产生的现金流量净额 | F97: =F83-F96 -> -350000
A98: 三、筹资活动产生的现金流量：
A99: 吸收投资收到的现金 | C99: 吸收投资收到的现金 | D99: =SUM(D100:D103) -> 0 | E99: 吸收投资收到的现金 | F99: =SUM(F100:F103) -> 0
C100: ＝ 实收资本 | D100: =SUMIF(科目余额表[科目名称],"实收资本",科目余额表[本期贷方]) -> 0 | E100: 对方科目是实收资本 | F100: =SUMIF(现金流数据聚合!D:D,E100,现金流数据聚合!B:B) -> 0
C101: ＋ 股本溢价 | D101: =SUMIF(科目余额表[科目名称],"股本溢价",科目余额表[本期贷方]) -> 0 | E101: 对方科目是股本溢价 | F101: =SUMIF(现金流数据聚合!D:D,E101,现金流数据聚合!B:B) -> 0
...

Sheet 现金流数据聚合
A1: 现金流对方科目 | B1: 借方金额 | C1: 贷方金额 | D1: 直接法归集
A2: {=_xlfn._xlws.SORT(_xlfn.UNIQUE(序时账[现金流分类]))} -> 办公费 | B2: =SUMIF(序时账[现金流分类],A2,序时账[借方金额]) -> 0 | C2: =SUMIF(序时账[现金流分类],A2,序时账[贷方金额]) -> 275 | D2: 对方科目是管理费用
A3: 轿车 | B3: =SUMIF(序时账[现金流分类],A3,序时账[借方金额]) -> 0 | C3: =SUMIF(序时账[现金流分类],A3,序时账[贷方金额]) -> 350000 | D3: 对方科目是固定资产
A4: 利息收入 | B4: =SUMIF(序时账[现金流分类],A4,序时账[借方金额]) -> 8749.38 | C4: =SUMIF(序时账[现金流分类],A4,序时账[贷方金额]) -> 0 | D4: 对方科目是利息收入
A5: 其他应付款-亥 | B5: =SUMIF(序时账[现金流分类],A5,序时账[借方金额]) -> 0 | C5: =SUMIF(序时账[现金流分类],A5,序时账[贷方金额]) -> 7000 | D5: 对方科目是其他应付款
A6: 其他应收款-李四 | B6: =SUMIF(序时账[现金流分类],A6,序时账[借方金额]) -> 10000 | C6: =SUMIF(序时账[现金流分类],A6,序时账[贷方金额]) -> 0 | D6: 对方科目是其他应收款
A7: 企业所得税 | B7: =SUMIF(序时账[现金流分类],A7,序时账[借方金额]) -> 0 | C7: =SUMIF(序时账[现金流分类],A7,序时账[贷方金额]) -> 111385.32 | D7: 对方科目是个所税以外的应交税费类
A8: 未交增值税 | B8: =SUMIF(序时账[现金流分类],A8,序时账[借方金额]) -> 0 | C8: =SUMIF(序时账[现金流分类],A8,序时账[贷方金额]) -> 624791.42 | D8: 对方科目是个所税以外的应交税费类
A9: 银行手续费 | B9: =SUMIF(序时账[现金流分类],A9,序时账[借方金额]) -> 0 | C9: =SUMIF(序时账[现金流分类],A9,序时账[贷方金额]) -> 200 | D9: 对方科目是银行手续费
A10: 应付账款-N有限公司 | B10: =SUMIF(序时账[现金流分类],A10,序时账[借方金额]) -> 0 | C10: =SUMIF(序时账[现金流分类],A10,序时账[贷方金额]) -> 720000 | D10: 对方科目是应付账款
A11: 应付账款-T有限公司 | B11: =SUMIF(序时账[现金流分类],A11,序时账[借方金额]) -> 1012000 | C11: =SUMIF(序时账[现金流分类],A11,序时账[贷方金额]) -> 0 | D11: 对方科目是应付账款
A12: 应付账款-V有限公司 | B12: =SUMIF(序时账[现金流分类],A12,序时账[借方金额]) -> 799000 | C12: =SUMIF(序时账[现金流分类],A12,序时账[贷方金额]) -> 0 | D12: 对方科目是应付账款
A13: 应付账款-W有限公司 | B13: =SUMIF(序时账[现金流分类],A13,序时账[借方金额]) -> 1003000 | C13: =SUMIF(序时账[现金流分类],A13,序时账[贷方金额]) -> 640000 | D13: 对方科目是应付账款
A14: 应付账款-X有限公司 | B14: =SUMIF(序时账[现金流分类],A14,序时账[借方金额]) -> 850000 | C14: =SUMIF(序时账[现金流分类],A14,序时账[贷方金额]) -> 0 | D14: 对方科目是应付账款
... A30: 预付账款-Q有限公司 | B30: =SUMIF(序时账[现金流分类],A30,序时账[借方金额]) -> 908000 | C30: =SUMIF(序时账[现金流分类],A30,序时账[贷方金额]) -> 0 | D30: 对方科目是预付账款
A31: 0 | B31: =SUMIF(序时账[现金流分类],A31,序时账[借方金额]) -> 0 | C31: =SUMIF(序时账[现金流分类],A31,序时账[贷方金额]) -> 0
B32: =SUMIF(序时账[现金流分类],A32,序时账[借方金额]) -> 0 | C32: =SUMIF(序时账[现金流分类],A32,序时账[贷方金额]) -> 0
B33: =SUMIF(序时账[现金流分类],A33,序时账[借方金额]) -> 0 | C33: =SUMIF(序时账[现金流分类],A33,序时账[贷方金额]) -> 0
B34: =SUMIF(序时账[现金流分类],A34,序时账[借方金额]) -> 0 | C34: =SUMIF(序时账[现金流分类],A34,序时账[贷方金额]) -> 0
B35: =SUMIF(序时账[现金流分类],A35,序时账[借方金额]) -> 0 | C35: =SUMIF(序时账[现金流分类],A35,序时账[贷方金额]) -> 0
B36: =SUMIF(序时账[现金流分类],A36,序时账[借方金额]) -> 0 | C36: =SUMIF(序时账[现金流分类],A36,序时账[贷方金额]) -> 0
B37: =SUMIF(序时账[现金流分类],A37,序时账[借方金额]) -> 0 | C37: =SUMIF(序时账[现金流分类],A37,序时账[贷方金额]) -> 0
B38: =SUMIF(序时账[现金流分类],A38,序时账[借方金额]) -> 0 | C38: =SUMIF(序时账[现金流分类],A38,序时账[贷方金额]) -> 0
B39: =SUMIF(序时账[现金流分类],A39,序时账[借方金额]) -> 0 | C39: =SUMIF(序时账[现金流分类],A39,序时账[贷方金额]) -> 0
B40: =SUMIF(序时账[现金流分类],A40,序时账[借方金额]) -> 0 | C40: =SUMIF(序时账[现金流分类],A40,序时账[贷方金额]) -> 0
B41: =SUMIF(序时账[现金流分类],A41,序时账[借方金额]) -> 0 | C41: =SUMIF(序时账[现金流分类],A41,序时账[贷方金额]) -> 0
B42: =SUMIF(序时账[现金流分类],A42,序时账[借方金额]) -> 0 | C42: =SUMIF(序时账[现金流分类],A42,序时账[贷方金额]) -> 0
B43: =SUMIF(序时账[现金流分类],A43,序时账[借方金额]) -> 0 | C43: =SUMIF(序时账[现金流分类],A43,序时账[贷方金额]) -> 0
... B251: =SUMIF(序时账[现金流分类],A251,序时账[借方金额]) -> 0 | C251: =SUMIF(序时账[现金流分类],A251,序时账[贷方金额]) -> 0

Sheet 凭证抽查
A1: 参数 | B1: 值 | C1: 序列清单 | D1: 覆盖检测
A2: 报表项目 | B2: 银行存款 | C2: {=ROUNDUP(_xlfn.SEQUENCE(B3,1,B6,B5),0)} -> 4 | D2: 项目 | E2: 本期借方发生额 | F2: 本期贷方发生额
A3: 抽查笔数 | B3: 5 | C3: 14 | D3: 科目余额表 | E3: =SUMIF(科目余额表!L:L,B2,科目余额表!E:E) -> 18485749 | F3: =SUMIF(科目余额表!L:L,B2,科目余额表!F:F) -> 5033601.7
A4: 凭证笔数 | B4: =COUNTA(序时账采集!B:B)-1 -> 49 | C4: 24 | D4: 序时账 | E4: =SUMIF(序时账!I:I,B2,序时账!G:G) -> 18485749 | F4: =SUMIF(序时账!I:I,B2,序时账!H:H) -> 5033601.7
A5: 间距 | B5: =B4/B3 -> 9.8 | C5: 34 | D5: 差额 | E5: =E3-E4 -> 0 | F5: =F3-F4 -> 0
A6: 随机起点 | B6: =IF(B2<>"",RAND()*B5,0) -> 3.9227031 | C6: 44
A8: 抽查表格式一
A9: 会 计 凭 证 | C9: 摘 要 | D9: 借 记 | F9: 贷 记
A10: 日期 | B10: 编号 | D10: 会计科目 | E10: 金 额 | F10: 会计科目 | G10: 金 额
A11: =_xlfn.XLOOKUP(C2,序时账采集!A:A,序时账采集!B:B) -> 45687 | B11: =_xlfn.XLOOKUP(C2,序时账采集!A:A,序时账采集!C:C) -> 10 | C11: =_xlfn.XLOOKUP(C2,序时账采集!A:A,序时账采集!F:F) -> 缴纳企业所得税 | D11: =IF(OR(I11=0,I11=""),_xlfn.XLOOKUP(C2,序时账采集!A:A,序时账采集!J:J),_xlfn.XLOOKUP(C2,序时账采集!A:A,序时账采集!E:E)) -> 企业所得税 | E11: =IF(OR(I11=0,I11=""),J11,I11) -> 111385.32 | F11: =IF(OR(J11=0,J11=""),_xlfn.XLOOKUP(C2,序时账采集!A:A,序时账采集!J:J),_xlfn.XLOOKUP(C2,序时账采集!A:A,序时账采集!E:E)) -> ABC银行账户 | G11: =IF(OR(J11=0,J11=""),I11,J11) -> 111385.32 | I11: =_xlfn.XLOOKUP(C2,序时账采集!A:A,序时账采集!G:G) -> 0 | J11: =_xlfn.XLOOKUP(C2,序时账采集!A:A,序时账采集!H:H) -> 111385.32
A12: =_xlfn.XLOOKUP(C3,序时账采集!A:A,序时账采集!B:B) -> 45767 | B12: =_xlfn.XLOOKUP(C3,序时账采集!A:A,序时账采集!C:C) -> 4 | C12: =_xlfn.XLOOKUP(C3,序时账采集!A:A,序时账采集!F:F) -> 收货款 | D12: =IF(OR(I12=0,I12=""),_xlfn.XLOOKUP(C3,序时账采集!A:A,序时账采集!J:J),_xlfn.XLOOKUP(C3,序时账采集!A:A,序时账采集!E:E)) -> ABC银行账户 | E12: =IF(OR(I12=0,I12=""),J12,I12) -> 1029000 | F12: =IF(OR(J12=0,J12=""),_xlfn.XLOOKUP(C3,序时账采集!A:A,序时账采集!J:J),_xlfn.XLOOKUP(C3,序时账采集!A:A,序时账采集!E:E)) -> 应收账款-B有限公司 | G12: =IF(OR(J12=0,J12=""),I12,J12) -> 1029000 | I12: =_xlfn.XLOOKUP(C3,序时账采集!A:A,序时账采集!G:G) -> 1029000 | J12: =_xlfn.XLOOKUP(C3,序时账采集!A:A,序时账采集!H:H) -> 0
A13: =_xlfn.XLOOKUP(C4,序时账采集!A:A,序时账采集!B:B) -> 45838 | B13: =_xlfn.XLOOKUP(C4,序时账采集!A:A,序时账采集!C:C) -> 8 | C13: =_xlfn.XLOOKUP(C4,序时账采集!A:A,序时账采集!F:F) -> 存款利息 | D13: =IF(OR(I13=0,I13=""),_xlfn.XLOOKUP(C4,序时账采集!A:A,序时账采集!J:J),_xlfn.XLOOKUP(C4,序时账采集!A:A,序时账采集!E:E)) -> EFG银行账户 | E13: =IF(OR(I13=0,I13=""),J13,I13) -> 120.12 | F13: =IF(OR(J13=0,J13=""),_xlfn.XLOOKUP(C4,序时账采集!A:A,序时账采集!J:J),_xlfn.XLOOKUP(C4,序时账采集!A:A,序时账采集!E:E)) | G13: =IF(OR(J13=0,J13=""),I13,J13) -> 120.12 | I13: =_xlfn.XLOOKUP(C4,序时账采集!A:A,序时账采集!G:G) -> 120.12 | J13: =_xlfn.XLOOKUP(C4,序时账采集!A:A,序时账采集!H:H) -> 0
A14: =_xlfn.XLOOKUP(C5,序时账采集!A:A,序时账采集!B:B) -> 45930 | B14: =_xlfn.XLOOKUP(C5,序时账采集!A:A,序时账采集!C:C) -> 10 | C14: =_xlfn.XLOOKUP(C5,序时账采集!A:A,序时账采集!F:F) -> 存款利息 | D14: =IF(OR(I14=0,I14=""),_xlfn.XLOOKUP(C5,序时账采集!A:A,序时账采集!J:J),_xlfn.XLOOKUP(C5,序时账采集!A:A,序时账采集!E:E)) -> ABC银行账户 | E14: =IF(OR(I14=0,I14=""),J14,I14) -> 1958.06 | F14: =IF(OR(J14=0,J14=""),_xlfn.XLOOKUP(C5,序时账采集!A:A,序时账采集!J:J),_xlfn.XLOOKUP(C5,序时账采集!A:A,序时账采集!E:E)) | G14: =IF(OR(J14=0,J14=""),I14,J14) -> 1958.06 | I14: =_xlfn.XLOOKUP(C5,序时账采集!A:A,序时账采集!G:G) -> 1958.06 | J14: =_xlfn.XLOOKUP(C5,序时账采集!A:A,序时账采集!H:H) -> 0
A15: =_xlfn.XLOOKUP(C6,序时账采集!A:A,序时账采集!B:B) -> 46011 | B15: =_xlfn.XLOOKUP(C6,序时账采集!A:A,序时账采集!C:C) -> 4 | C15: =_xlfn.XLOOKUP(C6,序时账采集!A:A,序时账采集!F:F) -> 收货款 | D15: =IF(OR(I15=0,I15=""),_xlfn.XLOOKUP(C6,序时账采集!A:A,序时账采集!J:J),_xlfn.XLOOKUP(C6,序时账采集!A:A,序时账采集!E:E)) -> ABC银行账户 | E15: =IF(OR(I15=0,I15=""),J15,I15) -> 1001000 | F15: =IF(OR(J15=0,J15=""),_xlfn.XLOOKUP(C6,序时账采集!A:A,序时账采集!J:J),_xlfn.XLOOKUP(C6,序时账采集!A:A,序时账采集!E:E)) -> 应收账款-E有限公司 | G15: =IF(OR(J15=0,J15=""),I15,J15) -> 1001000 | I15: =_xlfn.XLOOKUP(C6,序时账采集!A:A,序时账采集!G:G) -> 1001000 | J15: =_xlfn.XLOOKUP(C6,序时账采集!A:A,序时账采集!H:H) -> 0
A17: 抽查表格式二
A18: 会 计 凭 证 | C18: 摘 要 | D18: 借 记 | F18: 贷 记
A19: 日期 | B19: 编号 | D19: 会计科目 | E19: 金 额 | F19: 会计科目 | G19: 金 额
A20: =_xlfn.XLOOKUP(C2,序时账采集!A:A,序时账采集!B:B) -> 45687 | B20: =_xlfn.XLOOKUP(C2,序时账采集!A:A,序时账采集!C:C) -> 10 | C20: =_xlfn.XLOOKUP(C2,序时账采集!A:A,序时账采集!F:F) -> 缴纳企业所得税 | D20: =IF(OR(I20=0,I20=""),_xlfn.XLOOKUP(C2,序时账采集!A:A,序时账采集!J:J),_xlfn.XLOOKUP(C2,序时账采集!A:A,序时账采集!E:E)) -> 企业所得税 | E20: =IF(OR(I20=0,I20=""),J20,I20) -> 111385.32 | F20: =IF(OR(J20=0,J20=""),_xlfn.XLOOKUP(C2,序时账采集!A:A,序时账采集!J:J),_xlfn.XLOOKUP(C2,序时账采集!A:A,序时账采集!E:E)) -> ABC银行账户 | G20: =IF(OR(J20=0,J20=""),I20,J20) -> 111385.32 | I20: =_xlfn.XLOOKUP(C2,序时账采集!A:A,序时账采集!G:G) -> 0 | J20: =_xlfn.XLOOKUP(C2,序时账采集!A:A,序时账采集!H:H) -> 111385.32
A22: =_xlfn.XLOOKUP(C3,序时账采集!A:A,序时账采集!B:B) -> 45767 | B22: =_xlfn.XLOOKUP(C3,序时账采集!A:A,序时账采集!C:C) -> 4 | C22: =_xlfn.XLOOKUP(C3,序时账采集!A:A,序时账采集!F:F) -> 收货款 | D22: =IF(OR(I22=0,I22=""),_xlfn.XLOOKUP(C3,序时账采集!A:A,序时账采集!J:J),_xlfn.XLOOKUP(C3,序时账采集!A:A,序时账采集!E:E)) -> ABC银行账户 | E22: =IF(OR(I22=0,I22=""),J22,I22) -> 1029000 | F22: =IF(OR(J22=0,J22=""),_xlfn.XLOOKUP(C3,序时账采集!A:A,序时账采集!J:J),_xlfn.XLOOKUP(C3,序时账采集!A:A,序时账采集!E:E)) -> 应收账款-B有限公司 | G22: =IF(OR(J22=0,J22=""),I22,J22) -> 1029000 | I22: =_xlfn.XLOOKUP(C3,序时账采集!A:A,序时账采集!G:G) -> 1029000 | J22: =_xlfn.XLOOKUP(C3,序时账采集!A:A,序时账采集!H:H) -> 0
A24: =_xlfn.XLOOKUP(C4,序时账采集!A:A,序时账采集!B:B) -> 45838 | B24: =_xlfn.XLOOKUP(C4,序时账采集!A:A,序时账采集!C:C) -> 8 | C24: =_xlfn.XLOOKUP(C4,序时账采集!A:A,序时账采集!F:F) -> 存款利息 | D24: =IF(OR(I24=0,I24=""),_xlfn.XLOOKUP(C4,序时账采集!A:A,序时账采集!J:J),_xlfn.XLOOKUP(C4,序时账采集!A:A,序时账采集!E:E)) -> EFG银行账户 | E24: =IF(OR(I24=0,I24=""),J24,I24) -> 120.12 | F24: =IF(OR(J24=0,J24=""),_xlfn.XLOOKUP(C4,序时账采集!A:A,序时账采集!J:J),_xlfn.XLOOKUP(C4,序时账采集!A:A,序时账采集!E:E)) | G24: =IF(OR(J24=0,J24=""),I24,J24) -> 120.12 | I24: =_xlfn.XLOOKUP(C4,序时账采集!A:A,序时账采集!G:G) -> 120.12 | J24: =_xlfn.XLOOKUP(C4,序时账采集!A:A,序时账采集!H:H) -> 0
A26: =_xlfn.XLOOKUP(C5,序时账采集!A:A,序时账采集!B:B) -> 45930 | B26: =_xlfn.XLOOKUP(C5,序时账采集!A:A,序时账采集!C:C) -> 10 | C26: =_xlfn.XLOOKUP(C5,序时账采集!A:A,序时账采集!F:F) -> 存款利息 | D26: =IF(OR(I26=0,I26=""),_xlfn.XLOOKUP(C5,序时账采集!A:A,序时账采集!J:J),_xlfn.XLOOKUP(C5,序时账采集!A:A,序时账采集!E:E)) -> ABC银行账户 | E26: =IF(OR(I26=0,I26=""),J26,I26) -> 1958.06 | F26: =IF(OR(J26=0,J26=""),_xlfn.XLOOKUP(C5,序时账采集!A:A,序时账采集!J:J),_xlfn.XLOOKUP(C5,序时账采集!A:A,序时账采集!E:E)) | G26: =IF(OR(J26=0,J26=""),I26,J26) -> 1958.06 | I26: =_xlfn.XLOOKUP(C5,序时账采集!A:A,序时账采集!G:G) -> 1958.06 | J26: =_xlfn.XLOOKUP(C5,序时账采集!A:A,序时账采集!H:H) -> 0
A28: =_xlfn.XLOOKUP(C6,序时账采集!A:A,序时账采集!B:B) -> 46011 | B28: =_xlfn.XLOOKUP(C6,序时账采集!A:A,序时账采集!C:C) -> 4 | C28: =_xlfn.XLOOKUP(C6,序时账采集!A:A,序时账采集!F:F) -> 收货款 | D28: =IF(OR(I28=0,I28=""),_xlfn.XLOOKUP(C6,序时账采集!A:A,序时账采集!J:J),_xlfn.XLOOKUP(C6,序时账采集!A:A,序时账采集!E:E)) -> ABC银行账户 | E28: =IF(OR(I28=0,I28=""),J28,I28) -> 1001000 | F28: =IF(OR(J28=0,J28=""),_xlfn.XLOOKUP(C6,序时账采集!A:A,序时账采集!J:J),_xlfn.XLOOKUP(C6,序时账采集!A:A,序时账采集!E:E)) -> 应收账款-E有限公司 | G28: =IF(OR(J28=0,J28=""),I28,J28) -> 1001000 | I28: =_xlfn.XLOOKUP(C6,序时账采集!A:A,序时账采集!G:G) -> 1001000 | J28: =_xlfn.XLOOKUP(C6,序时账采集!A:A,序时账采集!H:H) -> 0
A31: 抽查表格式三
A32: 日期 | B32: 凭证 | C32: 业务内容 | D32: 金额 | F32: 对应科目 | G32: 核对内容 | N32: 备注
B33: 编号 | D33: 借方 | E33: 贷方 | G33: 1 | H33: 2 | I33: 3 | J33: 4 | K33: 5 | L33: 6 | M33: 7
A34: =_xlfn.XLOOKUP(C2,序时账采集!A:A,序时账采集!B:B) -> 45687 | B34: =_xlfn.XLOOKUP(C2,序时账采集!A:A,序时账采集!C:C) -> 10 | C34: =_xlfn.XLOOKUP(C2,序时账采集!A:A,序时账采集!F:F) -> 缴纳企业所得税 | D34: =_xlfn.XLOOKUP(C2,序时账采集!A:A,序时账采集!G:G) -> 0 | E34: =_xlfn.XLOOKUP(C2,序时账采集!A:A,序时账采集!H:H) -> 111385.32 | F34: =_xlfn.XLOOKUP(C2,序时账采集!A:A,序时账采集!J:J) -> 企业所得税 | G34: √ | H34: √ | I34: √ | J34: √ | K34: √ | L34: √ | M34: √
A35: =_xlfn.XLOOKUP(C3,序时账采集!A:A,序时账采集!B:B) -> 45767 | B35: =_xlfn.XLOOKUP(C3,序时账采集!A:A,序时账采集!C:C) -> 4 | C35: =_xlfn.XLOOKUP(C3,序时账采集!A:A,序时账采集!F:F) -> 收货款 | D35: =_xlfn.XLOOKUP(C3,序时账采集!A:A,序时账采集!G:G) -> 1029000 | E35: =_xlfn.XLOOKUP(C3,序时账采集!A:A,序时账采集!H:H) -> 0 | F35: =_xlfn.XLOOKUP(C3,序时账采集!A:A,序时账采集!J:J) -> 应收账款-B有限公司 | G35: √ | H35: √ | I35: √ | J35: √ | K35: √ | L35: √ | M35: √
A36: =_xlfn.XLOOKUP(C4,序时账采集!A:A,序时账采集!B:B) -> 45838 | B36: =_xlfn.XLOOKUP(C4,序时账采集!A:A,序时账采集!C:C) -> 8 | C36: =_xlfn.XLOOKUP(C4,序时账采集!A:A,序时账采集!F:F) -> 存款利息 | D36: =_xlfn.XLOOKUP(C4,序时账采集!A:A,序时账采集!G:G) -> 120.12 | E36: =_xlfn.XLOOKUP(C4,序时账采集!A:A,序时账采集!H:H) -> 0 | F36: =_xlfn.XLOOKUP(C4,序时账采集!A:A,序时账采集!J:J) | G36: √ | H36: √ | I36: √ | J36: √ | K36: √ | L36: √ | M36: √
A37: =_xlfn.XLOOKUP(C5,序时账采集!A:A,序时账采集!B:B) -> 45930 | B37: =_xlfn.XLOOKUP(C5,序时账采集!A:A,序时账采集!C:C) -> 10 | C37: =_xlfn.XLOOKUP(C5,序时账采集!A:A,序时账采集!F:F) -> 存款利息 | D37: =_xlfn.XLOOKUP(C5,序时账采集!A:A,序时账采集!G:G) -> 1958.06 | E37: =_xlfn.XLOOKUP(C5,序时账采集!A:A,序时账采集!H:H) -> 0 | F37: =_xlfn.XLOOKUP(C5,序时账采集!A:A,序时账采集!J:J) | G37: √ | H37: √ | I37: √ | J37: √ | K37: √ | L37: √ | M37: √
A38: =_xlfn.XLOOKUP(C6,序时账采集!A:A,序时账采集!B:B) -> 46011 | B38: =_xlfn.XLOOKUP(C6,序时账采集!A:A,序时账采集!C:C) -> 4 | C38: =_xlfn.XLOOKUP(C6,序时账采集!A:A,序时账采集!F:F) -> 收货款 | D38: =_xlfn.XLOOKUP(C6,序时账采集!A:A,序时账采集!G:G) -> 1001000 | E38: =_xlfn.XLOOKUP(C6,序时账采集!A:A,序时账采集!H:H) -> 0 | F38: =_xlfn.XLOOKUP(C6,序时账采集!A:A,序时账采集!J:J) -> 应收账款-E有限公司 | G38: √ | H38: √ | I38: √ | J38: √ | K38: √ | L38: √ | M38: √
A40: 抽查表格式四
A41: 日期 | B41: 凭证 | C41: 业务内容 | D41: 金额 | E41: 对应科目 | F41: 核对内容 | M41: 备注
B42: 编号 | F42: 1 | G42: 2 | H42: 3 | I42: 4 | J42: 5 | K42: 6 | L42: 7
A43: =_xlfn.XLOOKUP(C2,序时账采集!A:A,序时账采集!B:B) -> 45687 | B43: =_xlfn.XLOOKUP(C2,序时账采集!A:A,序时账采集!C:C) -> 10 | C43: =_xlfn.XLOOKUP(C2,序时账采集!A:A,序时账采集!F:F) -> 缴纳企业所得税 | D43: =_xlfn.XLOOKUP(C2,序时账采集!A:A,序时账采集!G:G)+_xlfn.XLOOKUP(C2,序时账采集!A:A,序时账采集!H:H) -> 111385.32 | E43: =_xlfn.XLOOKUP(C2,序时账采集!A:A,序时账采集!J:J) -> 企业所得税 | F43: √ | G43: √ | H43: √ | I43: √ | J43: √ | K43: √ | L43: √
A44: =_xlfn.XLOOKUP(C3,序时账采集!A:A,序时账采集!B:B) -> 45767 | B44: =_xlfn.XLOOKUP(C3,序时账采集!A:A,序时账采集!C:C) -> 4 | C44: =_xlfn.XLOOKUP(C3,序时账采集!A:A,序时账采集!F:F) -> 收货款 | D44: =_xlfn.XLOOKUP(C3,序时账采集!A:A,序时账采集!G:G)+_xlfn.XLOOKUP(C3,序时账采集!A:A,序时账采集!H:H) -> 1029000 | E44: =_xlfn.XLOOKUP(C3,序时账采集!A:A,序时账采集!J:J) -> 应收账款-B有限公司 | F44: √ | G44: √ | H44: √ | I44: √ | J44: √ | K44: √ | L44: √
A45: =_xlfn.XLOOKUP(C4,序时账采集!A:A,序时账采集!B:B) -> 45838 | B45: =_xlfn.XLOOKUP(C4,序时账采集!A:A,序时账采集!C:C) -> 8 | C45: =_xlfn.XLOOKUP(C4,序时账采集!A:A,序时账采集!F:F) -> 存款利息 | D45: =_xlfn.XLOOKUP(C4,序时账采集!A:A,序时账采集!G:G)+_xlfn.XLOOKUP(C4,序时账采集!A:A,序时账采集!H:H) -> 120.12 | E45: =_xlfn.XLOOKUP(C4,序时账采集!A:A,序时账采集!J:J) | F45: √ | G45: √ | H45: √ | I45: √ | J45: √ | K45: √ | L45: √
A46: =_xlfn.XLOOKUP(C5,序时账采集!A:A,序时账采集!B:B) -> 45930 | B46: =_xlfn.XLOOKUP(C5,序时账采集!A:A,序时账采集!C:C) -> 10 | C46: =_xlfn.XLOOKUP(C5,序时账采集!A:A,序时账采集!F:F) -> 存款利息 | D46: =_xlfn.XLOOKUP(C5,序时账采集!A:A,序时账采集!G:G)+_xlfn.XLOOKUP(C5,序时账采集!A:A,序时账采集!H:H) -> 1958.06 | E46: =_xlfn.XLOOKUP(C5,序时账采集!A:A,序时账采集!J:J) | F46: √ | G46: √ | H46: √ | I46: √ | J46: √ | K46: √ | L46: √
A47: =_xlfn.XLOOKUP(C6,序时账采集!A:A,序时账采集!B:B) -> 46011 | B47: =_xlfn.XLOOKUP(C6,序时账采集!A:A,序时账采集!C:C) -> 4 | C47: =_xlfn.XLOOKUP(C6,序时账采集!A:A,序时账采集!F:F) -> 收货款 | D47: =_xlfn.XLOOKUP(C6,序时账采集!A:A,序时账采集!H:H) -> 0 | E47: =_xlfn.XLOOKUP(C6,序时账采集!A:A,序时账采集!J:J) -> 应收账款-E有限公司 | F47: √ | G47: √ | H47: √ | I47: √ | J47: √ | K47: √ | L47: √

Sheet 往来项目数据聚合
A1: 应收账款 | K1: 预付款项 | U1: 合同资产 | AE1: 其他应收款 | AO1: 应付账款 | AY1: 预收款项 | BI1: 合同负债 | BS1: 其他应付款 | CD1: 应收账款 | CF1: 预付款项 | CH1: 合同资产 | CJ1: 其他应收款 | CL1: 应付账款 | CN1: 预收款项 | CP1: 合同负债 | CR1: 其他应付款
A2: 科目编码 | B2: 科目名称 | C2: 期初借方 | D2: 期初贷方 | E2: 本期借方 | F2: 本期贷方 | G2: 期末借方 | H2: 期末贷方 | I2: 1年以内 | J2: 1年以上 | K2: 科目编码 | L2: 科目名称 | M2: 期初借方 | N2: 期初贷方 | O2: 本期借方 | P2: 本期贷方 | Q2: 期末借方 | R2: 期末贷方 | S2: 1年以内 | T2: 1年以上 | U2: 科目编码 | V2: 科目名称 | W2: 期初借方 | X2: 期初贷方 | Y2: 本期借方 | Z2: 本期贷方 | AA2: 期末借方 | AB2: 期末贷方 | AC2: 1年以内 | AD2: 1年以上 | AE2: 科目编码 | AF2: 科目名称 | AG2: 期初借方 | AH2: 期初贷方 | AI2: 本期借方 | AJ2: 本期贷方 | AK2: 期末借方 | AL2: 期末贷方 | AM2: 1年以内 | AN2: 1年以上 | AO2: 科目编码 | AP2: 科目名称 | AQ2: 期初借方 | AR2: 期初贷方 | AS2: 本期借方 | AT2: 本期贷方 | AU2: 期末借方 | AV2: 期末贷方 | AW2: 1年以内 | AX2: 1年以上 | AY2: 科目编码 | AZ2: 科目名称 | BA2: 期初借方 | BB2: 期初贷方 | BC2: 本期借方 | BD2: 本期贷方 | BE2: 期末借方 | BF2: 期末贷方 | BG2: 1年以内 | BH2: 1年以上 | BI2: 科目编码 | BJ2: 科目名称 | BK2: 期初借方 | BL2: 期初贷方 | BM2: 本期借方 | BN2: 本期贷方 | BO2: 期末借方 | BP2: 期末贷方 | BQ2: 1年以内 | BR2: 1年以上 | BS2: 科目编码 | BT2: 科目名称 | BU2: 期初借方 | BV2: 期初贷方 | BW2: 本期借方 | BX2: 本期贷方 | BY2: 期末借方 | BZ2: 期末贷方 | CA2: 1年以内 | CB2: 1年以上 | CD2: {=_xlfn.UNIQUE(B:B)} -> 0 | CF2: {=_xlfn.UNIQUE(L:L)} -> 0 | CH2: {=_xlfn.UNIQUE(V:V)} -> 0 | CJ2: {=_xlfn.UNIQUE(AF:AF)} -> 0 | CL2: {=_xlfn.UNIQUE(AP:AP)} -> 0 | CN2: {=_xlfn.UNIQUE(AZ:AZ)} -> 0 | CP2: {=_xlfn.UNIQUE(BJ:BJ)} -> 0 | CR2: {=_xlfn.UNIQUE(BT:BT)} -> 0
A3: {=_xlfn._xlws.FILTER(科目余额表[[科目编码]:[期末贷方]],科目余额表[已审报表项目]="应收账款")} -> 1122001 | B3: A有限公司 | C3: 552444.45 | D3: 0 | E3: 2395600 | F3: 2030000 | G3: 918044.45 | H3: 0 | I3: =IF(F3>=C3-D3,G3-H3,E3) -> 918044.45 | J3: =IF(F3<C3-D3,C3-D3-F3,0) -> 0 | K3: {=_xlfn._xlws.FILTER(科目余额表[[科目编码]:[期末贷方]],科目余额表[已审报表项目]="预付款项")} -> 1123004 | L3: N有限公司 | M3: 334588.9 | N3: 0 | O3: 0 | P3: 0 | Q3: 334588.9 | R3: 0 | S3: =IF(P3>=M3-N3,Q3-R3,O3) -> 0 | T3: =IF(P3<M3-N3,M3-N3-P3,0) -> 334588.9 | U3: {=_xlfn._xlws.FILTER(科目余额表[[科目编码]:[期末贷方]],科目余额表[已审报表项目]="合同资产")} -> #VALUE! | AC3: =IF(Z3>=W3-X3,AA3-AB3,Y3) -> 0 | AD3: =IF(Z3<W3-X3,W3-X3-Z3,0) -> 0 | AE3: {=_xlfn._xlws.FILTER(科目余额表[[科目编码]:[期末贷方]],科目余额表[已审报表项目]="其他应收款")} -> 1221001 | AF3: 张三 | AG3: 78922.34 | AH3: 0 | AI3: 0 | AJ3: 0 | AK3: 78922.34 | AL3: 0 | AM3: =IF(AJ3>=AG3-AH3,AK3-AL3,AI3) -> 0 | AN3: =IF(AJ3<AG3-AH3,AG3-AH3-AJ3,0) -> 78922.34 | AO3: {=_xlfn._xlws.FILTER(科目余额表[[科目编码]:[期末贷方]],科目余额表[已审报表项目]="应付账款")} -> 1123001 | AP3: K有限公司 | AQ3: 200199.49 | AR3: 0 | AS3: 0 | AT3: 568842 | AU3: -368642.51 | AV3: 0 | AW3: =IF(AS3>=AR3-AQ3,AV3-AU3,AT3) -> 368642.51 | AX3: =IF(AS3<AR3-AQ3,AR3-AQ3-AS3,0) -> 0 | AY3: {=_xlfn._xlws.FILTER(科目余额表[[科目编码]:[期末贷方]],科目余额表[已审报表项目]="预收款项")} -> #VALUE! | BG3: =IF(BC3>=BB3-BA3,BF3-BE3,BD3) -> 0 | BH3: =IF(BC3<BB3-BA3,BB3-BA3-BC3,0) -> 0 | BI3: {=_xlfn._xlws.FILTER(科目余额表[[科目编码]:[期末贷方]],科目余额表[已审报表项目]="合同负债")} -> #VALUE! | BQ3: =IF(BM3>=BL3-BK3,BP3-BO3,BN3) -> 0 | BR3: =IF(BM3<BL3-BK3,BL3-BK3-BM3,0) -> 0 | BS3: {=_xlfn._xlws.FILTER(科目余额表[[科目编码]:[期末贷方]],科目余额表[已审报表项目]="其他应付款")} -> 2241001 | BT3: 甲 | BU3: 0 | BV3: 58834.45 | BW3: 0 | BX3: 0 | BY3: 0 | BZ3: 58834.45 | CA3: =IF(BW3>=BV3-BU3,BZ3-BY3,BX3) -> 0 | CB3: =IF(BW3<BV3-BU3,BV3-BU3-BW3,0) -> 58834.45 | CD3: 科目名称 | CE3: 期末金额 | CF3: 科目名称 | CG3: 期末金额 | CH3: 科目名称 | CI3: 期末金额 | CJ3: 科目名称 | CK3: 期末金额 | CL3: 科目名称 | CM3: 期末金额 | CN3: 科目名称 | CO3: 期末金额 | CP3: 科目名称 | CQ3: 期末金额 | CR3: 科目名称 | CS3: 期末金额
A4: 1122002 | B4: B有限公司 | C4: 449224.39 | D4: 0 | E4: 1152600 | F4: 1029000 | G4: 572824.39 | H4: 0 | I4: =IF(F4>=C4-D4,G4-H4,E4) -> 572824.39 | J4: =IF(F4<C4-D4,C4-D4-F4,0) -> 0 | K4: 1123006 | L4: O有限公司 | M4: 190048.34 | N4: 0 | O4: 540000 | P4: 0 | Q4: 730048.34 | R4: 0 | S4: =IF(P4>=M4-N4,Q4-R4,O4) -> 540000 | T4: =IF(P4<M4-N4,M4-N4-P4,0) -> 190048.34 | AC4: =IF(Z4>=W4-X4,AA4-AB4,Y4) -> 0 | AD4: =IF(Z4<W4-X4,W4-X4-Z4,0) -> 0 | AE4: 1221002 | AF4: 李四 | AG4: 68847.87 | AH4: 0 | AI4: 0 | AJ4: 10000 | AK4: 58847.87 | AL4: 0 | AM4: =IF(AJ4>=AG4-AH4,AK4-AL4,AI4) -> 0 | AN4: =IF(AJ4<AG4-AH4,AG4-AH4-AJ4,0) -> 58847.87 | AO4: 1123002 | AP4: L有限公司 | AQ4: 188355.45 | AR4: 0 | AS4: 0 | AT4: 698000 | AU4: -509644.55 | AV4: 0 | AW4: =IF(AS4>=AR4-AQ4,AV4-AU4,AT4) -> 509644.55 | AX4: =IF(AS4<AR4-AQ4,AR4-AQ4-AS4,0) -> 0 | BG4: =IF(BC4>=BB4-BA4,BF4-BE4,BD4) -> 0 | BH4: =IF(BC4<BB4-BA4,BB4-BA4-BC4,0) -> 0 | BQ4: =IF(BM4>=BL4-BK4,BP4-BO4,BN4) -> 0 | BR4: =IF(BM4<BL4-BK4,BL4-BK4-BM4,0) -> 0 | BS4: 2241002 | BT4: 乙 | BU4: 0 | BV4: 76440.34 | BW4: 0 | BX4: 0 | BY4: 0 | BZ4: 76440.34 | CA4: =IF(BW4>=BV4-BU4,BZ4-BY4,BX4) -> 0 | CB4: =IF(BW4<BV4-BU4,BV4-BU4-BW4,0) -> 76440.34 | CD4: A有限公司 | CE4: =SUMIF(B:B,CD4,G:G)-SUMIF(B:B,CD4,H:H) -> 918044.45 | CF4: N有限公司 | CG4: =SUMIF(L:L,CF4,Q:Q)-SUMIF(L:L,CF4,R:R) -> 0 | CI4: =SUMIF(V:V,CH4,AA:AA)-SUMIF(V:V,CH4,AB:AB) -> 0 | CJ4: 张三 | CK4: =SUMIF(AF:AF,CJ4,AK:AK)-SUMIF(AF:AF,CJ4,AL:AL) -> 78922.34 | CL4: K有限公司 | CM4: =SUMIF(AP:AP,CL4,AV:AV)-SUMIF(AP:AP,CL4,AU:AU) -> 368642.51 | CO4: =SUMIF(AZ:AZ,CN4,BF:BF)-SUMIF(AZ:AZ,CN4,BE:BE) -> 0 | CQ4: =SUMIF(BJ:BJ,CP4,BP:BP)-SUMIF(BJ:BJ,CP4,BO:BO) -> 0 | CR4: 甲 | CS4: =SUMIF(BT:BT,CR4,BZ:BZ)-SUMIF(BT:BT,CR4,BY:BY) -> 58834.45
A5: 1122003 | B5: C有限公司 | C5: 228599.99 | D5: 0 | E5: 2406900 | F5: 1993000 | G5: 642499.99 | H5: 0 | I5: =IF(F5>=C5-D5,G5-H5,E5) -> 642499.99 | J5: =IF(F5<C5-D5,C5-D5-F5,0) -> 0 | K5: 0 | L5: N有限公司 | M5: 0 | N5: 0 | O5: 0 | P5: 0 | Q5: -334588.9 | R5: 0 | S5: =IF(P5>=M5-N5,Q5-R5,O5) -> -334588.9 | T5: =IF(P5<M5-N5,M5-N5-P5,0) -> 0 | AC5: =IF(Z5>=W5-X5,AA5-AB5,Y5) -> 0 | AD5: =IF(Z5<W5-X5,W5-X5-Z5,0) -> 0 | AE5: 1221003 | AF5: 王五 | AG5: 82164.36 | AH5: 0 | AI5: 0 | AJ5: 0 | AK5: 82164.36 | AL5: 0 | AM5: =IF(AJ5>=AG5-AH5,AK5-AL5,AI5) -> 0 | AN5: =IF(AJ5<AG5-AH5,AG5-AH5-AJ5,0) -> 82164.36 | AO5: 1123003 | AP5: M有限公司 | AQ5: 422009.32 | AR5: 0 | AS5: 0 | AT5: 568842 | AU5: -146832.68 | AV5: 0 | AW5: =IF(AS5>=AR5-AQ5,AV5-AU5,AT5) -> 146832.68 | AX5: =IF(AS5<AR5-AQ5,AR5-AQ5-AS5,0) -> 0 | BG5: =IF(BC5>=BB5-BA5,BF5-BE5,BD5) -> 0 | BH5: =IF(BC5<BB5-BA5,BB5-BA5-BC5,0) -> 0 | BQ5: =IF(BM5>=BL5-BK5,BP5-BO5,BN5) -> 0 | BR5: =IF(BM5<BL5-BK5,BL5-BK5-BM5,0) -> 0 | BS5: 2241003 | BT5: 丙 | BU5: 0 | BV5: 48876.38 | BW5: 0 | BX5: 5000 | BY5: 0 | BZ5: 53876.38 | CA5: =IF(BW5>=BV5-BU5,BZ5-BY5,BX5) -> 5000 | CB5: =IF(BW5<BV5-BU5,BV5-BU5-BW5,0) -> 48876.38 | CD5: B有限公司 | CE5: =SUMIF(B:B,CD5,G:G)-SUMIF(B:B,CD5,H:H) -> 572824.39 | CF5: O有限公司 | CG5: =SUMIF(L:L,CF5,Q:Q)-SUMIF(L:L,CF5,R:R) -> 730048.34 | CI5: =SUMIF(V:V,CH5,AA:AA)-SUMIF(V:V,CH5,AB:AB) -> 0 | CJ5: 李四 | CK5: =SUMIF(AF:AF,CJ5,AK:AK)-SUMIF(AF:AF,CJ5,AL:AL) -> 58847.87 | CL5: L有限公司 | CM5: =SUMIF(AP:AP,CL5,AV:AV)-SUMIF(AP:AP,CL5,AU:AU) -> 509644.55 | CO5: =SUMIF(AZ:AZ,CN5,BF:BF)-SUMIF(AZ:AZ,CN5,BE:BE) -> 0 | CQ5: =SUMIF(BJ:BJ,CP5,BP:BP)-SUMIF(BJ:BJ,CP5,BO:BO) -> 0 | CR5: 乙 | CS5: =SUMIF(BT:BT,CR5,BZ:BZ)-SUMIF(BT:BT,CR5,BY:BY) -> 76440.34
A6: 1122004 | B6: D有限公司 | C6: 669788.45 | D6: 0 | E6: 1175200 | F6: 1018000 | G6: 826988.45 | H6: 0 | I6: =IF(F6>=C6-D6,G6-H6,E6) -> 826988.45 | J6: =IF(F6<C6-D6,C6-D6-F6,0) -> 0 | S6: =IF(P6>=M6-N6,Q6-R6,O6) -> 0 | T6: =IF(P6<M6-N6,M6-N6-P6,0) -> 0 | AC6: =IF(Z6>=W6-X6,AA6-AB6,Y6) -> 0 | AD6: =IF(Z6<W6-X6,W6-X6-Z6,0) -> 0 | AM6: =IF(AJ6>=AG6-AH6,AK6-AL6,AI6) -> 0 | AN6: =IF(AJ6<AG6-AH6,AG6-AH6-AJ6,0) -> 0 | AO6: 1123005 | AP6: C有限公司 | AQ6: 235333.35 | AR6: 0 | AS6: 0 | AT6: 1361700 | AU6: -1126366.6 | AV6: 0 | AW6: =IF(AS6>=AR6-AQ6,AV6-AU6,AT6) -> 1126366.6 | AX6: =IF(AS6<AR6-AQ6,AR6-AQ6-AS6,0) -> 0 | BG6: =IF(BC6>=BB6-BA6,BF6-BE6,BD6) -> 0 | BH6: =IF(BC6<BB6-BA6,BB6-BA6-BC6,0) -> 0 | BQ6: =IF(BM6>=BL6-BK6,BP6-BO6,BN6) -> 0 | BR6: =IF(BM6<BL6-BK6,BL6-BK6-BM6,0) -> 0 | BS6: 2241004 | BT6: 丁 | BU6: 0 | BV6: 46739.28 | BW6: 0 | BX6: 0 | BY6: 0 | BZ6: 46739.28 | CA6: =IF(BW6>=BV6-BU6,BZ6-BY6,BX6) -> 0 | CB6: =IF(BW6<BV6-BU6,BV6-BU6-BW6,0) -> 46739.28 | CD6: C有限公司 | CE6: =SUMIF(B:B,CD6,G:G)-SUMIF(B:B,CD6,H:H) -> 642499.99 | CG6: =SUMIF(L:L,CF6,Q:Q)-SUMIF(L:L,CF6,R:R) -> 0 | CI6: =SUMIF(V:V,CH6,AA:AA)-SUMIF(V:V,CH6,AB:AB) -> 0 | CJ6: 王五 | CK6: =SUMIF(AF:AF,CJ6,AK:AK)-SUMIF(AF:AF,CJ6,AL:AL) -> 82164.36 | CL6: M有限公司 | CM6: =SUMIF(AP:AP,CL6,AV:AV)-SUMIF(AP:AP,CL6,AU:AU) -> 4365231.5 | CO6: =SUMIF(AZ:AZ,CN6,BF:BF)-SUMIF(AZ:AZ,CN6,BE:BE) -> 0 | CQ6: =SUMIF(BJ:BJ,CP6,BP:BP)-SUMIF(BJ:BJ,CP6,BO:BO) -> 0 | CR6: 丙 | CS6: =SUMIF(BT:BT,CR6,BZ:BZ)-SUMIF(BT:BT,CR6,BY:BY) -> 53876.38
A7: 1122005 | B7: E有限公司 | C7: 550333.49 | D7: 0 | E7: 1751500 | F7: 2009000 | G7: 292833.49 | H7: 0 | I7: =IF(F7>=C7-D7,G7-H7,E7) -> 292833.49 | J7: =IF(F7<C7-D7,C7-D7-F7,0) -> 0 | S7: =IF(P7>=M7-N7,Q7-R7,O7) -> 0 | T7: =IF(P7<M7-N7,M7-N7-P7,0) -> 0 | AC7: =IF(Z7>=W7-X7,AA7-AB7,Y7) -> 0 | AD7: =IF(Z7<W7-X7,W7-X7-Z7,0) -> 0 | AM7: =IF(AJ7>=AG7-AH7,AK7-AL7,AI7) -> 0 | AN7: =IF(AJ7<AG7-AH7,AG7-AH7-AJ7,0) -> 0 | AO7: 1123007 | AP7: P有限公司 | AQ7: 230444.39 | AR7: 0 | AS7: 0 | AT7: 763880 | AU7: -533435.61 | AV7: 0 | AW7: =IF(AS7>=AR7-AQ7,AV7-AU7,AT7) -> 533435.61 | AX7: =IF(AS7<AR7-AQ7,AR7-AQ7-AS7,0) -> 0 | BG7: =IF(BC7>=BB7-BA7,BF7-BE7,BD7) -> 0 | BH7: =IF(BC7<BB7-BA7,BB7-BA7-BC7,0) -> 0 | BQ7: =IF(BM7>=BL7-BK7,BP7-BO7,BN7) -> 0 | BR7: =IF(BM7<BL7-BK7,BL7-BK7-BM7,0) -> 0 | BS7: 2241005 | BT7: 戊 | BU7: 0 | BV7: 33809.67 | BW7: 0 | BX7: 0 | BY7: 0 | BZ7: 33809.67 | CA7: =IF(BW7>=BV7-BU7,BZ7-BY7,BX7) -> 0 | CB7: =IF(BW7<BV7-BU7,BV7-BU7-BW7,0) -> 33809.67 | CD7: D有限公司 | CE7: =SUMIF(B:B,CD7,G:G)-SUMIF(B:B,CD7,H:H) -> 826988.45 | CG7: =SUMIF(L:L,CF7,Q:Q)-SUMIF(L:L,CF7,R:R) -> 0 | CI7: =SUMIF(V:V,CH7,AA:AA)-SUMIF(V:V,CH7,AB:AB) -> 0 | CK7: =SUMIF(AF:AF,CJ7,AK:AK)-SUMIF(AF:AF,CJ7,AL:AL) -> 0 | CL7: C有限公司 | CM7: =SUMIF(AP:AP,CL7,AV:AV)-SUMIF(AP:AP,CL7,AU:AU) -> 1126366.6 | CO7: =SUMIF(AZ:AZ,CN7,BF:BF)-SUMIF(AZ:AZ,CN7,BE:BE) -> 0 | CQ7: =SUMIF(BJ:BJ,CP7,BP:BP)-SUMIF(BJ:BJ,CP7,BO:BO) -> 0 | CR7: 丁 | CS7: =SUMIF(BT:BT,CR7,BZ:BZ)-SUMIF(BT:BT,CR7,BY:BY) -> 46739.28
A8: 1122006 | B8: F有限公司 | C8: 999200.88 | D8: 0 | E8: 1197800 | F8: 870000 | G8: 1327000.9 | H8: 0 | I8: =IF(F8>=C8-D8,G8-H8,E8) -> 1197800 | J8: =IF(F8<C8-D8,C8-D8-F8,0) -> 129200.88 | S8: =IF(P8>=M8-N8,Q8-R8,O8) -> 0 | T8: =IF(P8<M8-N8,M8-N8-P8,0) -> 0 | AC8: =IF(Z8>=W8-X8,AA8-AB8,Y8) -> 0 | AD8: =IF(Z8<W8-X8,W8-X8-Z8,0) -> 0 | AM8: =IF(AJ8>=AG8-AH8,AK8-AL8,AI8) -> 0 | AN8: =IF(AJ8<AG8-AH8,AG8-AH8-AJ8,0) -> 0 | AO8: 1123008 | AP8: Q有限公司 | AQ8: 201008 | AR8: 0 | AS8: 0 | AT8: 908000 | AU8: -706992 | AV8: 0 | AW8: =IF(AS8>=AR8-AQ8,AV8-AU8,AT8) -> 706992 | AX8: =IF(AS8<AR8-AQ8,AR8-AQ8-AS8,0) -> 0 | BG8: =IF(BC8>=BB8-BA8,BF8-BE8,BD8) -> 0 | BH8: =IF(BC8<BB8-BA8,BB8-BA8-BC8,0) -> 0 | BQ8: =IF(BM8>=BL8-BK8,BP8-BO8,BN8) -> 0 | BR8: =IF(BM8<BL8-BK8,BL8-BK8-BM8,0) -> 0 | BS8: 2241006 | BT8: 申 | BU8: 0 | BV8: 28606.34 | BW8: 0 | BX8: 0 | BY8: 0 | BZ8: 28606.34 | CA8: =IF(BW8>=BV8-BU8,BZ8-BY8,BX8) -> 0 | CB8: =IF(BW8<BV8-BU8,BV8-BU8-BW8,0) -> 28606.34 | CD8: E有限公司 | CE8: =SUMIF(B:B,CD8,G:G)-SUMIF(B:B,CD8,H:H) -> 292833.49 | CG8: =SUMIF(L:L,CF8,Q:Q)-SUMIF(L:L,CF8,R:R) -> 0 | CI8: =SUMIF(V:V,CH8,AA:AA)-SUMIF(V:V,CH8,AB:AB) -> 0 | CK8: =SUMIF(AF:AF,CJ8,AK:AK)-SUMIF(AF:AF,CJ8,AL:AL) -> 0 | CL8: P有限公司 | CM8: =SUMIF(AP:AP,CL8,AV:AV)-SUMIF(AP:AP,CL8,AU:AU) -> 533435.61 | CO8: =SUMIF(AZ:AZ,CN8,BF:BF)-SUMIF(AZ:AZ,CN8,BE:BE) -> 0 | CQ8: =SUMIF(BJ:BJ,CP8,BP:BP)-SUMIF(BJ:BJ,CP8,BO:BO) -> 0 | CR8: 戊 | CS8: =SUMIF(BT:BT,CR8,BZ:BZ)-SUMIF(BT:BT,CR8,BY:BY) -> 33809.67
A9: 1122007 | B9: G有限公司 | C9: 450055.23 | D9: 0 | E9: 1209100 | F9: 810000 | G9: 849155.23 | H9: 0 | I9: =IF(F9>=C9-D9,G9-H9,E9) -> 849155.23 | J9: =IF(F9<C9-D9,C9-D9-F9,0) -> 0 | S9: =IF(P9>=M9-N9,Q9-R9,O9) -> 0 | T9: =IF(P9<M9-N9,M9-N9-P9,0) -> 0 | AC9: =IF(Z9>=W9-X9,AA9-AB9,Y9) -> 0 | AD9: =IF(Z9<W9-X9,W9-X9-Z9,0) -> 0 | AM9: =IF(AJ9>=AG9-AH9,AK9-AL9,AI9) -> 0 | AN9: =IF(AJ9<AG9-AH9,AG9-AH9-AJ9,0) -> 0 | AO9: 2202001 | AP9: T有限公司 | AQ9: 0 | AR9: 566399.29 | AS9: 0 | AT9: 1566604 | AU9: 0 | AV9: 2133003.3 | AW9: =IF(AS9>=AR9-AQ9,AV9-AU9,AT9) -> 1566604 | AX9: =IF(AS9<AR9-AQ9,AR9-AQ9-AS9,0) -> 566399.29 | BG9: =IF(BC9>=BB9-BA9,BF9-BE9,BD9) -> 0 | BH9: =IF(BC9<BB9-BA9,BB9-BA9-BC9,0) -> 0 | BQ9: =IF(BM9>=BL9-BK9,BP9-BO9,BN9) -> 0 | BR9: =IF(BM9<BL9-BK9,BL9-BK9-BM9,0) -> 0 | BS9: 2241007 | BT9: 亥 | BU9: 0 | BV9: 52692.19 | BW9: 7000 | BX9: 0 | BY9: 0 | BZ9: 45692.19 | CA9: =IF(BW9>=BV9-BU9,BZ9-BY9,BX9) -> 0 | CB9: =IF(BW9<BV9-BU9,BV9-BU9-BW9,0) -> 45692.19 | CD9: F有限公司 | CE9: =SUMIF(B:B,CD9,G:G)-SUMIF(B:B,CD9,H:H) -> 1327000.9 | CG9: =SUMIF(L:L,CF9,Q:Q)-SUMIF(L:L,CF9,R:R) -> 0 | CI9: =SUMIF(V:V,CH9,AA:AA)-SUMIF(V:V,CH9,AB:AB) -> 0 | CK9: =SUMIF(AF:AF,CJ9,AK:AK)-SUMIF(AF:AF,CJ9,AL:AL) -> 0 | CL9: Q有限公司 | CM9: =SUMIF(AP:AP,CL9,AV:AV)-SUMIF(AP:AP,CL9,AU:AU) -> 706992 | CO9: =SUMIF(AZ:AZ,CN9,BF:BF)-SUMIF(AZ:AZ,CN9,BE:BE) -> 0 | CQ9: =SUMIF(BJ:BJ,CP9,BP:BP)-SUMIF(BJ:BJ,CP9,BO:BO) -> 0 | CR9: 申 | CS9: =SUMIF(BT:BT,CR9,BZ:BZ)-SUMIF(BT:BT,CR9,BY:BY) -> 28606.34
A10: 1122008 | B10: H有限公司 | C10: 555455.34 | D10: 0 | E10: 1220400 | F10: 770000 | G10: 1005855.3 | H10: 0 | I10: =IF(F10>=C10-D10,G10-H10,E10) -> 1005855.3 | J10: =IF(F10<C10-D10,C10-D10-F10,0) -> 0 | S10: =IF(P10>=M10-N10,Q10-R10,O10) -> 0 | T10: =IF(P10<M10-N10,M10-N10-P10,0) -> 0 | AC10: =IF(Z10>=W10-X10,AA10-AB10,Y10) -> 0 | AD10: =IF(Z10<W10-X10,W10-X10-Z10,0) -> 0 | AM10: =IF(AJ10>=AG10-AH10,AK10-AL10,AI10) -> 0 | AN10: =IF(AJ10<AG10-AH10,AG10-AH10-AJ10,0) -> 0 | AO10: 2202002 | AP10: U有限公司 | AQ10: 0 | AR10: 688466.23 | AS10: 0 | AT10: 553700 | AU10: 0 | AV10: 1242166.2 | AW10: =IF(AS10>=AR10-AQ10,AV10-AU10,AT10) -> 553700 | AX10: =IF(AS10<AR10-AQ10,AR10-AQ10-AS10,0) -> 688466.23 | BG10: =IF(BC10>=BB10-BA10,BF10-BE10,BD10) -> 0 | BH10: =IF(BC10<BB10-BA10,BB10-BA10-BC10,0) -> 0 | BQ10: =IF(BM10>=BL10-BK10,BP10-BO10,BN10) -> 0 | BR10: =IF(BM10<BL10-BK10,BL10-BK10-BM10,0) -> 0 | CA10: =IF(BW10>=BV10-BU10,BZ10-BY10,BX10) -> 0 | CB10: =IF(BW10<BV10-BU10,BV10-BU10-BW10,0) -> 0 | CD10: G有限公司 | CE10: =SUMIF(B:B,CD10,G:G)-SUMIF(B:B,CD10,H:H) -> 849155.23 | CG10: =SUMIF(L:L,CF10,Q:Q)-SUMIF(L:L,CF10,R:R) -> 0 | CI10: =SUMIF(V:V,CH10,AA:AA)-SUMIF(V:V,CH10,AB:AB) -> 0 | CK10: =SUMIF(AF:AF,CJ10,AK:AK)-SUMIF(AF:AF,CJ10,AL:AL) -> 0 | CL10: T有限公司 | CM10: =SUMIF(AP:AP,CL10,AV:AV)-SUMIF(AP:AP,CL10,AU:AU) -> 2133003.3 | CO10: =SUMIF(AZ:AZ,CN10,BF:BF)-SUMIF(AZ:AZ,CN10,BE:BE) -> 0 | CQ10: =SUMIF(BJ:BJ,CP10,BP:BP)-SUMIF(BJ:BJ,CP10,BO:BO) -> 0 | CR10: 亥 | CS10: =SUMIF(BT:BT,CR10,BZ:BZ)-SUMIF(BT:BT,CR10,BY:BY) -> 45692.19
A11: 1122009 | B11: I有限公司 | C11: 566229.43 | D11: 0 | E11: 1231700 | F11: 880000 | G11: 917929.43 | H11: 0 | I11: =IF(F11>=C11-D11,G11-H11,E11) -> 917929.43 | J11: =IF(F11<C11-D11,C11-D11-F11,0) -> 0 | S11: =IF(P11>=M11-N11,Q11-R11,O11) -> 0 | T11: =IF(P11<M11-N11,M11-N11-P11,0) -> 0 | AC11: =IF(Z11>=W11-X11,AA11-AB11,Y11) -> 0 | AD11: =IF(Z11<W11-X11,W11-X11-Z11,0) -> 0 | AM11: =IF(AJ11>=AG11-AH11,AK11-AL11,AI11) -> 0 | AN11: =IF(AJ11<AG11-AH11,AG11-AH11-AJ11,0) -> 0 | AO11: 2202003 | AP11: M有限公司 | AQ11: 0 | AR11: 599799.87 | AS11: 0 | AT11: 3618599 | AU11: 0 | AV11: 4218398.9 | AW11: =IF(AS11>=AR11-AQ11,AV11-AU11,AT11) -> 3618599 | AX11: =IF(AS11<AR11-AQ11,AR11-AQ11-AS11,0) -> 599799.87 | BG11: =IF(BC11>=BB11-BA11,BF11-BE11,BD11) -> 0 | BH11: =IF(BC11<BB11-BA11,BB11-BA11-BC11,0) -> 0 | BQ11: =IF(BM11>=BL11-BK11,BP11-BO11,BN11) -> 0 | BR11: =IF(BM11<BL11-BK11,BL11-BK11-BM11,0) -> 0 | CA11: =IF(BW11>=BV11-BU11,BZ11-BY11,BX11) -> 0 | CB11: =IF(BW11<BV11-BU11,BV11-BU11-BW11,0) -> 0 | CD11: H有限公司 | CE11: =SUMIF(B:B,CD11,G:G)-SUMIF(B:B,CD11,H:H) -> 1005855.3 | CG11: =SUMIF(L:L,CF11,Q:Q)-SUMIF(L:L,CF11,R:R) -> 0 | CI11: =SUMIF(V:V,CH11,AA:AA)-SUMIF(V:V,CH11,AB:AB) -> 0 | CK11: =SUMIF(AF:AF,CJ11,AK:AK)-SUMIF(AF:AF,CJ11,AL:AL) -> 0 | CL11: U有限公司 | CM11: =SUMIF(AP:AP,CL11,AV:AV)-SUMIF(AP:AP,CL11,AU:AU) -> 1242166.2 | CO11: =SUMIF(AZ:AZ,CN11,BF:BF)-SUMIF(AZ:AZ,CN11,BE:BE) -> 0 | CQ11: =SUMIF(BJ:BJ,CP11,BP:BP)-SUMIF(BJ:BJ,CP11,BO:BO) -> 0 | CS11: =SUMIF(BT:BT,CR11,BZ:BZ)-SUMIF(BT:BT,CR11,BY:BY) -> 0
